Workbook
Name X_Axis: OFFSET(#REF!,0,0,Page!$C$4,1)

Sheet Page
B2: Investment Settings | G2: Buy & Hold | V2: Rebalanced
B3: Starting Capital ($) | C3: 10000000
B4: Investment Horizon (Years) | C4: 20 | G4: Custom | J4: Traditional (Taxable) | M4: Traditional (PPLI) | P4: Alternatives Enhanced (Taxable) | S4: Alternatives Enhanced (PPLI) | V4: Custom | Y4: Traditional (Taxable) | AB4: Traditional (PPLI) | AE4: Alternatives Enhanced (Taxable) | AH4: Alternatives Enhanced (PPLI)
G5: Projected Value | H5: =Custom!C22 -> 29316021 | J5: =G5 -> Projected Value | K5: ='Trad. Tax.'!C22 -> 26762916 | M5: =G5 -> Projected Value | N5: ='Trad. PPLI'!C22 -> 28437126 | P5: =G5 -> Projected Value | Q5: ='Alts. Tax.'!C22 -> 27153622 | S5: =G5 -> Projected Value | T5: ='Alts. PPLI'!C22 -> 29906035 | V5: Projected Value | W5: =Custom!D22 -> 28633744 | Y5: =V5 -> Projected Value | Z5: ='Trad. Tax.'!D22 -> 25743809 | AB5: =V5 -> Projected Value | AC5: ='Trad. PPLI'!D22 -> 27214746 | AE5: =V5 -> Projected Value | AF5: ='Alts. Tax.'!D22 -> 26313895 | AH5: =V5 -> Projected Value | AI5: ='Alts. PPLI'!D22 -> 28484590
B6: Portfolio Allocation (%) | E6: Allocation Check
B7: Stocks | C7: 0.7 | E7: =IF(SUM(C7:C9)=1,"Good","Must Equal 100%") -> Good | G7: Total Return | J7: =G7 -> Total Return | M7: =J7 -> Total Return | P7: =M7 -> Total Return | S7: =P7 -> Total Return | V7: Total Return | Y7: =V7 -> Total Return | AB7: =Y7 -> Total Return | AE7: =AB7 -> Total Return | AH7: =AE7 -> Total Return
B8: Bonds | C8: 0.2 | G8: Gross | H8: =Custom!C24 -> 3.2594253 | J8: =G8 -> Gross | K8: ='Trad. Tax.'!C24 -> 2.8578934 | M8: =J8 -> Gross | N8: ='Trad. PPLI'!C24 -> 2.8578934 | P8: =M8 -> Gross | Q8: ='Alts. Tax.'!C24 -> 3.0185061 | S8: =P8 -> Gross | T8: ='Alts. PPLI'!C24 -> 3.0185061 | V8: Gross | W8: =Custom!D24 -> 3.1695158 | Y8: =V8 -> Gross | Z8: ='Trad. Tax.'!D24 -> 2.7275635 | AB8: =Y8 -> Gross | AC8: ='Trad. PPLI'!D24 -> 2.7275635 | AE8: =AB8 -> Gross | AF8: ='Alts. Tax.'!D24 -> 2.8987197 | AH8: =AE8 -> Gross | AI8: ='Alts. PPLI'!D24 -> 2.8987197
B9: Alternatives | C9: 0.1 | G9: Net | H9: =Custom!C25 -> 1.9316021 | J9: =G9 -> Net | K9: ='Trad. Tax.'!C25 -> 1.6762916 | M9: =J9 -> Net | N9: ='Trad. PPLI'!C25 -> 1.8437126 | P9: =M9 -> Net | Q9: ='Alts. Tax.'!C25 -> 1.7153622 | S9: =P9 -> Net | T9: ='Alts. PPLI'!C25 -> 1.9906035 | V9: Net | W9: =Custom!D25 -> 1.8633744 | Y9: =V9 -> Net | Z9: ='Trad. Tax.'!D25 -> 1.5743809 | AB9: =Y9 -> Net | AC9: ='Trad. PPLI'!D25 -> 1.7214746 | AE9: =AB9 -> Net | AF9: ='Alts. Tax.'!D25 -> 1.6313895 | AH9: =AE9 -> Net | AI9: ='Alts. PPLI'!D25 -> 1.848459
G10: Drag | H10: =Custom!C26 -> -1.3278232 | J10: =G10 -> Drag | K10: ='Trad. Tax.'!C26 -> -1.1816017 | M10: =J10 -> Drag | N10: ='Trad. PPLI'!C26 -> -1.0141808 | P10: =M10 -> Drag | Q10: ='Alts. Tax.'!C26 -> -1.3031439 | S10: =P10 -> Drag | T10: ='Alts. PPLI'!C26 -> -1.0279026 | V10: Drag | W10: =Custom!D26 -> -1.3061414 | Y10: =V10 -> Drag | Z10: ='Trad. Tax.'!D26 -> -1.1531826 | AB10: =Y10 -> Drag | AC10: ='Trad. PPLI'!D26 -> -1.006089 | AE10: =AB10 -> Drag | AF10: ='Alts. Tax.'!D26 -> -1.2673301 | AH10: =AE10 -> Drag | AI10: ='Alts. PPLI'!D26 -> -1.0502607
B11: Return Assumptions (%)
B12: Stocks | C12: 0.08 | G12: Annualized Return | J12: =G12 -> Annualized Return | M12: =J12 -> Annualized Return | P12: =M12 -> Annualized Return | S12: =P12 -> Annualized Return | V12: Annualized Return | Y12: =V12 -> Annualized Return | AB12: =Y12 -> Annualized Return | AE12: =AB12 -> Annualized Return | AH12: =AE12 -> Annualized Return
B13: Bonds | C13: 0.05 | G13: Gross | H13: =Custom!C28 -> 0.075146264 | J13: =G13 -> Gross | K13: ='Trad. Tax.'!C28 -> 0.069836747 | M13: =J13 -> Gross | N13: ='Trad. PPLI'!C28 -> 0.069836747 | P13: =M13 -> Gross | Q13: ='Alts. Tax.'!C28 -> 0.072020849 | S13: =P13 -> Gross | T13: ='Alts. PPLI'!C28 -> 0.072020849 | V13: Gross | W13: =Custom!D28 -> 0.074 | Y13: =V13 -> Gross | Z13: ='Trad. Tax.'!D28 -> 0.068 | AB13: =Y13 -> Gross | AC13: ='Trad. PPLI'!D28 -> 0.068 | AE13: =AB13 -> Gross | AF13: ='Alts. Tax.'!D28 -> 0.0704 | AH13: =AE13 -> Gross | AI13: ='Alts. PPLI'!D28 -> 0.0704
B14: Alternatives | C14: 0.08 | G14: Net | H14: =Custom!C29 -> 0.055249733 | J14: =G14 -> Net | K14: ='Trad. Tax.'!C29 -> 0.050453112 | M14: =J14 -> Net | N14: ='Trad. PPLI'!C29 -> 0.053644938 | P14: =M14 -> Net | Q14: ='Alts. Tax.'!C29 -> 0.05121461 | S14: =P14 -> Net | T14: ='Alts. PPLI'!C29 -> 0.056301611 | V14: Net | W14: =Custom!D29 -> 0.054008 | Y14: =V14 -> Net | Z14: ='Trad. Tax.'!D29 -> 0.048416 | AB14: =Y14 -> Net | AC14: ='Trad. PPLI'!D29 -> 0.0513328 | AE14: =AB14 -> Net | AF14: ='Alts. Tax.'!D29 -> 0.0495648 | AH14: =AE14 -> Net | AI14: ='Alts. PPLI'!D29 -> 0.0537328
G15: Drag | H15: =Custom!C30 -> -0.019896531 | J15: =G15 -> Drag | K15: ='Trad. Tax.'!C30 -> -0.019383635 | M15: =J15 -> Drag | N15: ='Trad. PPLI'!C30 -> -0.016191809 | P15: =M15 -> Drag | Q15: ='Alts. Tax.'!C30 -> -0.020806239 | S15: =P15 -> Drag | T15: ='Alts. PPLI'!C30 -> -0.015719238 | V15: Drag | W15: =Custom!D30 -> -0.019992 | Y15: =V15 -> Drag | Z15: ='Trad. Tax.'!D30 -> -0.019584 | AB15: =Y15 -> Drag | AC15: ='Trad. PPLI'!D30 -> -0.0166672 | AE15: =AB15 -> Drag | AF15: ='Alts. Tax.'!D30 -> -0.0208352 | AH15: =AE15 -> Drag | AI15: ='Alts. PPLI'!D30 -> -0.0166672
B16: Tax Assumptions (%)
B17: Ordinary Income | C17: 0.37
B18: Capital Gains | C18: 0.2
B19: NIIT | C19: 0.038
B21: PPLI Allocation (%)
B22: Stocks | C22: 0
B23: Bonds | C23: 0
B24: Alternatives | C24: 0
B26: PPLI Costs (%)
B27: Policy Costs | C27: 0.005
B29: Additional Contributions
B30: Year | C30: Amount ($)
M46: Rank | N46: Strategy | P46: Annualized Return (Net) | R46: Projected Value | AB46: Rank | AC46: Strategy | AE46: Annualized Return (Net) | AG46: Projected Value
M49: =Rank!M2 -> 1st | N49: =Rank!I2 -> Alternatives Enhanced (PPLI) | P49: =Rank!K2 -> 0.056301611 | Q49: =_xlfn.CONCAT("+ ",TEXT(P49-$P$61,"0.00%")) -> + 0.58% | R49: =Rank!J2 -> 29906035 | T49: =_xlfn.CONCAT("+ ",TEXT(R49-$R$61,"$#,##0.00")) -> + $3,143,118.93 | AB49: =Rank!M10 -> 1st | AC49: =Rank!I10 -> Custom | AE49: =Rank!K10 -> 0.054008 | AF49: =_xlfn.CONCAT("+ ",TEXT(AE49-$AE$61,"0.00%")) -> + 0.56% | AG49: =Rank!J10 -> 28633744 | AI49: =_xlfn.CONCAT("+ ",TEXT(AG49-$AG$61,"$#,##0.00")) -> + $2,889,935.53
M52: =Rank!M3 -> 2nd | N52: =Rank!I3 -> Custom | P52: =Rank!K3 -> 0.055249733 | Q52: =_xlfn.CONCAT("+ ",TEXT(P52-$P$61,"0.00%")) -> + 0.48% | R52: =Rank!J3 -> 29316021 | T52: =_xlfn.CONCAT("+ ",TEXT(R52-$R$61,"$#,##0.00")) -> + $2,553,104.27 | AB52: =Rank!M11 -> 2nd | AC52: =Rank!I11 -> Alternatives Enhanced (PPLI) | AE52: =Rank!K11 -> 0.0537328 | AF52: =_xlfn.CONCAT("+ ",TEXT(AE52-$AE$61,"0.00%")) -> + 0.53% | AG52: =Rank!J11 -> 28484590 | AI52: =_xlfn.CONCAT("+ ",TEXT(AG52-$AG$61,"$#,##0.00")) -> + $2,740,781.23
M55: =Rank!M4 -> 3rd | N55: =Rank!I4 -> Traditional (PPLI) | P55: =Rank!K4 -> 0.053644938 | Q55: =_xlfn.CONCAT("+ ",TEXT(P55-$P$61,"0.00%")) -> + 0.32% | R55: =Rank!J4 -> 28437126 | T55: =_xlfn.CONCAT("+ ",TEXT(R55-$R$61,"$#,##0.00")) -> + $1,674,209.27 | AB55: =Rank!M12 -> 3rd | AC55: =Rank!I12 -> Traditional (PPLI) | AE55: =Rank!K12 -> 0.0513328 | AF55: =_xlfn.CONCAT("+ ",TEXT(AE55-$AE$61,"0.00%")) -> + 0.29% | AG55: =Rank!J12 -> 27214746 | AI55: =_xlfn.CONCAT("+ ",TEXT(AG55-$AG$61,"$#,##0.00")) -> + $1,470,936.72
M58: =Rank!M5 -> 4th | N58: =Rank!I5 -> Alternatives Enhanced (Taxable) | P58: =Rank!K5 -> 0.05121461 | Q58: =_xlfn.CONCAT("+ ",TEXT(P58-$P$61,"0.00%")) -> + 0.08% | R58: =Rank!J5 -> 27153622 | T58: =_xlfn.CONCAT("+ ",TEXT(R58-$R$61,"$#,##0.00")) -> + $390,705.51 | AB58: =Rank!M13 -> 4th | AC58: =Rank!I13 -> Alternatives Enhanced (Taxable) | AE58: =Rank!K13 -> 0.0495648 | AF58: =_xlfn.CONCAT("+ ",TEXT(AE58-$AE$61,"0.00%")) -> + 0.11% | AG58: =Rank!J13 -> 26313895 | AI58: =_xlfn.CONCAT("+ ",TEXT(AG58-$AG$61,"$#,##0.00")) -> + $570,086.30
M61: =Rank!M6 -> 5th | N61: =Rank!I6 -> Traditional (Taxable) | P61: =Rank!K6 -> 0.050453112 | Q61: =_xlfn.CONCAT("+ ",TEXT(P61-$P$61,"0.00%")) -> + 0.00% | R61: =Rank!J6 -> 26762916 | T61: =_xlfn.CONCAT("+ ",TEXT(R61-$R$61,"$#,##0.00")) -> + $0.00 | AB61: =Rank!M14 -> 5th | AC61: =Rank!I14 -> Traditional (Taxable) | AE61: =Rank!K14 -> 0.048416 | AF61: =_xlfn.CONCAT("+ ",TEXT(AE61-$AE$61,"0.00%")) -> + 0.00% | AG61: =Rank!J14 -> 25743809 | AI61: =_xlfn.CONCAT("+ ",TEXT(AG61-$AG$61,"$#,##0.00")) -> + $0.00

Sheet Chart Feeder >

Sheet WA PIVOT
A1: Buy & Hold | I1: Rebalanced
A6: Row Labels | B6: Custom | C6: Traditional (Taxable) | D6: Traditional (PPLI) | E6: Alternatives Enhanced (Taxable) | F6: Alternatives Enhanced (PPLI) | I6: Row Labels | J6: Custom | K6: Traditional (Taxable) | L6: Traditional (PPLI) | M6: Alternatives Enhanced (Taxable) | N6: Alternatives Enhanced (PPLI)
A7: 1 | B7: 10540080 | C7: 10484160 | D7: 10513328 | E7: 10495648 | F7: 10537328 | I7: 1 | J7: 10540080 | K7: 10484160 | L7: 10513328 | M7: 10495648 | N7: 10537328
A8: 2 | B8: 11109329 | C8: 10991761 | D8: 11053007 | E8: 11015863 | F8: 11103528 | I8: 2 | J8: 11109329 | K8: 10991761 | L8: 11053007 | M8: 11015863 | N8: 11103528
A9: 3 | B9: 11709321 | C9: 11523938 | D9: 11620388 | E9: 11561862 | F9: 11700152 | I9: 3 | J9: 11709321 | K9: 11523938 | L9: 11620388 | M9: 11561862 | N9: 11700152
A10: 4 | B10: 12341718 | C10: 12081881 | D10: 12216895 | E10: 12134923 | F10: 12328834 | I10: 4 | J10: 12341718 | K10: 12081881 | L10: 12216895 | M10: 12134923 | N10: 12328834
A11: 5 | B11: 13008270 | C11: 12666838 | D11: 12844023 | E11: 12736388 | F11: 12991296 | I11: 5 | J11: 13008270 | K11: 12666838 | L11: 12844023 | M11: 12736388 | N11: 12991296
A12: 6 | B12: 13710820 | C12: 13280115 | D12: 13503343 | E12: 13367665 | F12: 13689355 | I12: 6 | J12: 13710820 | K12: 13280115 | L12: 13503343 | M12: 13367665 | N12: 13689355
A13: 7 | B13: 14451314 | C13: 13923085 | D13: 14196507 | E13: 14030230 | F13: 14424923 | I13: 7 | J13: 14451314 | K13: 13923085 | L13: 14196507 | M13: 14030230 | N13: 14424923
A14: 8 | B14: 15231801 | C14: 14597185 | D14: 14925253 | E14: 14725636 | F14: 15200014 | I14: 8 | J14: 15231801 | K14: 14597185 | L14: 14925253 | M14: 14725636 | N14: 15200014
A15: 9 | B15: 16054440 | C15: 15303923 | D15: 15691408 | E15: 15455509 | F15: 16016753 | I15: 9 | J15: 16054440 | K15: 15303923 | L15: 15691408 | M15: 15455509 | N15: 16016753
A16: 10 | B16: 16921508 | C16: 16044877 | D16: 16496892 | E16: 16221558 | F16: 16877378 | I16: 10 | J16: 16921508 | K16: 16044877 | L16: 16496892 | M16: 16221558 | N16: 16877378
A17: 11 | B17: 17835405 | C17: 16821706 | D17: 17343724 | E17: 17025577 | F17: 17784247 | I17: 11 | J17: 17835405 | K17: 16821706 | L17: 17343724 | M17: 17025577 | N17: 17784247
A18: 12 | B18: 18798660 | C18: 17636146 | D18: 18234026 | E18: 17869446 | F18: 18739845 | I18: 12 | J18: 18798660 | K18: 17636146 | L18: 18234026 | M18: 17869446 | N18: 18739845
... A26: 20 | B26: 28633744 | C26: 25743809 | D26: 27214746 | E26: 26313895 | F26: 28484590 | I26: 20 | J26: 28633744 | K26: 25743809 | L26: 27214746 | M26: 26313895 | N26: 28484590
A27: Grand Total | B27: 3.6365197e+08 | C27: 3.4092162e+08 | D27: 3.5257042e+08 | E27: 3.4545666e+08 | F27: 3.6249402e+08 | I27: Grand Total | J27: 3.6365197e+08 | K27: 3.4092162e+08 | L27: 3.5257042e+08 | M27: 3.4545666e+08 | N27: 3.6249402e+08

Sheet WA
A1: =Page!C4 -> 20 | B1: Buy & Hold | K1: =A1 -> 20 | L1: Rebalanced
A5: Year | B5: Custom_ | C5: Traditional (Taxable)_ | D5: Traditional (PPLI)_ | E5: Alternatives Enhanced (Taxable)_ | F5: Alternatives Enhanced (PPLI)_ | K5: Year | L5: Custom_ | M5: Traditional (Taxable)_ | N5: Traditional (PPLI)_ | O5: Alternatives Enhanced (Taxable)_ | P5: Alternatives Enhanced (PPLI)_
A6: {=_xlfn.SEQUENCE(A1,1,1,1)} -> 1 | B6: =IF(A6="","N/A",Custom!V10) -> 10540080 | C6: =IF(A6="","N/A",'Trad. Tax.'!V10) -> 10484160 | D6: =IF(A6="","N/A",'Trad. PPLI'!V10) -> 10513328 | E6: =IF(A6="","N/A",'Alts. Tax.'!V10) -> 10495648 | F6: =IF(A6="","N/A",'Alts. PPLI'!V10) -> 10537328 | K6: {=_xlfn.SEQUENCE(K1,1,1,1)} -> 1 | L6: =IF(K6="","N/A",Custom!X10) -> 10540080 | M6: =IF(K6="","N/A",'Trad. Tax.'!X10) -> 10484160 | N6: =IF(K6="","N/A",'Trad. PPLI'!X10) -> 10513328 | O6: =IF(K6="","N/A",'Alts. Tax.'!X10) -> 10495648 | P6: =IF(K6="","N/A",'Alts. PPLI'!X10) -> 10537328
A7: 2 | B7: =IF(A7="","N/A",Custom!V11) -> 11110858 | C7: =IF(A7="","N/A",'Trad. Tax.'!V11) -> 10994121 | D7: =IF(A7="","N/A",'Trad. PPLI'!V11) -> 11055667 | E7: =IF(A7="","N/A",'Alts. Tax.'!V11) -> 11017804 | F7: =IF(A7="","N/A",'Alts. PPLI'!V11) -> 11106547 | K7: 2 | L7: =IF(K7="","N/A",Custom!X11) -> 11109329 | M7: =IF(K7="","N/A",'Trad. Tax.'!X11) -> 10991761 | N7: =IF(K7="","N/A",'Trad. PPLI'!X11) -> 11053007 | O7: =IF(K7="","N/A",'Alts. Tax.'!X11) -> 11015863 | P7: =IF(K7="","N/A",'Alts. PPLI'!X11) -> 11103528
A8: 3 | B8: =IF(A8="","N/A",Custom!V12) -> 11714132 | C8: =IF(A8="","N/A",'Trad. Tax.'!V12) -> 11531347 | D8: =IF(A8="","N/A",'Trad. PPLI'!V12) -> 11628767 | E8: =IF(A8="","N/A",'Alts. Tax.'!V12) -> 11567955 | F8: =IF(A8="","N/A",'Alts. PPLI'!V12) -> 11709671 | K8: 3 | L8: =IF(K8="","N/A",Custom!X12) -> 11709321 | M8: =IF(K8="","N/A",'Trad. Tax.'!X12) -> 11523938 | N8: =IF(K8="","N/A",'Trad. PPLI'!X12) -> 11620388 | O8: =IF(K8="","N/A",'Alts. Tax.'!X12) -> 11561862 | P8: =IF(K8="","N/A",'Alts. PPLI'!X12) -> 11700152
A9: 4 | B9: =IF(A9="","N/A",Custom!V13) -> 12351804 | C9: =IF(A9="","N/A",'Trad. Tax.'!V13) -> 12097386 | D9: =IF(A9="","N/A",'Trad. PPLI'!V13) -> 12234487 | E9: =IF(A9="","N/A",'Alts. Tax.'!V13) -> 12147677 | F9: =IF(A9="","N/A",'Alts. PPLI'!V13) -> 12348847 | K9: 4 | L9: =IF(K9="","N/A",Custom!X13) -> 12341718 | M9: =IF(K9="","N/A",'Trad. Tax.'!X13) -> 12081881 | N9: =IF(K9="","N/A",'Trad. PPLI'!X13) -> 12216895 | O9: =IF(K9="","N/A",'Alts. Tax.'!X13) -> 12134923 | P9: =IF(K9="","N/A",'Alts. PPLI'!X13) -> 12328834
A10: 5 | B10: =IF(A10="","N/A",Custom!V14) -> 13025890 | C10: =IF(A10="","N/A",'Trad. Tax.'!V14) -> 12693878 | D10: =IF(A10="","N/A",'Trad. PPLI'!V14) -> 12874803 | E10: =IF(A10="","N/A",'Alts. Tax.'!V14) -> 12758633 | F10: =IF(A10="","N/A",'Alts. PPLI'!V14) -> 13026361 | K10: 5 | L10: =IF(K10="","N/A",Custom!X14) -> 13008270 | M10: =IF(K10="","N/A",'Trad. Tax.'!X14) -> 12666838 | N10: =IF(K10="","N/A",'Trad. PPLI'!X14) -> 12844023 | O10: =IF(K10="","N/A",'Alts. Tax.'!X14) -> 12736388 | P10: =IF(K10="","N/A",'Alts. PPLI'!X14) -> 12991296
A11: 6 | B11: =IF(A11="","N/A",Custom!V15) -> 13738528 | C11: =IF(A11="","N/A",'Trad. Tax.'!V15) -> 13322560 | D11: =IF(A11="","N/A",'Trad. PPLI'!V15) -> 13551818 | E11: =IF(A11="","N/A",'Alts. Tax.'!V15) -> 13402585 | F11: =IF(A11="","N/A",'Alts. PPLI'!V15) -> 13744651 | K11: 6 | L11: =IF(K11="","N/A",Custom!X15) -> 13710820 | M11: =IF(K11="","N/A",'Trad. Tax.'!X15) -> 13280115 | N11: =IF(K11="","N/A",'Trad. PPLI'!X15) -> 13503343 | O11: =IF(K11="","N/A",'Alts. Tax.'!X15) -> 13367665 | P11: =IF(K11="","N/A",'Alts. PPLI'!X15) -> 13689355
A12: 7 | B12: =IF(A12="","N/A",Custom!V16) -> 14491980 | C12: =IF(A12="","N/A",'Trad. Tax.'!V16) -> 13985270 | D12: =IF(A12="","N/A",'Trad. PPLI'!V16) -> 14267764 | E12: =IF(A12="","N/A",'Alts. Tax.'!V16) -> 14081397 | F12: =IF(A12="","N/A",'Alts. PPLI'!V16) -> 14506314 | K12: 7 | L12: =IF(K12="","N/A",Custom!X16) -> 14451314 | M12: =IF(K12="","N/A",'Trad. Tax.'!X16) -> 13923085 | N12: =IF(K12="","N/A",'Trad. PPLI'!X16) -> 14196507 | O12: =IF(K12="","N/A",'Alts. Tax.'!X16) -> 14030230 | P12: =IF(K12="","N/A",'Alts. PPLI'!X16) -> 14424923
A13: 8 | B13: =IF(A13="","N/A",Custom!V17) -> 15288646 | C13: =IF(A13="","N/A",'Trad. Tax.'!V17) -> 14683955 | D13: =IF(A13="","N/A",'Trad. PPLI'!V17) -> 15025018 | E13: =IF(A13="","N/A",'Alts. Tax.'!V17) -> 14797041 | F13: =IF(A13="","N/A",'Alts. PPLI'!V17) -> 15314120 | K13: 8 | L13: =IF(K13="","N/A",Custom!X17) -> 15231801 | M13: =IF(K13="","N/A",'Trad. Tax.'!X17) -> 14597185 | N13: =IF(K13="","N/A",'Trad. PPLI'!X17) -> 14925253 | O13: =IF(K13="","N/A",'Alts. Tax.'!X17) -> 14725636 | P13: =IF(K13="","N/A",'Alts. PPLI'!X17) -> 15200014
A14: 9 | B14: =IF(A14="","N/A",Custom!V18) -> 16131067 | C14: =IF(A14="","N/A",'Trad. Tax.'!V18) -> 15420678 | D14: =IF(A14="","N/A",'Trad. PPLI'!V18) -> 15826105 | E14: =IF(A14="","N/A",'Alts. Tax.'!V18) -> 15551601 | F14: =IF(A14="","N/A",'Alts. PPLI'!V18) -> 16171020 | K14: 9 | L14: =IF(K14="","N/A",Custom!X18) -> 16054440 | M14: =IF(K14="","N/A",'Trad. Tax.'!X18) -> 15303923 | N14: =IF(K14="","N/A",'Trad. PPLI'!X18) -> 15691408 | O14: =IF(K14="","N/A",'Alts. Tax.'!X18) -> 15455509 | P14: =IF(K14="","N/A",'Alts. PPLI'!X18) -> 16016753
A15: 10 | B15: =IF(A15="","N/A",Custom!V19) -> 17021936 | C15: =IF(A15="","N/A",'Trad. Tax.'!V19) -> 16197623 | D15: =IF(A15="","N/A",'Trad. PPLI'!V19) -> 16673712 | E15: =IF(A15="","N/A",'Alts. Tax.'!V19) -> 16347284 | F15: =IF(A15="","N/A",'Alts. PPLI'!V19) -> 17080162 | K15: 10 | L15: =IF(K15="","N/A",Custom!X19) -> 16921508 | M15: =IF(K15="","N/A",'Trad. Tax.'!X19) -> 16044877 | N15: =IF(K15="","N/A",'Trad. PPLI'!X19) -> 16496892 | O15: =IF(K15="","N/A",'Alts. Tax.'!X19) -> 16221558 | P15: =IF(K15="","N/A",'Alts. PPLI'!X19) -> 16877378
A16: 11 | B16: =IF(A16="","N/A",Custom!V20) -> 17964107 | C16: =IF(A16="","N/A",'Trad. Tax.'!V20) -> 17017103 | D16: =IF(A16="","N/A",'Trad. PPLI'!V20) -> 17570696 | E16: =IF(A16="","N/A",'Alts. Tax.'!V20) -> 17186426 | F16: =IF(A16="","N/A",'Alts. PPLI'!V20) -> 18044900 | K16: 11 | L16: =IF(K16="","N/A",Custom!X20) -> 17835405 | M16: =IF(K16="","N/A",'Trad. Tax.'!X20) -> 16821706 | N16: =IF(K16="","N/A",'Trad. PPLI'!X20) -> 17343724 | O16: =IF(K16="","N/A",'Alts. Tax.'!X20) -> 17025577 | P16: =IF(K16="","N/A",'Alts. PPLI'!X20) -> 17784247
A17: 12 | B17: =IF(A17="","N/A",Custom!V21) -> 18960602 | C17: =IF(A17="","N/A",'Trad. Tax.'!V21) -> 17881568 | D17: =IF(A17="","N/A",'Trad. PPLI'!V21) -> 18520095 | E17: =IF(A17="","N/A",'Alts. Tax.'!V21) -> 18071498 | F17: =IF(A17="","N/A",'Alts. PPLI'!V21) -> 19068813 | K17: 12 | L17: =IF(K17="","N/A",Custom!X21) -> 18798660 | M17: =IF(K17="","N/A",'Trad. Tax.'!X21) -> 17636146 | N17: =IF(K17="","N/A",'Trad. PPLI'!X21) -> 18234026 | O17: =IF(K17="","N/A",'Alts. Tax.'!X21) -> 17869446 | P17: =IF(K17="","N/A",'Alts. PPLI'!X21) -> 18739845
A18: 13 | B18: =IF(A18="","N/A",Custom!V22) -> 20014627 | C18: =IF(A18="","N/A",'Trad. Tax.'!V22) -> 18793612 | D18: =IF(A18="","N/A",'Trad. PPLI'!V22) -> 19525142 | E18: =IF(A18="","N/A",'Alts. Tax.'!V22) -> 19005113 | F18: =IF(A18="","N/A",'Alts. PPLI'!V22) -> 20155716 | K18: 13 | L18: =IF(K18="","N/A",Custom!X22) -> 19813938 | M18: =IF(K18="","N/A",'Trad. Tax.'!X22) -> 18490017 | N18: =IF(K18="","N/A",'Trad. PPLI'!X22) -> 19170030 | O18: =IF(K18="","N/A",'Alts. Tax.'!X22) -> 18755141 | P18: =IF(K18="","N/A",'Alts. PPLI'!X22) -> 19746789
... A25: 20 | B25: =IF(A25="","N/A",Custom!V29) -> 29316021 | C25: =IF(A25="","N/A",'Trad. Tax.'!V29) -> 26762916 | D25: =IF(A25="","N/A",'Trad. PPLI'!V29) -> 28437126 | E25: =IF(A25="","N/A",'Alts. Tax.'!V29) -> 27153622 | F25: =IF(A25="","N/A",'Alts. PPLI'!V29) -> 29906035 | K25: 20 | L25: =IF(K25="","N/A",Custom!X29) -> 28633744 | M25: =IF(K25="","N/A",'Trad. Tax.'!X29) -> 25743809 | N25: =IF(K25="","N/A",'Trad. PPLI'!X29) -> 27214746 | O25: =IF(K25="","N/A",'Alts. Tax.'!X29) -> 26313895 | P25: =IF(K25="","N/A",'Alts. PPLI'!X29) -> 28484590
B26: =IF(A26="","N/A",Custom!V30) -> N/A | C26: =IF(A26="","N/A",'Trad. Tax.'!V30) -> N/A | D26: =IF(A26="","N/A",'Trad. PPLI'!V30) -> N/A | E26: =IF(A26="","N/A",'Alts. Tax.'!V30) -> N/A | F26: =IF(A26="","N/A",'Alts. PPLI'!V30) -> N/A | L26: =IF(K26="","N/A",Custom!X30) -> N/A | M26: =IF(K26="","N/A",'Trad. Tax.'!X30) -> N/A | N26: =IF(K26="","N/A",'Trad. PPLI'!X30) -> N/A | O26: =IF(K26="","N/A",'Alts. Tax.'!X30) -> N/A | P26: =IF(K26="","N/A",'Alts. PPLI'!X30) -> N/A
B27: =IF(A27="","N/A",Custom!V31) -> N/A | C27: =IF(A27="","N/A",'Trad. Tax.'!V31) -> N/A | D27: =IF(A27="","N/A",'Trad. PPLI'!V31) -> N/A | E27: =IF(A27="","N/A",'Alts. Tax.'!V31) -> N/A | F27: =IF(A27="","N/A",'Alts. PPLI'!V31) -> N/A | L27: =IF(K27="","N/A",Custom!X31) -> N/A | M27: =IF(K27="","N/A",'Trad. Tax.'!X31) -> N/A | N27: =IF(K27="","N/A",'Trad. PPLI'!X31) -> N/A | O27: =IF(K27="","N/A",'Alts. Tax.'!X31) -> N/A | P27: =IF(K27="","N/A",'Alts. PPLI'!X31) -> N/A
B28: =IF(A28="","N/A",Custom!V32) -> N/A | C28: =IF(A28="","N/A",'Trad. Tax.'!V32) -> N/A | D28: =IF(A28="","N/A",'Trad. PPLI'!V32) -> N/A | E28: =IF(A28="","N/A",'Alts. Tax.'!V32) -> N/A | F28: =IF(A28="","N/A",'Alts. PPLI'!V32) -> N/A | L28: =IF(K28="","N/A",Custom!X32) -> N/A | M28: =IF(K28="","N/A",'Trad. Tax.'!X32) -> N/A | N28: =IF(K28="","N/A",'Trad. PPLI'!X32) -> N/A | O28: =IF(K28="","N/A",'Alts. Tax.'!X32) -> N/A | P28: =IF(K28="","N/A",'Alts. PPLI'!X32) -> N/A
B29: =IF(A29="","N/A",Custom!V33) -> N/A | C29: =IF(A29="","N/A",'Trad. Tax.'!V33) -> N/A | D29: =IF(A29="","N/A",'Trad. PPLI'!V33) -> N/A | E29: =IF(A29="","N/A",'Alts. Tax.'!V33) -> N/A | F29: =IF(A29="","N/A",'Alts. PPLI'!V33) -> N/A | L29: =IF(K29="","N/A",Custom!X33) -> N/A | M29: =IF(K29="","N/A",'Trad. Tax.'!X33) -> N/A | N29: =IF(K29="","N/A",'Trad. PPLI'!X33) -> N/A | O29: =IF(K29="","N/A",'Alts. Tax.'!X33) -> N/A | P29: =IF(K29="","N/A",'Alts. PPLI'!X33) -> N/A
B30: =IF(A30="","N/A",Custom!V34) -> N/A | C30: =IF(A30="","N/A",'Trad. Tax.'!V34) -> N/A | D30: =IF(A30="","N/A",'Trad. PPLI'!V34) -> N/A | E30: =IF(A30="","N/A",'Alts. Tax.'!V34) -> N/A | F30: =IF(A30="","N/A",'Alts. PPLI'!V34) -> N/A | L30: =IF(K30="","N/A",Custom!X34) -> N/A | M30: =IF(K30="","N/A",'Trad. Tax.'!X34) -> N/A | N30: =IF(K30="","N/A",'Trad. PPLI'!X34) -> N/A | O30: =IF(K30="","N/A",'Alts. Tax.'!X34) -> N/A | P30: =IF(K30="","N/A",'Alts. PPLI'!X34) -> N/A
B31: =IF(A31="","N/A",Custom!V35) -> N/A | C31: =IF(A31="","N/A",'Trad. Tax.'!V35) -> N/A | D31: =IF(A31="","N/A",'Trad. PPLI'!V35) -> N/A | E31: =IF(A31="","N/A",'Alts. Tax.'!V35) -> N/A | F31: =IF(A31="","N/A",'Alts. PPLI'!V35) -> N/A | L31: =IF(K31="","N/A",Custom!X35) -> N/A | M31: =IF(K31="","N/A",'Trad. Tax.'!X35) -> N/A | N31: =IF(K31="","N/A",'Trad. PPLI'!X35) -> N/A | O31: =IF(K31="","N/A",'Alts. Tax.'!X35) -> N/A | P31: =IF(K31="","N/A",'Alts. PPLI'!X35) -> N/A
B32: =IF(A32="","N/A",Custom!V36) -> N/A | C32: =IF(A32="","N/A",'Trad. Tax.'!V36) -> N/A | D32: =IF(A32="","N/A",'Trad. PPLI'!V36) -> N/A | E32: =IF(A32="","N/A",'Alts. Tax.'!V36) -> N/A | F32: =IF(A32="","N/A",'Alts. PPLI'!V36) -> N/A | L32: =IF(K32="","N/A",Custom!X36) -> N/A | M32: =IF(K32="","N/A",'Trad. Tax.'!X36) -> N/A | N32: =IF(K32="","N/A",'Trad. PPLI'!X36) -> N/A | O32: =IF(K32="","N/A",'Alts. Tax.'!X36) -> N/A | P32: =IF(K32="","N/A",'Alts. PPLI'!X36) -> N/A
B33: =IF(A33="","N/A",Custom!V37) -> N/A | C33: =IF(A33="","N/A",'Trad. Tax.'!V37) -> N/A | D33: =IF(A33="","N/A",'Trad. PPLI'!V37) -> N/A | E33: =IF(A33="","N/A",'Alts. Tax.'!V37) -> N/A | F33: =IF(A33="","N/A",'Alts. PPLI'!V37) -> N/A | L33: =IF(K33="","N/A",Custom!X37) -> N/A | M33: =IF(K33="","N/A",'Trad. Tax.'!X37) -> N/A | N33: =IF(K33="","N/A",'Trad. PPLI'!X37) -> N/A | O33: =IF(K33="","N/A",'Alts. Tax.'!X37) -> N/A | P33: =IF(K33="","N/A",'Alts. PPLI'!X37) -> N/A
B34: =IF(A34="","N/A",Custom!V38) -> N/A | C34: =IF(A34="","N/A",'Trad. Tax.'!V38) -> N/A | D34: =IF(A34="","N/A",'Trad. PPLI'!V38) -> N/A | E34: =IF(A34="","N/A",'Alts. Tax.'!V38) -> N/A | F34: =IF(A34="","N/A",'Alts. PPLI'!V38) -> N/A | L34: =IF(K34="","N/A",Custom!X38) -> N/A | M34: =IF(K34="","N/A",'Trad. Tax.'!X38) -> N/A | N34: =IF(K34="","N/A",'Trad. PPLI'!X38) -> N/A | O34: =IF(K34="","N/A",'Alts. Tax.'!X38) -> N/A | P34: =IF(K34="","N/A",'Alts. PPLI'!X38) -> N/A
B35: =IF(A35="","N/A",Custom!V39) -> N/A | C35: =IF(A35="","N/A",'Trad. Tax.'!V39) -> N/A | D35: =IF(A35="","N/A",'Trad. PPLI'!V39) -> N/A | E35: =IF(A35="","N/A",'Alts. Tax.'!V39) -> N/A | F35: =IF(A35="","N/A",'Alts. PPLI'!V39) -> N/A | L35: =IF(K35="","N/A",Custom!X39) -> N/A | M35: =IF(K35="","N/A",'Trad. Tax.'!X39) -> N/A | N35: =IF(K35="","N/A",'Trad. PPLI'!X39) -> N/A | O35: =IF(K35="","N/A",'Alts. Tax.'!X39) -> N/A | P35: =IF(K35="","N/A",'Alts. PPLI'!X39) -> N/A
B36: =IF(A36="","N/A",Custom!V40) -> N/A | C36: =IF(A36="","N/A",'Trad. Tax.'!V40) -> N/A | D36: =IF(A36="","N/A",'Trad. PPLI'!V40) -> N/A | E36: =IF(A36="","N/A",'Alts. Tax.'!V40) -> N/A | F36: =IF(A36="","N/A",'Alts. PPLI'!V40) -> N/A | L36: =IF(K36="","N/A",Custom!X40) -> N/A | M36: =IF(K36="","N/A",'Trad. Tax.'!X40) -> N/A | N36: =IF(K36="","N/A",'Trad. PPLI'!X40) -> N/A | O36: =IF(K36="","N/A",'Alts. Tax.'!X40) -> N/A | P36: =IF(K36="","N/A",'Alts. PPLI'!X40) -> N/A
B37: =IF(A37="","N/A",Custom!V41) -> N/A | C37: =IF(A37="","N/A",'Trad. Tax.'!V41) -> N/A | D37: =IF(A37="","N/A",'Trad. PPLI'!V41) -> N/A | E37: =IF(A37="","N/A",'Alts. Tax.'!V41) -> N/A | F37: =IF(A37="","N/A",'Alts. PPLI'!V41) -> N/A | L37: =IF(K37="","N/A",Custom!X41) -> N/A | M37: =IF(K37="","N/A",'Trad. Tax.'!X41) -> N/A | N37: =IF(K37="","N/A",'Trad. PPLI'!X41) -> N/A | O37: =IF(K37="","N/A",'Alts. Tax.'!X41) -> N/A | P37: =IF(K37="","N/A",'Alts. PPLI'!X41) -> N/A
... B105: =IF(A105="","N/A",Custom!V109) -> N/A | C105: =IF(A105="","N/A",'Trad. Tax.'!V109) -> N/A | D105: =IF(A105="","N/A",'Trad. PPLI'!V109) -> N/A | E105: =IF(A105="","N/A",'Alts. Tax.'!V109) -> N/A | F105: =IF(A105="","N/A",'Alts. PPLI'!V109) -> N/A | L105: =IF(K105="","N/A",Custom!X109) -> N/A | M105: =IF(K105="","N/A",'Trad. Tax.'!X109) -> N/A | N105: =IF(K105="","N/A",'Trad. PPLI'!X109) -> N/A | O105: =IF(K105="","N/A",'Alts. Tax.'!X109) -> N/A | P105: =IF(K105="","N/A",'Alts. PPLI'!X109) -> N/A

Sheet Rank
A1: Buy & Hold
A2: =Page!C4 -> 20 | C2: Custom | D2: =Page!H5 -> 29316021 | E2: =Page!H14 -> 0.055249733 | F2: =_xlfn.RANK.EQ(D2,$D$2:$D$6,0) -> 2 | G2: =_xlfn.XLOOKUP(F2,$O$2:$O$6,$P$2:$P$6) -> 2nd | I2: {=_xlfn._xlws.SORT(C2:G6,2,-1)} -> Alternatives Enhanced (PPLI) | J2: 29906035 | K2: 0.056301611 | L2: 1 | M2: 1st | O2: 1 | P2: 1st
C3: Traditional (Taxable) | D3: =Page!K5 -> 26762916 | E3: =Page!K14 -> 0.050453112 | F3: =_xlfn.RANK.EQ(D3,$D$2:$D$6,0) -> 5 | G3: =_xlfn.XLOOKUP(F3,$O$2:$O$6,$P$2:$P$6) -> 5th | I3: Custom | J3: 29316021 | K3: 0.055249733 | L3: 2 | M3: 2nd | O3: 2 | P3: 2nd
C4: Traditional (PPLI) | D4: =Page!N5 -> 28437126 | E4: =Page!N14 -> 0.053644938 | F4: =_xlfn.RANK.EQ(D4,$D$2:$D$6,0) -> 3 | G4: =_xlfn.XLOOKUP(F4,$O$2:$O$6,$P$2:$P$6) -> 3rd | I4: Traditional (PPLI) | J4: 28437126 | K4: 0.053644938 | L4: 3 | M4: 3rd | O4: 3 | P4: 3rd
C5: Alternatives Enhanced (Taxable) | D5: =Page!Q5 -> 27153622 | E5: =Page!Q14 -> 0.05121461 | F5: =_xlfn.RANK.EQ(D5,$D$2:$D$6,0) -> 4 | G5: =_xlfn.XLOOKUP(F5,$O$2:$O$6,$P$2:$P$6) -> 4th | I5: Alternatives Enhanced (Taxable) | J5: 27153622 | K5: 0.05121461 | L5: 4 | M5: 4th | O5: 4 | P5: 4th
C6: Alternatives Enhanced (PPLI) | D6: =Page!T5 -> 29906035 | E6: =Page!T14 -> 0.056301611 | F6: =_xlfn.RANK.EQ(D6,$D$2:$D$6,0) -> 1 | G6: =_xlfn.XLOOKUP(F6,$O$2:$O$6,$P$2:$P$6) -> 1st | I6: Traditional (Taxable) | J6: 26762916 | K6: 0.050453112 | L6: 5 | M6: 5th | O6: 5 | P6: 5th
A9: Rebalanced
A10: =A2 -> 20 | C10: Custom | D10: =Page!W5 -> 28633744 | E10: =Page!W14 -> 0.054008 | F10: =_xlfn.RANK.EQ(D10,$D$10:$D$14,0) -> 1 | G10: =_xlfn.XLOOKUP(F10,$O$2:$O$6,$P$2:$P$6) -> 1st | I10: {=_xlfn._xlws.SORT(C10:G14,2,-1)} -> Custom | J10: 28633744 | K10: 0.054008 | L10: 1 | M10: 1st | O10: 1 | P10: 1st
C11: Traditional (Taxable) | D11: =Page!Z5 -> 25743809 | E11: =Page!Z14 -> 0.048416 | F11: =_xlfn.RANK.EQ(D11,$D$10:$D$14,0) -> 5 | G11: =_xlfn.XLOOKUP(F11,$O$2:$O$6,$P$2:$P$6) -> 5th | I11: Alternatives Enhanced (PPLI) | J11: 28484590 | K11: 0.0537328 | L11: 2 | M11: 2nd | O11: 2 | P11: 2nd
C12: Traditional (PPLI) | D12: =Page!AC5 -> 27214746 | E12: =Page!AC14 -> 0.0513328 | F12: =_xlfn.RANK.EQ(D12,$D$10:$D$14,0) -> 3 | G12: =_xlfn.XLOOKUP(F12,$O$2:$O$6,$P$2:$P$6) -> 3rd | I12: Traditional (PPLI) | J12: 27214746 | K12: 0.0513328 | L12: 3 | M12: 3rd | O12: 3 | P12: 3rd
C13: Alternatives Enhanced (Taxable) | D13: =Page!AF5 -> 26313895 | E13: =Page!AF14 -> 0.0495648 | F13: =_xlfn.RANK.EQ(D13,$D$10:$D$14,0) -> 4 | G13: =_xlfn.XLOOKUP(F13,$O$2:$O$6,$P$2:$P$6) -> 4th | I13: Alternatives Enhanced (Taxable) | J13: 26313895 | K13: 0.0495648 | L13: 4 | M13: 4th | O13: 4 | P13: 4th
C14: Alternatives Enhanced (PPLI) | D14: =Page!AI5 -> 28484590 | E14: =Page!AI14 -> 0.0537328 | F14: =_xlfn.RANK.EQ(D14,$D$10:$D$14,0) -> 2 | G14: =_xlfn.XLOOKUP(F14,$O$2:$O$6,$P$2:$P$6) -> 2nd | I14: Traditional (Taxable) | J14: 25743809 | K14: 0.048416 | L14: 5 | M14: 5th | O14: 5 | P14: 5th

Sheet Strategy Feeder >

Sheet Custom
B2: Initial Capital ($) | C2: =Page!C3 -> 10000000 | I2: Stocks (Taxable) | J2: Stocks (Taxable) | K2: Stocks (PPLI) | L2: Stocks (PPLI) | M2: Bonds (Taxable) | N2: Bonds (Taxable) | O2: Bonds (PPLI) | P2: Bonds (PPLI) | Q2: Alternatives (Taxable) | R2: Alternatives (Taxable) | S2: Alternatives (PPLI) | T2: Alternatives (PPLI) | W2: Weighted Average | X2: Weighted Average
B3: Time Horizon (Years) | C3: =Page!C4 -> 20 | H3: Weight | I3: =$D$7*(1-$E$7) -> 0.7 | J3: =$D$7*(1-$E$7) -> 0.7 | K3: =$D$7*$E$7 -> 0 | L3: =$D$7*$E$7 -> 0 | M3: =$D$8*(1-$E$8) -> 0.2 | N3: =$D$8*(1-$E$8) -> 0.2 | O3: =$D$8*$E$8 -> 0 | P3: =$D$8*$E$8 -> 0 | Q3: =$D$9*(1-$E$9) -> 0.1 | R3: =$D$9*(1-$E$9) -> 0.1 | S3: =$D$9*$E$9 -> 0 | T3: =$D$9*$E$9 -> 0 | W3: =SUM(I3,K3,M3,O3,Q3,S3) -> 1 | X3: =SUM(J3,L3,N3,P3,R3,T3) -> 1
H4: Return | I4: =$C$7 -> 0.08 | J4: =$C$7 -> 0.08 | K4: =$C$7 -> 0.08 | L4: =$C$7 -> 0.08 | M4: =$C$8 -> 0.05 | N4: =$C$8 -> 0.05 | O4: =$C$8 -> 0.05 | P4: =$C$8 -> 0.05 | Q4: =$C$9 -> 0.08 | R4: =$C$9 -> 0.08 | S4: =$C$9 -> 0.08 | T4: =$C$9 -> 0.08 | W4: =SUMPRODUCT(I3:T3,I4:T4)/2 -> 0.074 | X4: =SUMPRODUCT(I3:T3,I4:T4)/2 -> 0.074
D5: =IF(SUM(D7:D9)<>1,"Error","Good") -> Good | H5: Drag | I5: 0 | J5: =$C$7*($C$15+$C$16) -> 0.01904 | K5: 0 | L5: =$C$11 -> 0.005 | M5: 0 | N5: =$C$8*($C$14+$C$16) -> 0.0204 | O5: 0 | P5: =$C$11 -> 0.005 | Q5: 0 | R5: =(50%*$C$9*($C$14+$C$16))+(50%*$C$9*($C$15+$C$16)) -> 0.02584 | S5: 0 | T5: =$C$11 -> 0.005 | W5: 0 | X5: =SUMPRODUCT(J3:T3,J5:T5) -> 0.019992
C6: Returns | D6: Weight | E6: PPLI Allocation
B7: Stocks | C7: =Page!C12 -> 0.08 | D7: =Page!C7 -> 0.7 | E7: =Page!C22 -> 0 | U7: Buy & Hold | V7: Buy & Hold | W7: Rebalanced | X7: Rebalanced | Y7: Buy & Hold | Z7: Buy & Hold | AA7: Buy & Hold | AB7: Rebalanced | AC7: Rebalanced | AD7: Rebalanced | AE7: Buy & Hold | AF7: Buy & Hold | AG7: Buy & Hold | AH7: Rebalanced | AI7: Rebalanced | AJ7: Rebalanced | AK7: Buy & Hold | AL7: Buy & Hold | AM7: Buy & Hold | AN7: Rebalanced | AO7: Rebalanced | AP7: Rebalanced
B8: Bonds | C8: =Page!C13 -> 0.05 | D8: =Page!C8 -> 0.2 | E8: =Page!C23 -> 0 | I8: Gross | J8: Net | K8: Gross | L8: Net | M8: Gross | N8: Net | O8: Gross | P8: Net | Q8: Gross | R8: Net | S8: Gross | T8: Net | U8: Gross | V8: Net | W8: Gross | X8: Net | Y8: Gross | Z8: Net | AB8: Gross | AC8: Net | AE8: Gross | AF8: Net | AH8: Gross | AI8: Net | AK8: Gross | AL8: Net | AN8: Gross | AO8: Net
B9: Alternatives | C9: =Page!C14 -> 0.08 | D9: =Page!C9 -> 0.1 | E9: =Page!C24 -> 0 | G9: Year | H9: Contributions | I9: Stocks (Taxable) | J9: Stocks (Taxable) | K9: Stocks (PPLI) | L9: Stocks (PPLI) | M9: Bonds (Taxable) | N9: Bonds (Taxable) | O9: Bonds (PPLI) | P9: Bonds (PPLI) | Q9: Alternatives (Taxable) | R9: Alternatives (Taxable) | S9: Alternatives (PPLI) | T9: Alternatives (PPLI) | U9: Total | V9: Total | W9: Total | X9: Total | Y9: Period Return | Z9: Period Return | AA9: Period Drag | AB9: Period Return | AC9: Period Return | AD9: Period Drag | AE9: Total Return | AF9: Total Return | AG9: Total Drag | AH9: Total Return | AI9: Total Return | AJ9: Total Drag | AK9: Total Return (Annualized) | AL9: Total Return (Annualized) | AM9: Annaulized Drag | AN9: Total Return (Annualized) | AO9: Total Return (Annualized) | AP9: Annaulized Drag
G10: {=_xlfn.SEQUENCE(C3,1,1,1)} -> 1 | H10: =IF(G10="","",SUMIFS(Add_Contributions[[#All],[Amount ($)]],Add_Contributions[[#All],[Year]],G10)) -> 0 | I10: =IF($G10="","",IF($G10=1,(($C$2+$H10)*I$3)*(1+(I$4-I$5)),((I9+($H10*I$3))*(1+(I$4-I$5))))) -> 7560000 | J10: =IF($G10="","",IF($G10=1,(($C$2+$H10)*J$3)*(1+(J$4-J$5)),((J9+($H10*J$3))*(1+(J$4-J$5))))) -> 7426720 | K10: =IF($G10="","",IF($G10=1,(($C$2+$H10)*K$3)*(1+(K$4-K$5)),((K9+($H10*K$3))*(1+(K$4-K$5))))) -> 0 | L10: =IF($G10="","",IF($G10=1,(($C$2+$H10)*L$3)*(1+(L$4-L$5)),((L9+($H10*L$3))*(1+(L$4-L$5))))) -> 0 | M10: =IF($G10="","",IF($G10=1,(($C$2+$H10)*M$3)*(1+(M$4-M$5)),((M9+($H10*M$3))*(1+(M$4-M$5))))) -> 2100000 | N10: =IF($G10="","",IF($G10=1,(($C$2+$H10)*N$3)*(1+(N$4-N$5)),((N9+($H10*N$3))*(1+(N$4-N$5))))) -> 2059200 | O10: =IF($G10="","",IF($G10=1,(($C$2+$H10)*O$3)*(1+(O$4-O$5)),((O9+($H10*O$3))*(1+(O$4-O$5))))) -> 0 | P10: =IF($G10="","",IF($G10=1,(($C$2+$H10)*P$3)*(1+(P$4-P$5)),((P9+($H10*P$3))*(1+(P$4-P$5))))) -> 0 | ... T10: =IF($G10="","",IF($G10=1,(($C$2+$H10)*T$3)*(1+(T$4-T$5)),((T9+($H10*T$3))*(1+(T$4-T$5))))) -> 0 | U10: =IF(G10="","",SUM(I10,K10,M10,O10,Q10,S10)) -> 10740000 | V10: =IF(H10="","",SUM(J10,L10,N10,P10,R10,T10)) -> 10540080 | W10: =IF($G10="","",IF($G10=1,(($C$2+$H10)*W$3)*(1+(W$4-W$5)),((W9+($H10*W$3))*(1+(W$4-W$5))))) -> 10740000 | X10: =IF($G10="","",IF($G10=1,(($C$2+$H10)*X$3)*(1+(X$4-X$5)),((X9+($H10*X$3))*(1+(X$4-X$5))))) -> 10540080 | Y10: =IF($G10="","",IF($G10=1,(U10-$C$2-H10)/($C$2+H10),(U10-U9-H10)/(U9+H10))) -> 0.074 | Z10: =IF($G10="","",IF($G10=1,(V10-$C$2-H10)/($C$2+H10),(V10-V9-H10)/(V9+H10))) -> 0.054008 | AA10: =IF($G10="","",Z10-Y10) -> -0.019992 | AB10: =IF($G10="","",IF($G10=1,(W10-$C$2-H10)/($C$2+H10),(W10-W9-H10)/(W9+H10))) -> 0.074 | AC10: =IF($G10="","",IF($G10=1,(X10-$C$2-H10)/($C$2+H10),(X10-X9-H10)/(X9+H10))) -> 0.054008 | AD10: =IF($G10="","",AC10-AB10) -> -0.019992 | AE10: =IF($G10="","",IF($G10=1,Y10,(1+Y10)*(1+AE9)-1)) -> 0.074 | AF10: =IF($G10="","",IF($G10=1,Z10,(1+Z10)*(1+AF9)-1)) -> 0.054008 | AG10: =IF($G10="","",AF10-AE10) -> -0.019992 | AH10: =IF($G10="","",IF($G10=1,AB10,(1+AB10)*(1+AH9)-1)) -> 0.074 | AI10: =IF($G10="","",IF($G10=1,AC10,(1+AC10)*(1+AI9)-1)) -> 0.054008 | AJ10: =IF($G10="","",AI10-AH10) -> -0.019992 | AK10: =IF($G10="","",(1+AE10)^(1/G10)-1) -> 0.074 | AL10: =IF($G10="","",(1+AF10)^(1/G10)-1) -> 0.054008 | AM10: =IF($G10="","",AL10-AK10) -> -0.019992 | AN10: =IF($G10="","",(1+AH10)^(1/G10)-1) -> 0.074 | AO10: =IF($G10="","",(1+AI10)^(1/G10)-1) -> 0.054008 | AP10: =IF($G10="","",AO10-AN10) -> -0.019992
B11: PPLI Policy Costs | C11: =Page!C27 -> 0.005 | G11: 2 | H11: =IF(G11="","",SUMIFS(Add_Contributions[[#All],[Amount ($)]],Add_Contributions[[#All],[Year]],G11)) -> 0 | I11: =IF($G11="","",IF($G11=1,(($C$2+$H11)*I$3)*(1+(I$4-I$5)),((I10+($H11*I$3))*(1+(I$4-I$5))))) -> 8164800 | J11: =IF($G11="","",IF($G11=1,(($C$2+$H11)*J$3)*(1+(J$4-J$5)),((J10+($H11*J$3))*(1+(J$4-J$5))))) -> 7879452.9 | K11: =IF($G11="","",IF($G11=1,(($C$2+$H11)*K$3)*(1+(K$4-K$5)),((K10+($H11*K$3))*(1+(K$4-K$5))))) -> 0 | L11: =IF($G11="","",IF($G11=1,(($C$2+$H11)*L$3)*(1+(L$4-L$5)),((L10+($H11*L$3))*(1+(L$4-L$5))))) -> 0 | M11: =IF($G11="","",IF($G11=1,(($C$2+$H11)*M$3)*(1+(M$4-M$5)),((M10+($H11*M$3))*(1+(M$4-M$5))))) -> 2205000 | N11: =IF($G11="","",IF($G11=1,(($C$2+$H11)*N$3)*(1+(N$4-N$5)),((N10+($H11*N$3))*(1+(N$4-N$5))))) -> 2120152.3 | O11: =IF($G11="","",IF($G11=1,(($C$2+$H11)*O$3)*(1+(O$4-O$5)),((O10+($H11*O$3))*(1+(O$4-O$5))))) -> 0 | P11: =IF($G11="","",IF($G11=1,(($C$2+$H11)*P$3)*(1+(P$4-P$5)),((P10+($H11*P$3))*(1+(P$4-P$5))))) -> 0 | ... T11: =IF($G11="","",IF($G11=1,(($C$2+$H11)*T$3)*(1+(T$4-T$5)),((T10+($H11*T$3))*(1+(T$4-T$5))))) -> 0 | U11: =IF(G11="","",SUM(I11,K11,M11,O11,Q11,S11)) -> 11536200 | V11: =IF(H11="","",SUM(J11,L11,N11,P11,R11,T11)) -> 11110858 | W11: =IF($G11="","",IF($G11=1,(($C$2+$H11)*W$3)*(1+(W$4-W$5)),((W10+($H11*W$3))*(1+(W$4-W$5))))) -> 11534760 | X11: =IF($G11="","",IF($G11=1,(($C$2+$H11)*X$3)*(1+(X$4-X$5)),((X10+($H11*X$3))*(1+(X$4-X$5))))) -> 11109329 | Y11: =IF($G11="","",IF($G11=1,(U11-$C$2-H11)/($C$2+H11),(U11-U10-H11)/(U10+H11))) -> 0.074134078 | Z11: =IF($G11="","",IF($G11=1,(V11-$C$2-H11)/($C$2+H11),(V11-V10-H11)/(V10+H11))) -> 0.054153145 | AA11: =IF($G11="","",Z11-Y11) -> -0.019980934 | AB11: =IF($G11="","",IF($G11=1,(W11-$C$2-H11)/($C$2+H11),(W11-W10-H11)/(W10+H11))) -> 0.074 | AC11: =IF($G11="","",IF($G11=1,(X11-$C$2-H11)/($C$2+H11),(X11-X10-H11)/(X10+H11))) -> 0.054008 | AD11: =IF($G11="","",AC11-AB11) -> -0.019992 | AE11: =IF($G11="","",IF($G11=1,Y11,(1+Y11)*(1+AE10)-1)) -> 0.15362 | AF11: =IF($G11="","",IF($G11=1,Z11,(1+Z11)*(1+AF10)-1)) -> 0.11108585 | AG11: =IF($G11="","",AF11-AE11) -> -0.042534152 | AH11: =IF($G11="","",IF($G11=1,AB11,(1+AB11)*(1+AH10)-1)) -> 0.153476 | AI11: =IF($G11="","",IF($G11=1,AC11,(1+AC11)*(1+AI10)-1)) -> 0.11093286 | AJ11: =IF($G11="","",AI11-AH11) -> -0.042543136 | AK11: =IF($G11="","",(1+AE11)^(1/G11)-1) -> 0.074067037 | AL11: =IF($G11="","",(1+AF11)^(1/G11)-1) -> 0.05408057 | AM11: =IF($G11="","",AL11-AK11) -> -0.019986467 | AN11: =IF($G11="","",(1+AH11)^(1/G11)-1) -> 0.074 | AO11: =IF($G11="","",(1+AI11)^(1/G11)-1) -> 0.054008 | AP11: =IF($G11="","",AO11-AN11) -> -0.019992
B12: PPLI Start Up Costs | G12: 3 | H12: =IF(G12="","",SUMIFS(Add_Contributions[[#All],[Amount ($)]],Add_Contributions[[#All],[Year]],G12)) -> 0 | I12: =IF($G12="","",IF($G12=1,(($C$2+$H12)*I$3)*(1+(I$4-I$5)),((I11+($H12*I$3))*(1+(I$4-I$5))))) -> 8817984 | J12: =IF($G12="","",IF($G12=1,(($C$2+$H12)*J$3)*(1+(J$4-J$5)),((J11+($H12*J$3))*(1+(J$4-J$5))))) -> 8359784.3 | K12: =IF($G12="","",IF($G12=1,(($C$2+$H12)*K$3)*(1+(K$4-K$5)),((K11+($H12*K$3))*(1+(K$4-K$5))))) -> 0 | L12: =IF($G12="","",IF($G12=1,(($C$2+$H12)*L$3)*(1+(L$4-L$5)),((L11+($H12*L$3))*(1+(L$4-L$5))))) -> 0 | M12: =IF($G12="","",IF($G12=1,(($C$2+$H12)*M$3)*(1+(M$4-M$5)),((M11+($H12*M$3))*(1+(M$4-M$5))))) -> 2315250 | N12: =IF($G12="","",IF($G12=1,(($C$2+$H12)*N$3)*(1+(N$4-N$5)),((N11+($H12*N$3))*(1+(N$4-N$5))))) -> 2182908.8 | O12: =IF($G12="","",IF($G12=1,(($C$2+$H12)*O$3)*(1+(O$4-O$5)),((O11+($H12*O$3))*(1+(O$4-O$5))))) -> 0 | P12: =IF($G12="","",IF($G12=1,(($C$2+$H12)*P$3)*(1+(P$4-P$5)),((P11+($H12*P$3))*(1+(P$4-P$5))))) -> 0 | ... T12: =IF($G12="","",IF($G12=1,(($C$2+$H12)*T$3)*(1+(T$4-T$5)),((T11+($H12*T$3))*(1+(T$4-T$5))))) -> 0 | U12: =IF(G12="","",SUM(I12,K12,M12,O12,Q12,S12)) -> 12392946 | V12: =IF(H12="","",SUM(J12,L12,N12,P12,R12,T12)) -> 11714132 | W12: =IF($G12="","",IF($G12=1,(($C$2+$H12)*W$3)*(1+(W$4-W$5)),((W11+($H12*W$3))*(1+(W$4-W$5))))) -> 12388332 | X12: =IF($G12="","",IF($G12=1,(($C$2+$H12)*X$3)*(1+(X$4-X$5)),((X11+($H12*X$3))*(1+(X$4-X$5))))) -> 11709321 | Y12: =IF($G12="","",IF($G12=1,(U12-$C$2-H12)/($C$2+H12),(U12-U11-H12)/(U11+H12))) -> 0.074265876 | Z12: =IF($G12="","",IF($G12=1,(V12-$C$2-H12)/($C$2+H12),(V12-V11-H12)/(V11+H12))) -> 0.054295844 | AA12: =IF($G12="","",Z12-Y12) -> -0.019970033 | AB12: =IF($G12="","",IF($G12=1,(W12-$C$2-H12)/($C$2+H12),(W12-W11-H12)/(W11+H12))) -> 0.074 | AC12: =IF($G12="","",IF($G12=1,(X12-$C$2-H12)/($C$2+H12),(X12-X11-H12)/(X11+H12))) -> 0.054008 | AD12: =IF($G12="","",AC12-AB12) -> -0.019992 | AE12: =IF($G12="","",IF($G12=1,Y12,(1+Y12)*(1+AE11)-1)) -> 0.2392946 | AF12: =IF($G12="","",IF($G12=1,Z12,(1+Z12)*(1+AF11)-1)) -> 0.17141319 | AG12: =IF($G12="","",AF12-AE12) -> -0.067881409 | AH12: =IF($G12="","",IF($G12=1,AB12,(1+AB12)*(1+AH11)-1)) -> 0.23883322 | AI12: =IF($G12="","",IF($G12=1,AC12,(1+AC12)*(1+AI11)-1)) -> 0.17093213 | AJ12: =IF($G12="","",AI12-AH12) -> -0.067901098 | AK12: =IF($G12="","",(1+AE12)^(1/G12)-1) -> 0.074133313 | AL12: =IF($G12="","",(1+AF12)^(1/G12)-1) -> 0.054152323 | AM12: =IF($G12="","",AL12-AK12) -> -0.01998099 | AN12: =IF($G12="","",(1+AH12)^(1/G12)-1) -> 0.074 | AO12: =IF($G12="","",(1+AI12)^(1/G12)-1) -> 0.054008 | AP12: =IF($G12="","",AO12-AN12) -> -0.019992
G13: 4 | H13: =IF(G13="","",SUMIFS(Add_Contributions[[#All],[Amount ($)]],Add_Contributions[[#All],[Year]],G13)) -> 0 | I13: =IF($G13="","",IF($G13=1,(($C$2+$H13)*I$3)*(1+(I$4-I$5)),((I12+($H13*I$3))*(1+(I$4-I$5))))) -> 9523422.7 | J13: =IF($G13="","",IF($G13=1,(($C$2+$H13)*J$3)*(1+(J$4-J$5)),((J12+($H13*J$3))*(1+(J$4-J$5))))) -> 8869396.7 | K13: =IF($G13="","",IF($G13=1,(($C$2+$H13)*K$3)*(1+(K$4-K$5)),((K12+($H13*K$3))*(1+(K$4-K$5))))) -> 0 | L13: =IF($G13="","",IF($G13=1,(($C$2+$H13)*L$3)*(1+(L$4-L$5)),((L12+($H13*L$3))*(1+(L$4-L$5))))) -> 0 | M13: =IF($G13="","",IF($G13=1,(($C$2+$H13)*M$3)*(1+(M$4-M$5)),((M12+($H13*M$3))*(1+(M$4-M$5))))) -> 2431012.5 | N13: =IF($G13="","",IF($G13=1,(($C$2+$H13)*N$3)*(1+(N$4-N$5)),((N12+($H13*N$3))*(1+(N$4-N$5))))) -> 2247522.9 | O13: =IF($G13="","",IF($G13=1,(($C$2+$H13)*O$3)*(1+(O$4-O$5)),((O12+($H13*O$3))*(1+(O$4-O$5))))) -> 0 | P13: =IF($G13="","",IF($G13=1,(($C$2+$H13)*P$3)*(1+(P$4-P$5)),((P12+($H13*P$3))*(1+(P$4-P$5))))) -> 0 | ... T13: =IF($G13="","",IF($G13=1,(($C$2+$H13)*T$3)*(1+(T$4-T$5)),((T12+($H13*T$3))*(1+(T$4-T$5))))) -> 0 | U13: =IF(G13="","",SUM(I13,K13,M13,O13,Q13,S13)) -> 13314924 | V13: =IF(H13="","",SUM(J13,L13,N13,P13,R13,T13)) -> 12351804 | W13: =IF($G13="","",IF($G13=1,(($C$2+$H13)*W$3)*(1+(W$4-W$5)),((W12+($H13*W$3))*(1+(W$4-W$5))))) -> 13305069 | X13: =IF($G13="","",IF($G13=1,(($C$2+$H13)*X$3)*(1+(X$4-X$5)),((X12+($H13*X$3))*(1+(X$4-X$5))))) -> 12341718 | Y13: =IF($G13="","",IF($G13=1,(U13-$C$2-H13)/($C$2+H13),(U13-U12-H13)/(U12+H13))) -> 0.0743954 | Z13: =IF($G13="","",IF($G13=1,(V13-$C$2-H13)/($C$2+H13),(V13-V12-H13)/(V12+H13))) -> 0.054436102 | AA13: =IF($G13="","",Z13-Y13) -> -0.019959299 | AB13: =IF($G13="","",IF($G13=1,(W13-$C$2-H13)/($C$2+H13),(W13-W12-H13)/(W12+H13))) -> 0.074 | AC13: =IF($G13="","",IF($G13=1,(X13-$C$2-H13)/($C$2+H13),(X13-X12-H13)/(X12+H13))) -> 0.054008 | AD13: =IF($G13="","",AC13-AB13) -> -0.019992 | AE13: =IF($G13="","",IF($G13=1,Y13,(1+Y13)*(1+AE12)-1)) -> 0.33149242 | AF13: =IF($G13="","",IF($G13=1,Z13,(1+Z13)*(1+AF12)-1)) -> 0.23518036 | AG13: =IF($G13="","",AF13-AE13) -> -0.096312059 | AH13: =IF($G13="","",IF($G13=1,AB13,(1+AB13)*(1+AH12)-1)) -> 0.33050688 | AI13: =IF($G13="","",IF($G13=1,AC13,(1+AC13)*(1+AI12)-1)) -> 0.23417183 | AJ13: =IF($G13="","",AI13-AH13) -> -0.096335054 | AK13: =IF($G13="","",(1+AE13)^(1/G13)-1) -> 0.074198829 | AL13: =IF($G13="","",(1+AF13)^(1/G13)-1) -> 0.05422326 | AM13: =IF($G13="","",AL13-AK13) -> -0.019975568 | AN13: =IF($G13="","",(1+AH13)^(1/G13)-1) -> 0.074 | AO13: =IF($G13="","",(1+AI13)^(1/G13)-1) -> 0.054008 | AP13: =IF($G13="","",AO13-AN13) -> -0.019992
B14: Federal Income Tax | C14: =Page!C17 -> 0.37 | G14: 5 | H14: =IF(G14="","",SUMIFS(Add_Contributions[[#All],[Amount ($)]],Add_Contributions[[#All],[Year]],G14)) -> 0 | I14: =IF($G14="","",IF($G14=1,(($C$2+$H14)*I$3)*(1+(I$4-I$5)),((I13+($H14*I$3))*(1+(I$4-I$5))))) -> 10285297 | J14: =IF($G14="","",IF($G14=1,(($C$2+$H14)*J$3)*(1+(J$4-J$5)),((J13+($H14*J$3))*(1+(J$4-J$5))))) -> 9410075.2 | K14: =IF($G14="","",IF($G14=1,(($C$2+$H14)*K$3)*(1+(K$4-K$5)),((K13+($H14*K$3))*(1+(K$4-K$5))))) -> 0 | L14: =IF($G14="","",IF($G14=1,(($C$2+$H14)*L$3)*(1+(L$4-L$5)),((L13+($H14*L$3))*(1+(L$4-L$5))))) -> 0 | M14: =IF($G14="","",IF($G14=1,(($C$2+$H14)*M$3)*(1+(M$4-M$5)),((M13+($H14*M$3))*(1+(M$4-M$5))))) -> 2552563.1 | N14: =IF($G14="","",IF($G14=1,(($C$2+$H14)*N$3)*(1+(N$4-N$5)),((N13+($H14*N$3))*(1+(N$4-N$5))))) -> 2314049.6 | O14: =IF($G14="","",IF($G14=1,(($C$2+$H14)*O$3)*(1+(O$4-O$5)),((O13+($H14*O$3))*(1+(O$4-O$5))))) -> 0 | P14: =IF($G14="","",IF($G14=1,(($C$2+$H14)*P$3)*(1+(P$4-P$5)),((P13+($H14*P$3))*(1+(P$4-P$5))))) -> 0 | ... T14: =IF($G14="","",IF($G14=1,(($C$2+$H14)*T$3)*(1+(T$4-T$5)),((T13+($H14*T$3))*(1+(T$4-T$5))))) -> 0 | U14: =IF(G14="","",SUM(I14,K14,M14,O14,Q14,S14)) -> 14307188 | V14: =IF(H14="","",SUM(J14,L14,N14,P14,R14,T14)) -> 13025890 | W14: =IF($G14="","",IF($G14=1,(($C$2+$H14)*W$3)*(1+(W$4-W$5)),((W13+($H14*W$3))*(1+(W$4-W$5))))) -> 14289644 | X14: =IF($G14="","",IF($G14=1,(($C$2+$H14)*X$3)*(1+(X$4-X$5)),((X13+($H14*X$3))*(1+(X$4-X$5))))) -> 13008270 | Y14: =IF($G14="","",IF($G14=1,(U14-$C$2-H14)/($C$2+H14),(U14-U13-H14)/(U13+H14))) -> 0.074522659 | Z14: =IF($G14="","",IF($G14=1,(V14-$C$2-H14)/($C$2+H14),(V14-V13-H14)/(V13+H14))) -> 0.054573926 | AA14: =IF($G14="","",Z14-Y14) -> -0.019948733 | AB14: =IF($G14="","",IF($G14=1,(W14-$C$2-H14)/($C$2+H14),(W14-W13-H14)/(W13+H14))) -> 0.074 | AC14: =IF($G14="","",IF($G14=1,(X14-$C$2-H14)/($C$2+H14),(X14-X13-H14)/(X13+H14))) -> 0.054008 | AD14: =IF($G14="","",AC14-AB14) -> -0.019992 | AE14: =IF($G14="","",IF($G14=1,Y14,(1+Y14)*(1+AE13)-1)) -> 0.43071877 | AF14: =IF($G14="","",IF($G14=1,Z14,(1+Z14)*(1+AF13)-1)) -> 0.302589 | AG14: =IF($G14="","",AF14-AE14) -> -0.12812977 | AH14: =IF($G14="","",IF($G14=1,AB14,(1+AB14)*(1+AH13)-1)) -> 0.42896439 | AI14: =IF($G14="","",IF($G14=1,AC14,(1+AC14)*(1+AI13)-1)) -> 0.30082698 | AJ14: =IF($G14="","",AI14-AH14) -> -0.12813741 | AK14: =IF($G14="","",(1+AE14)^(1/G14)-1) -> 0.074263587 | AL14: =IF($G14="","",(1+AF14)^(1/G14)-1) -> 0.054293384 | AM14: =IF($G14="","",AL14-AK14) -> -0.019970203 | AN14: =IF($G14="","",(1+AH14)^(1/G14)-1) -> 0.074 | AO14: =IF($G14="","",(1+AI14)^(1/G14)-1) -> 0.054008 | AP14: =IF($G14="","",AO14-AN14) -> -0.019992
B15: Capital Gains Tax | C15: =Page!C18 -> 0.2 | G15: 6 | H15: =IF(G15="","",SUMIFS(Add_Contributions[[#All],[Amount ($)]],Add_Contributions[[#All],[Year]],G15)) -> 0 | I15: =IF($G15="","",IF($G15=1,(($C$2+$H15)*I$3)*(1+(I$4-I$5)),((I14+($H15*I$3))*(1+(I$4-I$5))))) -> 11108120 | J15: =IF($G15="","",IF($G15=1,(($C$2+$H15)*J$3)*(1+(J$4-J$5)),((J14+($H15*J$3))*(1+(J$4-J$5))))) -> 9983713.4 | K15: =IF($G15="","",IF($G15=1,(($C$2+$H15)*K$3)*(1+(K$4-K$5)),((K14+($H15*K$3))*(1+(K$4-K$5))))) -> 0 | L15: =IF($G15="","",IF($G15=1,(($C$2+$H15)*L$3)*(1+(L$4-L$5)),((L14+($H15*L$3))*(1+(L$4-L$5))))) -> 0 | M15: =IF($G15="","",IF($G15=1,(($C$2+$H15)*M$3)*(1+(M$4-M$5)),((M14+($H15*M$3))*(1+(M$4-M$5))))) -> 2680191.3 | N15: =IF($G15="","",IF($G15=1,(($C$2+$H15)*N$3)*(1+(N$4-N$5)),((N14+($H15*N$3))*(1+(N$4-N$5))))) -> 2382545.5 | O15: =IF($G15="","",IF($G15=1,(($C$2+$H15)*O$3)*(1+(O$4-O$5)),((O14+($H15*O$3))*(1+(O$4-O$5))))) -> 0 | P15: =IF($G15="","",IF($G15=1,(($C$2+$H15)*P$3)*(1+(P$4-P$5)),((P14+($H15*P$3))*(1+(P$4-P$5))))) -> 0 | ... T15: =IF($G15="","",IF($G15=1,(($C$2+$H15)*T$3)*(1+(T$4-T$5)),((T14+($H15*T$3))*(1+(T$4-T$5))))) -> 0 | U15: =IF(G15="","",SUM(I15,K15,M15,O15,Q15,S15)) -> 15375186 | V15: =IF(H15="","",SUM(J15,L15,N15,P15,R15,T15)) -> 13738528 | W15: =IF($G15="","",IF($G15=1,(($C$2+$H15)*W$3)*(1+(W$4-W$5)),((W14+($H15*W$3))*(1+(W$4-W$5))))) -> 15347078 | X15: =IF($G15="","",IF($G15=1,(($C$2+$H15)*X$3)*(1+(X$4-X$5)),((X14+($H15*X$3))*(1+(X$4-X$5))))) -> 13710820 | Y15: =IF($G15="","",IF($G15=1,(U15-$C$2-H15)/($C$2+H15),(U15-U14-H15)/(U14+H15))) -> 0.074647663 | Z15: =IF($G15="","",IF($G15=1,(V15-$C$2-H15)/($C$2+H15),(V15-V14-H15)/(V14+H15))) -> 0.054709325 | AA15: =IF($G15="","",Z15-Y15) -> -0.019938337 | AB15: =IF($G15="","",IF($G15=1,(W15-$C$2-H15)/($C$2+H15),(W15-W14-H15)/(W14+H15))) -> 0.074 | AC15: =IF($G15="","",IF($G15=1,(X15-$C$2-H15)/($C$2+H15),(X15-X14-H15)/(X14+H15))) -> 0.054008 | AD15: =IF($G15="","",AC15-AB15) -> -0.019992 | AE15: =IF($G15="","",IF($G15=1,Y15,(1+Y15)*(1+AE14)-1)) -> 0.53751859 | AF15: =IF($G15="","",IF($G15=1,Z15,(1+Z15)*(1+AF14)-1)) -> 0.37385277 | AG15: =IF($G15="","",AF15-AE15) -> -0.16366582 | AH15: =IF($G15="","",IF($G15=1,AB15,(1+AB15)*(1+AH14)-1)) -> 0.53470776 | AI15: =IF($G15="","",IF($G15=1,AC15,(1+AC15)*(1+AI14)-1)) -> 0.37108204 | AJ15: =IF($G15="","",AI15-AH15) -> -0.16362571 | AK15: =IF($G15="","",(1+AE15)^(1/G15)-1) -> 0.07432759 | AL15: =IF($G15="","",(1+AF15)^(1/G15)-1) -> 0.054362696 | AM15: =IF($G15="","",AL15-AK15) -> -0.019964894 | AN15: =IF($G15="","",(1+AH15)^(1/G15)-1) -> 0.074 | AO15: =IF($G15="","",(1+AI15)^(1/G15)-1) -> 0.054008 | AP15: =IF($G15="","",AO15-AN15) -> -0.019992
B16: Net Investment Income Tax | C16: =Page!C19 -> 0.038 | G16: 7 | H16: =IF(G16="","",SUMIFS(Add_Contributions[[#All],[Amount ($)]],Add_Contributions[[#All],[Year]],G16)) -> 0 | I16: =IF($G16="","",IF($G16=1,(($C$2+$H16)*I$3)*(1+(I$4-I$5)),((I15+($H16*I$3))*(1+(I$4-I$5))))) -> 11996770 | J16: =IF($G16="","",IF($G16=1,(($C$2+$H16)*J$3)*(1+(J$4-J$5)),((J15+($H16*J$3))*(1+(J$4-J$5))))) -> 10592321 | K16: =IF($G16="","",IF($G16=1,(($C$2+$H16)*K$3)*(1+(K$4-K$5)),((K15+($H16*K$3))*(1+(K$4-K$5))))) -> 0 | L16: =IF($G16="","",IF($G16=1,(($C$2+$H16)*L$3)*(1+(L$4-L$5)),((L15+($H16*L$3))*(1+(L$4-L$5))))) -> 0 | M16: =IF($G16="","",IF($G16=1,(($C$2+$H16)*M$3)*(1+(M$4-M$5)),((M15+($H16*M$3))*(1+(M$4-M$5))))) -> 2814200.8 | N16: =IF($G16="","",IF($G16=1,(($C$2+$H16)*N$3)*(1+(N$4-N$5)),((N15+($H16*N$3))*(1+(N$4-N$5))))) -> 2453068.8 | O16: =IF($G16="","",IF($G16=1,(($C$2+$H16)*O$3)*(1+(O$4-O$5)),((O15+($H16*O$3))*(1+(O$4-O$5))))) -> 0 | P16: =IF($G16="","",IF($G16=1,(($C$2+$H16)*P$3)*(1+(P$4-P$5)),((P15+($H16*P$3))*(1+(P$4-P$5))))) -> 0 | ... T16: =IF($G16="","",IF($G16=1,(($C$2+$H16)*T$3)*(1+(T$4-T$5)),((T15+($H16*T$3))*(1+(T$4-T$5))))) -> 0 | U16: =IF(G16="","",SUM(I16,K16,M16,O16,Q16,S16)) -> 16524795 | V16: =IF(H16="","",SUM(J16,L16,N16,P16,R16,T16)) -> 14491980 | W16: =IF($G16="","",IF($G16=1,(($C$2+$H16)*W$3)*(1+(W$4-W$5)),((W15+($H16*W$3))*(1+(W$4-W$5))))) -> 16482761 | X16: =IF($G16="","",IF($G16=1,(($C$2+$H16)*X$3)*(1+(X$4-X$5)),((X15+($H16*X$3))*(1+(X$4-X$5))))) -> 14451314 | Y16: =IF($G16="","",IF($G16=1,(U16-$C$2-H16)/($C$2+H16),(U16-U15-H16)/(U15+H16))) -> 0.074770422 | Z16: =IF($G16="","",IF($G16=1,(V16-$C$2-H16)/($C$2+H16),(V16-V15-H16)/(V15+H16))) -> 0.05484231 | AA16: =IF($G16="","",Z16-Y16) -> -0.019928112 | AB16: =IF($G16="","",IF($G16=1,(W16-$C$2-H16)/($C$2+H16),(W16-W15-H16)/(W15+H16))) -> 0.074 | AC16: =IF($G16="","",IF($G16=1,(X16-$C$2-H16)/($C$2+H16),(X16-X15-H16)/(X15+H16))) -> 0.054008 | AD16: =IF($G16="","",AC16-AB16) -> -0.019992 | AE16: =IF($G16="","",IF($G16=1,Y16,(1+Y16)*(1+AE15)-1)) -> 0.6524795 | AF16: =IF($G16="","",IF($G16=1,Z16,(1+Z16)*(1+AF15)-1)) -> 0.44919803 | AG16: =IF($G16="","",AF16-AE16) -> -0.20328147 | AH16: =IF($G16="","",IF($G16=1,AB16,(1+AB16)*(1+AH15)-1)) -> 0.64827613 | AI16: =IF($G16="","",IF($G16=1,AC16,(1+AC16)*(1+AI15)-1)) -> 0.44513144 | AJ16: =IF($G16="","",AI16-AH16) -> -0.20314469 | AK16: =IF($G16="","",(1+AE16)^(1/G16)-1) -> 0.074390841 | AL16: =IF($G16="","",(1+AF16)^(1/G16)-1) -> 0.054431199 | AM16: =IF($G16="","",AL16-AK16) -> -0.019959641 | AN16: =IF($G16="","",(1+AH16)^(1/G16)-1) -> 0.074 | AO16: =IF($G16="","",(1+AI16)^(1/G16)-1) -> 0.054008 | AP16: =IF($G16="","",AO16-AN16) -> -0.019992
B17: State Income Tax | G17: 8 | H17: =IF(G17="","",SUMIFS(Add_Contributions[[#All],[Amount ($)]],Add_Contributions[[#All],[Year]],G17)) -> 0 | I17: =IF($G17="","",IF($G17=1,(($C$2+$H17)*I$3)*(1+(I$4-I$5)),((I16+($H17*I$3))*(1+(I$4-I$5))))) -> 12956511 | J17: =IF($G17="","",IF($G17=1,(($C$2+$H17)*J$3)*(1+(J$4-J$5)),((J16+($H17*J$3))*(1+(J$4-J$5))))) -> 11238028 | K17: =IF($G17="","",IF($G17=1,(($C$2+$H17)*K$3)*(1+(K$4-K$5)),((K16+($H17*K$3))*(1+(K$4-K$5))))) -> 0 | L17: =IF($G17="","",IF($G17=1,(($C$2+$H17)*L$3)*(1+(L$4-L$5)),((L16+($H17*L$3))*(1+(L$4-L$5))))) -> 0 | M17: =IF($G17="","",IF($G17=1,(($C$2+$H17)*M$3)*(1+(M$4-M$5)),((M16+($H17*M$3))*(1+(M$4-M$5))))) -> 2954910.9 | N17: =IF($G17="","",IF($G17=1,(($C$2+$H17)*N$3)*(1+(N$4-N$5)),((N16+($H17*N$3))*(1+(N$4-N$5))))) -> 2525679.7 | O17: =IF($G17="","",IF($G17=1,(($C$2+$H17)*O$3)*(1+(O$4-O$5)),((O16+($H17*O$3))*(1+(O$4-O$5))))) -> 0 | P17: =IF($G17="","",IF($G17=1,(($C$2+$H17)*P$3)*(1+(P$4-P$5)),((P16+($H17*P$3))*(1+(P$4-P$5))))) -> 0 | ... T17: =IF($G17="","",IF($G17=1,(($C$2+$H17)*T$3)*(1+(T$4-T$5)),((T16+($H17*T$3))*(1+(T$4-T$5))))) -> 0 | U17: =IF(G17="","",SUM(I17,K17,M17,O17,Q17,S17)) -> 17762353 | V17: =IF(H17="","",SUM(J17,L17,N17,P17,R17,T17)) -> 15288646 | W17: =IF($G17="","",IF($G17=1,(($C$2+$H17)*W$3)*(1+(W$4-W$5)),((W16+($H17*W$3))*(1+(W$4-W$5))))) -> 17702486 | X17: =IF($G17="","",IF($G17=1,(($C$2+$H17)*X$3)*(1+(X$4-X$5)),((X16+($H17*X$3))*(1+(X$4-X$5))))) -> 15231801 | Y17: =IF($G17="","",IF($G17=1,(U17-$C$2-H17)/($C$2+H17),(U17-U16-H17)/(U16+H17))) -> 0.074890949 | Z17: =IF($G17="","",IF($G17=1,(V17-$C$2-H17)/($C$2+H17),(V17-V16-H17)/(V16+H17))) -> 0.054972892 | AA17: =IF($G17="","",Z17-Y17) -> -0.019918057 | AB17: =IF($G17="","",IF($G17=1,(W17-$C$2-H17)/($C$2+H17),(W17-W16-H17)/(W16+H17))) -> 0.074 | AC17: =IF($G17="","",IF($G17=1,(X17-$C$2-H17)/($C$2+H17),(X17-X16-H17)/(X16+H17))) -> 0.054008 | AD17: =IF($G17="","",AC17-AB17) -> -0.019992 | AE17: =IF($G17="","",IF($G17=1,Y17,(1+Y17)*(1+AE16)-1)) -> 0.77623526 | AF17: =IF($G17="","",IF($G17=1,Z17,(1+Z17)*(1+AF16)-1)) -> 0.52886463 | AG17: =IF($G17="","",AF17-AE17) -> -0.24737063 | AH17: =IF($G17="","",IF($G17=1,AB17,(1+AB17)*(1+AH16)-1)) -> 0.77024856 | AI17: =IF($G17="","",IF($G17=1,AC17,(1+AC17)*(1+AI16)-1)) -> 0.5231801 | AJ17: =IF($G17="","",AI17-AH17) -> -0.24706846 | AK17: =IF($G17="","",(1+AE17)^(1/G17)-1) -> 0.074453341 | AL17: =IF($G17="","",(1+AF17)^(1/G17)-1) -> 0.054498896 | AM17: =IF($G17="","",AL17-AK17) -> -0.019954446 | AN17: =IF($G17="","",(1+AH17)^(1/G17)-1) -> 0.074 | AO17: =IF($G17="","",(1+AI17)^(1/G17)-1) -> 0.054008 | AP17: =IF($G17="","",AO17-AN17) -> -0.019992
G18: 9 | H18: =IF(G18="","",SUMIFS(Add_Contributions[[#All],[Amount ($)]],Add_Contributions[[#All],[Year]],G18)) -> 0 | I18: =IF($G18="","",IF($G18=1,(($C$2+$H18)*I$3)*(1+(I$4-I$5)),((I17+($H18*I$3))*(1+(I$4-I$5))))) -> 13993032 | J18: =IF($G18="","",IF($G18=1,(($C$2+$H18)*J$3)*(1+(J$4-J$5)),((J17+($H18*J$3))*(1+(J$4-J$5))))) -> 11923099 | K18: =IF($G18="","",IF($G18=1,(($C$2+$H18)*K$3)*(1+(K$4-K$5)),((K17+($H18*K$3))*(1+(K$4-K$5))))) -> 0 | L18: =IF($G18="","",IF($G18=1,(($C$2+$H18)*L$3)*(1+(L$4-L$5)),((L17+($H18*L$3))*(1+(L$4-L$5))))) -> 0 | M18: =IF($G18="","",IF($G18=1,(($C$2+$H18)*M$3)*(1+(M$4-M$5)),((M17+($H18*M$3))*(1+(M$4-M$5))))) -> 3102656.4 | N18: =IF($G18="","",IF($G18=1,(($C$2+$H18)*N$3)*(1+(N$4-N$5)),((N17+($H18*N$3))*(1+(N$4-N$5))))) -> 2600439.8 | O18: =IF($G18="","",IF($G18=1,(($C$2+$H18)*O$3)*(1+(O$4-O$5)),((O17+($H18*O$3))*(1+(O$4-O$5))))) -> 0 | P18: =IF($G18="","",IF($G18=1,(($C$2+$H18)*P$3)*(1+(P$4-P$5)),((P17+($H18*P$3))*(1+(P$4-P$5))))) -> 0 | ... T18: =IF($G18="","",IF($G18=1,(($C$2+$H18)*T$3)*(1+(T$4-T$5)),((T17+($H18*T$3))*(1+(T$4-T$5))))) -> 0 | U18: =IF(G18="","",SUM(I18,K18,M18,O18,Q18,S18)) -> 19094693 | V18: =IF(H18="","",SUM(J18,L18,N18,P18,R18,T18)) -> 16131067 | W18: =IF($G18="","",IF($G18=1,(($C$2+$H18)*W$3)*(1+(W$4-W$5)),((W17+($H18*W$3))*(1+(W$4-W$5))))) -> 19012470 | X18: =IF($G18="","",IF($G18=1,(($C$2+$H18)*X$3)*(1+(X$4-X$5)),((X17+($H18*X$3))*(1+(X$4-X$5))))) -> 16054440 | Y18: =IF($G18="","",IF($G18=1,(U18-$C$2-H18)/($C$2+H18),(U18-U17-H18)/(U17+H18))) -> 0.075009258 | Z18: =IF($G18="","",IF($G18=1,(V18-$C$2-H18)/($C$2+H18),(V18-V17-H18)/(V17+H18))) -> 0.055101084 | AA18: =IF($G18="","",Z18-Y18) -> -0.019908174 | AB18: =IF($G18="","",IF($G18=1,(W18-$C$2-H18)/($C$2+H18),(W18-W17-H18)/(W17+H18))) -> 0.074 | AC18: =IF($G18="","",IF($G18=1,(X18-$C$2-H18)/($C$2+H18),(X18-X17-H18)/(X17+H18))) -> 0.054008 | AD18: =IF($G18="","",AC18-AB18) -> -0.019992 | AE18: =IF($G18="","",IF($G18=1,Y18,(1+Y18)*(1+AE17)-1)) -> 0.90946934 | AF18: =IF($G18="","",IF($G18=1,Z18,(1+Z18)*(1+AF17)-1)) -> 0.61310673 | AG18: =IF($G18="","",AF18-AE18) -> -0.29636262 | AH18: =IF($G18="","",IF($G18=1,AB18,(1+AB18)*(1+AH17)-1)) -> 0.90124696 | AI18: =IF($G18="","",IF($G18=1,AC18,(1+AC18)*(1+AI17)-1)) -> 0.60544401 | AJ18: =IF($G18="","",AI18-AH18) -> -0.29580295 | AK18: =IF($G18="","",(1+AE18)^(1/G18)-1) -> 0.074515096 | AL18: =IF($G18="","",(1+AF18)^(1/G18)-1) -> 0.054565788 | AM18: =IF($G18="","",AL18-AK18) -> -0.019949307 | AN18: =IF($G18="","",(1+AH18)^(1/G18)-1) -> 0.074 | AO18: =IF($G18="","",(1+AI18)^(1/G18)-1) -> 0.054008 | AP18: =IF($G18="","",AO18-AN18) -> -0.019992
G19: 10 | H19: =IF(G19="","",SUMIFS(Add_Contributions[[#All],[Amount ($)]],Add_Contributions[[#All],[Year]],G19)) -> 0 | I19: =IF($G19="","",IF($G19=1,(($C$2+$H19)*I$3)*(1+(I$4-I$5)),((I18+($H19*I$3))*(1+(I$4-I$5))))) -> 15112475 | J19: =IF($G19="","",IF($G19=1,(($C$2+$H19)*J$3)*(1+(J$4-J$5)),((J18+($H19*J$3))*(1+(J$4-J$5))))) -> 12649931 | K19: =IF($G19="","",IF($G19=1,(($C$2+$H19)*K$3)*(1+(K$4-K$5)),((K18+($H19*K$3))*(1+(K$4-K$5))))) -> 0 | L19: =IF($G19="","",IF($G19=1,(($C$2+$H19)*L$3)*(1+(L$4-L$5)),((L18+($H19*L$3))*(1+(L$4-L$5))))) -> 0 | M19: =IF($G19="","",IF($G19=1,(($C$2+$H19)*M$3)*(1+(M$4-M$5)),((M18+($H19*M$3))*(1+(M$4-M$5))))) -> 3257789.3 | N19: =IF($G19="","",IF($G19=1,(($C$2+$H19)*N$3)*(1+(N$4-N$5)),((N18+($H19*N$3))*(1+(N$4-N$5))))) -> 2677412.8 | O19: =IF($G19="","",IF($G19=1,(($C$2+$H19)*O$3)*(1+(O$4-O$5)),((O18+($H19*O$3))*(1+(O$4-O$5))))) -> 0 | P19: =IF($G19="","",IF($G19=1,(($C$2+$H19)*P$3)*(1+(P$4-P$5)),((P18+($H19*P$3))*(1+(P$4-P$5))))) -> 0 | ... T19: =IF($G19="","",IF($G19=1,(($C$2+$H19)*T$3)*(1+(T$4-T$5)),((T18+($H19*T$3))*(1+(T$4-T$5))))) -> 0 | U19: =IF(G19="","",SUM(I19,K19,M19,O19,Q19,S19)) -> 20529189 | V19: =IF(H19="","",SUM(J19,L19,N19,P19,R19,T19)) -> 17021936 | W19: =IF($G19="","",IF($G19=1,(($C$2+$H19)*W$3)*(1+(W$4-W$5)),((W18+($H19*W$3))*(1+(W$4-W$5))))) -> 20419392 | X19: =IF($G19="","",IF($G19=1,(($C$2+$H19)*X$3)*(1+(X$4-X$5)),((X18+($H19*X$3))*(1+(X$4-X$5))))) -> 16921508 | Y19: =IF($G19="","",IF($G19=1,(U19-$C$2-H19)/($C$2+H19),(U19-U18-H19)/(U18+H19))) -> 0.075125363 | Z19: =IF($G19="","",IF($G19=1,(V19-$C$2-H19)/($C$2+H19),(V19-V18-H19)/(V18+H19))) -> 0.055226902 | AA19: =IF($G19="","",Z19-Y19) -> -0.019898461 | AB19: =IF($G19="","",IF($G19=1,(W19-$C$2-H19)/($C$2+H19),(W19-W18-H19)/(W18+H19))) -> 0.074 | AC19: =IF($G19="","",IF($G19=1,(X19-$C$2-H19)/($C$2+H19),(X19-X18-H19)/(X18+H19))) -> 0.054008 | AD19: =IF($G19="","",AC19-AB19) -> -0.019992 | AE19: =IF($G19="","",IF($G19=1,Y19,(1+Y19)*(1+AE18)-1)) -> 1.0529189 | AF19: =IF($G19="","",IF($G19=1,Z19,(1+Z19)*(1+AF18)-1)) -> 0.70219362 | AG19: =IF($G19="","",AF19-AE19) -> -0.35072531 | AH19: =IF($G19="","",IF($G19=1,AB19,(1+AB19)*(1+AH18)-1)) -> 1.0419392 | AI19: =IF($G19="","",IF($G19=1,AC19,(1+AC19)*(1+AI18)-1)) -> 0.69215083 | AJ19: =IF($G19="","",AI19-AH19) -> -0.3497884 | AK19: =IF($G19="","",(1+AE19)^(1/G19)-1) -> 0.074576107 | AL19: =IF($G19="","",(1+AF19)^(1/G19)-1) -> 0.054631881 | AM19: =IF($G19="","",AL19-AK19) -> -0.019944226 | AN19: =IF($G19="","",(1+AH19)^(1/G19)-1) -> 0.074 | AO19: =IF($G19="","",(1+AI19)^(1/G19)-1) -> 0.054008 | AP19: =IF($G19="","",AO19-AN19) -> -0.019992
G20: 11 | H20: =IF(G20="","",SUMIFS(Add_Contributions[[#All],[Amount ($)]],Add_Contributions[[#All],[Year]],G20)) -> 0 | I20: =IF($G20="","",IF($G20=1,(($C$2+$H20)*I$3)*(1+(I$4-I$5)),((I19+($H20*I$3))*(1+(I$4-I$5))))) -> 16321473 | J20: =IF($G20="","",IF($G20=1,(($C$2+$H20)*J$3)*(1+(J$4-J$5)),((J19+($H20*J$3))*(1+(J$4-J$5))))) -> 13421070 | K20: =IF($G20="","",IF($G20=1,(($C$2+$H20)*K$3)*(1+(K$4-K$5)),((K19+($H20*K$3))*(1+(K$4-K$5))))) -> 0 | L20: =IF($G20="","",IF($G20=1,(($C$2+$H20)*L$3)*(1+(L$4-L$5)),((L19+($H20*L$3))*(1+(L$4-L$5))))) -> 0 | M20: =IF($G20="","",IF($G20=1,(($C$2+$H20)*M$3)*(1+(M$4-M$5)),((M19+($H20*M$3))*(1+(M$4-M$5))))) -> 3420678.7 | N20: =IF($G20="","",IF($G20=1,(($C$2+$H20)*N$3)*(1+(N$4-N$5)),((N19+($H20*N$3))*(1+(N$4-N$5))))) -> 2756664.2 | O20: =IF($G20="","",IF($G20=1,(($C$2+$H20)*O$3)*(1+(O$4-O$5)),((O19+($H20*O$3))*(1+(O$4-O$5))))) -> 0 | P20: =IF($G20="","",IF($G20=1,(($C$2+$H20)*P$3)*(1+(P$4-P$5)),((P19+($H20*P$3))*(1+(P$4-P$5))))) -> 0 | ... T20: =IF($G20="","",IF($G20=1,(($C$2+$H20)*T$3)*(1+(T$4-T$5)),((T19+($H20*T$3))*(1+(T$4-T$5))))) -> 0 | U20: =IF(G20="","",SUM(I20,K20,M20,O20,Q20,S20)) -> 22073791 | V20: =IF(H20="","",SUM(J20,L20,N20,P20,R20,T20)) -> 17964107 | W20: =IF($G20="","",IF($G20=1,(($C$2+$H20)*W$3)*(1+(W$4-W$5)),((W19+($H20*W$3))*(1+(W$4-W$5))))) -> 21930427 | X20: =IF($G20="","",IF($G20=1,(($C$2+$H20)*X$3)*(1+(X$4-X$5)),((X19+($H20*X$3))*(1+(X$4-X$5))))) -> 17835405 | Y20: =IF($G20="","",IF($G20=1,(U20-$C$2-H20)/($C$2+H20),(U20-U19-H20)/(U19+H20))) -> 0.075239282 | Z20: =IF($G20="","",IF($G20=1,(V20-$C$2-H20)/($C$2+H20),(V20-V19-H20)/(V19+H20))) -> 0.055350362 | AA20: =IF($G20="","",Z20-Y20) -> -0.01988892 | AB20: =IF($G20="","",IF($G20=1,(W20-$C$2-H20)/($C$2+H20),(W20-W19-H20)/(W19+H20))) -> 0.074 | AC20: =IF($G20="","",IF($G20=1,(X20-$C$2-H20)/($C$2+H20),(X20-X19-H20)/(X19+H20))) -> 0.054008 | AD20: =IF($G20="","",AC20-AB20) -> -0.019992 | AE20: =IF($G20="","",IF($G20=1,Y20,(1+Y20)*(1+AE19)-1)) -> 1.2073791 | AF20: =IF($G20="","",IF($G20=1,Z20,(1+Z20)*(1+AF19)-1)) -> 0.79641065 | AG20: =IF($G20="","",AF20-AE20) -> -0.41096842 | AH20: =IF($G20="","",IF($G20=1,AB20,(1+AB20)*(1+AH19)-1)) -> 1.1930427 | AI20: =IF($G20="","",IF($G20=1,AC20,(1+AC20)*(1+AI19)-1)) -> 0.78354052 | AJ20: =IF($G20="","",AI20-AH20) -> -0.40950222 | AK20: =IF($G20="","",(1+AE20)^(1/G20)-1) -> 0.074636379 | AL20: =IF($G20="","",(1+AF20)^(1/G20)-1) -> 0.054697177 | AM20: =IF($G20="","",AL20-AK20) -> -0.019939201 | AN20: =IF($G20="","",(1+AH20)^(1/G20)-1) -> 0.074 | AO20: =IF($G20="","",(1+AI20)^(1/G20)-1) -> 0.054008 | AP20: =IF($G20="","",AO20-AN20) -> -0.019992
B21: Metrics | C21: Buy & Hold | D21: Rebalanced | G21: 12 | H21: =IF(G21="","",SUMIFS(Add_Contributions[[#All],[Amount ($)]],Add_Contributions[[#All],[Year]],G21)) -> 0 | I21: =IF($G21="","",IF($G21=1,(($C$2+$H21)*I$3)*(1+(I$4-I$5)),((I20+($H21*I$3))*(1+(I$4-I$5))))) -> 17627191 | J21: =IF($G21="","",IF($G21=1,(($C$2+$H21)*J$3)*(1+(J$4-J$5)),((J20+($H21*J$3))*(1+(J$4-J$5))))) -> 14239219 | K21: =IF($G21="","",IF($G21=1,(($C$2+$H21)*K$3)*(1+(K$4-K$5)),((K20+($H21*K$3))*(1+(K$4-K$5))))) -> 0 | L21: =IF($G21="","",IF($G21=1,(($C$2+$H21)*L$3)*(1+(L$4-L$5)),((L20+($H21*L$3))*(1+(L$4-L$5))))) -> 0 | M21: =IF($G21="","",IF($G21=1,(($C$2+$H21)*M$3)*(1+(M$4-M$5)),((M20+($H21*M$3))*(1+(M$4-M$5))))) -> 3591712.7 | N21: =IF($G21="","",IF($G21=1,(($C$2+$H21)*N$3)*(1+(N$4-N$5)),((N20+($H21*N$3))*(1+(N$4-N$5))))) -> 2838261.5 | O21: =IF($G21="","",IF($G21=1,(($C$2+$H21)*O$3)*(1+(O$4-O$5)),((O20+($H21*O$3))*(1+(O$4-O$5))))) -> 0 | P21: =IF($G21="","",IF($G21=1,(($C$2+$H21)*P$3)*(1+(P$4-P$5)),((P20+($H21*P$3))*(1+(P$4-P$5))))) -> 0 | ... T21: =IF($G21="","",IF($G21=1,(($C$2+$H21)*T$3)*(1+(T$4-T$5)),((T20+($H21*T$3))*(1+(T$4-T$5))))) -> 0 | U21: =IF(G21="","",SUM(I21,K21,M21,O21,Q21,S21)) -> 23737074 | V21: =IF(H21="","",SUM(J21,L21,N21,P21,R21,T21)) -> 18960602 | W21: =IF($G21="","",IF($G21=1,(($C$2+$H21)*W$3)*(1+(W$4-W$5)),((W20+($H21*W$3))*(1+(W$4-W$5))))) -> 23553279 | X21: =IF($G21="","",IF($G21=1,(($C$2+$H21)*X$3)*(1+(X$4-X$5)),((X20+($H21*X$3))*(1+(X$4-X$5))))) -> 18798660 | Y21: =IF($G21="","",IF($G21=1,(U21-$C$2-H21)/($C$2+H21),(U21-U20-H21)/(U20+H21))) -> 0.075351031 | Z21: =IF($G21="","",IF($G21=1,(V21-$C$2-H21)/($C$2+H21),(V21-V20-H21)/(V20+H21))) -> 0.055471482 | AA21: =IF($G21="","",Z21-Y21) -> -0.019879549 | AB21: =IF($G21="","",IF($G21=1,(W21-$C$2-H21)/($C$2+H21),(W21-W20-H21)/(W20+H21))) -> 0.074 | AC21: =IF($G21="","",IF($G21=1,(X21-$C$2-H21)/($C$2+H21),(X21-X20-H21)/(X20+H21))) -> 0.054008 | AD21: =IF($G21="","",AC21-AB21) -> -0.019992 | AE21: =IF($G21="","",IF($G21=1,Y21,(1+Y21)*(1+AE20)-1)) -> 1.3737074 | AF21: =IF($G21="","",IF($G21=1,Z21,(1+Z21)*(1+AF20)-1)) -> 0.89606021 | AG21: =IF($G21="","",AF21-AE21) -> -0.47764715 | AH21: =IF($G21="","",IF($G21=1,AB21,(1+AB21)*(1+AH20)-1)) -> 1.3553279 | AI21: =IF($G21="","",IF($G21=1,AC21,(1+AC21)*(1+AI20)-1)) -> 0.87986597 | AJ21: =IF($G21="","",AI21-AH21) -> -0.47546193 | AK21: =IF($G21="","",(1+AE21)^(1/G21)-1) -> 0.074695915 | AL21: =IF($G21="","",(1+AF21)^(1/G21)-1) -> 0.054761681 | AM21: =IF($G21="","",AL21-AK21) -> -0.019934234 | AN21: =IF($G21="","",(1+AH21)^(1/G21)-1) -> 0.074 | AO21: =IF($G21="","",(1+AI21)^(1/G21)-1) -> 0.054008 | AP21: =IF($G21="","",AO21-AN21) -> -0.019992
B22: Projected Value | C22: =_xlfn.XLOOKUP(C3,G:G,V:V) -> 29316021 | D22: =_xlfn.XLOOKUP(C3,G:G,X:X) -> 28633744 | G22: 13 | H22: =IF(G22="","",SUMIFS(Add_Contributions[[#All],[Amount ($)]],Add_Contributions[[#All],[Year]],G22)) -> 0 | I22: =IF($G22="","",IF($G22=1,(($C$2+$H22)*I$3)*(1+(I$4-I$5)),((I21+($H22*I$3))*(1+(I$4-I$5))))) -> 19037366 | J22: =IF($G22="","",IF($G22=1,(($C$2+$H22)*J$3)*(1+(J$4-J$5)),((J21+($H22*J$3))*(1+(J$4-J$5))))) -> 15107242 | K22: =IF($G22="","",IF($G22=1,(($C$2+$H22)*K$3)*(1+(K$4-K$5)),((K21+($H22*K$3))*(1+(K$4-K$5))))) -> 0 | L22: =IF($G22="","",IF($G22=1,(($C$2+$H22)*L$3)*(1+(L$4-L$5)),((L21+($H22*L$3))*(1+(L$4-L$5))))) -> 0 | M22: =IF($G22="","",IF($G22=1,(($C$2+$H22)*M$3)*(1+(M$4-M$5)),((M21+($H22*M$3))*(1+(M$4-M$5))))) -> 3771298.3 | N22: =IF($G22="","",IF($G22=1,(($C$2+$H22)*N$3)*(1+(N$4-N$5)),((N21+($H22*N$3))*(1+(N$4-N$5))))) -> 2922274 | O22: =IF($G22="","",IF($G22=1,(($C$2+$H22)*O$3)*(1+(O$4-O$5)),((O21+($H22*O$3))*(1+(O$4-O$5))))) -> 0 | P22: =IF($G22="","",IF($G22=1,(($C$2+$H22)*P$3)*(1+(P$4-P$5)),((P21+($H22*P$3))*(1+(P$4-P$5))))) -> 0 | ... T22: =IF($G22="","",IF($G22=1,(($C$2+$H22)*T$3)*(1+(T$4-T$5)),((T21+($H22*T$3))*(1+(T$4-T$5))))) -> 0 | U22: =IF(G22="","",SUM(I22,K22,M22,O22,Q22,S22)) -> 25528288 | V22: =IF(H22="","",SUM(J22,L22,N22,P22,R22,T22)) -> 20014627 | W22: =IF($G22="","",IF($G22=1,(($C$2+$H22)*W$3)*(1+(W$4-W$5)),((W21+($H22*W$3))*(1+(W$4-W$5))))) -> 25296222 | X22: =IF($G22="","",IF($G22=1,(($C$2+$H22)*X$3)*(1+(X$4-X$5)),((X21+($H22*X$3))*(1+(X$4-X$5))))) -> 19813938 | Y22: =IF($G22="","",IF($G22=1,(U22-$C$2-H22)/($C$2+H22),(U22-U21-H22)/(U21+H22))) -> 0.075460629 | Z22: =IF($G22="","",IF($G22=1,(V22-$C$2-H22)/($C$2+H22),(V22-V21-H22)/(V21+H22))) -> 0.055590281 | AA22: =IF($G22="","",Z22-Y22) -> -0.019870348 | AB22: =IF($G22="","",IF($G22=1,(W22-$C$2-H22)/($C$2+H22),(W22-W21-H22)/(W21+H22))) -> 0.074 | AC22: =IF($G22="","",IF($G22=1,(X22-$C$2-H22)/($C$2+H22),(X22-X21-H22)/(X21+H22))) -> 0.054008 | AD22: =IF($G22="","",AC22-AB22) -> -0.019992 | AE22: =IF($G22="","",IF($G22=1,Y22,(1+Y22)*(1+AE21)-1)) -> 1.5528288 | AF22: =IF($G22="","",IF($G22=1,Z22,(1+Z22)*(1+AF21)-1)) -> 1.0014627 | AG22: =IF($G22="","",AF22-AE22) -> -0.55136608 | AH22: =IF($G22="","",IF($G22=1,AB22,(1+AB22)*(1+AH21)-1)) -> 1.5296222 | AI22: =IF($G22="","",IF($G22=1,AC22,(1+AC22)*(1+AI21)-1)) -> 0.98139377 | AJ22: =IF($G22="","",AI22-AH22) -> -0.54822839 | AK22: =IF($G22="","",(1+AE22)^(1/G22)-1) -> 0.07475472 | AL22: =IF($G22="","",(1+AF22)^(1/G22)-1) -> 0.054825396 | AM22: =IF($G22="","",AL22-AK22) -> -0.019929323 | AN22: =IF($G22="","",(1+AH22)^(1/G22)-1) -> 0.074 | AO22: =IF($G22="","",(1+AI22)^(1/G22)-1) -> 0.054008 | AP22: =IF($G22="","",AO22-AN22) -> -0.019992
G23: 14 | H23: =IF(G23="","",SUMIFS(Add_Contributions[[#All],[Amount ($)]],Add_Contributions[[#All],[Year]],G23)) -> 0 | I23: =IF($G23="","",IF($G23=1,(($C$2+$H23)*I$3)*(1+(I$4-I$5)),((I22+($H23*I$3))*(1+(I$4-I$5))))) -> 20560355 | J23: =IF($G23="","",IF($G23=1,(($C$2+$H23)*J$3)*(1+(J$4-J$5)),((J22+($H23*J$3))*(1+(J$4-J$5))))) -> 16028179 | K23: =IF($G23="","",IF($G23=1,(($C$2+$H23)*K$3)*(1+(K$4-K$5)),((K22+($H23*K$3))*(1+(K$4-K$5))))) -> 0 | L23: =IF($G23="","",IF($G23=1,(($C$2+$H23)*L$3)*(1+(L$4-L$5)),((L22+($H23*L$3))*(1+(L$4-L$5))))) -> 0 | M23: =IF($G23="","",IF($G23=1,(($C$2+$H23)*M$3)*(1+(M$4-M$5)),((M22+($H23*M$3))*(1+(M$4-M$5))))) -> 3959863.2 | N23: =IF($G23="","",IF($G23=1,(($C$2+$H23)*N$3)*(1+(N$4-N$5)),((N22+($H23*N$3))*(1+(N$4-N$5))))) -> 3008773.3 | O23: =IF($G23="","",IF($G23=1,(($C$2+$H23)*O$3)*(1+(O$4-O$5)),((O22+($H23*O$3))*(1+(O$4-O$5))))) -> 0 | P23: =IF($G23="","",IF($G23=1,(($C$2+$H23)*P$3)*(1+(P$4-P$5)),((P22+($H23*P$3))*(1+(P$4-P$5))))) -> 0 | ... T23: =IF($G23="","",IF($G23=1,(($C$2+$H23)*T$3)*(1+(T$4-T$5)),((T22+($H23*T$3))*(1+(T$4-T$5))))) -> 0 | U23: =IF(G23="","",SUM(I23,K23,M23,O23,Q23,S23)) -> 27457412 | V23: =IF(H23="","",SUM(J23,L23,N23,P23,R23,T23)) -> 21129578 | W23: =IF($G23="","",IF($G23=1,(($C$2+$H23)*W$3)*(1+(W$4-W$5)),((W22+($H23*W$3))*(1+(W$4-W$5))))) -> 27168142 | X23: =IF($G23="","",IF($G23=1,(($C$2+$H23)*X$3)*(1+(X$4-X$5)),((X22+($H23*X$3))*(1+(X$4-X$5))))) -> 20884049 | Y23: =IF($G23="","",IF($G23=1,(U23-$C$2-H23)/($C$2+H23),(U23-U22-H23)/(U22+H23))) -> 0.075568095 | Z23: =IF($G23="","",IF($G23=1,(V23-$C$2-H23)/($C$2+H23),(V23-V22-H23)/(V22+H23))) -> 0.055706778 | AA23: =IF($G23="","",Z23-Y23) -> -0.019861317 | AB23: =IF($G23="","",IF($G23=1,(W23-$C$2-H23)/($C$2+H23),(W23-W22-H23)/(W22+H23))) -> 0.074 | AC23: =IF($G23="","",IF($G23=1,(X23-$C$2-H23)/($C$2+H23),(X23-X22-H23)/(X22+H23))) -> 0.054008 | AD23: =IF($G23="","",AC23-AB23) -> -0.019992 | AE23: =IF($G23="","",IF($G23=1,Y23,(1+Y23)*(1+AE22)-1)) -> 1.7457412 | AF23: =IF($G23="","",IF($G23=1,Z23,(1+Z23)*(1+AF22)-1)) -> 1.1129578 | AG23: =IF($G23="","",AF23-AE23) -> -0.63278345 | AH23: =IF($G23="","",IF($G23=1,AB23,(1+AB23)*(1+AH22)-1)) -> 1.7168142 | AI23: =IF($G23="","",IF($G23=1,AC23,(1+AC23)*(1+AI22)-1)) -> 1.0884049 | AJ23: =IF($G23="","",AI23-AH23) -> -0.62840932 | AK23: =IF($G23="","",(1+AE23)^(1/G23)-1) -> 0.074812797 | AL23: =IF($G23="","",(1+AF23)^(1/G23)-1) -> 0.054888328 | AM23: =IF($G23="","",AL23-AK23) -> -0.01992447 | AN23: =IF($G23="","",(1+AH23)^(1/G23)-1) -> 0.074 | AO23: =IF($G23="","",(1+AI23)^(1/G23)-1) -> 0.054008 | AP23: =IF($G23="","",AO23-AN23) -> -0.019992
B24: Total Return (Gross) | C24: =_xlfn.XLOOKUP(C3,G:G,AE:AE) -> 3.2594253 | D24: =_xlfn.XLOOKUP(C3,G:G,AH:AH) -> 3.1695158 | G24: 15 | H24: =IF(G24="","",SUMIFS(Add_Contributions[[#All],[Amount ($)]],Add_Contributions[[#All],[Year]],G24)) -> 0 | I24: =IF($G24="","",IF($G24=1,(($C$2+$H24)*I$3)*(1+(I$4-I$5)),((I23+($H24*I$3))*(1+(I$4-I$5))))) -> 22205184 | J24: =IF($G24="","",IF($G24=1,(($C$2+$H24)*J$3)*(1+(J$4-J$5)),((J23+($H24*J$3))*(1+(J$4-J$5))))) -> 17005257 | K24: =IF($G24="","",IF($G24=1,(($C$2+$H24)*K$3)*(1+(K$4-K$5)),((K23+($H24*K$3))*(1+(K$4-K$5))))) -> 0 | L24: =IF($G24="","",IF($G24=1,(($C$2+$H24)*L$3)*(1+(L$4-L$5)),((L23+($H24*L$3))*(1+(L$4-L$5))))) -> 0 | M24: =IF($G24="","",IF($G24=1,(($C$2+$H24)*M$3)*(1+(M$4-M$5)),((M23+($H24*M$3))*(1+(M$4-M$5))))) -> 4157856.4 | N24: =IF($G24="","",IF($G24=1,(($C$2+$H24)*N$3)*(1+(N$4-N$5)),((N23+($H24*N$3))*(1+(N$4-N$5))))) -> 3097833 | O24: =IF($G24="","",IF($G24=1,(($C$2+$H24)*O$3)*(1+(O$4-O$5)),((O23+($H24*O$3))*(1+(O$4-O$5))))) -> 0 | P24: =IF($G24="","",IF($G24=1,(($C$2+$H24)*P$3)*(1+(P$4-P$5)),((P23+($H24*P$3))*(1+(P$4-P$5))))) -> 0 | ... T24: =IF($G24="","",IF($G24=1,(($C$2+$H24)*T$3)*(1+(T$4-T$5)),((T23+($H24*T$3))*(1+(T$4-T$5))))) -> 0 | U24: =IF(G24="","",SUM(I24,K24,M24,O24,Q24,S24)) -> 29535209 | V24: =IF(H24="","",SUM(J24,L24,N24,P24,R24,T24)) -> 22309052 | W24: =IF($G24="","",IF($G24=1,(($C$2+$H24)*W$3)*(1+(W$4-W$5)),((W23+($H24*W$3))*(1+(W$4-W$5))))) -> 29178585 | X24: =IF($G24="","",IF($G24=1,(($C$2+$H24)*X$3)*(1+(X$4-X$5)),((X23+($H24*X$3))*(1+(X$4-X$5))))) -> 22011955 | Y24: =IF($G24="","",IF($G24=1,(U24-$C$2-H24)/($C$2+H24),(U24-U23-H24)/(U23+H24))) -> 0.075673449 | Z24: =IF($G24="","",IF($G24=1,(V24-$C$2-H24)/($C$2+H24),(V24-V23-H24)/(V23+H24))) -> 0.055820996 | AA24: =IF($G24="","",Z24-Y24) -> -0.019852453 | AB24: =IF($G24="","",IF($G24=1,(W24-$C$2-H24)/($C$2+H24),(W24-W23-H24)/(W23+H24))) -> 0.074 | AC24: =IF($G24="","",IF($G24=1,(X24-$C$2-H24)/($C$2+H24),(X24-X23-H24)/(X23+H24))) -> 0.054008 | AD24: =IF($G24="","",AC24-AB24) -> -0.019992 | AE24: =IF($G24="","",IF($G24=1,Y24,(1+Y24)*(1+AE23)-1)) -> 1.9535209 | AF24: =IF($G24="","",IF($G24=1,Z24,(1+Z24)*(1+AF23)-1)) -> 1.2309052 | AG24: =IF($G24="","",AF24-AE24) -> -0.72261575 | AH24: =IF($G24="","",IF($G24=1,AB24,(1+AB24)*(1+AH23)-1)) -> 1.9178585 | AI24: =IF($G24="","",IF($G24=1,AC24,(1+AC24)*(1+AI23)-1)) -> 1.2011955 | AJ24: =IF($G24="","",AI24-AH24) -> -0.716663 | AK24: =IF($G24="","",(1+AE24)^(1/G24)-1) -> 0.074870153 | AL24: =IF($G24="","",(1+AF24)^(1/G24)-1) -> 0.05495048 | AM24: =IF($G24="","",AL24-AK24) -> -0.019919673 | AN24: =IF($G24="","",(1+AH24)^(1/G24)-1) -> 0.074 | AO24: =IF($G24="","",(1+AI24)^(1/G24)-1) -> 0.054008 | AP24: =IF($G24="","",AO24-AN24) -> -0.019992
B25: Total Return (Net) | C25: =_xlfn.XLOOKUP(C3,G:G,AF:AF) -> 1.9316021 | D25: =_xlfn.XLOOKUP(C3,G:G,AI:AI) -> 1.8633744 | G25: 16 | H25: =IF(G25="","",SUMIFS(Add_Contributions[[#All],[Amount ($)]],Add_Contributions[[#All],[Year]],G25)) -> 0 | I25: =IF($G25="","",IF($G25=1,(($C$2+$H25)*I$3)*(1+(I$4-I$5)),((I24+($H25*I$3))*(1+(I$4-I$5))))) -> 23981599 | J25: =IF($G25="","",IF($G25=1,(($C$2+$H25)*J$3)*(1+(J$4-J$5)),((J24+($H25*J$3))*(1+(J$4-J$5))))) -> 18041897 | K25: =IF($G25="","",IF($G25=1,(($C$2+$H25)*K$3)*(1+(K$4-K$5)),((K24+($H25*K$3))*(1+(K$4-K$5))))) -> 0 | L25: =IF($G25="","",IF($G25=1,(($C$2+$H25)*L$3)*(1+(L$4-L$5)),((L24+($H25*L$3))*(1+(L$4-L$5))))) -> 0 | M25: =IF($G25="","",IF($G25=1,(($C$2+$H25)*M$3)*(1+(M$4-M$5)),((M24+($H25*M$3))*(1+(M$4-M$5))))) -> 4365749.2 | N25: =IF($G25="","",IF($G25=1,(($C$2+$H25)*N$3)*(1+(N$4-N$5)),((N24+($H25*N$3))*(1+(N$4-N$5))))) -> 3189528.9 | O25: =IF($G25="","",IF($G25=1,(($C$2+$H25)*O$3)*(1+(O$4-O$5)),((O24+($H25*O$3))*(1+(O$4-O$5))))) -> 0 | P25: =IF($G25="","",IF($G25=1,(($C$2+$H25)*P$3)*(1+(P$4-P$5)),((P24+($H25*P$3))*(1+(P$4-P$5))))) -> 0 | ... T25: =IF($G25="","",IF($G25=1,(($C$2+$H25)*T$3)*(1+(T$4-T$5)),((T24+($H25*T$3))*(1+(T$4-T$5))))) -> 0 | U25: =IF(G25="","",SUM(I25,K25,M25,O25,Q25,S25)) -> 31773290 | V25: =IF(H25="","",SUM(J25,L25,N25,P25,R25,T25)) -> 23556863 | W25: =IF($G25="","",IF($G25=1,(($C$2+$H25)*W$3)*(1+(W$4-W$5)),((W24+($H25*W$3))*(1+(W$4-W$5))))) -> 31337800 | X25: =IF($G25="","",IF($G25=1,(($C$2+$H25)*X$3)*(1+(X$4-X$5)),((X24+($H25*X$3))*(1+(X$4-X$5))))) -> 23200776 | Y25: =IF($G25="","",IF($G25=1,(U25-$C$2-H25)/($C$2+H25),(U25-U24-H25)/(U24+H25))) -> 0.075776712 | Z25: =IF($G25="","",IF($G25=1,(V25-$C$2-H25)/($C$2+H25),(V25-V24-H25)/(V24+H25))) -> 0.055932956 | AA25: =IF($G25="","",Z25-Y25) -> -0.019843756 | AB25: =IF($G25="","",IF($G25=1,(W25-$C$2-H25)/($C$2+H25),(W25-W24-H25)/(W24+H25))) -> 0.074 | AC25: =IF($G25="","",IF($G25=1,(X25-$C$2-H25)/($C$2+H25),(X25-X24-H25)/(X24+H25))) -> 0.054008 | AD25: =IF($G25="","",AC25-AB25) -> -0.019992 | AE25: =IF($G25="","",IF($G25=1,Y25,(1+Y25)*(1+AE24)-1)) -> 2.177329 | AF25: =IF($G25="","",IF($G25=1,Z25,(1+Z25)*(1+AF24)-1)) -> 1.3556863 | AG25: =IF($G25="","",AF25-AE25) -> -0.82164273 | AH25: =IF($G25="","",IF($G25=1,AB25,(1+AB25)*(1+AH24)-1)) -> 2.13378 | AI25: =IF($G25="","",IF($G25=1,AC25,(1+AC25)*(1+AI24)-1)) -> 1.3200776 | AJ25: =IF($G25="","",AI25-AH25) -> -0.81370236 | AK25: =IF($G25="","",(1+AE25)^(1/G25)-1) -> 0.07492679 | AL25: =IF($G25="","",(1+AF25)^(1/G25)-1) -> 0.055011858 | AM25: =IF($G25="","",AL25-AK25) -> -0.019914932 | AN25: =IF($G25="","",(1+AH25)^(1/G25)-1) -> 0.074 | AO25: =IF($G25="","",(1+AI25)^(1/G25)-1) -> 0.054008 | AP25: =IF($G25="","",AO25-AN25) -> -0.019992
B26: Total Return (Drag) | C26: =_xlfn.XLOOKUP(C3,G:G,AG:AG) -> -1.3278232 | D26: =_xlfn.XLOOKUP(C3,G:G,AJ:AJ) -> -1.3061414 | G26: 17 | H26: =IF(G26="","",SUMIFS(Add_Contributions[[#All],[Amount ($)]],Add_Contributions[[#All],[Year]],G26)) -> 0 | I26: =IF($G26="","",IF($G26=1,(($C$2+$H26)*I$3)*(1+(I$4-I$5)),((I25+($H26*I$3))*(1+(I$4-I$5))))) -> 25900126 | J26: =IF($G26="","",IF($G26=1,(($C$2+$H26)*J$3)*(1+(J$4-J$5)),((J25+($H26*J$3))*(1+(J$4-J$5))))) -> 19141731 | K26: =IF($G26="","",IF($G26=1,(($C$2+$H26)*K$3)*(1+(K$4-K$5)),((K25+($H26*K$3))*(1+(K$4-K$5))))) -> 0 | L26: =IF($G26="","",IF($G26=1,(($C$2+$H26)*L$3)*(1+(L$4-L$5)),((L25+($H26*L$3))*(1+(L$4-L$5))))) -> 0 | M26: =IF($G26="","",IF($G26=1,(($C$2+$H26)*M$3)*(1+(M$4-M$5)),((M25+($H26*M$3))*(1+(M$4-M$5))))) -> 4584036.6 | N26: =IF($G26="","",IF($G26=1,(($C$2+$H26)*N$3)*(1+(N$4-N$5)),((N25+($H26*N$3))*(1+(N$4-N$5))))) -> 3283938.9 | O26: =IF($G26="","",IF($G26=1,(($C$2+$H26)*O$3)*(1+(O$4-O$5)),((O25+($H26*O$3))*(1+(O$4-O$5))))) -> 0 | P26: =IF($G26="","",IF($G26=1,(($C$2+$H26)*P$3)*(1+(P$4-P$5)),((P25+($H26*P$3))*(1+(P$4-P$5))))) -> 0 | ... T26: =IF($G26="","",IF($G26=1,(($C$2+$H26)*T$3)*(1+(T$4-T$5)),((T25+($H26*T$3))*(1+(T$4-T$5))))) -> 0 | U26: =IF(G26="","",SUM(I26,K26,M26,O26,Q26,S26)) -> 34184181 | V26: =IF(H26="","",SUM(J26,L26,N26,P26,R26,T26)) -> 24877053 | W26: =IF($G26="","",IF($G26=1,(($C$2+$H26)*W$3)*(1+(W$4-W$5)),((W25+($H26*W$3))*(1+(W$4-W$5))))) -> 33656797 | X26: =IF($G26="","",IF($G26=1,(($C$2+$H26)*X$3)*(1+(X$4-X$5)),((X25+($H26*X$3))*(1+(X$4-X$5))))) -> 24453804 | Y26: =IF($G26="","",IF($G26=1,(U26-$C$2-H26)/($C$2+H26),(U26-U25-H26)/(U25+H26))) -> 0.075877906 | Z26: =IF($G26="","",IF($G26=1,(V26-$C$2-H26)/($C$2+H26),(V26-V25-H26)/(V25+H26))) -> 0.056042682 | AA26: =IF($G26="","",Z26-Y26) -> -0.019835225 | AB26: =IF($G26="","",IF($G26=1,(W26-$C$2-H26)/($C$2+H26),(W26-W25-H26)/(W25+H26))) -> 0.074 | AC26: =IF($G26="","",IF($G26=1,(X26-$C$2-H26)/($C$2+H26),(X26-X25-H26)/(X25+H26))) -> 0.054008 | AD26: =IF($G26="","",AC26-AB26) -> -0.019992 | AE26: =IF($G26="","",IF($G26=1,Y26,(1+Y26)*(1+AE25)-1)) -> 2.4184181 | AF26: =IF($G26="","",IF($G26=1,Z26,(1+Z26)*(1+AF25)-1)) -> 1.4877053 | AG26: =IF($G26="","",AF26-AE26) -> -0.93071283 | AH26: =IF($G26="","",IF($G26=1,AB26,(1+AB26)*(1+AH25)-1)) -> 2.3656797 | AI26: =IF($G26="","",IF($G26=1,AC26,(1+AC26)*(1+AI25)-1)) -> 1.4453804 | AJ26: =IF($G26="","",AI26-AH26) -> -0.92029932 | AK26: =IF($G26="","",(1+AE26)^(1/G26)-1) -> 0.074982715 | AL26: =IF($G26="","",(1+AF26)^(1/G26)-1) -> 0.055072467 | AM26: =IF($G26="","",AL26-AK26) -> -0.019910248 | AN26: =IF($G26="","",(1+AH26)^(1/G26)-1) -> 0.074 | AO26: =IF($G26="","",(1+AI26)^(1/G26)-1) -> 0.054008 | AP26: =IF($G26="","",AO26-AN26) -> -0.019992
G27: 18 | H27: =IF(G27="","",SUMIFS(Add_Contributions[[#All],[Amount ($)]],Add_Contributions[[#All],[Year]],G27)) -> 0 | I27: =IF($G27="","",IF($G27=1,(($C$2+$H27)*I$3)*(1+(I$4-I$5)),((I26+($H27*I$3))*(1+(I$4-I$5))))) -> 27972136 | J27: =IF($G27="","",IF($G27=1,(($C$2+$H27)*J$3)*(1+(J$4-J$5)),((J26+($H27*J$3))*(1+(J$4-J$5))))) -> 20308611 | K27: =IF($G27="","",IF($G27=1,(($C$2+$H27)*K$3)*(1+(K$4-K$5)),((K26+($H27*K$3))*(1+(K$4-K$5))))) -> 0 | L27: =IF($G27="","",IF($G27=1,(($C$2+$H27)*L$3)*(1+(L$4-L$5)),((L26+($H27*L$3))*(1+(L$4-L$5))))) -> 0 | M27: =IF($G27="","",IF($G27=1,(($C$2+$H27)*M$3)*(1+(M$4-M$5)),((M26+($H27*M$3))*(1+(M$4-M$5))))) -> 4813238.5 | N27: =IF($G27="","",IF($G27=1,(($C$2+$H27)*N$3)*(1+(N$4-N$5)),((N26+($H27*N$3))*(1+(N$4-N$5))))) -> 3381143.5 | O27: =IF($G27="","",IF($G27=1,(($C$2+$H27)*O$3)*(1+(O$4-O$5)),((O26+($H27*O$3))*(1+(O$4-O$5))))) -> 0 | P27: =IF($G27="","",IF($G27=1,(($C$2+$H27)*P$3)*(1+(P$4-P$5)),((P26+($H27*P$3))*(1+(P$4-P$5))))) -> 0 | ... T27: =IF($G27="","",IF($G27=1,(($C$2+$H27)*T$3)*(1+(T$4-T$5)),((T26+($H27*T$3))*(1+(T$4-T$5))))) -> 0 | U27: =IF(G27="","",SUM(I27,K27,M27,O27,Q27,S27)) -> 36781394 | V27: =IF(H27="","",SUM(J27,L27,N27,P27,R27,T27)) -> 26273904 | W27: =IF($G27="","",IF($G27=1,(($C$2+$H27)*W$3)*(1+(W$4-W$5)),((W26+($H27*W$3))*(1+(W$4-W$5))))) -> 36147400 | X27: =IF($G27="","",IF($G27=1,(($C$2+$H27)*X$3)*(1+(X$4-X$5)),((X26+($H27*X$3))*(1+(X$4-X$5))))) -> 25774505 | Y27: =IF($G27="","",IF($G27=1,(U27-$C$2-H27)/($C$2+H27),(U27-U26-H27)/(U26+H27))) -> 0.075977054 | Z27: =IF($G27="","",IF($G27=1,(V27-$C$2-H27)/($C$2+H27),(V27-V26-H27)/(V26+H27))) -> 0.056150197 | AA27: =IF($G27="","",Z27-Y27) -> -0.019826858 | AB27: =IF($G27="","",IF($G27=1,(W27-$C$2-H27)/($C$2+H27),(W27-W26-H27)/(W26+H27))) -> 0.074 | AC27: =IF($G27="","",IF($G27=1,(X27-$C$2-H27)/($C$2+H27),(X27-X26-H27)/(X26+H27))) -> 0.054008 | AD27: =IF($G27="","",AC27-AB27) -> -0.019992 | AE27: =IF($G27="","",IF($G27=1,Y27,(1+Y27)*(1+AE26)-1)) -> 2.6781394 | AF27: =IF($G27="","",IF($G27=1,Z27,(1+Z27)*(1+AF26)-1)) -> 1.6273904 | AG27: =IF($G27="","",AF27-AE27) -> -1.050749 | AH27: =IF($G27="","",IF($G27=1,AB27,(1+AB27)*(1+AH26)-1)) -> 2.61474 | AI27: =IF($G27="","",IF($G27=1,AC27,(1+AC27)*(1+AI26)-1)) -> 1.5774505 | AJ27: =IF($G27="","",AI27-AH27) -> -1.0372895 | AK27: =IF($G27="","",(1+AE27)^(1/G27)-1) -> 0.075037932 | AL27: =IF($G27="","",(1+AF27)^(1/G27)-1) -> 0.055132312 | AM27: =IF($G27="","",AL27-AK27) -> -0.01990562 | AN27: =IF($G27="","",(1+AH27)^(1/G27)-1) -> 0.074 | AO27: =IF($G27="","",(1+AI27)^(1/G27)-1) -> 0.054008 | AP27: =IF($G27="","",AO27-AN27) -> -0.019992
B28: Annualized Return (Gross) | C28: =_xlfn.XLOOKUP(C3,G:G,AK:AK) -> 0.075146264 | D28: =_xlfn.XLOOKUP(C3,G:G,AN:AN) -> 0.074 | G28: 19 | H28: =IF(G28="","",SUMIFS(Add_Contributions[[#All],[Amount ($)]],Add_Contributions[[#All],[Year]],G28)) -> 0 | I28: =IF($G28="","",IF($G28=1,(($C$2+$H28)*I$3)*(1+(I$4-I$5)),((I27+($H28*I$3))*(1+(I$4-I$5))))) -> 30209907 | J28: =IF($G28="","",IF($G28=1,(($C$2+$H28)*J$3)*(1+(J$4-J$5)),((J27+($H28*J$3))*(1+(J$4-J$5))))) -> 21546624 | K28: =IF($G28="","",IF($G28=1,(($C$2+$H28)*K$3)*(1+(K$4-K$5)),((K27+($H28*K$3))*(1+(K$4-K$5))))) -> 0 | L28: =IF($G28="","",IF($G28=1,(($C$2+$H28)*L$3)*(1+(L$4-L$5)),((L27+($H28*L$3))*(1+(L$4-L$5))))) -> 0 | M28: =IF($G28="","",IF($G28=1,(($C$2+$H28)*M$3)*(1+(M$4-M$5)),((M27+($H28*M$3))*(1+(M$4-M$5))))) -> 5053900.4 | N28: =IF($G28="","",IF($G28=1,(($C$2+$H28)*N$3)*(1+(N$4-N$5)),((N27+($H28*N$3))*(1+(N$4-N$5))))) -> 3481225.4 | O28: =IF($G28="","",IF($G28=1,(($C$2+$H28)*O$3)*(1+(O$4-O$5)),((O27+($H28*O$3))*(1+(O$4-O$5))))) -> 0 | P28: =IF($G28="","",IF($G28=1,(($C$2+$H28)*P$3)*(1+(P$4-P$5)),((P27+($H28*P$3))*(1+(P$4-P$5))))) -> 0 | ... T28: =IF($G28="","",IF($G28=1,(($C$2+$H28)*T$3)*(1+(T$4-T$5)),((T27+($H28*T$3))*(1+(T$4-T$5))))) -> 0 | U28: =IF(G28="","",SUM(I28,K28,M28,O28,Q28,S28)) -> 39579509 | V28: =IF(H28="","",SUM(J28,L28,N28,P28,R28,T28)) -> 27751957 | W28: =IF($G28="","",IF($G28=1,(($C$2+$H28)*W$3)*(1+(W$4-W$5)),((W27+($H28*W$3))*(1+(W$4-W$5))))) -> 38822308 | X28: =IF($G28="","",IF($G28=1,(($C$2+$H28)*X$3)*(1+(X$4-X$5)),((X27+($H28*X$3))*(1+(X$4-X$5))))) -> 27166534 | Y28: =IF($G28="","",IF($G28=1,(U28-$C$2-H28)/($C$2+H28),(U28-U27-H28)/(U27+H28))) -> 0.076074179 | Z28: =IF($G28="","",IF($G28=1,(V28-$C$2-H28)/($C$2+H28),(V28-V27-H28)/(V27+H28))) -> 0.056255527 | AA28: =IF($G28="","",Z28-Y28) -> -0.019818653 | AB28: =IF($G28="","",IF($G28=1,(W28-$C$2-H28)/($C$2+H28),(W28-W27-H28)/(W27+H28))) -> 0.074 | AC28: =IF($G28="","",IF($G28=1,(X28-$C$2-H28)/($C$2+H28),(X28-X27-H28)/(X27+H28))) -> 0.054008 | AD28: =IF($G28="","",AC28-AB28) -> -0.019992 | AE28: =IF($G28="","",IF($G28=1,Y28,(1+Y28)*(1+AE27)-1)) -> 2.9579509 | AF28: =IF($G28="","",IF($G28=1,Z28,(1+Z28)*(1+AF27)-1)) -> 1.7751957 | AG28: =IF($G28="","",AF28-AE28) -> -1.1827552 | AH28: =IF($G28="","",IF($G28=1,AB28,(1+AB28)*(1+AH27)-1)) -> 2.8822308 | AI28: =IF($G28="","",IF($G28=1,AC28,(1+AC28)*(1+AI27)-1)) -> 1.7166534 | AJ28: =IF($G28="","",AI28-AH28) -> -1.1655773 | AK28: =IF($G28="","",(1+AE28)^(1/G28)-1) -> 0.075092447 | AL28: =IF($G28="","",(1+AF28)^(1/G28)-1) -> 0.055191399 | AM28: =IF($G28="","",AL28-AK28) -> -0.019901048 | AN28: =IF($G28="","",(1+AH28)^(1/G28)-1) -> 0.074 | AO28: =IF($G28="","",(1+AI28)^(1/G28)-1) -> 0.054008 | AP28: =IF($G28="","",AO28-AN28) -> -0.019992
B29: Annualized Return (Net) | C29: =_xlfn.XLOOKUP(C3,G:G,AL:AL) -> 0.055249733 | D29: =_xlfn.XLOOKUP(C3,G:G,AO:AO) -> 0.054008 | G29: 20 | H29: =IF(G29="","",SUMIFS(Add_Contributions[[#All],[Amount ($)]],Add_Contributions[[#All],[Year]],G29)) -> 0 | I29: =IF($G29="","",IF($G29=1,(($C$2+$H29)*I$3)*(1+(I$4-I$5)),((I28+($H29*I$3))*(1+(I$4-I$5))))) -> 32626700 | J29: =IF($G29="","",IF($G29=1,(($C$2+$H29)*J$3)*(1+(J$4-J$5)),((J28+($H29*J$3))*(1+(J$4-J$5))))) -> 22860107 | K29: =IF($G29="","",IF($G29=1,(($C$2+$H29)*K$3)*(1+(K$4-K$5)),((K28+($H29*K$3))*(1+(K$4-K$5))))) -> 0 | L29: =IF($G29="","",IF($G29=1,(($C$2+$H29)*L$3)*(1+(L$4-L$5)),((L28+($H29*L$3))*(1+(L$4-L$5))))) -> 0 | M29: =IF($G29="","",IF($G29=1,(($C$2+$H29)*M$3)*(1+(M$4-M$5)),((M28+($H29*M$3))*(1+(M$4-M$5))))) -> 5306595.4 | N29: =IF($G29="","",IF($G29=1,(($C$2+$H29)*N$3)*(1+(N$4-N$5)),((N28+($H29*N$3))*(1+(N$4-N$5))))) -> 3584269.6 | O29: =IF($G29="","",IF($G29=1,(($C$2+$H29)*O$3)*(1+(O$4-O$5)),((O28+($H29*O$3))*(1+(O$4-O$5))))) -> 0 | P29: =IF($G29="","",IF($G29=1,(($C$2+$H29)*P$3)*(1+(P$4-P$5)),((P28+($H29*P$3))*(1+(P$4-P$5))))) -> 0 | ... T29: =IF($G29="","",IF($G29=1,(($C$2+$H29)*T$3)*(1+(T$4-T$5)),((T28+($H29*T$3))*(1+(T$4-T$5))))) -> 0 | U29: =IF(G29="","",SUM(I29,K29,M29,O29,Q29,S29)) -> 42594253 | V29: =IF(H29="","",SUM(J29,L29,N29,P29,R29,T29)) -> 29316021 | W29: =IF($G29="","",IF($G29=1,(($C$2+$H29)*W$3)*(1+(W$4-W$5)),((W28+($H29*W$3))*(1+(W$4-W$5))))) -> 41695158 | X29: =IF($G29="","",IF($G29=1,(($C$2+$H29)*X$3)*(1+(X$4-X$5)),((X28+($H29*X$3))*(1+(X$4-X$5))))) -> 28633744 | Y29: =IF($G29="","",IF($G29=1,(U29-$C$2-H29)/($C$2+H29),(U29-U28-H29)/(U28+H29))) -> 0.076169305 | Z29: =IF($G29="","",IF($G29=1,(V29-$C$2-H29)/($C$2+H29),(V29-V28-H29)/(V28+H29))) -> 0.056358697 | AA29: =IF($G29="","",Z29-Y29) -> -0.019810608 | AB29: =IF($G29="","",IF($G29=1,(W29-$C$2-H29)/($C$2+H29),(W29-W28-H29)/(W28+H29))) -> 0.074 | AC29: =IF($G29="","",IF($G29=1,(X29-$C$2-H29)/($C$2+H29),(X29-X28-H29)/(X28+H29))) -> 0.054008 | AD29: =IF($G29="","",AC29-AB29) -> -0.019992 | AE29: =IF($G29="","",IF($G29=1,Y29,(1+Y29)*(1+AE28)-1)) -> 3.2594253 | AF29: =IF($G29="","",IF($G29=1,Z29,(1+Z29)*(1+AF28)-1)) -> 1.9316021 | AG29: =IF($G29="","",AF29-AE29) -> -1.3278232 | AH29: =IF($G29="","",IF($G29=1,AB29,(1+AB29)*(1+AH28)-1)) -> 3.1695158 | AI29: =IF($G29="","",IF($G29=1,AC29,(1+AC29)*(1+AI28)-1)) -> 1.8633744 | AJ29: =IF($G29="","",AI29-AH29) -> -1.3061414 | AK29: =IF($G29="","",(1+AE29)^(1/G29)-1) -> 0.075146264 | AL29: =IF($G29="","",(1+AF29)^(1/G29)-1) -> 0.055249733 | AM29: =IF($G29="","",AL29-AK29) -> -0.019896531 | AN29: =IF($G29="","",(1+AH29)^(1/G29)-1) -> 0.074 | AO29: =IF($G29="","",(1+AI29)^(1/G29)-1) -> 0.054008 | AP29: =IF($G29="","",AO29-AN29) -> -0.019992
B30: Annualized Return (Drag) | C30: =_xlfn.XLOOKUP(C3,G:G,AM:AM) -> -0.019896531 | D30: =_xlfn.XLOOKUP(C3,G:G,AP:AP) -> -0.019992 | H30: =IF(G30="","",SUMIFS(Add_Contributions[[#All],[Amount ($)]],Add_Contributions[[#All],[Year]],G30)) | I30: =IF($G30="","",IF($G30=1,(($C$2+$H30)*I$3)*(1+(I$4-I$5)),((I29+($H30*I$3))*(1+(I$4-I$5))))) | J30: =IF($G30="","",IF($G30=1,(($C$2+$H30)*J$3)*(1+(J$4-J$5)),((J29+($H30*J$3))*(1+(J$4-J$5))))) | K30: =IF($G30="","",IF($G30=1,(($C$2+$H30)*K$3)*(1+(K$4-K$5)),((K29+($H30*K$3))*(1+(K$4-K$5))))) | L30: =IF($G30="","",IF($G30=1,(($C$2+$H30)*L$3)*(1+(L$4-L$5)),((L29+($H30*L$3))*(1+(L$4-L$5))))) | M30: =IF($G30="","",IF($G30=1,(($C$2+$H30)*M$3)*(1+(M$4-M$5)),((M29+($H30*M$3))*(1+(M$4-M$5))))) | N30: =IF($G30="","",IF($G30=1,(($C$2+$H30)*N$3)*(1+(N$4-N$5)),((N29+($H30*N$3))*(1+(N$4-N$5))))) | O30: =IF($G30="","",IF($G30=1,(($C$2+$H30)*O$3)*(1+(O$4-O$5)),((O29+($H30*O$3))*(1+(O$4-O$5))))) | P30: =IF($G30="","",IF($G30=1,(($C$2+$H30)*P$3)*(1+(P$4-P$5)),((P29+($H30*P$3))*(1+(P$4-P$5))))) | ... T30: =IF($G30="","",IF($G30=1,(($C$2+$H30)*T$3)*(1+(T$4-T$5)),((T29+($H30*T$3))*(1+(T$4-T$5))))) | U30: =IF(G30="","",SUM(I30,K30,M30,O30,Q30,S30)) | V30: =IF(H30="","",SUM(J30,L30,N30,P30,R30,T30)) | W30: =IF($G30="","",IF($G30=1,(($C$2+$H30)*W$3)*(1+(W$4-W$5)),((W29+($H30*W$3))*(1+(W$4-W$5))))) | X30: =IF($G30="","",IF($G30=1,(($C$2+$H30)*X$3)*(1+(X$4-X$5)),((X29+($H30*X$3))*(1+(X$4-X$5))))) | Y30: =IF($G30="","",IF($G30=1,(U30-$C$2-H30)/($C$2+H30),(U30-U29-H30)/(U29+H30))) | Z30: =IF($G30="","",IF($G30=1,(V30-$C$2-H30)/($C$2+H30),(V30-V29-H30)/(V29+H30))) | AA30: =IF($G30="","",Z30-Y30) | AB30: =IF($G30="","",IF($G30=1,(W30-$C$2-H30)/($C$2+H30),(W30-W29-H30)/(W29+H30))) | AC30: =IF($G30="","",IF($G30=1,(X30-$C$2-H30)/($C$2+H30),(X30-X29-H30)/(X29+H30))) | AD30: =IF($G30="","",AC30-AB30) | AE30: =IF($G30="","",IF($G30=1,Y30,(1+Y30)*(1+AE29)-1)) | AF30: =IF($G30="","",IF($G30=1,Z30,(1+Z30)*(1+AF29)-1)) | AG30: =IF($G30="","",AF30-AE30) | AH30: =IF($G30="","",IF($G30=1,AB30,(1+AB30)*(1+AH29)-1)) | AI30: =IF($G30="","",IF($G30=1,AC30,(1+AC30)*(1+AI29)-1)) | AJ30: =IF($G30="","",AI30-AH30) | AK30: =IF($G30="","",(1+AE30)^(1/G30)-1) | AL30: =IF($G30="","",(1+AF30)^(1/G30)-1) | AM30: =IF($G30="","",AL30-AK30) | AN30: =IF($G30="","",(1+AH30)^(1/G30)-1) | AO30: =IF($G30="","",(1+AI30)^(1/G30)-1) | AP30: =IF($G30="","",AO30-AN30)
H31: =IF(G31="","",SUMIFS(Add_Contributions[[#All],[Amount ($)]],Add_Contributions[[#All],[Year]],G31)) | I31: =IF($G31="","",IF($G31=1,(($C$2+$H31)*I$3)*(1+(I$4-I$5)),((I30+($H31*I$3))*(1+(I$4-I$5))))) | J31: =IF($G31="","",IF($G31=1,(($C$2+$H31)*J$3)*(1+(J$4-J$5)),((J30+($H31*J$3))*(1+(J$4-J$5))))) | K31: =IF($G31="","",IF($G31=1,(($C$2+$H31)*K$3)*(1+(K$4-K$5)),((K30+($H31*K$3))*(1+(K$4-K$5))))) | L31: =IF($G31="","",IF($G31=1,(($C$2+$H31)*L$3)*(1+(L$4-L$5)),((L30+($H31*L$3))*(1+(L$4-L$5))))) | M31: =IF($G31="","",IF($G31=1,(($C$2+$H31)*M$3)*(1+(M$4-M$5)),((M30+($H31*M$3))*(1+(M$4-M$5))))) | N31: =IF($G31="","",IF($G31=1,(($C$2+$H31)*N$3)*(1+(N$4-N$5)),((N30+($H31*N$3))*(1+(N$4-N$5))))) | O31: =IF($G31="","",IF($G31=1,(($C$2+$H31)*O$3)*(1+(O$4-O$5)),((O30+($H31*O$3))*(1+(O$4-O$5))))) | P31: =IF($G31="","",IF($G31=1,(($C$2+$H31)*P$3)*(1+(P$4-P$5)),((P30+($H31*P$3))*(1+(P$4-P$5))))) | ... T31: =IF($G31="","",IF($G31=1,(($C$2+$H31)*T$3)*(1+(T$4-T$5)),((T30+($H31*T$3))*(1+(T$4-T$5))))) | U31: =IF(G31="","",SUM(I31,K31,M31,O31,Q31,S31)) | V31: =IF(H31="","",SUM(J31,L31,N31,P31,R31,T31)) | W31: =IF($G31="","",IF($G31=1,(($C$2+$H31)*W$3)*(1+(W$4-W$5)),((W30+($H31*W$3))*(1+(W$4-W$5))))) | X31: =IF($G31="","",IF($G31=1,(($C$2+$H31)*X$3)*(1+(X$4-X$5)),((X30+($H31*X$3))*(1+(X$4-X$5))))) | Y31: =IF($G31="","",IF($G31=1,(U31-$C$2-H31)/($C$2+H31),(U31-U30-H31)/(U30+H31))) | Z31: =IF($G31="","",IF($G31=1,(V31-$C$2-H31)/($C$2+H31),(V31-V30-H31)/(V30+H31))) | AA31: =IF($G31="","",Z31-Y31) | AB31: =IF($G31="","",IF($G31=1,(W31-$C$2-H31)/($C$2+H31),(W31-W30-H31)/(W30+H31))) | AC31: =IF($G31="","",IF($G31=1,(X31-$C$2-H31)/($C$2+H31),(X31-X30-H31)/(X30+H31))) | AD31: =IF($G31="","",AC31-AB31) | AE31: =IF($G31="","",IF($G31=1,Y31,(1+Y31)*(1+AE30)-1)) | AF31: =IF($G31="","",IF($G31=1,Z31,(1+Z31)*(1+AF30)-1)) | AG31: =IF($G31="","",AF31-AE31) | AH31: =IF($G31="","",IF($G31=1,AB31,(1+AB31)*(1+AH30)-1)) | AI31: =IF($G31="","",IF($G31=1,AC31,(1+AC31)*(1+AI30)-1)) | AJ31: =IF($G31="","",AI31-AH31) | AK31: =IF($G31="","",(1+AE31)^(1/G31)-1) | AL31: =IF($G31="","",(1+AF31)^(1/G31)-1) | AM31: =IF($G31="","",AL31-AK31) | AN31: =IF($G31="","",(1+AH31)^(1/G31)-1) | AO31: =IF($G31="","",(1+AI31)^(1/G31)-1) | AP31: =IF($G31="","",AO31-AN31)
H32: =IF(G32="","",SUMIFS(Add_Contributions[[#All],[Amount ($)]],Add_Contributions[[#All],[Year]],G32)) | I32: =IF($G32="","",IF($G32=1,(($C$2+$H32)*I$3)*(1+(I$4-I$5)),((I31+($H32*I$3))*(1+(I$4-I$5))))) | J32: =IF($G32="","",IF($G32=1,(($C$2+$H32)*J$3)*(1+(J$4-J$5)),((J31+($H32*J$3))*(1+(J$4-J$5))))) | K32: =IF($G32="","",IF($G32=1,(($C$2+$H32)*K$3)*(1+(K$4-K$5)),((K31+($H32*K$3))*(1+(K$4-K$5))))) | L32: =IF($G32="","",IF($G32=1,(($C$2+$H32)*L$3)*(1+(L$4-L$5)),((L31+($H32*L$3))*(1+(L$4-L$5))))) | M32: =IF($G32="","",IF($G32=1,(($C$2+$H32)*M$3)*(1+(M$4-M$5)),((M31+($H32*M$3))*(1+(M$4-M$5))))) | N32: =IF($G32="","",IF($G32=1,(($C$2+$H32)*N$3)*(1+(N$4-N$5)),((N31+($H32*N$3))*(1+(N$4-N$5))))) | O32: =IF($G32="","",IF($G32=1,(($C$2+$H32)*O$3)*(1+(O$4-O$5)),((O31+($H32*O$3))*(1+(O$4-O$5))))) | P32: =IF($G32="","",IF($G32=1,(($C$2+$H32)*P$3)*(1+(P$4-P$5)),((P31+($H32*P$3))*(1+(P$4-P$5))))) | ... T32: =IF($G32="","",IF($G32=1,(($C$2+$H32)*T$3)*(1+(T$4-T$5)),((T31+($H32*T$3))*(1+(T$4-T$5))))) | U32: =IF(G32="","",SUM(I32,K32,M32,O32,Q32,S32)) | V32: =IF(H32="","",SUM(J32,L32,N32,P32,R32,T32)) | W32: =IF($G32="","",IF($G32=1,(($C$2+$H32)*W$3)*(1+(W$4-W$5)),((W31+($H32*W$3))*(1+(W$4-W$5))))) | X32: =IF($G32="","",IF($G32=1,(($C$2+$H32)*X$3)*(1+(X$4-X$5)),((X31+($H32*X$3))*(1+(X$4-X$5))))) | Y32: =IF($G32="","",IF($G32=1,(U32-$C$2-H32)/($C$2+H32),(U32-U31-H32)/(U31+H32))) | Z32: =IF($G32="","",IF($G32=1,(V32-$C$2-H32)/($C$2+H32),(V32-V31-H32)/(V31+H32))) | AA32: =IF($G32="","",Z32-Y32) | AB32: =IF($G32="","",IF($G32=1,(W32-$C$2-H32)/($C$2+H32),(W32-W31-H32)/(W31+H32))) | AC32: =IF($G32="","",IF($G32=1,(X32-$C$2-H32)/($C$2+H32),(X32-X31-H32)/(X31+H32))) | AD32: =IF($G32="","",AC32-AB32) | AE32: =IF($G32="","",IF($G32=1,Y32,(1+Y32)*(1+AE31)-1)) | AF32: =IF($G32="","",IF($G32=1,Z32,(1+Z32)*(1+AF31)-1)) | AG32: =IF($G32="","",AF32-AE32) | AH32: =IF($G32="","",IF($G32=1,AB32,(1+AB32)*(1+AH31)-1)) | AI32: =IF($G32="","",IF($G32=1,AC32,(1+AC32)*(1+AI31)-1)) | AJ32: =IF($G32="","",AI32-AH32) | AK32: =IF($G32="","",(1+AE32)^(1/G32)-1) | AL32: =IF($G32="","",(1+AF32)^(1/G32)-1) | AM32: =IF($G32="","",AL32-AK32) | AN32: =IF($G32="","",(1+AH32)^(1/G32)-1) | AO32: =IF($G32="","",(1+AI32)^(1/G32)-1) | AP32: =IF($G32="","",AO32-AN32)
H33: =IF(G33="","",SUMIFS(Add_Contributions[[#All],[Amount ($)]],Add_Contributions[[#All],[Year]],G33)) | I33: =IF($G33="","",IF($G33=1,(($C$2+$H33)*I$3)*(1+(I$4-I$5)),((I32+($H33*I$3))*(1+(I$4-I$5))))) | J33: =IF($G33="","",IF($G33=1,(($C$2+$H33)*J$3)*(1+(J$4-J$5)),((J32+($H33*J$3))*(1+(J$4-J$5))))) | K33: =IF($G33="","",IF($G33=1,(($C$2+$H33)*K$3)*(1+(K$4-K$5)),((K32+($H33*K$3))*(1+(K$4-K$5))))) | L33: =IF($G33="","",IF($G33=1,(($C$2+$H33)*L$3)*(1+(L$4-L$5)),((L32+($H33*L$3))*(1+(L$4-L$5))))) | M33: =IF($G33="","",IF($G33=1,(($C$2+$H33)*M$3)*(1+(M$4-M$5)),((M32+($H33*M$3))*(1+(M$4-M$5))))) | N33: =IF($G33="","",IF($G33=1,(($C$2+$H33)*N$3)*(1+(N$4-N$5)),((N32+($H33*N$3))*(1+(N$4-N$5))))) | O33: =IF($G33="","",IF($G33=1,(($C$2+$H33)*O$3)*(1+(O$4-O$5)),((O32+($H33*O$3))*(1+(O$4-O$5))))) | P33: =IF($G33="","",IF($G33=1,(($C$2+$H33)*P$3)*(1+(P$4-P$5)),((P32+($H33*P$3))*(1+(P$4-P$5))))) | ... T33: =IF($G33="","",IF($G33=1,(($C$2+$H33)*T$3)*(1+(T$4-T$5)),((T32+($H33*T$3))*(1+(T$4-T$5))))) | U33: =IF(G33="","",SUM(I33,K33,M33,O33,Q33,S33)) | V33: =IF(H33="","",SUM(J33,L33,N33,P33,R33,T33)) | W33: =IF($G33="","",IF($G33=1,(($C$2+$H33)*W$3)*(1+(W$4-W$5)),((W32+($H33*W$3))*(1+(W$4-W$5))))) | X33: =IF($G33="","",IF($G33=1,(($C$2+$H33)*X$3)*(1+(X$4-X$5)),((X32+($H33*X$3))*(1+(X$4-X$5))))) | Y33: =IF($G33="","",IF($G33=1,(U33-$C$2-H33)/($C$2+H33),(U33-U32-H33)/(U32+H33))) | Z33: =IF($G33="","",IF($G33=1,(V33-$C$2-H33)/($C$2+H33),(V33-V32-H33)/(V32+H33))) | AA33: =IF($G33="","",Z33-Y33) | AB33: =IF($G33="","",IF($G33=1,(W33-$C$2-H33)/($C$2+H33),(W33-W32-H33)/(W32+H33))) | AC33: =IF($G33="","",IF($G33=1,(X33-$C$2-H33)/($C$2+H33),(X33-X32-H33)/(X32+H33))) | AD33: =IF($G33="","",AC33-AB33) | AE33: =IF($G33="","",IF($G33=1,Y33,(1+Y33)*(1+AE32)-1)) | AF33: =IF($G33="","",IF($G33=1,Z33,(1+Z33)*(1+AF32)-1)) | AG33: =IF($G33="","",AF33-AE33) | AH33: =IF($G33="","",IF($G33=1,AB33,(1+AB33)*(1+AH32)-1)) | AI33: =IF($G33="","",IF($G33=1,AC33,(1+AC33)*(1+AI32)-1)) | AJ33: =IF($G33="","",AI33-AH33) | AK33: =IF($G33="","",(1+AE33)^(1/G33)-1) | AL33: =IF($G33="","",(1+AF33)^(1/G33)-1) | AM33: =IF($G33="","",AL33-AK33) | AN33: =IF($G33="","",(1+AH33)^(1/G33)-1) | AO33: =IF($G33="","",(1+AI33)^(1/G33)-1) | AP33: =IF($G33="","",AO33-AN33)
H34: =IF(G34="","",SUMIFS(Add_Contributions[[#All],[Amount ($)]],Add_Contributions[[#All],[Year]],G34)) | I34: =IF($G34="","",IF($G34=1,(($C$2+$H34)*I$3)*(1+(I$4-I$5)),((I33+($H34*I$3))*(1+(I$4-I$5))))) | J34: =IF($G34="","",IF($G34=1,(($C$2+$H34)*J$3)*(1+(J$4-J$5)),((J33+($H34*J$3))*(1+(J$4-J$5))))) | K34: =IF($G34="","",IF($G34=1,(($C$2+$H34)*K$3)*(1+(K$4-K$5)),((K33+($H34*K$3))*(1+(K$4-K$5))))) | L34: =IF($G34="","",IF($G34=1,(($C$2+$H34)*L$3)*(1+(L$4-L$5)),((L33+($H34*L$3))*(1+(L$4-L$5))))) | M34: =IF($G34="","",IF($G34=1,(($C$2+$H34)*M$3)*(1+(M$4-M$5)),((M33+($H34*M$3))*(1+(M$4-M$5))))) | N34: =IF($G34="","",IF($G34=1,(($C$2+$H34)*N$3)*(1+(N$4-N$5)),((N33+($H34*N$3))*(1+(N$4-N$5))))) | O34: =IF($G34="","",IF($G34=1,(($C$2+$H34)*O$3)*(1+(O$4-O$5)),((O33+($H34*O$3))*(1+(O$4-O$5))))) | P34: =IF($G34="","",IF($G34=1,(($C$2+$H34)*P$3)*(1+(P$4-P$5)),((P33+($H34*P$3))*(1+(P$4-P$5))))) | ... T34: =IF($G34="","",IF($G34=1,(($C$2+$H34)*T$3)*(1+(T$4-T$5)),((T33+($H34*T$3))*(1+(T$4-T$5))))) | U34: =IF(G34="","",SUM(I34,K34,M34,O34,Q34,S34)) | V34: =IF(H34="","",SUM(J34,L34,N34,P34,R34,T34)) | W34: =IF($G34="","",IF($G34=1,(($C$2+$H34)*W$3)*(1+(W$4-W$5)),((W33+($H34*W$3))*(1+(W$4-W$5))))) | X34: =IF($G34="","",IF($G34=1,(($C$2+$H34)*X$3)*(1+(X$4-X$5)),((X33+($H34*X$3))*(1+(X$4-X$5))))) | Y34: =IF($G34="","",IF($G34=1,(U34-$C$2-H34)/($C$2+H34),(U34-U33-H34)/(U33+H34))) | Z34: =IF($G34="","",IF($G34=1,(V34-$C$2-H34)/($C$2+H34),(V34-V33-H34)/(V33+H34))) | AA34: =IF($G34="","",Z34-Y34) | AB34: =IF($G34="","",IF($G34=1,(W34-$C$2-H34)/($C$2+H34),(W34-W33-H34)/(W33+H34))) | AC34: =IF($G34="","",IF($G34=1,(X34-$C$2-H34)/($C$2+H34),(X34-X33-H34)/(X33+H34))) | AD34: =IF($G34="","",AC34-AB34) | AE34: =IF($G34="","",IF($G34=1,Y34,(1+Y34)*(1+AE33)-1)) | AF34: =IF($G34="","",IF($G34=1,Z34,(1+Z34)*(1+AF33)-1)) | AG34: =IF($G34="","",AF34-AE34) | AH34: =IF($G34="","",IF($G34=1,AB34,(1+AB34)*(1+AH33)-1)) | AI34: =IF($G34="","",IF($G34=1,AC34,(1+AC34)*(1+AI33)-1)) | AJ34: =IF($G34="","",AI34-AH34) | AK34: =IF($G34="","",(1+AE34)^(1/G34)-1) | AL34: =IF($G34="","",(1+AF34)^(1/G34)-1) | AM34: =IF($G34="","",AL34-AK34) | AN34: =IF($G34="","",(1+AH34)^(1/G34)-1) | AO34: =IF($G34="","",(1+AI34)^(1/G34)-1) | AP34: =IF($G34="","",AO34-AN34)
H35: =IF(G35="","",SUMIFS(Add_Contributions[[#All],[Amount ($)]],Add_Contributions[[#All],[Year]],G35)) | I35: =IF($G35="","",IF($G35=1,(($C$2+$H35)*I$3)*(1+(I$4-I$5)),((I34+($H35*I$3))*(1+(I$4-I$5))))) | J35: =IF($G35="","",IF($G35=1,(($C$2+$H35)*J$3)*(1+(J$4-J$5)),((J34+($H35*J$3))*(1+(J$4-J$5))))) | K35: =IF($G35="","",IF($G35=1,(($C$2+$H35)*K$3)*(1+(K$4-K$5)),((K34+($H35*K$3))*(1+(K$4-K$5))))) | L35: =IF($G35="","",IF($G35=1,(($C$2+$H35)*L$3)*(1+(L$4-L$5)),((L34+($H35*L$3))*(1+(L$4-L$5))))) | M35: =IF($G35="","",IF($G35=1,(($C$2+$H35)*M$3)*(1+(M$4-M$5)),((M34+($H35*M$3))*(1+(M$4-M$5))))) | N35: =IF($G35="","",IF($G35=1,(($C$2+$H35)*N$3)*(1+(N$4-N$5)),((N34+($H35*N$3))*(1+(N$4-N$5))))) | O35: =IF($G35="","",IF($G35=1,(($C$2+$H35)*O$3)*(1+(O$4-O$5)),((O34+($H35*O$3))*(1+(O$4-O$5))))) | P35: =IF($G35="","",IF($G35=1,(($C$2+$H35)*P$3)*(1+(P$4-P$5)),((P34+($H35*P$3))*(1+(P$4-P$5))))) | ... T35: =IF($G35="","",IF($G35=1,(($C$2+$H35)*T$3)*(1+(T$4-T$5)),((T34+($H35*T$3))*(1+(T$4-T$5))))) | U35: =IF(G35="","",SUM(I35,K35,M35,O35,Q35,S35)) | V35: =IF(H35="","",SUM(J35,L35,N35,P35,R35,T35)) | W35: =IF($G35="","",IF($G35=1,(($C$2+$H35)*W$3)*(1+(W$4-W$5)),((W34+($H35*W$3))*(1+(W$4-W$5))))) | X35: =IF($G35="","",IF($G35=1,(($C$2+$H35)*X$3)*(1+(X$4-X$5)),((X34+($H35*X$3))*(1+(X$4-X$5))))) | Y35: =IF($G35="","",IF($G35=1,(U35-$C$2-H35)/($C$2+H35),(U35-U34-H35)/(U34+H35))) | Z35: =IF($G35="","",IF($G35=1,(V35-$C$2-H35)/($C$2+H35),(V35-V34-H35)/(V34+H35))) | AA35: =IF($G35="","",Z35-Y35) | AB35: =IF($G35="","",IF($G35=1,(W35-$C$2-H35)/($C$2+H35),(W35-W34-H35)/(W34+H35))) | AC35: =IF($G35="","",IF($G35=1,(X35-$C$2-H35)/($C$2+H35),(X35-X34-H35)/(X34+H35))) | AD35: =IF($G35="","",AC35-AB35) | AE35: =IF($G35="","",IF($G35=1,Y35,(1+Y35)*(1+AE34)-1)) | AF35: =IF($G35="","",IF($G35=1,Z35,(1+Z35)*(1+AF34)-1)) | AG35: =IF($G35="","",AF35-AE35) | AH35: =IF($G35="","",IF($G35=1,AB35,(1+AB35)*(1+AH34)-1)) | AI35: =IF($G35="","",IF($G35=1,AC35,(1+AC35)*(1+AI34)-1)) | AJ35: =IF($G35="","",AI35-AH35) | AK35: =IF($G35="","",(1+AE35)^(1/G35)-1) | AL35: =IF($G35="","",(1+AF35)^(1/G35)-1) | AM35: =IF($G35="","",AL35-AK35) | AN35: =IF($G35="","",(1+AH35)^(1/G35)-1) | AO35: =IF($G35="","",(1+AI35)^(1/G35)-1) | AP35: =IF($G35="","",AO35-AN35)
H36: =IF(G36="","",SUMIFS(Add_Contributions[[#All],[Amount ($)]],Add_Contributions[[#All],[Year]],G36)) | I36: =IF($G36="","",IF($G36=1,(($C$2+$H36)*I$3)*(1+(I$4-I$5)),((I35+($H36*I$3))*(1+(I$4-I$5))))) | J36: =IF($G36="","",IF($G36=1,(($C$2+$H36)*J$3)*(1+(J$4-J$5)),((J35+($H36*J$3))*(1+(J$4-J$5))))) | K36: =IF($G36="","",IF($G36=1,(($C$2+$H36)*K$3)*(1+(K$4-K$5)),((K35+($H36*K$3))*(1+(K$4-K$5))))) | L36: =IF($G36="","",IF($G36=1,(($C$2+$H36)*L$3)*(1+(L$4-L$5)),((L35+($H36*L$3))*(1+(L$4-L$5))))) | M36: =IF($G36="","",IF($G36=1,(($C$2+$H36)*M$3)*(1+(M$4-M$5)),((M35+($H36*M$3))*(1+(M$4-M$5))))) | N36: =IF($G36="","",IF($G36=1,(($C$2+$H36)*N$3)*(1+(N$4-N$5)),((N35+($H36*N$3))*(1+(N$4-N$5))))) | O36: =IF($G36="","",IF($G36=1,(($C$2+$H36)*O$3)*(1+(O$4-O$5)),((O35+($H36*O$3))*(1+(O$4-O$5))))) | P36: =IF($G36="","",IF($G36=1,(($C$2+$H36)*P$3)*(1+(P$4-P$5)),((P35+($H36*P$3))*(1+(P$4-P$5))))) | ... T36: =IF($G36="","",IF($G36=1,(($C$2+$H36)*T$3)*(1+(T$4-T$5)),((T35+($H36*T$3))*(1+(T$4-T$5))))) | U36: =IF(G36="","",SUM(I36,K36,M36,O36,Q36,S36)) | V36: =IF(H36="","",SUM(J36,L36,N36,P36,R36,T36)) | W36: =IF($G36="","",IF($G36=1,(($C$2+$H36)*W$3)*(1+(W$4-W$5)),((W35+($H36*W$3))*(1+(W$4-W$5))))) | X36: =IF($G36="","",IF($G36=1,(($C$2+$H36)*X$3)*(1+(X$4-X$5)),((X35+($H36*X$3))*(1+(X$4-X$5))))) | Y36: =IF($G36="","",IF($G36=1,(U36-$C$2-H36)/($C$2+H36),(U36-U35-H36)/(U35+H36))) | Z36: =IF($G36="","",IF($G36=1,(V36-$C$2-H36)/($C$2+H36),(V36-V35-H36)/(V35+H36))) | AA36: =IF($G36="","",Z36-Y36) | AB36: =IF($G36="","",IF($G36=1,(W36-$C$2-H36)/($C$2+H36),(W36-W35-H36)/(W35+H36))) | AC36: =IF($G36="","",IF($G36=1,(X36-$C$2-H36)/($C$2+H36),(X36-X35-H36)/(X35+H36))) | AD36: =IF($G36="","",AC36-AB36) | AE36: =IF($G36="","",IF($G36=1,Y36,(1+Y36)*(1+AE35)-1)) | AF36: =IF($G36="","",IF($G36=1,Z36,(1+Z36)*(1+AF35)-1)) | AG36: =IF($G36="","",AF36-AE36) | AH36: =IF($G36="","",IF($G36=1,AB36,(1+AB36)*(1+AH35)-1)) | AI36: =IF($G36="","",IF($G36=1,AC36,(1+AC36)*(1+AI35)-1)) | AJ36: =IF($G36="","",AI36-AH36) | AK36: =IF($G36="","",(1+AE36)^(1/G36)-1) | AL36: =IF($G36="","",(1+AF36)^(1/G36)-1) | AM36: =IF($G36="","",AL36-AK36) | AN36: =IF($G36="","",(1+AH36)^(1/G36)-1) | AO36: =IF($G36="","",(1+AI36)^(1/G36)-1) | AP36: =IF($G36="","",AO36-AN36)
H37: =IF(G37="","",SUMIFS(Add_Contributions[[#All],[Amount ($)]],Add_Contributions[[#All],[Year]],G37)) | I37: =IF($G37="","",IF($G37=1,(($C$2+$H37)*I$3)*(1+(I$4-I$5)),((I36+($H37*I$3))*(1+(I$4-I$5))))) | J37: =IF($G37="","",IF($G37=1,(($C$2+$H37)*J$3)*(1+(J$4-J$5)),((J36+($H37*J$3))*(1+(J$4-J$5))))) | K37: =IF($G37="","",IF($G37=1,(($C$2+$H37)*K$3)*(1+(K$4-K$5)),((K36+($H37*K$3))*(1+(K$4-K$5))))) | L37: =IF($G37="","",IF($G37=1,(($C$2+$H37)*L$3)*(1+(L$4-L$5)),((L36+($H37*L$3))*(1+(L$4-L$5))))) | M37: =IF($G37="","",IF($G37=1,(($C$2+$H37)*M$3)*(1+(M$4-M$5)),((M36+($H37*M$3))*(1+(M$4-M$5))))) | N37: =IF($G37="","",IF($G37=1,(($C$2+$H37)*N$3)*(1+(N$4-N$5)),((N36+($H37*N$3))*(1+(N$4-N$5))))) | O37: =IF($G37="","",IF($G37=1,(($C$2+$H37)*O$3)*(1+(O$4-O$5)),((O36+($H37*O$3))*(1+(O$4-O$5))))) | P37: =IF($G37="","",IF($G37=1,(($C$2+$H37)*P$3)*(1+(P$4-P$5)),((P36+($H37*P$3))*(1+(P$4-P$5))))) | ... T37: =IF($G37="","",IF($G37=1,(($C$2+$H37)*T$3)*(1+(T$4-T$5)),((T36+($H37*T$3))*(1+(T$4-T$5))))) | U37: =IF(G37="","",SUM(I37,K37,M37,O37,Q37,S37)) | V37: =IF(H37="","",SUM(J37,L37,N37,P37,R37,T37)) | W37: =IF($G37="","",IF($G37=1,(($C$2+$H37)*W$3)*(1+(W$4-W$5)),((W36+($H37*W$3))*(1+(W$4-W$5))))) | X37: =IF($G37="","",IF($G37=1,(($C$2+$H37)*X$3)*(1+(X$4-X$5)),((X36+($H37*X$3))*(1+(X$4-X$5))))) | Y37: =IF($G37="","",IF($G37=1,(U37-$C$2-H37)/($C$2+H37),(U37-U36-H37)/(U36+H37))) | Z37: =IF($G37="","",IF($G37=1,(V37-$C$2-H37)/($C$2+H37),(V37-V36-H37)/(V36+H37))) | AA37: =IF($G37="","",Z37-Y37) | AB37: =IF($G37="","",IF($G37=1,(W37-$C$2-H37)/($C$2+H37),(W37-W36-H37)/(W36+H37))) | AC37: =IF($G37="","",IF($G37=1,(X37-$C$2-H37)/($C$2+H37),(X37-X36-H37)/(X36+H37))) | AD37: =IF($G37="","",AC37-AB37) | AE37: =IF($G37="","",IF($G37=1,Y37,(1+Y37)*(1+AE36)-1)) | AF37: =IF($G37="","",IF($G37=1,Z37,(1+Z37)*(1+AF36)-1)) | AG37: =IF($G37="","",AF37-AE37) | AH37: =IF($G37="","",IF($G37=1,AB37,(1+AB37)*(1+AH36)-1)) | AI37: =IF($G37="","",IF($G37=1,AC37,(1+AC37)*(1+AI36)-1)) | AJ37: =IF($G37="","",AI37-AH37) | AK37: =IF($G37="","",(1+AE37)^(1/G37)-1) | AL37: =IF($G37="","",(1+AF37)^(1/G37)-1) | AM37: =IF($G37="","",AL37-AK37) | AN37: =IF($G37="","",(1+AH37)^(1/G37)-1) | AO37: =IF($G37="","",(1+AI37)^(1/G37)-1) | AP37: =IF($G37="","",AO37-AN37)
H38: =IF(G38="","",SUMIFS(Add_Contributions[[#All],[Amount ($)]],Add_Contributions[[#All],[Year]],G38)) | I38: =IF($G38="","",IF($G38=1,(($C$2+$H38)*I$3)*(1+(I$4-I$5)),((I37+($H38*I$3))*(1+(I$4-I$5))))) | J38: =IF($G38="","",IF($G38=1,(($C$2+$H38)*J$3)*(1+(J$4-J$5)),((J37+($H38*J$3))*(1+(J$4-J$5))))) | K38: =IF($G38="","",IF($G38=1,(($C$2+$H38)*K$3)*(1+(K$4-K$5)),((K37+($H38*K$3))*(1+(K$4-K$5))))) | L38: =IF($G38="","",IF($G38=1,(($C$2+$H38)*L$3)*(1+(L$4-L$5)),((L37+($H38*L$3))*(1+(L$4-L$5))))) | M38: =IF($G38="","",IF($G38=1,(($C$2+$H38)*M$3)*(1+(M$4-M$5)),((M37+($H38*M$3))*(1+(M$4-M$5))))) | N38: =IF($G38="","",IF($G38=1,(($C$2+$H38)*N$3)*(1+(N$4-N$5)),((N37+($H38*N$3))*(1+(N$4-N$5))))) | O38: =IF($G38="","",IF($G38=1,(($C$2+$H38)*O$3)*(1+(O$4-O$5)),((O37+($H38*O$3))*(1+(O$4-O$5))))) | P38: =IF($G38="","",IF($G38=1,(($C$2+$H38)*P$3)*(1+(P$4-P$5)),((P37+($H38*P$3))*(1+(P$4-P$5))))) | ... T38: =IF($G38="","",IF($G38=1,(($C$2+$H38)*T$3)*(1+(T$4-T$5)),((T37+($H38*T$3))*(1+(T$4-T$5))))) | U38: =IF(G38="","",SUM(I38,K38,M38,O38,Q38,S38)) | V38: =IF(H38="","",SUM(J38,L38,N38,P38,R38,T38)) | W38: =IF($G38="","",IF($G38=1,(($C$2+$H38)*W$3)*(1+(W$4-W$5)),((W37+($H38*W$3))*(1+(W$4-W$5))))) | X38: =IF($G38="","",IF($G38=1,(($C$2+$H38)*X$3)*(1+(X$4-X$5)),((X37+($H38*X$3))*(1+(X$4-X$5))))) | Y38: =IF($G38="","",IF($G38=1,(U38-$C$2-H38)/($C$2+H38),(U38-U37-H38)/(U37+H38))) | Z38: =IF($G38="","",IF($G38=1,(V38-$C$2-H38)/($C$2+H38),(V38-V37-H38)/(V37+H38))) | AA38: =IF($G38="","",Z38-Y38) | AB38: =IF($G38="","",IF($G38=1,(W38-$C$2-H38)/($C$2+H38),(W38-W37-H38)/(W37+H38))) | AC38: =IF($G38="","",IF($G38=1,(X38-$C$2-H38)/($C$2+H38),(X38-X37-H38)/(X37+H38))) | AD38: =IF($G38="","",AC38-AB38) | AE38: =IF($G38="","",IF($G38=1,Y38,(1+Y38)*(1+AE37)-1)) | AF38: =IF($G38="","",IF($G38=1,Z38,(1+Z38)*(1+AF37)-1)) | AG38: =IF($G38="","",AF38-AE38) | AH38: =IF($G38="","",IF($G38=1,AB38,(1+AB38)*(1+AH37)-1)) | AI38: =IF($G38="","",IF($G38=1,AC38,(1+AC38)*(1+AI37)-1)) | AJ38: =IF($G38="","",AI38-AH38) | AK38: =IF($G38="","",(1+AE38)^(1/G38)-1) | AL38: =IF($G38="","",(1+AF38)^(1/G38)-1) | AM38: =IF($G38="","",AL38-AK38) | AN38: =IF($G38="","",(1+AH38)^(1/G38)-1) | AO38: =IF($G38="","",(1+AI38)^(1/G38)-1) | AP38: =IF($G38="","",AO38-AN38)
H39: =IF(G39="","",SUMIFS(Add_Contributions[[#All],[Amount ($)]],Add_Contributions[[#All],[Year]],G39)) | I39: =IF($G39="","",IF($G39=1,(($C$2+$H39)*I$3)*(1+(I$4-I$5)),((I38+($H39*I$3))*(1+(I$4-I$5))))) | J39: =IF($G39="","",IF($G39=1,(($C$2+$H39)*J$3)*(1+(J$4-J$5)),((J38+($H39*J$3))*(1+(J$4-J$5))))) | K39: =IF($G39="","",IF($G39=1,(($C$2+$H39)*K$3)*(1+(K$4-K$5)),((K38+($H39*K$3))*(1+(K$4-K$5))))) | L39: =IF($G39="","",IF($G39=1,(($C$2+$H39)*L$3)*(1+(L$4-L$5)),((L38+($H39*L$3))*(1+(L$4-L$5))))) | M39: =IF($G39="","",IF($G39=1,(($C$2+$H39)*M$3)*(1+(M$4-M$5)),((M38+($H39*M$3))*(1+(M$4-M$5))))) | N39: =IF($G39="","",IF($G39=1,(($C$2+$H39)*N$3)*(1+(N$4-N$5)),((N38+($H39*N$3))*(1+(N$4-N$5))))) | O39: =IF($G39="","",IF($G39=1,(($C$2+$H39)*O$3)*(1+(O$4-O$5)),((O38+($H39*O$3))*(1+(O$4-O$5))))) | P39: =IF($G39="","",IF($G39=1,(($C$2+$H39)*P$3)*(1+(P$4-P$5)),((P38+($H39*P$3))*(1+(P$4-P$5))))) | ... T39: =IF($G39="","",IF($G39=1,(($C$2+$H39)*T$3)*(1+(T$4-T$5)),((T38+($H39*T$3))*(1+(T$4-T$5))))) | U39: =IF(G39="","",SUM(I39,K39,M39,O39,Q39,S39)) | V39: =IF(H39="","",SUM(J39,L39,N39,P39,R39,T39)) | W39: =IF($G39="","",IF($G39=1,(($C$2+$H39)*W$3)*(1+(W$4-W$5)),((W38+($H39*W$3))*(1+(W$4-W$5))))) | X39: =IF($G39="","",IF($G39=1,(($C$2+$H39)*X$3)*(1+(X$4-X$5)),((X38+($H39*X$3))*(1+(X$4-X$5))))) | Y39: =IF($G39="","",IF($G39=1,(U39-$C$2-H39)/($C$2+H39),(U39-U38-H39)/(U38+H39))) | Z39: =IF($G39="","",IF($G39=1,(V39-$C$2-H39)/($C$2+H39),(V39-V38-H39)/(V38+H39))) | AA39: =IF($G39="","",Z39-Y39) | AB39: =IF($G39="","",IF($G39=1,(W39-$C$2-H39)/($C$2+H39),(W39-W38-H39)/(W38+H39))) | AC39: =IF($G39="","",IF($G39=1,(X39-$C$2-H39)/($C$2+H39),(X39-X38-H39)/(X38+H39))) | AD39: =IF($G39="","",AC39-AB39) | AE39: =IF($G39="","",IF($G39=1,Y39,(1+Y39)*(1+AE38)-1)) | AF39: =IF($G39="","",IF($G39=1,Z39,(1+Z39)*(1+AF38)-1)) | AG39: =IF($G39="","",AF39-AE39) | AH39: =IF($G39="","",IF($G39=1,AB39,(1+AB39)*(1+AH38)-1)) | AI39: =IF($G39="","",IF($G39=1,AC39,(1+AC39)*(1+AI38)-1)) | AJ39: =IF($G39="","",AI39-AH39) | AK39: =IF($G39="","",(1+AE39)^(1/G39)-1) | AL39: =IF($G39="","",(1+AF39)^(1/G39)-1) | AM39: =IF($G39="","",AL39-AK39) | AN39: =IF($G39="","",(1+AH39)^(1/G39)-1) | AO39: =IF($G39="","",(1+AI39)^(1/G39)-1) | AP39: =IF($G39="","",AO39-AN39)
H40: =IF(G40="","",SUMIFS(Add_Contributions[[#All],[Amount ($)]],Add_Contributions[[#All],[Year]],G40)) | I40: =IF($G40="","",IF($G40=1,(($C$2+$H40)*I$3)*(1+(I$4-I$5)),((I39+($H40*I$3))*(1+(I$4-I$5))))) | J40: =IF($G40="","",IF($G40=1,(($C$2+$H40)*J$3)*(1+(J$4-J$5)),((J39+($H40*J$3))*(1+(J$4-J$5))))) | K40: =IF($G40="","",IF($G40=1,(($C$2+$H40)*K$3)*(1+(K$4-K$5)),((K39+($H40*K$3))*(1+(K$4-K$5))))) | L40: =IF($G40="","",IF($G40=1,(($C$2+$H40)*L$3)*(1+(L$4-L$5)),((L39+($H40*L$3))*(1+(L$4-L$5))))) | M40: =IF($G40="","",IF($G40=1,(($C$2+$H40)*M$3)*(1+(M$4-M$5)),((M39+($H40*M$3))*(1+(M$4-M$5))))) | N40: =IF($G40="","",IF($G40=1,(($C$2+$H40)*N$3)*(1+(N$4-N$5)),((N39+($H40*N$3))*(1+(N$4-N$5))))) | O40: =IF($G40="","",IF($G40=1,(($C$2+$H40)*O$3)*(1+(O$4-O$5)),((O39+($H40*O$3))*(1+(O$4-O$5))))) | P40: =IF($G40="","",IF($G40=1,(($C$2+$H40)*P$3)*(1+(P$4-P$5)),((P39+($H40*P$3))*(1+(P$4-P$5))))) | ... T40: =IF($G40="","",IF($G40=1,(($C$2+$H40)*T$3)*(1+(T$4-T$5)),((T39+($H40*T$3))*(1+(T$4-T$5))))) | U40: =IF(G40="","",SUM(I40,K40,M40,O40,Q40,S40)) | V40: =IF(H40="","",SUM(J40,L40,N40,P40,R40,T40)) | W40: =IF($G40="","",IF($G40=1,(($C$2+$H40)*W$3)*(1+(W$4-W$5)),((W39+($H40*W$3))*(1+(W$4-W$5))))) | X40: =IF($G40="","",IF($G40=1,(($C$2+$H40)*X$3)*(1+(X$4-X$5)),((X39+($H40*X$3))*(1+(X$4-X$5))))) | Y40: =IF($G40="","",IF($G40=1,(U40-$C$2-H40)/($C$2+H40),(U40-U39-H40)/(U39+H40))) | Z40: =IF($G40="","",IF($G40=1,(V40-$C$2-H40)/($C$2+H40),(V40-V39-H40)/(V39+H40))) | AA40: =IF($G40="","",Z40-Y40) | AB40: =IF($G40="","",IF($G40=1,(W40-$C$2-H40)/($C$2+H40),(W40-W39-H40)/(W39+H40))) | AC40: =IF($G40="","",IF($G40=1,(X40-$C$2-H40)/($C$2+H40),(X40-X39-H40)/(X39+H40))) | AD40: =IF($G40="","",AC40-AB40) | AE40: =IF($G40="","",IF($G40=1,Y40,(1+Y40)*(1+AE39)-1)) | AF40: =IF($G40="","",IF($G40=1,Z40,(1+Z40)*(1+AF39)-1)) | AG40: =IF($G40="","",AF40-AE40) | AH40: =IF($G40="","",IF($G40=1,AB40,(1+AB40)*(1+AH39)-1)) | AI40: =IF($G40="","",IF($G40=1,AC40,(1+AC40)*(1+AI39)-1)) | AJ40: =IF($G40="","",AI40-AH40) | AK40: =IF($G40="","",(1+AE40)^(1/G40)-1) | AL40: =IF($G40="","",(1+AF40)^(1/G40)-1) | AM40: =IF($G40="","",AL40-AK40) | AN40: =IF($G40="","",(1+AH40)^(1/G40)-1) | AO40: =IF($G40="","",(1+AI40)^(1/G40)-1) | AP40: =IF($G40="","",AO40-AN40)
H41: =IF(G41="","",SUMIFS(Add_Contributions[[#All],[Amount ($)]],Add_Contributions[[#All],[Year]],G41)) | I41: =IF($G41="","",IF($G41=1,(($C$2+$H41)*I$3)*(1+(I$4-I$5)),((I40+($H41*I$3))*(1+(I$4-I$5))))) | J41: =IF($G41="","",IF($G41=1,(($C$2+$H41)*J$3)*(1+(J$4-J$5)),((J40+($H41*J$3))*(1+(J$4-J$5))))) | K41: =IF($G41="","",IF($G41=1,(($C$2+$H41)*K$3)*(1+(K$4-K$5)),((K40+($H41*K$3))*(1+(K$4-K$5))))) | L41: =IF($G41="","",IF($G41=1,(($C$2+$H41)*L$3)*(1+(L$4-L$5)),((L40+($H41*L$3))*(1+(L$4-L$5))))) | M41: =IF($G41="","",IF($G41=1,(($C$2+$H41)*M$3)*(1+(M$4-M$5)),((M40+($H41*M$3))*(1+(M$4-M$5))))) | N41: =IF($G41="","",IF($G41=1,(($C$2+$H41)*N$3)*(1+(N$4-N$5)),((N40+($H41*N$3))*(1+(N$4-N$5))))) | O41: =IF($G41="","",IF($G41=1,(($C$2+$H41)*O$3)*(1+(O$4-O$5)),((O40+($H41*O$3))*(1+(O$4-O$5))))) | P41: =IF($G41="","",IF($G41=1,(($C$2+$H41)*P$3)*(1+(P$4-P$5)),((P40+($H41*P$3))*(1+(P$4-P$5))))) | ... T41: =IF($G41="","",IF($G41=1,(($C$2+$H41)*T$3)*(1+(T$4-T$5)),((T40+($H41*T$3))*(1+(T$4-T$5))))) | U41: =IF(G41="","",SUM(I41,K41,M41,O41,Q41,S41)) | V41: =IF(H41="","",SUM(J41,L41,N41,P41,R41,T41)) | W41: =IF($G41="","",IF($G41=1,(($C$2+$H41)*W$3)*(1+(W$4-W$5)),((W40+($H41*W$3))*(1+(W$4-W$5))))) | X41: =IF($G41="","",IF($G41=1,(($C$2+$H41)*X$3)*(1+(X$4-X$5)),((X40+($H41*X$3))*(1+(X$4-X$5))))) | Y41: =IF($G41="","",IF($G41=1,(U41-$C$2-H41)/($C$2+H41),(U41-U40-H41)/(U40+H41))) | Z41: =IF($G41="","",IF($G41=1,(V41-$C$2-H41)/($C$2+H41),(V41-V40-H41)/(V40+H41))) | AA41: =IF($G41="","",Z41-Y41) | AB41: =IF($G41="","",IF($G41=1,(W41-$C$2-H41)/($C$2+H41),(W41-W40-H41)/(W40+H41))) | AC41: =IF($G41="","",IF($G41=1,(X41-$C$2-H41)/($C$2+H41),(X41-X40-H41)/(X40+H41))) | AD41: =IF($G41="","",AC41-AB41) | AE41: =IF($G41="","",IF($G41=1,Y41,(1+Y41)*(1+AE40)-1)) | AF41: =IF($G41="","",IF($G41=1,Z41,(1+Z41)*(1+AF40)-1)) | AG41: =IF($G41="","",AF41-AE41) | AH41: =IF($G41="","",IF($G41=1,AB41,(1+AB41)*(1+AH40)-1)) | AI41: =IF($G41="","",IF($G41=1,AC41,(1+AC41)*(1+AI40)-1)) | AJ41: =IF($G41="","",AI41-AH41) | AK41: =IF($G41="","",(1+AE41)^(1/G41)-1) | AL41: =IF($G41="","",(1+AF41)^(1/G41)-1) | AM41: =IF($G41="","",AL41-AK41) | AN41: =IF($G41="","",(1+AH41)^(1/G41)-1) | AO41: =IF($G41="","",(1+AI41)^(1/G41)-1) | AP41: =IF($G41="","",AO41-AN41)
H42: =IF(G42="","",SUMIFS(Add_Contributions[[#All],[Amount ($)]],Add_Contributions[[#All],[Year]],G42)) | I42: =IF($G42="","",IF($G42=1,(($C$2+$H42)*I$3)*(1+(I$4-I$5)),((I41+($H42*I$3))*(1+(I$4-I$5))))) | J42: =IF($G42="","",IF($G42=1,(($C$2+$H42)*J$3)*(1+(J$4-J$5)),((J41+($H42*J$3))*(1+(J$4-J$5))))) | K42: =IF($G42="","",IF($G42=1,(($C$2+$H42)*K$3)*(1+(K$4-K$5)),((K41+($H42*K$3))*(1+(K$4-K$5))))) | L42: =IF($G42="","",IF($G42=1,(($C$2+$H42)*L$3)*(1+(L$4-L$5)),((L41+($H42*L$3))*(1+(L$4-L$5))))) | M42: =IF($G42="","",IF($G42=1,(($C$2+$H42)*M$3)*(1+(M$4-M$5)),((M41+($H42*M$3))*(1+(M$4-M$5))))) | N42: =IF($G42="","",IF($G42=1,(($C$2+$H42)*N$3)*(1+(N$4-N$5)),((N41+($H42*N$3))*(1+(N$4-N$5))))) | O42: =IF($G42="","",IF($G42=1,(($C$2+$H42)*O$3)*(1+(O$4-O$5)),((O41+($H42*O$3))*(1+(O$4-O$5))))) | P42: =IF($G42="","",IF($G42=1,(($C$2+$H42)*P$3)*(1+(P$4-P$5)),((P41+($H42*P$3))*(1+(P$4-P$5))))) | ... T42: =IF($G42="","",IF($G42=1,(($C$2+$H42)*T$3)*(1+(T$4-T$5)),((T41+($H42*T$3))*(1+(T$4-T$5))))) | U42: =IF(G42="","",SUM(I42,K42,M42,O42,Q42,S42)) | V42: =IF(H42="","",SUM(J42,L42,N42,P42,R42,T42)) | W42: =IF($G42="","",IF($G42=1,(($C$2+$H42)*W$3)*(1+(W$4-W$5)),((W41+($H42*W$3))*(1+(W$4-W$5))))) | X42: =IF($G42="","",IF($G42=1,(($C$2+$H42)*X$3)*(1+(X$4-X$5)),((X41+($H42*X$3))*(1+(X$4-X$5))))) | Y42: =IF($G42="","",IF($G42=1,(U42-$C$2-H42)/($C$2+H42),(U42-U41-H42)/(U41+H42))) | Z42: =IF($G42="","",IF($G42=1,(V42-$C$2-H42)/($C$2+H42),(V42-V41-H42)/(V41+H42))) | AA42: =IF($G42="","",Z42-Y42) | AB42: =IF($G42="","",IF($G42=1,(W42-$C$2-H42)/($C$2+H42),(W42-W41-H42)/(W41+H42))) | AC42: =IF($G42="","",IF($G42=1,(X42-$C$2-H42)/($C$2+H42),(X42-X41-H42)/(X41+H42))) | AD42: =IF($G42="","",AC42-AB42) | AE42: =IF($G42="","",IF($G42=1,Y42,(1+Y42)*(1+AE41)-1)) | AF42: =IF($G42="","",IF($G42=1,Z42,(1+Z42)*(1+AF41)-1)) | AG42: =IF($G42="","",AF42-AE42) | AH42: =IF($G42="","",IF($G42=1,AB42,(1+AB42)*(1+AH41)-1)) | AI42: =IF($G42="","",IF($G42=1,AC42,(1+AC42)*(1+AI41)-1)) | AJ42: =IF($G42="","",AI42-AH42) | AK42: =IF($G42="","",(1+AE42)^(1/G42)-1) | AL42: =IF($G42="","",(1+AF42)^(1/G42)-1) | AM42: =IF($G42="","",AL42-AK42) | AN42: =IF($G42="","",(1+AH42)^(1/G42)-1) | AO42: =IF($G42="","",(1+AI42)^(1/G42)-1) | AP42: =IF($G42="","",AO42-AN42)
... H109: =IF(G109="","",SUMIFS(Add_Contributions[[#All],[Amount ($)]],Add_Contributions[[#All],[Year]],G109)) | I109: =IF($G109="","",IF($G109=1,(($C$2+$H109)*I$3)*(1+(I$4-I$5)),((I108+($H109*I$3))*(1+(I$4-I$5))))) | J109: =IF($G109="","",IF($G109=1,(($C$2+$H109)*J$3)*(1+(J$4-J$5)),((J108+($H109*J$3))*(1+(J$4-J$5))))) | K109: =IF($G109="","",IF($G109=1,(($C$2+$H109)*K$3)*(1+(K$4-K$5)),((K108+($H109*K$3))*(1+(K$4-K$5))))) | L109: =IF($G109="","",IF($G109=1,(($C$2+$H109)*L$3)*(1+(L$4-L$5)),((L108+($H109*L$3))*(1+(L$4-L$5))))) | M109: =IF($G109="","",IF($G109=1,(($C$2+$H109)*M$3)*(1+(M$4-M$5)),((M108+($H109*M$3))*(1+(M$4-M$5))))) | N109: =IF($G109="","",IF($G109=1,(($C$2+$H109)*N$3)*(1+(N$4-N$5)),((N108+($H109*N$3))*(1+(N$4-N$5))))) | O109: =IF($G109="","",IF($G109=1,(($C$2+$H109)*O$3)*(1+(O$4-O$5)),((O108+($H109*O$3))*(1+(O$4-O$5))))) | P109: =IF($G109="","",IF($G109=1,(($C$2+$H109)*P$3)*(1+(P$4-P$5)),((P108+($H109*P$3))*(1+(P$4-P$5))))) | ... T109: =IF($G109="","",IF($G109=1,(($C$2+$H109)*T$3)*(1+(T$4-T$5)),((T108+($H109*T$3))*(1+(T$4-T$5))))) | U109: =IF(G109="","",SUM(I109,K109,M109,O109,Q109,S109)) | V109: =IF(H109="","",SUM(J109,L109,N109,P109,R109,T109)) | W109: =IF($G109="","",IF($G109=1,(($C$2+$H109)*W$3)*(1+(W$4-W$5)),((W108+($H109*W$3))*(1+(W$4-W$5))))) | X109: =IF($G109="","",IF($G109=1,(($C$2+$H109)*X$3)*(1+(X$4-X$5)),((X108+($H109*X$3))*(1+(X$4-X$5))))) | Y109: =IF($G109="","",IF($G109=1,(U109-$C$2-H109)/($C$2+H109),(U109-U108-H109)/(U108+H109))) | Z109: =IF($G109="","",IF($G109=1,(V109-$C$2-H109)/($C$2+H109),(V109-V108-H109)/(V108+H109))) | AA109: =IF($G109="","",Z109-Y109) | AB109: =IF($G109="","",IF($G109=1,(W109-$C$2-H109)/($C$2+H109),(W109-W108-H109)/(W108+H109))) | AC109: =IF($G109="","",IF($G109=1,(X109-$C$2-H109)/($C$2+H109),(X109-X108-H109)/(X108+H109))) | AD109: =IF($G109="","",AC109-AB109) | AE109: =IF($G109="","",IF($G109=1,Y109,(1+Y109)*(1+AE108)-1)) | AF109: =IF($G109="","",IF($G109=1,Z109,(1+Z109)*(1+AF108)-1)) | AG109: =IF($G109="","",AF109-AE109) | AH109: =IF($G109="","",IF($G109=1,AB109,(1+AB109)*(1+AH108)-1)) | AI109: =IF($G109="","",IF($G109=1,AC109,(1+AC109)*(1+AI108)-1)) | AJ109: =IF($G109="","",AI109-AH109) | AK109: =IF($G109="","",(1+AE109)^(1/G109)-1) | AL109: =IF($G109="","",(1+AF109)^(1/G109)-1) | AM109: =IF($G109="","",AL109-AK109) | AN109: =IF($G109="","",(1+AH109)^(1/G109)-1) | AO109: =IF($G109="","",(1+AI109)^(1/G109)-1) | AP109: =IF($G109="","",AO109-AN109)

Sheet Trad. Tax.
B2: Initial Capital ($) | C2: =Page!C3 -> 10000000 | I2: Stocks (Taxable) | J2: Stocks (Taxable) | K2: Stocks (PPLI) | L2: Stocks (PPLI) | M2: Bonds (Taxable) | N2: Bonds (Taxable) | O2: Bonds (PPLI) | P2: Bonds (PPLI) | Q2: Alternatives (Taxable) | R2: Alternatives (Taxable) | S2: Alternatives (PPLI) | T2: Alternatives (PPLI) | W2: Weighted Average | X2: Weighted Average
B3: Time Horizon (Years) | C3: =Page!C4 -> 20 | H3: Weight | I3: =$D$7*(1-$E$7) -> 0.6 | J3: =$D$7*(1-$E$7) -> 0.6 | K3: =$D$7*$E$7 -> 0 | L3: =$D$7*$E$7 -> 0 | M3: =$D$8*(1-$E$8) -> 0.4 | N3: =$D$8*(1-$E$8) -> 0.4 | O3: =$D$8*$E$8 -> 0 | P3: =$D$8*$E$8 -> 0 | Q3: =$D$9*(1-$E$9) -> 0 | R3: =$D$9*(1-$E$9) -> 0 | S3: =$D$9*$E$9 -> 0 | T3: =$D$9*$E$9 -> 0 | W3: =SUM(I3,K3,M3,O3,Q3,S3) -> 1 | X3: =SUM(J3,L3,N3,P3,R3,T3) -> 1
H4: Return | I4: =$C$7 -> 0.08 | J4: =$C$7 -> 0.08 | K4: =$C$7 -> 0.08 | L4: =$C$7 -> 0.08 | M4: =$C$8 -> 0.05 | N4: =$C$8 -> 0.05 | O4: =$C$8 -> 0.05 | P4: =$C$8 -> 0.05 | Q4: =$C$9 -> 0.08 | R4: =$C$9 -> 0.08 | S4: =$C$9 -> 0.08 | T4: =$C$9 -> 0.08 | W4: =SUMPRODUCT(I3:T3,I4:T4)/2 -> 0.068 | X4: =SUMPRODUCT(I3:T3,I4:T4)/2 -> 0.068
D5: =IF(SUM(D7:D9)<>1,"Error","Good") -> Good | H5: Drag | I5: 0 | J5: =$C$7*($C$15+$C$16) -> 0.01904 | K5: 0 | L5: =$C$11 -> 0.005 | M5: 0 | N5: =$C$8*($C$14+$C$16) -> 0.0204 | O5: 0 | P5: =$C$11 -> 0.005 | Q5: 0 | R5: =(50%*$C$9*($C$14+$C$16))+(50%*$C$9*($C$15+$C$16)) -> 0.02584 | S5: 0 | T5: =$C$11 -> 0.005 | W5: 0 | X5: =SUMPRODUCT(J3:T3,J5:T5) -> 0.019584
C6: Returns | D6: Weight | E6: PPLI Allocation
B7: Stocks | C7: =Page!C12 -> 0.08 | D7: 0.6 | E7: 0 | U7: Buy & Hold | V7: Buy & Hold | W7: Rebalanced | X7: Rebalanced | Y7: Buy & Hold | Z7: Buy & Hold | AA7: Buy & Hold | AB7: Rebalanced | AC7: Rebalanced | AD7: Rebalanced | AE7: Buy & Hold | AF7: Buy & Hold | AG7: Buy & Hold | AH7: Rebalanced | AI7: Rebalanced | AJ7: Rebalanced | AK7: Buy & Hold | AL7: Buy & Hold | AM7: Buy & Hold | AN7: Rebalanced | AO7: Rebalanced | AP7: Rebalanced
B8: Bonds | C8: =Page!C13 -> 0.05 | D8: 0.4 | E8: 0 | I8: Gross | J8: Net | K8: Gross | L8: Net | M8: Gross | N8: Net | O8: Gross | P8: Net | Q8: Gross | R8: Net | S8: Gross | T8: Net | U8: Gross | V8: Net | W8: Gross | X8: Net | Y8: Gross | Z8: Net | AB8: Gross | AC8: Net | AE8: Gross | AF8: Net | AH8: Gross | AI8: Net | AK8: Gross | AL8: Net | AN8: Gross | AO8: Net
B9: Alternatives | C9: =Page!C14 -> 0.08 | D9: 0 | E9: 0 | G9: Year | H9: Contributions | I9: Stocks (Taxable) | J9: Stocks (Taxable) | K9: Stocks (PPLI) | L9: Stocks (PPLI) | M9: Bonds (Taxable) | N9: Bonds (Taxable) | O9: Bonds (PPLI) | P9: Bonds (PPLI) | Q9: Alternatives (Taxable) | R9: Alternatives (Taxable) | S9: Alternatives (PPLI) | T9: Alternatives (PPLI) | U9: Total | V9: Total | W9: Total | X9: Total | Y9: Period Return | Z9: Period Return | AA9: Period Drag | AB9: Period Return | AC9: Period Return | AD9: Period Drag | AE9: Total Return | AF9: Total Return | AG9: Total Drag | AH9: Total Return | AI9: Total Return | AJ9: Total Drag | AK9: Total Return (Annualized) | AL9: Total Return (Annualized) | AM9: Annaulized Drag | AN9: Total Return (Annualized) | AO9: Total Return (Annualized) | AP9: Annaulized Drag
D10: * Weights Static | E10: * Weights Static | G10: {=_xlfn.SEQUENCE(C3,1,1,1)} -> 1 | H10: =IF(G10="","",SUMIFS(Add_Contributions[[#All],[Amount ($)]],Add_Contributions[[#All],[Year]],G10)) -> 0 | I10: =IF($G10="","",IF($G10=1,(($C$2+$H10)*I$3)*(1+(I$4-I$5)),((I9+($H10*I$3))*(1+(I$4-I$5))))) -> 6480000 | J10: =IF($G10="","",IF($G10=1,(($C$2+$H10)*J$3)*(1+(J$4-J$5)),((J9+($H10*J$3))*(1+(J$4-J$5))))) -> 6365760 | K10: =IF($G10="","",IF($G10=1,(($C$2+$H10)*K$3)*(1+(K$4-K$5)),((K9+($H10*K$3))*(1+(K$4-K$5))))) -> 0 | L10: =IF($G10="","",IF($G10=1,(($C$2+$H10)*L$3)*(1+(L$4-L$5)),((L9+($H10*L$3))*(1+(L$4-L$5))))) -> 0 | M10: =IF($G10="","",IF($G10=1,(($C$2+$H10)*M$3)*(1+(M$4-M$5)),((M9+($H10*M$3))*(1+(M$4-M$5))))) -> 4200000 | N10: =IF($G10="","",IF($G10=1,(($C$2+$H10)*N$3)*(1+(N$4-N$5)),((N9+($H10*N$3))*(1+(N$4-N$5))))) -> 4118400 | O10: =IF($G10="","",IF($G10=1,(($C$2+$H10)*O$3)*(1+(O$4-O$5)),((O9+($H10*O$3))*(1+(O$4-O$5))))) -> 0 | P10: =IF($G10="","",IF($G10=1,(($C$2+$H10)*P$3)*(1+(P$4-P$5)),((P9+($H10*P$3))*(1+(P$4-P$5))))) -> 0 | ... T10: =IF($G10="","",IF($G10=1,(($C$2+$H10)*T$3)*(1+(T$4-T$5)),((T9+($H10*T$3))*(1+(T$4-T$5))))) -> 0 | U10: =IF(G10="","",SUM(I10,K10,M10,O10,Q10,S10)) -> 10680000 | V10: =IF(H10="","",SUM(J10,L10,N10,P10,R10,T10)) -> 10484160 | W10: =IF($G10="","",IF($G10=1,(($C$2+$H10)*W$3)*(1+(W$4-W$5)),((W9+($H10*W$3))*(1+(W$4-W$5))))) -> 10680000 | X10: =IF($G10="","",IF($G10=1,(($C$2+$H10)*X$3)*(1+(X$4-X$5)),((X9+($H10*X$3))*(1+(X$4-X$5))))) -> 10484160 | Y10: =IF($G10="","",IF($G10=1,(U10-$C$2-H10)/($C$2+H10),(U10-U9-H10)/(U9+H10))) -> 0.068 | Z10: =IF($G10="","",IF($G10=1,(V10-$C$2-H10)/($C$2+H10),(V10-V9-H10)/(V9+H10))) -> 0.048416 | AA10: =IF($G10="","",Z10-Y10) -> -0.019584 | AB10: =IF($G10="","",IF($G10=1,(W10-$C$2-H10)/($C$2+H10),(W10-W9-H10)/(W9+H10))) -> 0.068 | AC10: =IF($G10="","",IF($G10=1,(X10-$C$2-H10)/($C$2+H10),(X10-X9-H10)/(X9+H10))) -> 0.048416 | AD10: =IF($G10="","",AC10-AB10) -> -0.019584 | AE10: =IF($G10="","",IF($G10=1,Y10,(1+Y10)*(1+AE9)-1)) -> 0.068 | AF10: =IF($G10="","",IF($G10=1,Z10,(1+Z10)*(1+AF9)-1)) -> 0.048416 | AG10: =IF($G10="","",AF10-AE10) -> -0.019584 | AH10: =IF($G10="","",IF($G10=1,AB10,(1+AB10)*(1+AH9)-1)) -> 0.068 | AI10: =IF($G10="","",IF($G10=1,AC10,(1+AC10)*(1+AI9)-1)) -> 0.048416 | AJ10: =IF($G10="","",AI10-AH10) -> -0.019584 | AK10: =IF($G10="","",(1+AE10)^(1/G10)-1) -> 0.068 | AL10: =IF($G10="","",(1+AF10)^(1/G10)-1) -> 0.048416 | AM10: =IF($G10="","",AL10-AK10) -> -0.019584 | AN10: =IF($G10="","",(1+AH10)^(1/G10)-1) -> 0.068 | AO10: =IF($G10="","",(1+AI10)^(1/G10)-1) -> 0.048416 | AP10: =IF($G10="","",AO10-AN10) -> -0.019584
B11: PPLI Policy Costs | C11: =Page!C27 -> 0.005 | G11: 2 | H11: =IF(G11="","",SUMIFS(Add_Contributions[[#All],[Amount ($)]],Add_Contributions[[#All],[Year]],G11)) -> 0 | I11: =IF($G11="","",IF($G11=1,(($C$2+$H11)*I$3)*(1+(I$4-I$5)),((I10+($H11*I$3))*(1+(I$4-I$5))))) -> 6998400 | J11: =IF($G11="","",IF($G11=1,(($C$2+$H11)*J$3)*(1+(J$4-J$5)),((J10+($H11*J$3))*(1+(J$4-J$5))))) -> 6753816.7 | K11: =IF($G11="","",IF($G11=1,(($C$2+$H11)*K$3)*(1+(K$4-K$5)),((K10+($H11*K$3))*(1+(K$4-K$5))))) -> 0 | L11: =IF($G11="","",IF($G11=1,(($C$2+$H11)*L$3)*(1+(L$4-L$5)),((L10+($H11*L$3))*(1+(L$4-L$5))))) -> 0 | M11: =IF($G11="","",IF($G11=1,(($C$2+$H11)*M$3)*(1+(M$4-M$5)),((M10+($H11*M$3))*(1+(M$4-M$5))))) -> 4410000 | N11: =IF($G11="","",IF($G11=1,(($C$2+$H11)*N$3)*(1+(N$4-N$5)),((N10+($H11*N$3))*(1+(N$4-N$5))))) -> 4240304.6 | O11: =IF($G11="","",IF($G11=1,(($C$2+$H11)*O$3)*(1+(O$4-O$5)),((O10+($H11*O$3))*(1+(O$4-O$5))))) -> 0 | P11: =IF($G11="","",IF($G11=1,(($C$2+$H11)*P$3)*(1+(P$4-P$5)),((P10+($H11*P$3))*(1+(P$4-P$5))))) -> 0 | ... T11: =IF($G11="","",IF($G11=1,(($C$2+$H11)*T$3)*(1+(T$4-T$5)),((T10+($H11*T$3))*(1+(T$4-T$5))))) -> 0 | U11: =IF(G11="","",SUM(I11,K11,M11,O11,Q11,S11)) -> 11408400 | V11: =IF(H11="","",SUM(J11,L11,N11,P11,R11,T11)) -> 10994121 | W11: =IF($G11="","",IF($G11=1,(($C$2+$H11)*W$3)*(1+(W$4-W$5)),((W10+($H11*W$3))*(1+(W$4-W$5))))) -> 11406240 | X11: =IF($G11="","",IF($G11=1,(($C$2+$H11)*X$3)*(1+(X$4-X$5)),((X10+($H11*X$3))*(1+(X$4-X$5))))) -> 10991761 | Y11: =IF($G11="","",IF($G11=1,(U11-$C$2-H11)/($C$2+H11),(U11-U10-H11)/(U10+H11))) -> 0.068202247 | Z11: =IF($G11="","",IF($G11=1,(V11-$C$2-H11)/($C$2+H11),(V11-V10-H11)/(V10+H11))) -> 0.048641128 | AA11: =IF($G11="","",Z11-Y11) -> -0.019561119 | AB11: =IF($G11="","",IF($G11=1,(W11-$C$2-H11)/($C$2+H11),(W11-W10-H11)/(W10+H11))) -> 0.068 | AC11: =IF($G11="","",IF($G11=1,(X11-$C$2-H11)/($C$2+H11),(X11-X10-H11)/(X10+H11))) -> 0.048416 | AD11: =IF($G11="","",AC11-AB11) -> -0.019584 | AE11: =IF($G11="","",IF($G11=1,Y11,(1+Y11)*(1+AE10)-1)) -> 0.14084 | AF11: =IF($G11="","",IF($G11=1,Z11,(1+Z11)*(1+AF10)-1)) -> 0.099412137 | AG11: =IF($G11="","",AF11-AE11) -> -0.041427863 | AH11: =IF($G11="","",IF($G11=1,AB11,(1+AB11)*(1+AH10)-1)) -> 0.140624 | AI11: =IF($G11="","",IF($G11=1,AC11,(1+AC11)*(1+AI10)-1)) -> 0.099176109 | AJ11: =IF($G11="","",AI11-AH11) -> -0.041447891 | AK11: =IF($G11="","",(1+AE11)^(1/G11)-1) -> 0.068101119 | AL11: =IF($G11="","",(1+AF11)^(1/G11)-1) -> 0.048528558 | AM11: =IF($G11="","",AL11-AK11) -> -0.019572561 | AN11: =IF($G11="","",(1+AH11)^(1/G11)-1) -> 0.068 | AO11: =IF($G11="","",(1+AI11)^(1/G11)-1) -> 0.048416 | AP11: =IF($G11="","",AO11-AN11) -> -0.019584
B12: PPLI Start Up Costs | G12: 3 | H12: =IF(G12="","",SUMIFS(Add_Contributions[[#All],[Amount ($)]],Add_Contributions[[#All],[Year]],G12)) -> 0 | I12: =IF($G12="","",IF($G12=1,(($C$2+$H12)*I$3)*(1+(I$4-I$5)),((I11+($H12*I$3))*(1+(I$4-I$5))))) -> 7558272 | J12: =IF($G12="","",IF($G12=1,(($C$2+$H12)*J$3)*(1+(J$4-J$5)),((J11+($H12*J$3))*(1+(J$4-J$5))))) -> 7165529.4 | K12: =IF($G12="","",IF($G12=1,(($C$2+$H12)*K$3)*(1+(K$4-K$5)),((K11+($H12*K$3))*(1+(K$4-K$5))))) -> 0 | L12: =IF($G12="","",IF($G12=1,(($C$2+$H12)*L$3)*(1+(L$4-L$5)),((L11+($H12*L$3))*(1+(L$4-L$5))))) -> 0 | M12: =IF($G12="","",IF($G12=1,(($C$2+$H12)*M$3)*(1+(M$4-M$5)),((M11+($H12*M$3))*(1+(M$4-M$5))))) -> 4630500 | N12: =IF($G12="","",IF($G12=1,(($C$2+$H12)*N$3)*(1+(N$4-N$5)),((N11+($H12*N$3))*(1+(N$4-N$5))))) -> 4365817.7 | O12: =IF($G12="","",IF($G12=1,(($C$2+$H12)*O$3)*(1+(O$4-O$5)),((O11+($H12*O$3))*(1+(O$4-O$5))))) -> 0 | P12: =IF($G12="","",IF($G12=1,(($C$2+$H12)*P$3)*(1+(P$4-P$5)),((P11+($H12*P$3))*(1+(P$4-P$5))))) -> 0 | ... T12: =IF($G12="","",IF($G12=1,(($C$2+$H12)*T$3)*(1+(T$4-T$5)),((T11+($H12*T$3))*(1+(T$4-T$5))))) -> 0 | U12: =IF(G12="","",SUM(I12,K12,M12,O12,Q12,S12)) -> 12188772 | V12: =IF(H12="","",SUM(J12,L12,N12,P12,R12,T12)) -> 11531347 | W12: =IF($G12="","",IF($G12=1,(($C$2+$H12)*W$3)*(1+(W$4-W$5)),((W11+($H12*W$3))*(1+(W$4-W$5))))) -> 12181864 | X12: =IF($G12="","",IF($G12=1,(($C$2+$H12)*X$3)*(1+(X$4-X$5)),((X11+($H12*X$3))*(1+(X$4-X$5))))) -> 11523938 | Y12: =IF($G12="","",IF($G12=1,(U12-$C$2-H12)/($C$2+H12),(U12-U11-H12)/(U11+H12))) -> 0.068403282 | Z12: =IF($G12="","",IF($G12=1,(V12-$C$2-H12)/($C$2+H12),(V12-V11-H12)/(V11+H12))) -> 0.048864813 | AA12: =IF($G12="","",Z12-Y12) -> -0.019538469 | AB12: =IF($G12="","",IF($G12=1,(W12-$C$2-H12)/($C$2+H12),(W12-W11-H12)/(W11+H12))) -> 0.068 | AC12: =IF($G12="","",IF($G12=1,(X12-$C$2-H12)/($C$2+H12),(X12-X11-H12)/(X11+H12))) -> 0.048416 | AD12: =IF($G12="","",AC12-AB12) -> -0.019584 | AE12: =IF($G12="","",IF($G12=1,Y12,(1+Y12)*(1+AE11)-1)) -> 0.2188772 | AF12: =IF($G12="","",IF($G12=1,Z12,(1+Z12)*(1+AF11)-1)) -> 0.15313471 | AG12: =IF($G12="","",AF12-AE12) -> -0.065742495 | AH12: =IF($G12="","",IF($G12=1,AB12,(1+AB12)*(1+AH11)-1)) -> 0.21818643 | AI12: =IF($G12="","",IF($G12=1,AC12,(1+AC12)*(1+AI11)-1)) -> 0.15239382 | AJ12: =IF($G12="","",AI12-AH12) -> -0.065792612 | AK12: =IF($G12="","",(1+AE12)^(1/G12)-1) -> 0.06820183 | AL12: =IF($G12="","",(1+AF12)^(1/G12)-1) -> 0.048640631 | AM12: =IF($G12="","",AL12-AK12) -> -0.019561199 | AN12: =IF($G12="","",(1+AH12)^(1/G12)-1) -> 0.068 | AO12: =IF($G12="","",(1+AI12)^(1/G12)-1) -> 0.048416 | AP12: =IF($G12="","",AO12-AN12) -> -0.019584
G13: 4 | H13: =IF(G13="","",SUMIFS(Add_Contributions[[#All],[Amount ($)]],Add_Contributions[[#All],[Year]],G13)) -> 0 | I13: =IF($G13="","",IF($G13=1,(($C$2+$H13)*I$3)*(1+(I$4-I$5)),((I12+($H13*I$3))*(1+(I$4-I$5))))) -> 8162933.8 | J13: =IF($G13="","",IF($G13=1,(($C$2+$H13)*J$3)*(1+(J$4-J$5)),((J12+($H13*J$3))*(1+(J$4-J$5))))) -> 7602340.1 | K13: =IF($G13="","",IF($G13=1,(($C$2+$H13)*K$3)*(1+(K$4-K$5)),((K12+($H13*K$3))*(1+(K$4-K$5))))) -> 0 | L13: =IF($G13="","",IF($G13=1,(($C$2+$H13)*L$3)*(1+(L$4-L$5)),((L12+($H13*L$3))*(1+(L$4-L$5))))) -> 0 | M13: =IF($G13="","",IF($G13=1,(($C$2+$H13)*M$3)*(1+(M$4-M$5)),((M12+($H13*M$3))*(1+(M$4-M$5))))) -> 4862025 | N13: =IF($G13="","",IF($G13=1,(($C$2+$H13)*N$3)*(1+(N$4-N$5)),((N12+($H13*N$3))*(1+(N$4-N$5))))) -> 4495045.9 | O13: =IF($G13="","",IF($G13=1,(($C$2+$H13)*O$3)*(1+(O$4-O$5)),((O12+($H13*O$3))*(1+(O$4-O$5))))) -> 0 | P13: =IF($G13="","",IF($G13=1,(($C$2+$H13)*P$3)*(1+(P$4-P$5)),((P12+($H13*P$3))*(1+(P$4-P$5))))) -> 0 | ... T13: =IF($G13="","",IF($G13=1,(($C$2+$H13)*T$3)*(1+(T$4-T$5)),((T12+($H13*T$3))*(1+(T$4-T$5))))) -> 0 | U13: =IF(G13="","",SUM(I13,K13,M13,O13,Q13,S13)) -> 13024959 | V13: =IF(H13="","",SUM(J13,L13,N13,P13,R13,T13)) -> 12097386 | W13: =IF($G13="","",IF($G13=1,(($C$2+$H13)*W$3)*(1+(W$4-W$5)),((W12+($H13*W$3))*(1+(W$4-W$5))))) -> 13010231 | X13: =IF($G13="","",IF($G13=1,(($C$2+$H13)*X$3)*(1+(X$4-X$5)),((X12+($H13*X$3))*(1+(X$4-X$5))))) -> 12081881 | Y13: =IF($G13="","",IF($G13=1,(U13-$C$2-H13)/($C$2+H13),(U13-U12-H13)/(U12+H13))) -> 0.068603036 | Z13: =IF($G13="","",IF($G13=1,(V13-$C$2-H13)/($C$2+H13),(V13-V12-H13)/(V12+H13))) -> 0.049086969 | AA13: =IF($G13="","",Z13-Y13) -> -0.019516067 | AB13: =IF($G13="","",IF($G13=1,(W13-$C$2-H13)/($C$2+H13),(W13-W12-H13)/(W12+H13))) -> 0.068 | AC13: =IF($G13="","",IF($G13=1,(X13-$C$2-H13)/($C$2+H13),(X13-X12-H13)/(X12+H13))) -> 0.048416 | AD13: =IF($G13="","",AC13-AB13) -> -0.019584 | AE13: =IF($G13="","",IF($G13=1,Y13,(1+Y13)*(1+AE12)-1)) -> 0.30249588 | AF13: =IF($G13="","",IF($G13=1,Z13,(1+Z13)*(1+AF12)-1)) -> 0.20973859 | AG13: =IF($G13="","",AF13-AE13) -> -0.092757283 | AH13: =IF($G13="","",IF($G13=1,AB13,(1+AB13)*(1+AH12)-1)) -> 0.30102311 | AI13: =IF($G13="","",IF($G13=1,AC13,(1+AC13)*(1+AI12)-1)) -> 0.20818812 | AJ13: =IF($G13="","",AI13-AH13) -> -0.092834991 | AK13: =IF($G13="","",(1+AE13)^(1/G13)-1) -> 0.068302118 | AL13: =IF($G13="","",(1+AF13)^(1/G13)-1) -> 0.048752198 | AM13: =IF($G13="","",AL13-AK13) -> -0.01954992 | AN13: =IF($G13="","",(1+AH13)^(1/G13)-1) -> 0.068 | AO13: =IF($G13="","",(1+AI13)^(1/G13)-1) -> 0.048416 | AP13: =IF($G13="","",AO13-AN13) -> -0.019584
B14: Federal Income Tax | C14: =Page!C17 -> 0.37 | G14: 5 | H14: =IF(G14="","",SUMIFS(Add_Contributions[[#All],[Amount ($)]],Add_Contributions[[#All],[Year]],G14)) -> 0 | I14: =IF($G14="","",IF($G14=1,(($C$2+$H14)*I$3)*(1+(I$4-I$5)),((I13+($H14*I$3))*(1+(I$4-I$5))))) -> 8815968.5 | J14: =IF($G14="","",IF($G14=1,(($C$2+$H14)*J$3)*(1+(J$4-J$5)),((J13+($H14*J$3))*(1+(J$4-J$5))))) -> 8065778.7 | K14: =IF($G14="","",IF($G14=1,(($C$2+$H14)*K$3)*(1+(K$4-K$5)),((K13+($H14*K$3))*(1+(K$4-K$5))))) -> 0 | L14: =IF($G14="","",IF($G14=1,(($C$2+$H14)*L$3)*(1+(L$4-L$5)),((L13+($H14*L$3))*(1+(L$4-L$5))))) -> 0 | M14: =IF($G14="","",IF($G14=1,(($C$2+$H14)*M$3)*(1+(M$4-M$5)),((M13+($H14*M$3))*(1+(M$4-M$5))))) -> 5105126.2 | N14: =IF($G14="","",IF($G14=1,(($C$2+$H14)*N$3)*(1+(N$4-N$5)),((N13+($H14*N$3))*(1+(N$4-N$5))))) -> 4628099.2 | O14: =IF($G14="","",IF($G14=1,(($C$2+$H14)*O$3)*(1+(O$4-O$5)),((O13+($H14*O$3))*(1+(O$4-O$5))))) -> 0 | P14: =IF($G14="","",IF($G14=1,(($C$2+$H14)*P$3)*(1+(P$4-P$5)),((P13+($H14*P$3))*(1+(P$4-P$5))))) -> 0 | ... T14: =IF($G14="","",IF($G14=1,(($C$2+$H14)*T$3)*(1+(T$4-T$5)),((T13+($H14*T$3))*(1+(T$4-T$5))))) -> 0 | U14: =IF(G14="","",SUM(I14,K14,M14,O14,Q14,S14)) -> 13921095 | V14: =IF(H14="","",SUM(J14,L14,N14,P14,R14,T14)) -> 12693878 | W14: =IF($G14="","",IF($G14=1,(($C$2+$H14)*W$3)*(1+(W$4-W$5)),((W13+($H14*W$3))*(1+(W$4-W$5))))) -> 13894927 | X14: =IF($G14="","",IF($G14=1,(($C$2+$H14)*X$3)*(1+(X$4-X$5)),((X13+($H14*X$3))*(1+(X$4-X$5))))) -> 12666838 | Y14: =IF($G14="","",IF($G14=1,(U14-$C$2-H14)/($C$2+H14),(U14-U13-H14)/(U13+H14))) -> 0.068801442 | Z14: =IF($G14="","",IF($G14=1,(V14-$C$2-H14)/($C$2+H14),(V14-V13-H14)/(V13+H14))) -> 0.049307513 | AA14: =IF($G14="","",Z14-Y14) -> -0.01949393 | AB14: =IF($G14="","",IF($G14=1,(W14-$C$2-H14)/($C$2+H14),(W14-W13-H14)/(W13+H14))) -> 0.068 | AC14: =IF($G14="","",IF($G14=1,(X14-$C$2-H14)/($C$2+H14),(X14-X13-H14)/(X13+H14))) -> 0.048416 | AD14: =IF($G14="","",AC14-AB14) -> -0.019584 | AE14: =IF($G14="","",IF($G14=1,Y14,(1+Y14)*(1+AE13)-1)) -> 0.39210947 | AF14: =IF($G14="","",IF($G14=1,Z14,(1+Z14)*(1+AF13)-1)) -> 0.26938779 | AG14: =IF($G14="","",AF14-AE14) -> -0.12272168 | AH14: =IF($G14="","",IF($G14=1,AB14,(1+AB14)*(1+AH13)-1)) -> 0.38949268 | AI14: =IF($G14="","",IF($G14=1,AC14,(1+AC14)*(1+AI13)-1)) -> 0.26668375 | AJ14: =IF($G14="","",AI14-AH14) -> -0.12280893 | AK14: =IF($G14="","",(1+AE14)^(1/G14)-1) -> 0.068401964 | AL14: =IF($G14="","",(1+AF14)^(1/G14)-1) -> 0.048863237 | AM14: =IF($G14="","",AL14-AK14) -> -0.019538727 | AN14: =IF($G14="","",(1+AH14)^(1/G14)-1) -> 0.068 | AO14: =IF($G14="","",(1+AI14)^(1/G14)-1) -> 0.048416 | AP14: =IF($G14="","",AO14-AN14) -> -0.019584
B15: Capital Gains Tax | C15: =Page!C18 -> 0.2 | G15: 6 | H15: =IF(G15="","",SUMIFS(Add_Contributions[[#All],[Amount ($)]],Add_Contributions[[#All],[Year]],G15)) -> 0 | I15: =IF($G15="","",IF($G15=1,(($C$2+$H15)*I$3)*(1+(I$4-I$5)),((I14+($H15*I$3))*(1+(I$4-I$5))))) -> 9521245.9 | J15: =IF($G15="","",IF($G15=1,(($C$2+$H15)*J$3)*(1+(J$4-J$5)),((J14+($H15*J$3))*(1+(J$4-J$5))))) -> 8557468.6 | K15: =IF($G15="","",IF($G15=1,(($C$2+$H15)*K$3)*(1+(K$4-K$5)),((K14+($H15*K$3))*(1+(K$4-K$5))))) -> 0 | L15: =IF($G15="","",IF($G15=1,(($C$2+$H15)*L$3)*(1+(L$4-L$5)),((L14+($H15*L$3))*(1+(L$4-L$5))))) -> 0 | M15: =IF($G15="","",IF($G15=1,(($C$2+$H15)*M$3)*(1+(M$4-M$5)),((M14+($H15*M$3))*(1+(M$4-M$5))))) -> 5360382.6 | N15: =IF($G15="","",IF($G15=1,(($C$2+$H15)*N$3)*(1+(N$4-N$5)),((N14+($H15*N$3))*(1+(N$4-N$5))))) -> 4765091 | O15: =IF($G15="","",IF($G15=1,(($C$2+$H15)*O$3)*(1+(O$4-O$5)),((O14+($H15*O$3))*(1+(O$4-O$5))))) -> 0 | P15: =IF($G15="","",IF($G15=1,(($C$2+$H15)*P$3)*(1+(P$4-P$5)),((P14+($H15*P$3))*(1+(P$4-P$5))))) -> 0 | ... T15: =IF($G15="","",IF($G15=1,(($C$2+$H15)*T$3)*(1+(T$4-T$5)),((T14+($H15*T$3))*(1+(T$4-T$5))))) -> 0 | U15: =IF(G15="","",SUM(I15,K15,M15,O15,Q15,S15)) -> 14881629 | V15: =IF(H15="","",SUM(J15,L15,N15,P15,R15,T15)) -> 13322560 | W15: =IF($G15="","",IF($G15=1,(($C$2+$H15)*W$3)*(1+(W$4-W$5)),((W14+($H15*W$3))*(1+(W$4-W$5))))) -> 14839782 | X15: =IF($G15="","",IF($G15=1,(($C$2+$H15)*X$3)*(1+(X$4-X$5)),((X14+($H15*X$3))*(1+(X$4-X$5))))) -> 13280115 | Y15: =IF($G15="","",IF($G15=1,(U15-$C$2-H15)/($C$2+H15),(U15-U14-H15)/(U14+H15))) -> 0.068998438 | Z15: =IF($G15="","",IF($G15=1,(V15-$C$2-H15)/($C$2+H15),(V15-V14-H15)/(V14+H15))) -> 0.049526363 | AA15: =IF($G15="","",Z15-Y15) -> -0.019472075 | AB15: =IF($G15="","",IF($G15=1,(W15-$C$2-H15)/($C$2+H15),(W15-W14-H15)/(W14+H15))) -> 0.068 | AC15: =IF($G15="","",IF($G15=1,(X15-$C$2-H15)/($C$2+H15),(X15-X14-H15)/(X14+H15))) -> 0.048416 | AD15: =IF($G15="","",AC15-AB15) -> -0.019584 | AE15: =IF($G15="","",IF($G15=1,Y15,(1+Y15)*(1+AE14)-1)) -> 0.48816285 | AF15: =IF($G15="","",IF($G15=1,Z15,(1+Z15)*(1+AF14)-1)) -> 0.33225595 | AG15: =IF($G15="","",AF15-AE15) -> -0.1559069 | AH15: =IF($G15="","",IF($G15=1,AB15,(1+AB15)*(1+AH14)-1)) -> 0.48397818 | AI15: =IF($G15="","",IF($G15=1,AC15,(1+AC15)*(1+AI14)-1)) -> 0.32801152 | AJ15: =IF($G15="","",AI15-AH15) -> -0.15596667 | AK15: =IF($G15="","",(1+AE15)^(1/G15)-1) -> 0.068501353 | AL15: =IF($G15="","",(1+AF15)^(1/G15)-1) -> 0.048973729 | AM15: =IF($G15="","",AL15-AK15) -> -0.019527624 | AN15: =IF($G15="","",(1+AH15)^(1/G15)-1) -> 0.068 | AO15: =IF($G15="","",(1+AI15)^(1/G15)-1) -> 0.048416 | AP15: =IF($G15="","",AO15-AN15) -> -0.019584
B16: Net Investment Income Tax | C16: =Page!C19 -> 0.038 | G16: 7 | H16: =IF(G16="","",SUMIFS(Add_Contributions[[#All],[Amount ($)]],Add_Contributions[[#All],[Year]],G16)) -> 0 | I16: =IF($G16="","",IF($G16=1,(($C$2+$H16)*I$3)*(1+(I$4-I$5)),((I15+($H16*I$3))*(1+(I$4-I$5))))) -> 10282946 | J16: =IF($G16="","",IF($G16=1,(($C$2+$H16)*J$3)*(1+(J$4-J$5)),((J15+($H16*J$3))*(1+(J$4-J$5))))) -> 9079131.9 | K16: =IF($G16="","",IF($G16=1,(($C$2+$H16)*K$3)*(1+(K$4-K$5)),((K15+($H16*K$3))*(1+(K$4-K$5))))) -> 0 | L16: =IF($G16="","",IF($G16=1,(($C$2+$H16)*L$3)*(1+(L$4-L$5)),((L15+($H16*L$3))*(1+(L$4-L$5))))) -> 0 | M16: =IF($G16="","",IF($G16=1,(($C$2+$H16)*M$3)*(1+(M$4-M$5)),((M15+($H16*M$3))*(1+(M$4-M$5))))) -> 5628401.7 | N16: =IF($G16="","",IF($G16=1,(($C$2+$H16)*N$3)*(1+(N$4-N$5)),((N15+($H16*N$3))*(1+(N$4-N$5))))) -> 4906137.6 | O16: =IF($G16="","",IF($G16=1,(($C$2+$H16)*O$3)*(1+(O$4-O$5)),((O15+($H16*O$3))*(1+(O$4-O$5))))) -> 0 | P16: =IF($G16="","",IF($G16=1,(($C$2+$H16)*P$3)*(1+(P$4-P$5)),((P15+($H16*P$3))*(1+(P$4-P$5))))) -> 0 | ... T16: =IF($G16="","",IF($G16=1,(($C$2+$H16)*T$3)*(1+(T$4-T$5)),((T15+($H16*T$3))*(1+(T$4-T$5))))) -> 0 | U16: =IF(G16="","",SUM(I16,K16,M16,O16,Q16,S16)) -> 15911347 | V16: =IF(H16="","",SUM(J16,L16,N16,P16,R16,T16)) -> 13985270 | W16: =IF($G16="","",IF($G16=1,(($C$2+$H16)*W$3)*(1+(W$4-W$5)),((W15+($H16*W$3))*(1+(W$4-W$5))))) -> 15848887 | X16: =IF($G16="","",IF($G16=1,(($C$2+$H16)*X$3)*(1+(X$4-X$5)),((X15+($H16*X$3))*(1+(X$4-X$5))))) -> 13923085 | Y16: =IF($G16="","",IF($G16=1,(U16-$C$2-H16)/($C$2+H16),(U16-U15-H16)/(U15+H16))) -> 0.06919396 | Z16: =IF($G16="","",IF($G16=1,(V16-$C$2-H16)/($C$2+H16),(V16-V15-H16)/(V15+H16))) -> 0.049743443 | AA16: =IF($G16="","",Z16-Y16) -> -0.019450517 | AB16: =IF($G16="","",IF($G16=1,(W16-$C$2-H16)/($C$2+H16),(W16-W15-H16)/(W15+H16))) -> 0.068 | AC16: =IF($G16="","",IF($G16=1,(X16-$C$2-H16)/($C$2+H16),(X16-X15-H16)/(X15+H16))) -> 0.048416 | AD16: =IF($G16="","",AC16-AB16) -> -0.019584 | AE16: =IF($G16="","",IF($G16=1,Y16,(1+Y16)*(1+AE15)-1)) -> 0.59113473 | AF16: =IF($G16="","",IF($G16=1,Z16,(1+Z16)*(1+AF15)-1)) -> 0.39852695 | AG16: =IF($G16="","",AF16-AE16) -> -0.19260778 | AH16: =IF($G16="","",IF($G16=1,AB16,(1+AB16)*(1+AH15)-1)) -> 0.5848887 | AI16: =IF($G16="","",IF($G16=1,AC16,(1+AC16)*(1+AI15)-1)) -> 0.39230852 | AJ16: =IF($G16="","",AI16-AH16) -> -0.19258018 | AK16: =IF($G16="","",(1+AE16)^(1/G16)-1) -> 0.068600269 | AL16: =IF($G16="","",(1+AF16)^(1/G16)-1) -> 0.049083654 | AM16: =IF($G16="","",AL16-AK16) -> -0.019516616 | AN16: =IF($G16="","",(1+AH16)^(1/G16)-1) -> 0.068 | AO16: =IF($G16="","",(1+AI16)^(1/G16)-1) -> 0.048416 | AP16: =IF($G16="","",AO16-AN16) -> -0.019584
B17: State Income Tax | G17: 8 | H17: =IF(G17="","",SUMIFS(Add_Contributions[[#All],[Amount ($)]],Add_Contributions[[#All],[Year]],G17)) -> 0 | I17: =IF($G17="","",IF($G17=1,(($C$2+$H17)*I$3)*(1+(I$4-I$5)),((I16+($H17*I$3))*(1+(I$4-I$5))))) -> 11105581 | J17: =IF($G17="","",IF($G17=1,(($C$2+$H17)*J$3)*(1+(J$4-J$5)),((J16+($H17*J$3))*(1+(J$4-J$5))))) -> 9632595.8 | K17: =IF($G17="","",IF($G17=1,(($C$2+$H17)*K$3)*(1+(K$4-K$5)),((K16+($H17*K$3))*(1+(K$4-K$5))))) -> 0 | L17: =IF($G17="","",IF($G17=1,(($C$2+$H17)*L$3)*(1+(L$4-L$5)),((L16+($H17*L$3))*(1+(L$4-L$5))))) -> 0 | M17: =IF($G17="","",IF($G17=1,(($C$2+$H17)*M$3)*(1+(M$4-M$5)),((M16+($H17*M$3))*(1+(M$4-M$5))))) -> 5909821.8 | N17: =IF($G17="","",IF($G17=1,(($C$2+$H17)*N$3)*(1+(N$4-N$5)),((N16+($H17*N$3))*(1+(N$4-N$5))))) -> 5051359.3 | O17: =IF($G17="","",IF($G17=1,(($C$2+$H17)*O$3)*(1+(O$4-O$5)),((O16+($H17*O$3))*(1+(O$4-O$5))))) -> 0 | P17: =IF($G17="","",IF($G17=1,(($C$2+$H17)*P$3)*(1+(P$4-P$5)),((P16+($H17*P$3))*(1+(P$4-P$5))))) -> 0 | ... T17: =IF($G17="","",IF($G17=1,(($C$2+$H17)*T$3)*(1+(T$4-T$5)),((T16+($H17*T$3))*(1+(T$4-T$5))))) -> 0 | U17: =IF(G17="","",SUM(I17,K17,M17,O17,Q17,S17)) -> 17015403 | V17: =IF(H17="","",SUM(J17,L17,N17,P17,R17,T17)) -> 14683955 | W17: =IF($G17="","",IF($G17=1,(($C$2+$H17)*W$3)*(1+(W$4-W$5)),((W16+($H17*W$3))*(1+(W$4-W$5))))) -> 16926611 | X17: =IF($G17="","",IF($G17=1,(($C$2+$H17)*X$3)*(1+(X$4-X$5)),((X16+($H17*X$3))*(1+(X$4-X$5))))) -> 14597185 | Y17: =IF($G17="","",IF($G17=1,(U17-$C$2-H17)/($C$2+H17),(U17-U16-H17)/(U16+H17))) -> 0.069387948 | Z17: =IF($G17="","",IF($G17=1,(V17-$C$2-H17)/($C$2+H17),(V17-V16-H17)/(V16+H17))) -> 0.049958676 | AA17: =IF($G17="","",Z17-Y17) -> -0.019429271 | AB17: =IF($G17="","",IF($G17=1,(W17-$C$2-H17)/($C$2+H17),(W17-W16-H17)/(W16+H17))) -> 0.068 | AC17: =IF($G17="","",IF($G17=1,(X17-$C$2-H17)/($C$2+H17),(X17-X16-H17)/(X16+H17))) -> 0.048416 | AD17: =IF($G17="","",AC17-AB17) -> -0.019584 | AE17: =IF($G17="","",IF($G17=1,Y17,(1+Y17)*(1+AE16)-1)) -> 0.7015403 | AF17: =IF($G17="","",IF($G17=1,Z17,(1+Z17)*(1+AF16)-1)) -> 0.46839551 | AG17: =IF($G17="","",AF17-AE17) -> -0.2331448 | AH17: =IF($G17="","",IF($G17=1,AB17,(1+AB17)*(1+AH16)-1)) -> 0.69266113 | AI17: =IF($G17="","",IF($G17=1,AC17,(1+AC17)*(1+AI16)-1)) -> 0.45971853 | AJ17: =IF($G17="","",AI17-AH17) -> -0.2329426 | AK17: =IF($G17="","",(1+AE17)^(1/G17)-1) -> 0.068698697 | AL17: =IF($G17="","",(1+AF17)^(1/G17)-1) -> 0.049192992 | AM17: =IF($G17="","",AL17-AK17) -> -0.019505706 | AN17: =IF($G17="","",(1+AH17)^(1/G17)-1) -> 0.068 | AO17: =IF($G17="","",(1+AI17)^(1/G17)-1) -> 0.048416 | AP17: =IF($G17="","",AO17-AN17) -> -0.019584
G18: 9 | H18: =IF(G18="","",SUMIFS(Add_Contributions[[#All],[Amount ($)]],Add_Contributions[[#All],[Year]],G18)) -> 0 | I18: =IF($G18="","",IF($G18=1,(($C$2+$H18)*I$3)*(1+(I$4-I$5)),((I17+($H18*I$3))*(1+(I$4-I$5))))) -> 11994028 | J18: =IF($G18="","",IF($G18=1,(($C$2+$H18)*J$3)*(1+(J$4-J$5)),((J17+($H18*J$3))*(1+(J$4-J$5))))) -> 10219799 | K18: =IF($G18="","",IF($G18=1,(($C$2+$H18)*K$3)*(1+(K$4-K$5)),((K17+($H18*K$3))*(1+(K$4-K$5))))) -> 0 | L18: =IF($G18="","",IF($G18=1,(($C$2+$H18)*L$3)*(1+(L$4-L$5)),((L17+($H18*L$3))*(1+(L$4-L$5))))) -> 0 | M18: =IF($G18="","",IF($G18=1,(($C$2+$H18)*M$3)*(1+(M$4-M$5)),((M17+($H18*M$3))*(1+(M$4-M$5))))) -> 6205312.9 | N18: =IF($G18="","",IF($G18=1,(($C$2+$H18)*N$3)*(1+(N$4-N$5)),((N17+($H18*N$3))*(1+(N$4-N$5))))) -> 5200879.6 | O18: =IF($G18="","",IF($G18=1,(($C$2+$H18)*O$3)*(1+(O$4-O$5)),((O17+($H18*O$3))*(1+(O$4-O$5))))) -> 0 | P18: =IF($G18="","",IF($G18=1,(($C$2+$H18)*P$3)*(1+(P$4-P$5)),((P17+($H18*P$3))*(1+(P$4-P$5))))) -> 0 | ... T18: =IF($G18="","",IF($G18=1,(($C$2+$H18)*T$3)*(1+(T$4-T$5)),((T17+($H18*T$3))*(1+(T$4-T$5))))) -> 0 | U18: =IF(G18="","",SUM(I18,K18,M18,O18,Q18,S18)) -> 18199341 | V18: =IF(H18="","",SUM(J18,L18,N18,P18,R18,T18)) -> 15420678 | W18: =IF($G18="","",IF($G18=1,(($C$2+$H18)*W$3)*(1+(W$4-W$5)),((W17+($H18*W$3))*(1+(W$4-W$5))))) -> 18077621 | X18: =IF($G18="","",IF($G18=1,(($C$2+$H18)*X$3)*(1+(X$4-X$5)),((X17+($H18*X$3))*(1+(X$4-X$5))))) -> 15303923 | Y18: =IF($G18="","",IF($G18=1,(U18-$C$2-H18)/($C$2+H18),(U18-U17-H18)/(U17+H18))) -> 0.069580344 | Z18: =IF($G18="","",IF($G18=1,(V18-$C$2-H18)/($C$2+H18),(V18-V17-H18)/(V17+H18))) -> 0.050171992 | AA18: =IF($G18="","",Z18-Y18) -> -0.019408352 | AB18: =IF($G18="","",IF($G18=1,(W18-$C$2-H18)/($C$2+H18),(W18-W17-H18)/(W17+H18))) -> 0.068 | AC18: =IF($G18="","",IF($G18=1,(X18-$C$2-H18)/($C$2+H18),(X18-X17-H18)/(X17+H18))) -> 0.048416 | AD18: =IF($G18="","",AC18-AB18) -> -0.019584 | AE18: =IF($G18="","",IF($G18=1,Y18,(1+Y18)*(1+AE17)-1)) -> 0.81993406 | AF18: =IF($G18="","",IF($G18=1,Z18,(1+Z18)*(1+AF17)-1)) -> 0.54206783 | AG18: =IF($G18="","",AF18-AE18) -> -0.27786623 | AH18: =IF($G18="","",IF($G18=1,AB18,(1+AB18)*(1+AH17)-1)) -> 0.80776209 | AI18: =IF($G18="","",IF($G18=1,AC18,(1+AC18)*(1+AI17)-1)) -> 0.53039226 | AJ18: =IF($G18="","",AI18-AH18) -> -0.27736983 | AK18: =IF($G18="","",(1+AE18)^(1/G18)-1) -> 0.068796622 | AL18: =IF($G18="","",(1+AF18)^(1/G18)-1) -> 0.049301724 | AM18: =IF($G18="","",AL18-AK18) -> -0.019494898 | AN18: =IF($G18="","",(1+AH18)^(1/G18)-1) -> 0.068 | AO18: =IF($G18="","",(1+AI18)^(1/G18)-1) -> 0.048416 | AP18: =IF($G18="","",AO18-AN18) -> -0.019584
G19: 10 | H19: =IF(G19="","",SUMIFS(Add_Contributions[[#All],[Amount ($)]],Add_Contributions[[#All],[Year]],G19)) -> 0 | I19: =IF($G19="","",IF($G19=1,(($C$2+$H19)*I$3)*(1+(I$4-I$5)),((I18+($H19*I$3))*(1+(I$4-I$5))))) -> 12953550 | J19: =IF($G19="","",IF($G19=1,(($C$2+$H19)*J$3)*(1+(J$4-J$5)),((J18+($H19*J$3))*(1+(J$4-J$5))))) -> 10842798 | K19: =IF($G19="","",IF($G19=1,(($C$2+$H19)*K$3)*(1+(K$4-K$5)),((K18+($H19*K$3))*(1+(K$4-K$5))))) -> 0 | L19: =IF($G19="","",IF($G19=1,(($C$2+$H19)*L$3)*(1+(L$4-L$5)),((L18+($H19*L$3))*(1+(L$4-L$5))))) -> 0 | M19: =IF($G19="","",IF($G19=1,(($C$2+$H19)*M$3)*(1+(M$4-M$5)),((M18+($H19*M$3))*(1+(M$4-M$5))))) -> 6515578.5 | N19: =IF($G19="","",IF($G19=1,(($C$2+$H19)*N$3)*(1+(N$4-N$5)),((N18+($H19*N$3))*(1+(N$4-N$5))))) -> 5354825.6 | O19: =IF($G19="","",IF($G19=1,(($C$2+$H19)*O$3)*(1+(O$4-O$5)),((O18+($H19*O$3))*(1+(O$4-O$5))))) -> 0 | P19: =IF($G19="","",IF($G19=1,(($C$2+$H19)*P$3)*(1+(P$4-P$5)),((P18+($H19*P$3))*(1+(P$4-P$5))))) -> 0 | ... T19: =IF($G19="","",IF($G19=1,(($C$2+$H19)*T$3)*(1+(T$4-T$5)),((T18+($H19*T$3))*(1+(T$4-T$5))))) -> 0 | U19: =IF(G19="","",SUM(I19,K19,M19,O19,Q19,S19)) -> 19469128 | V19: =IF(H19="","",SUM(J19,L19,N19,P19,R19,T19)) -> 16197623 | W19: =IF($G19="","",IF($G19=1,(($C$2+$H19)*W$3)*(1+(W$4-W$5)),((W18+($H19*W$3))*(1+(W$4-W$5))))) -> 19306899 | X19: =IF($G19="","",IF($G19=1,(($C$2+$H19)*X$3)*(1+(X$4-X$5)),((X18+($H19*X$3))*(1+(X$4-X$5))))) -> 16044877 | Y19: =IF($G19="","",IF($G19=1,(U19-$C$2-H19)/($C$2+H19),(U19-U18-H19)/(U18+H19))) -> 0.069771092 | Z19: =IF($G19="","",IF($G19=1,(V19-$C$2-H19)/($C$2+H19),(V19-V18-H19)/(V18+H19))) -> 0.05038332 | AA19: =IF($G19="","",Z19-Y19) -> -0.019387772 | AB19: =IF($G19="","",IF($G19=1,(W19-$C$2-H19)/($C$2+H19),(W19-W18-H19)/(W18+H19))) -> 0.068 | AC19: =IF($G19="","",IF($G19=1,(X19-$C$2-H19)/($C$2+H19),(X19-X18-H19)/(X18+H19))) -> 0.048416 | AD19: =IF($G19="","",AC19-AB19) -> -0.019584 | AE19: =IF($G19="","",IF($G19=1,Y19,(1+Y19)*(1+AE18)-1)) -> 0.94691285 | AF19: =IF($G19="","",IF($G19=1,Z19,(1+Z19)*(1+AF18)-1)) -> 0.61976233 | AG19: =IF($G19="","",AF19-AE19) -> -0.32715052 | AH19: =IF($G19="","",IF($G19=1,AB19,(1+AB19)*(1+AH18)-1)) -> 0.93068991 | AI19: =IF($G19="","",IF($G19=1,AC19,(1+AC19)*(1+AI18)-1)) -> 0.60448773 | AJ19: =IF($G19="","",AI19-AH19) -> -0.32620218 | AK19: =IF($G19="","",(1+AE19)^(1/G19)-1) -> 0.068894029 | AL19: =IF($G19="","",(1+AF19)^(1/G19)-1) -> 0.049409834 | AM19: =IF($G19="","",AL19-AK19) -> -0.019484196 | AN19: =IF($G19="","",(1+AH19)^(1/G19)-1) -> 0.068 | AO19: =IF($G19="","",(1+AI19)^(1/G19)-1) -> 0.048416 | AP19: =IF($G19="","",AO19-AN19) -> -0.019584
G20: 11 | H20: =IF(G20="","",SUMIFS(Add_Contributions[[#All],[Amount ($)]],Add_Contributions[[#All],[Year]],G20)) -> 0 | I20: =IF($G20="","",IF($G20=1,(($C$2+$H20)*I$3)*(1+(I$4-I$5)),((I19+($H20*I$3))*(1+(I$4-I$5))))) -> 13989834 | J20: =IF($G20="","",IF($G20=1,(($C$2+$H20)*J$3)*(1+(J$4-J$5)),((J19+($H20*J$3))*(1+(J$4-J$5))))) -> 11503775 | K20: =IF($G20="","",IF($G20=1,(($C$2+$H20)*K$3)*(1+(K$4-K$5)),((K19+($H20*K$3))*(1+(K$4-K$5))))) -> 0 | L20: =IF($G20="","",IF($G20=1,(($C$2+$H20)*L$3)*(1+(L$4-L$5)),((L19+($H20*L$3))*(1+(L$4-L$5))))) -> 0 | M20: =IF($G20="","",IF($G20=1,(($C$2+$H20)*M$3)*(1+(M$4-M$5)),((M19+($H20*M$3))*(1+(M$4-M$5))))) -> 6841357.4 | N20: =IF($G20="","",IF($G20=1,(($C$2+$H20)*N$3)*(1+(N$4-N$5)),((N19+($H20*N$3))*(1+(N$4-N$5))))) -> 5513328.4 | O20: =IF($G20="","",IF($G20=1,(($C$2+$H20)*O$3)*(1+(O$4-O$5)),((O19+($H20*O$3))*(1+(O$4-O$5))))) -> 0 | P20: =IF($G20="","",IF($G20=1,(($C$2+$H20)*P$3)*(1+(P$4-P$5)),((P19+($H20*P$3))*(1+(P$4-P$5))))) -> 0 | ... T20: =IF($G20="","",IF($G20=1,(($C$2+$H20)*T$3)*(1+(T$4-T$5)),((T19+($H20*T$3))*(1+(T$4-T$5))))) -> 0 | U20: =IF(G20="","",SUM(I20,K20,M20,O20,Q20,S20)) -> 20831191 | V20: =IF(H20="","",SUM(J20,L20,N20,P20,R20,T20)) -> 17017103 | W20: =IF($G20="","",IF($G20=1,(($C$2+$H20)*W$3)*(1+(W$4-W$5)),((W19+($H20*W$3))*(1+(W$4-W$5))))) -> 20619768 | X20: =IF($G20="","",IF($G20=1,(($C$2+$H20)*X$3)*(1+(X$4-X$5)),((X19+($H20*X$3))*(1+(X$4-X$5))))) -> 16821706 | Y20: =IF($G20="","",IF($G20=1,(U20-$C$2-H20)/($C$2+H20),(U20-U19-H20)/(U19+H20))) -> 0.069960138 | Z20: =IF($G20="","",IF($G20=1,(V20-$C$2-H20)/($C$2+H20),(V20-V19-H20)/(V19+H20))) -> 0.050592594 | AA20: =IF($G20="","",Z20-Y20) -> -0.019367544 | AB20: =IF($G20="","",IF($G20=1,(W20-$C$2-H20)/($C$2+H20),(W20-W19-H20)/(W19+H20))) -> 0.068 | AC20: =IF($G20="","",IF($G20=1,(X20-$C$2-H20)/($C$2+H20),(X20-X19-H20)/(X19+H20))) -> 0.048416 | AD20: =IF($G20="","",AC20-AB20) -> -0.019584 | AE20: =IF($G20="","",IF($G20=1,Y20,(1+Y20)*(1+AE19)-1)) -> 1.0831191 | AF20: =IF($G20="","",IF($G20=1,Z20,(1+Z20)*(1+AF19)-1)) -> 0.70171031 | AG20: =IF($G20="","",AF20-AE20) -> -0.38140883 | AH20: =IF($G20="","",IF($G20=1,AB20,(1+AB20)*(1+AH19)-1)) -> 1.0619768 | AI20: =IF($G20="","",IF($G20=1,AC20,(1+AC20)*(1+AI19)-1)) -> 0.68217061 | AJ20: =IF($G20="","",AI20-AH20) -> -0.37980621 | AK20: =IF($G20="","",(1+AE20)^(1/G20)-1) -> 0.068990904 | AL20: =IF($G20="","",(1+AF20)^(1/G20)-1) -> 0.049517302 | AM20: =IF($G20="","",AL20-AK20) -> -0.019473602 | AN20: =IF($G20="","",(1+AH20)^(1/G20)-1) -> 0.068 | AO20: =IF($G20="","",(1+AI20)^(1/G20)-1) -> 0.048416 | AP20: =IF($G20="","",AO20-AN20) -> -0.019584
B21: Metrics | C21: Buy & Hold | D21: Rebalanced | G21: 12 | H21: =IF(G21="","",SUMIFS(Add_Contributions[[#All],[Amount ($)]],Add_Contributions[[#All],[Year]],G21)) -> 0 | I21: =IF($G21="","",IF($G21=1,(($C$2+$H21)*I$3)*(1+(I$4-I$5)),((I20+($H21*I$3))*(1+(I$4-I$5))))) -> 15109021 | J21: =IF($G21="","",IF($G21=1,(($C$2+$H21)*J$3)*(1+(J$4-J$5)),((J20+($H21*J$3))*(1+(J$4-J$5))))) -> 12205045 | K21: =IF($G21="","",IF($G21=1,(($C$2+$H21)*K$3)*(1+(K$4-K$5)),((K20+($H21*K$3))*(1+(K$4-K$5))))) -> 0 | L21: =IF($G21="","",IF($G21=1,(($C$2+$H21)*L$3)*(1+(L$4-L$5)),((L20+($H21*L$3))*(1+(L$4-L$5))))) -> 0 | M21: =IF($G21="","",IF($G21=1,(($C$2+$H21)*M$3)*(1+(M$4-M$5)),((M20+($H21*M$3))*(1+(M$4-M$5))))) -> 7183425.3 | N21: =IF($G21="","",IF($G21=1,(($C$2+$H21)*N$3)*(1+(N$4-N$5)),((N20+($H21*N$3))*(1+(N$4-N$5))))) -> 5676523 | O21: =IF($G21="","",IF($G21=1,(($C$2+$H21)*O$3)*(1+(O$4-O$5)),((O20+($H21*O$3))*(1+(O$4-O$5))))) -> 0 | P21: =IF($G21="","",IF($G21=1,(($C$2+$H21)*P$3)*(1+(P$4-P$5)),((P20+($H21*P$3))*(1+(P$4-P$5))))) -> 0 | ... T21: =IF($G21="","",IF($G21=1,(($C$2+$H21)*T$3)*(1+(T$4-T$5)),((T20+($H21*T$3))*(1+(T$4-T$5))))) -> 0 | U21: =IF(G21="","",SUM(I21,K21,M21,O21,Q21,S21)) -> 22292446 | V21: =IF(H21="","",SUM(J21,L21,N21,P21,R21,T21)) -> 17881568 | W21: =IF($G21="","",IF($G21=1,(($C$2+$H21)*W$3)*(1+(W$4-W$5)),((W20+($H21*W$3))*(1+(W$4-W$5))))) -> 22021912 | X21: =IF($G21="","",IF($G21=1,(($C$2+$H21)*X$3)*(1+(X$4-X$5)),((X20+($H21*X$3))*(1+(X$4-X$5))))) -> 17636146 | Y21: =IF($G21="","",IF($G21=1,(U21-$C$2-H21)/($C$2+H21),(U21-U20-H21)/(U20+H21))) -> 0.070147432 | Z21: =IF($G21="","",IF($G21=1,(V21-$C$2-H21)/($C$2+H21),(V21-V20-H21)/(V20+H21))) -> 0.050799752 | AA21: =IF($G21="","",Z21-Y21) -> -0.01934768 | AB21: =IF($G21="","",IF($G21=1,(W21-$C$2-H21)/($C$2+H21),(W21-W20-H21)/(W20+H21))) -> 0.068 | AC21: =IF($G21="","",IF($G21=1,(X21-$C$2-H21)/($C$2+H21),(X21-X20-H21)/(X20+H21))) -> 0.048416 | AD21: =IF($G21="","",AC21-AB21) -> -0.019584 | AE21: =IF($G21="","",IF($G21=1,Y21,(1+Y21)*(1+AE20)-1)) -> 1.2292446 | AF21: =IF($G21="","",IF($G21=1,Z21,(1+Z21)*(1+AF20)-1)) -> 0.78815677 | AG21: =IF($G21="","",AF21-AE21) -> -0.44108783 | AH21: =IF($G21="","",IF($G21=1,AB21,(1+AB21)*(1+AH20)-1)) -> 1.2021912 | AI21: =IF($G21="","",IF($G21=1,AC21,(1+AC21)*(1+AI20)-1)) -> 0.76361458 | AJ21: =IF($G21="","",AI21-AH21) -> -0.43857666 | AK21: =IF($G21="","",(1+AE21)^(1/G21)-1) -> 0.069087234 | AL21: =IF($G21="","",(1+AF21)^(1/G21)-1) -> 0.049624113 | AM21: =IF($G21="","",AL21-AK21) -> -0.019463121 | AN21: =IF($G21="","",(1+AH21)^(1/G21)-1) -> 0.068 | AO21: =IF($G21="","",(1+AI21)^(1/G21)-1) -> 0.048416 | AP21: =IF($G21="","",AO21-AN21) -> -0.019584
B22: Projected Value | C22: =_xlfn.XLOOKUP(C3,G:G,V:V) -> 26762916 | D22: =_xlfn.XLOOKUP(C3,G:G,X:X) -> 25743809 | G22: 13 | H22: =IF(G22="","",SUMIFS(Add_Contributions[[#All],[Amount ($)]],Add_Contributions[[#All],[Year]],G22)) -> 0 | I22: =IF($G22="","",IF($G22=1,(($C$2+$H22)*I$3)*(1+(I$4-I$5)),((I21+($H22*I$3))*(1+(I$4-I$5))))) -> 16317742 | J22: =IF($G22="","",IF($G22=1,(($C$2+$H22)*J$3)*(1+(J$4-J$5)),((J21+($H22*J$3))*(1+(J$4-J$5))))) -> 12949064 | K22: =IF($G22="","",IF($G22=1,(($C$2+$H22)*K$3)*(1+(K$4-K$5)),((K21+($H22*K$3))*(1+(K$4-K$5))))) -> 0 | L22: =IF($G22="","",IF($G22=1,(($C$2+$H22)*L$3)*(1+(L$4-L$5)),((L21+($H22*L$3))*(1+(L$4-L$5))))) -> 0 | M22: =IF($G22="","",IF($G22=1,(($C$2+$H22)*M$3)*(1+(M$4-M$5)),((M21+($H22*M$3))*(1+(M$4-M$5))))) -> 7542596.6 | N22: =IF($G22="","",IF($G22=1,(($C$2+$H22)*N$3)*(1+(N$4-N$5)),((N21+($H22*N$3))*(1+(N$4-N$5))))) -> 5844548 | O22: =IF($G22="","",IF($G22=1,(($C$2+$H22)*O$3)*(1+(O$4-O$5)),((O21+($H22*O$3))*(1+(O$4-O$5))))) -> 0 | P22: =IF($G22="","",IF($G22=1,(($C$2+$H22)*P$3)*(1+(P$4-P$5)),((P21+($H22*P$3))*(1+(P$4-P$5))))) -> 0 | ... T22: =IF($G22="","",IF($G22=1,(($C$2+$H22)*T$3)*(1+(T$4-T$5)),((T21+($H22*T$3))*(1+(T$4-T$5))))) -> 0 | U22: =IF(G22="","",SUM(I22,K22,M22,O22,Q22,S22)) -> 23860339 | V22: =IF(H22="","",SUM(J22,L22,N22,P22,R22,T22)) -> 18793612 | W22: =IF($G22="","",IF($G22=1,(($C$2+$H22)*W$3)*(1+(W$4-W$5)),((W21+($H22*W$3))*(1+(W$4-W$5))))) -> 23519403 | X22: =IF($G22="","",IF($G22=1,(($C$2+$H22)*X$3)*(1+(X$4-X$5)),((X21+($H22*X$3))*(1+(X$4-X$5))))) -> 18490017 | Y22: =IF($G22="","",IF($G22=1,(U22-$C$2-H22)/($C$2+H22),(U22-U21-H22)/(U21+H22))) -> 0.070332924 | Z22: =IF($G22="","",IF($G22=1,(V22-$C$2-H22)/($C$2+H22),(V22-V21-H22)/(V21+H22))) -> 0.051004734 | AA22: =IF($G22="","",Z22-Y22) -> -0.01932819 | AB22: =IF($G22="","",IF($G22=1,(W22-$C$2-H22)/($C$2+H22),(W22-W21-H22)/(W21+H22))) -> 0.068 | AC22: =IF($G22="","",IF($G22=1,(X22-$C$2-H22)/($C$2+H22),(X22-X21-H22)/(X21+H22))) -> 0.048416 | AD22: =IF($G22="","",AC22-AB22) -> -0.019584 | AE22: =IF($G22="","",IF($G22=1,Y22,(1+Y22)*(1+AE21)-1)) -> 1.3860339 | AF22: =IF($G22="","",IF($G22=1,Z22,(1+Z22)*(1+AF21)-1)) -> 0.87936123 | AG22: =IF($G22="","",AF22-AE22) -> -0.50667266 | AH22: =IF($G22="","",IF($G22=1,AB22,(1+AB22)*(1+AH21)-1)) -> 1.3519403 | AI22: =IF($G22="","",IF($G22=1,AC22,(1+AC22)*(1+AI21)-1)) -> 0.84900175 | AJ22: =IF($G22="","",AI22-AH22) -> -0.5029385 | AK22: =IF($G22="","",(1+AE22)^(1/G22)-1) -> 0.069183005 | AL22: =IF($G22="","",(1+AF22)^(1/G22)-1) -> 0.049730251 | AM22: =IF($G22="","",AL22-AK22) -> -0.019452754 | AN22: =IF($G22="","",(1+AH22)^(1/G22)-1) -> 0.068 | AO22: =IF($G22="","",(1+AI22)^(1/G22)-1) -> 0.048416 | AP22: =IF($G22="","",AO22-AN22) -> -0.019584
G23: 14 | H23: =IF(G23="","",SUMIFS(Add_Contributions[[#All],[Amount ($)]],Add_Contributions[[#All],[Year]],G23)) -> 0 | I23: =IF($G23="","",IF($G23=1,(($C$2+$H23)*I$3)*(1+(I$4-I$5)),((I22+($H23*I$3))*(1+(I$4-I$5))))) -> 17623162 | J23: =IF($G23="","",IF($G23=1,(($C$2+$H23)*J$3)*(1+(J$4-J$5)),((J22+($H23*J$3))*(1+(J$4-J$5))))) -> 13738439 | K23: =IF($G23="","",IF($G23=1,(($C$2+$H23)*K$3)*(1+(K$4-K$5)),((K22+($H23*K$3))*(1+(K$4-K$5))))) -> 0 | L23: =IF($G23="","",IF($G23=1,(($C$2+$H23)*L$3)*(1+(L$4-L$5)),((L22+($H23*L$3))*(1+(L$4-L$5))))) -> 0 | M23: =IF($G23="","",IF($G23=1,(($C$2+$H23)*M$3)*(1+(M$4-M$5)),((M22+($H23*M$3))*(1+(M$4-M$5))))) -> 7919726.4 | N23: =IF($G23="","",IF($G23=1,(($C$2+$H23)*N$3)*(1+(N$4-N$5)),((N22+($H23*N$3))*(1+(N$4-N$5))))) -> 6017546.7 | O23: =IF($G23="","",IF($G23=1,(($C$2+$H23)*O$3)*(1+(O$4-O$5)),((O22+($H23*O$3))*(1+(O$4-O$5))))) -> 0 | P23: =IF($G23="","",IF($G23=1,(($C$2+$H23)*P$3)*(1+(P$4-P$5)),((P22+($H23*P$3))*(1+(P$4-P$5))))) -> 0 | ... T23: =IF($G23="","",IF($G23=1,(($C$2+$H23)*T$3)*(1+(T$4-T$5)),((T22+($H23*T$3))*(1+(T$4-T$5))))) -> 0 | U23: =IF(G23="","",SUM(I23,K23,M23,O23,Q23,S23)) -> 25542888 | V23: =IF(H23="","",SUM(J23,L23,N23,P23,R23,T23)) -> 19755986 | W23: =IF($G23="","",IF($G23=1,(($C$2+$H23)*W$3)*(1+(W$4-W$5)),((W22+($H23*W$3))*(1+(W$4-W$5))))) -> 25118722 | X23: =IF($G23="","",IF($G23=1,(($C$2+$H23)*X$3)*(1+(X$4-X$5)),((X22+($H23*X$3))*(1+(X$4-X$5))))) -> 19385230 | Y23: =IF($G23="","",IF($G23=1,(U23-$C$2-H23)/($C$2+H23),(U23-U22-H23)/(U22+H23))) -> 0.070516568 | Z23: =IF($G23="","",IF($G23=1,(V23-$C$2-H23)/($C$2+H23),(V23-V22-H23)/(V22+H23))) -> 0.051207483 | AA23: =IF($G23="","",Z23-Y23) -> -0.019309085 | AB23: =IF($G23="","",IF($G23=1,(W23-$C$2-H23)/($C$2+H23),(W23-W22-H23)/(W22+H23))) -> 0.068 | AC23: =IF($G23="","",IF($G23=1,(X23-$C$2-H23)/($C$2+H23),(X23-X22-H23)/(X22+H23))) -> 0.048416 | AD23: =IF($G23="","",AC23-AB23) -> -0.019584 | AE23: =IF($G23="","",IF($G23=1,Y23,(1+Y23)*(1+AE22)-1)) -> 1.5542888 | AF23: =IF($G23="","",IF($G23=1,Z23,(1+Z23)*(1+AF22)-1)) -> 0.97559859 | AG23: =IF($G23="","",AF23-AE23) -> -0.57869022 | AH23: =IF($G23="","",IF($G23=1,AB23,(1+AB23)*(1+AH22)-1)) -> 1.5118722 | AI23: =IF($G23="","",IF($G23=1,AC23,(1+AC23)*(1+AI22)-1)) -> 0.93852302 | AJ23: =IF($G23="","",AI23-AH23) -> -0.57334917 | AK23: =IF($G23="","",(1+AE23)^(1/G23)-1) -> 0.069278204 | AL23: =IF($G23="","",(1+AF23)^(1/G23)-1) -> 0.049835698 | AM23: =IF($G23="","",AL23-AK23) -> -0.019442506 | AN23: =IF($G23="","",(1+AH23)^(1/G23)-1) -> 0.068 | AO23: =IF($G23="","",(1+AI23)^(1/G23)-1) -> 0.048416 | AP23: =IF($G23="","",AO23-AN23) -> -0.019584
B24: Total Return (Gross) | C24: =_xlfn.XLOOKUP(C3,G:G,AE:AE) -> 2.8578934 | D24: =_xlfn.XLOOKUP(C3,G:G,AH:AH) -> 2.7275635 | G24: 15 | H24: =IF(G24="","",SUMIFS(Add_Contributions[[#All],[Amount ($)]],Add_Contributions[[#All],[Year]],G24)) -> 0 | I24: =IF($G24="","",IF($G24=1,(($C$2+$H24)*I$3)*(1+(I$4-I$5)),((I23+($H24*I$3))*(1+(I$4-I$5))))) -> 19033015 | J24: =IF($G24="","",IF($G24=1,(($C$2+$H24)*J$3)*(1+(J$4-J$5)),((J23+($H24*J$3))*(1+(J$4-J$5))))) -> 14575935 | K24: =IF($G24="","",IF($G24=1,(($C$2+$H24)*K$3)*(1+(K$4-K$5)),((K23+($H24*K$3))*(1+(K$4-K$5))))) -> 0 | L24: =IF($G24="","",IF($G24=1,(($C$2+$H24)*L$3)*(1+(L$4-L$5)),((L23+($H24*L$3))*(1+(L$4-L$5))))) -> 0 | M24: =IF($G24="","",IF($G24=1,(($C$2+$H24)*M$3)*(1+(M$4-M$5)),((M23+($H24*M$3))*(1+(M$4-M$5))))) -> 8315712.7 | N24: =IF($G24="","",IF($G24=1,(($C$2+$H24)*N$3)*(1+(N$4-N$5)),((N23+($H24*N$3))*(1+(N$4-N$5))))) -> 6195666 | O24: =IF($G24="","",IF($G24=1,(($C$2+$H24)*O$3)*(1+(O$4-O$5)),((O23+($H24*O$3))*(1+(O$4-O$5))))) -> 0 | P24: =IF($G24="","",IF($G24=1,(($C$2+$H24)*P$3)*(1+(P$4-P$5)),((P23+($H24*P$3))*(1+(P$4-P$5))))) -> 0 | ... T24: =IF($G24="","",IF($G24=1,(($C$2+$H24)*T$3)*(1+(T$4-T$5)),((T23+($H24*T$3))*(1+(T$4-T$5))))) -> 0 | U24: =IF(G24="","",SUM(I24,K24,M24,O24,Q24,S24)) -> 27348727 | V24: =IF(H24="","",SUM(J24,L24,N24,P24,R24,T24)) -> 20771601 | W24: =IF($G24="","",IF($G24=1,(($C$2+$H24)*W$3)*(1+(W$4-W$5)),((W23+($H24*W$3))*(1+(W$4-W$5))))) -> 26826795 | X24: =IF($G24="","",IF($G24=1,(($C$2+$H24)*X$3)*(1+(X$4-X$5)),((X23+($H24*X$3))*(1+(X$4-X$5))))) -> 20323785 | Y24: =IF($G24="","",IF($G24=1,(U24-$C$2-H24)/($C$2+H24),(U24-U23-H24)/(U23+H24))) -> 0.070698319 | Z24: =IF($G24="","",IF($G24=1,(V24-$C$2-H24)/($C$2+H24),(V24-V23-H24)/(V23+H24))) -> 0.051407945 | AA24: =IF($G24="","",Z24-Y24) -> -0.019290374 | AB24: =IF($G24="","",IF($G24=1,(W24-$C$2-H24)/($C$2+H24),(W24-W23-H24)/(W23+H24))) -> 0.068 | AC24: =IF($G24="","",IF($G24=1,(X24-$C$2-H24)/($C$2+H24),(X24-X23-H24)/(X23+H24))) -> 0.048416 | AD24: =IF($G24="","",AC24-AB24) -> -0.019584 | AE24: =IF($G24="","",IF($G24=1,Y24,(1+Y24)*(1+AE23)-1)) -> 1.7348727 | AF24: =IF($G24="","",IF($G24=1,Z24,(1+Z24)*(1+AF23)-1)) -> 1.0771601 | AG24: =IF($G24="","",AF24-AE24) -> -0.65771268 | AH24: =IF($G24="","",IF($G24=1,AB24,(1+AB24)*(1+AH23)-1)) -> 1.6826795 | AI24: =IF($G24="","",IF($G24=1,AC24,(1+AC24)*(1+AI23)-1)) -> 1.0323785 | AJ24: =IF($G24="","",AI24-AH24) -> -0.65030095 | AK24: =IF($G24="","",(1+AE24)^(1/G24)-1) -> 0.06937282 | AL24: =IF($G24="","",(1+AF24)^(1/G24)-1) -> 0.049940442 | AM24: =IF($G24="","",AL24-AK24) -> -0.019432378 | AN24: =IF($G24="","",(1+AH24)^(1/G24)-1) -> 0.068 | AO24: =IF($G24="","",(1+AI24)^(1/G24)-1) -> 0.048416 | AP24: =IF($G24="","",AO24-AN24) -> -0.019584
B25: Total Return (Net) | C25: =_xlfn.XLOOKUP(C3,G:G,AF:AF) -> 1.6762916 | D25: =_xlfn.XLOOKUP(C3,G:G,AI:AI) -> 1.5743809 | G25: 16 | H25: =IF(G25="","",SUMIFS(Add_Contributions[[#All],[Amount ($)]],Add_Contributions[[#All],[Year]],G25)) -> 0 | I25: =IF($G25="","",IF($G25=1,(($C$2+$H25)*I$3)*(1+(I$4-I$5)),((I24+($H25*I$3))*(1+(I$4-I$5))))) -> 20555656 | J25: =IF($G25="","",IF($G25=1,(($C$2+$H25)*J$3)*(1+(J$4-J$5)),((J24+($H25*J$3))*(1+(J$4-J$5))))) -> 15464483 | K25: =IF($G25="","",IF($G25=1,(($C$2+$H25)*K$3)*(1+(K$4-K$5)),((K24+($H25*K$3))*(1+(K$4-K$5))))) -> 0 | L25: =IF($G25="","",IF($G25=1,(($C$2+$H25)*L$3)*(1+(L$4-L$5)),((L24+($H25*L$3))*(1+(L$4-L$5))))) -> 0 | M25: =IF($G25="","",IF($G25=1,(($C$2+$H25)*M$3)*(1+(M$4-M$5)),((M24+($H25*M$3))*(1+(M$4-M$5))))) -> 8731498.4 | N25: =IF($G25="","",IF($G25=1,(($C$2+$H25)*N$3)*(1+(N$4-N$5)),((N24+($H25*N$3))*(1+(N$4-N$5))))) -> 6379057.7 | O25: =IF($G25="","",IF($G25=1,(($C$2+$H25)*O$3)*(1+(O$4-O$5)),((O24+($H25*O$3))*(1+(O$4-O$5))))) -> 0 | P25: =IF($G25="","",IF($G25=1,(($C$2+$H25)*P$3)*(1+(P$4-P$5)),((P24+($H25*P$3))*(1+(P$4-P$5))))) -> 0 | ... T25: =IF($G25="","",IF($G25=1,(($C$2+$H25)*T$3)*(1+(T$4-T$5)),((T24+($H25*T$3))*(1+(T$4-T$5))))) -> 0 | U25: =IF(G25="","",SUM(I25,K25,M25,O25,Q25,S25)) -> 29287154 | V25: =IF(H25="","",SUM(J25,L25,N25,P25,R25,T25)) -> 21843541 | W25: =IF($G25="","",IF($G25=1,(($C$2+$H25)*W$3)*(1+(W$4-W$5)),((W24+($H25*W$3))*(1+(W$4-W$5))))) -> 28651017 | X25: =IF($G25="","",IF($G25=1,(($C$2+$H25)*X$3)*(1+(X$4-X$5)),((X24+($H25*X$3))*(1+(X$4-X$5))))) -> 21307782 | Y25: =IF($G25="","",IF($G25=1,(U25-$C$2-H25)/($C$2+H25),(U25-U24-H25)/(U24+H25))) -> 0.070878136 | Z25: =IF($G25="","",IF($G25=1,(V25-$C$2-H25)/($C$2+H25),(V25-V24-H25)/(V24+H25))) -> 0.051606071 | AA25: =IF($G25="","",Z25-Y25) -> -0.019272065 | AB25: =IF($G25="","",IF($G25=1,(W25-$C$2-H25)/($C$2+H25),(W25-W24-H25)/(W24+H25))) -> 0.068 | AC25: =IF($G25="","",IF($G25=1,(X25-$C$2-H25)/($C$2+H25),(X25-X24-H25)/(X24+H25))) -> 0.048416 | AD25: =IF($G25="","",AC25-AB25) -> -0.019584 | AE25: =IF($G25="","",IF($G25=1,Y25,(1+Y25)*(1+AE24)-1)) -> 1.9287154 | AF25: =IF($G25="","",IF($G25=1,Z25,(1+Z25)*(1+AF24)-1)) -> 1.1843541 | AG25: =IF($G25="","",AF25-AE25) -> -0.7443613 | AH25: =IF($G25="","",IF($G25=1,AB25,(1+AB25)*(1+AH24)-1)) -> 1.8651017 | AI25: =IF($G25="","",IF($G25=1,AC25,(1+AC25)*(1+AI24)-1)) -> 1.1307782 | AJ25: =IF($G25="","",AI25-AH25) -> -0.73432352 | AK25: =IF($G25="","",(1+AE25)^(1/G25)-1) -> 0.06946684 | AL25: =IF($G25="","",(1+AF25)^(1/G25)-1) -> 0.050044466 | AM25: =IF($G25="","",AL25-AK25) -> -0.019422374 | AN25: =IF($G25="","",(1+AH25)^(1/G25)-1) -> 0.068 | AO25: =IF($G25="","",(1+AI25)^(1/G25)-1) -> 0.048416 | AP25: =IF($G25="","",AO25-AN25) -> -0.019584
B26: Total Return (Drag) | C26: =_xlfn.XLOOKUP(C3,G:G,AG:AG) -> -1.1816017 | D26: =_xlfn.XLOOKUP(C3,G:G,AJ:AJ) -> -1.1531826 | G26: 17 | H26: =IF(G26="","",SUMIFS(Add_Contributions[[#All],[Amount ($)]],Add_Contributions[[#All],[Year]],G26)) -> 0 | I26: =IF($G26="","",IF($G26=1,(($C$2+$H26)*I$3)*(1+(I$4-I$5)),((I25+($H26*I$3))*(1+(I$4-I$5))))) -> 22200108 | J26: =IF($G26="","",IF($G26=1,(($C$2+$H26)*J$3)*(1+(J$4-J$5)),((J25+($H26*J$3))*(1+(J$4-J$5))))) -> 16407198 | K26: =IF($G26="","",IF($G26=1,(($C$2+$H26)*K$3)*(1+(K$4-K$5)),((K25+($H26*K$3))*(1+(K$4-K$5))))) -> 0 | L26: =IF($G26="","",IF($G26=1,(($C$2+$H26)*L$3)*(1+(L$4-L$5)),((L25+($H26*L$3))*(1+(L$4-L$5))))) -> 0 | M26: =IF($G26="","",IF($G26=1,(($C$2+$H26)*M$3)*(1+(M$4-M$5)),((M25+($H26*M$3))*(1+(M$4-M$5))))) -> 9168073.3 | N26: =IF($G26="","",IF($G26=1,(($C$2+$H26)*N$3)*(1+(N$4-N$5)),((N25+($H26*N$3))*(1+(N$4-N$5))))) -> 6567877.9 | O26: =IF($G26="","",IF($G26=1,(($C$2+$H26)*O$3)*(1+(O$4-O$5)),((O25+($H26*O$3))*(1+(O$4-O$5))))) -> 0 | P26: =IF($G26="","",IF($G26=1,(($C$2+$H26)*P$3)*(1+(P$4-P$5)),((P25+($H26*P$3))*(1+(P$4-P$5))))) -> 0 | ... T26: =IF($G26="","",IF($G26=1,(($C$2+$H26)*T$3)*(1+(T$4-T$5)),((T25+($H26*T$3))*(1+(T$4-T$5))))) -> 0 | U26: =IF(G26="","",SUM(I26,K26,M26,O26,Q26,S26)) -> 31368182 | V26: =IF(H26="","",SUM(J26,L26,N26,P26,R26,T26)) -> 22975076 | W26: =IF($G26="","",IF($G26=1,(($C$2+$H26)*W$3)*(1+(W$4-W$5)),((W25+($H26*W$3))*(1+(W$4-W$5))))) -> 30599286 | X26: =IF($G26="","",IF($G26=1,(($C$2+$H26)*X$3)*(1+(X$4-X$5)),((X25+($H26*X$3))*(1+(X$4-X$5))))) -> 22339419 | Y26: =IF($G26="","",IF($G26=1,(U26-$C$2-H26)/($C$2+H26),(U26-U25-H26)/(U25+H26))) -> 0.071055978 | Z26: =IF($G26="","",IF($G26=1,(V26-$C$2-H26)/($C$2+H26),(V26-V25-H26)/(V25+H26))) -> 0.051801812 | AA26: =IF($G26="","",Z26-Y26) -> -0.019254166 | AB26: =IF($G26="","",IF($G26=1,(W26-$C$2-H26)/($C$2+H26),(W26-W25-H26)/(W25+H26))) -> 0.068 | AC26: =IF($G26="","",IF($G26=1,(X26-$C$2-H26)/($C$2+H26),(X26-X25-H26)/(X25+H26))) -> 0.048416 | AD26: =IF($G26="","",AC26-AB26) -> -0.019584 | AE26: =IF($G26="","",IF($G26=1,Y26,(1+Y26)*(1+AE25)-1)) -> 2.1368182 | AF26: =IF($G26="","",IF($G26=1,Z26,(1+Z26)*(1+AF25)-1)) -> 1.2975076 | AG26: =IF($G26="","",AF26-AE26) -> -0.83931053 | AH26: =IF($G26="","",IF($G26=1,AB26,(1+AB26)*(1+AH25)-1)) -> 2.0599286 | AI26: =IF($G26="","",IF($G26=1,AC26,(1+AC26)*(1+AI25)-1)) -> 1.2339419 | AJ26: =IF($G26="","",AI26-AH26) -> -0.82598668 | AK26: =IF($G26="","",(1+AE26)^(1/G26)-1) -> 0.069560253 | AL26: =IF($G26="","",(1+AF26)^(1/G26)-1) -> 0.050147758 | AM26: =IF($G26="","",AL26-AK26) -> -0.019412496 | AN26: =IF($G26="","",(1+AH26)^(1/G26)-1) -> 0.068 | AO26: =IF($G26="","",(1+AI26)^(1/G26)-1) -> 0.048416 | AP26: =IF($G26="","",AO26-AN26) -> -0.019584
G27: 18 | H27: =IF(G27="","",SUMIFS(Add_Contributions[[#All],[Amount ($)]],Add_Contributions[[#All],[Year]],G27)) -> 0 | I27: =IF($G27="","",IF($G27=1,(($C$2+$H27)*I$3)*(1+(I$4-I$5)),((I26+($H27*I$3))*(1+(I$4-I$5))))) -> 23976117 | J27: =IF($G27="","",IF($G27=1,(($C$2+$H27)*J$3)*(1+(J$4-J$5)),((J26+($H27*J$3))*(1+(J$4-J$5))))) -> 17407381 | K27: =IF($G27="","",IF($G27=1,(($C$2+$H27)*K$3)*(1+(K$4-K$5)),((K26+($H27*K$3))*(1+(K$4-K$5))))) -> 0 | L27: =IF($G27="","",IF($G27=1,(($C$2+$H27)*L$3)*(1+(L$4-L$5)),((L26+($H27*L$3))*(1+(L$4-L$5))))) -> 0 | M27: =IF($G27="","",IF($G27=1,(($C$2+$H27)*M$3)*(1+(M$4-M$5)),((M26+($H27*M$3))*(1+(M$4-M$5))))) -> 9626476.9 | N27: =IF($G27="","",IF($G27=1,(($C$2+$H27)*N$3)*(1+(N$4-N$5)),((N26+($H27*N$3))*(1+(N$4-N$5))))) -> 6762287 | O27: =IF($G27="","",IF($G27=1,(($C$2+$H27)*O$3)*(1+(O$4-O$5)),((O26+($H27*O$3))*(1+(O$4-O$5))))) -> 0 | P27: =IF($G27="","",IF($G27=1,(($C$2+$H27)*P$3)*(1+(P$4-P$5)),((P26+($H27*P$3))*(1+(P$4-P$5))))) -> 0 | ... T27: =IF($G27="","",IF($G27=1,(($C$2+$H27)*T$3)*(1+(T$4-T$5)),((T26+($H27*T$3))*(1+(T$4-T$5))))) -> 0 | U27: =IF(G27="","",SUM(I27,K27,M27,O27,Q27,S27)) -> 33602594 | V27: =IF(H27="","",SUM(J27,L27,N27,P27,R27,T27)) -> 24169668 | W27: =IF($G27="","",IF($G27=1,(($C$2+$H27)*W$3)*(1+(W$4-W$5)),((W26+($H27*W$3))*(1+(W$4-W$5))))) -> 32680038 | X27: =IF($G27="","",IF($G27=1,(($C$2+$H27)*X$3)*(1+(X$4-X$5)),((X26+($H27*X$3))*(1+(X$4-X$5))))) -> 23421005 | Y27: =IF($G27="","",IF($G27=1,(U27-$C$2-H27)/($C$2+H27),(U27-U26-H27)/(U26+H27))) -> 0.071231809 | Z27: =IF($G27="","",IF($G27=1,(V27-$C$2-H27)/($C$2+H27),(V27-V26-H27)/(V26+H27))) -> 0.051995127 | AA27: =IF($G27="","",Z27-Y27) -> -0.019236683 | AB27: =IF($G27="","",IF($G27=1,(W27-$C$2-H27)/($C$2+H27),(W27-W26-H27)/(W26+H27))) -> 0.068 | AC27: =IF($G27="","",IF($G27=1,(X27-$C$2-H27)/($C$2+H27),(X27-X26-H27)/(X26+H27))) -> 0.048416 | AD27: =IF($G27="","",AC27-AB27) -> -0.019584 | AE27: =IF($G27="","",IF($G27=1,Y27,(1+Y27)*(1+AE26)-1)) -> 2.3602594 | AF27: =IF($G27="","",IF($G27=1,Z27,(1+Z27)*(1+AF26)-1)) -> 1.4169668 | AG27: =IF($G27="","",AF27-AE27) -> -0.94329257 | AH27: =IF($G27="","",IF($G27=1,AB27,(1+AB27)*(1+AH26)-1)) -> 2.2680038 | AI27: =IF($G27="","",IF($G27=1,AC27,(1+AC27)*(1+AI26)-1)) -> 1.3421005 | AJ27: =IF($G27="","",AI27-AH27) -> -0.92590329 | AK27: =IF($G27="","",(1+AE27)^(1/G27)-1) -> 0.069653049 | AL27: =IF($G27="","",(1+AF27)^(1/G27)-1) -> 0.050250304 | AM27: =IF($G27="","",AL27-AK27) -> -0.019402745 | AN27: =IF($G27="","",(1+AH27)^(1/G27)-1) -> 0.068 | AO27: =IF($G27="","",(1+AI27)^(1/G27)-1) -> 0.048416 | AP27: =IF($G27="","",AO27-AN27) -> -0.019584
B28: Annualized Return (Gross) | C28: =_xlfn.XLOOKUP(C3,G:G,AK:AK) -> 0.069836747 | D28: =_xlfn.XLOOKUP(C3,G:G,AN:AN) -> 0.068 | G28: 19 | H28: =IF(G28="","",SUMIFS(Add_Contributions[[#All],[Amount ($)]],Add_Contributions[[#All],[Year]],G28)) -> 0 | I28: =IF($G28="","",IF($G28=1,(($C$2+$H28)*I$3)*(1+(I$4-I$5)),((I27+($H28*I$3))*(1+(I$4-I$5))))) -> 25894206 | J28: =IF($G28="","",IF($G28=1,(($C$2+$H28)*J$3)*(1+(J$4-J$5)),((J27+($H28*J$3))*(1+(J$4-J$5))))) -> 18468535 | K28: =IF($G28="","",IF($G28=1,(($C$2+$H28)*K$3)*(1+(K$4-K$5)),((K27+($H28*K$3))*(1+(K$4-K$5))))) -> 0 | L28: =IF($G28="","",IF($G28=1,(($C$2+$H28)*L$3)*(1+(L$4-L$5)),((L27+($H28*L$3))*(1+(L$4-L$5))))) -> 0 | M28: =IF($G28="","",IF($G28=1,(($C$2+$H28)*M$3)*(1+(M$4-M$5)),((M27+($H28*M$3))*(1+(M$4-M$5))))) -> 10107801 | N28: =IF($G28="","",IF($G28=1,(($C$2+$H28)*N$3)*(1+(N$4-N$5)),((N27+($H28*N$3))*(1+(N$4-N$5))))) -> 6962450.7 | O28: =IF($G28="","",IF($G28=1,(($C$2+$H28)*O$3)*(1+(O$4-O$5)),((O27+($H28*O$3))*(1+(O$4-O$5))))) -> 0 | P28: =IF($G28="","",IF($G28=1,(($C$2+$H28)*P$3)*(1+(P$4-P$5)),((P27+($H28*P$3))*(1+(P$4-P$5))))) -> 0 | ... T28: =IF($G28="","",IF($G28=1,(($C$2+$H28)*T$3)*(1+(T$4-T$5)),((T27+($H28*T$3))*(1+(T$4-T$5))))) -> 0 | U28: =IF(G28="","",SUM(I28,K28,M28,O28,Q28,S28)) -> 36002007 | V28: =IF(H28="","",SUM(J28,L28,N28,P28,R28,T28)) -> 25430986 | W28: =IF($G28="","",IF($G28=1,(($C$2+$H28)*W$3)*(1+(W$4-W$5)),((W27+($H28*W$3))*(1+(W$4-W$5))))) -> 34902280 | X28: =IF($G28="","",IF($G28=1,(($C$2+$H28)*X$3)*(1+(X$4-X$5)),((X27+($H28*X$3))*(1+(X$4-X$5))))) -> 24554956 | Y28: =IF($G28="","",IF($G28=1,(U28-$C$2-H28)/($C$2+H28),(U28-U27-H28)/(U27+H28))) -> 0.071405595 | Z28: =IF($G28="","",IF($G28=1,(V28-$C$2-H28)/($C$2+H28),(V28-V27-H28)/(V27+H28))) -> 0.052185973 | AA28: =IF($G28="","",Z28-Y28) -> -0.019219622 | AB28: =IF($G28="","",IF($G28=1,(W28-$C$2-H28)/($C$2+H28),(W28-W27-H28)/(W27+H28))) -> 0.068 | AC28: =IF($G28="","",IF($G28=1,(X28-$C$2-H28)/($C$2+H28),(X28-X27-H28)/(X27+H28))) -> 0.048416 | AD28: =IF($G28="","",AC28-AB28) -> -0.019584 | AE28: =IF($G28="","",IF($G28=1,Y28,(1+Y28)*(1+AE27)-1)) -> 2.6002007 | AF28: =IF($G28="","",IF($G28=1,Z28,(1+Z28)*(1+AF27)-1)) -> 1.5430986 | AG28: =IF($G28="","",AF28-AE28) -> -1.0571021 | AH28: =IF($G28="","",IF($G28=1,AB28,(1+AB28)*(1+AH27)-1)) -> 2.490228 | AI28: =IF($G28="","",IF($G28=1,AC28,(1+AC28)*(1+AI27)-1)) -> 1.4554956 | AJ28: =IF($G28="","",AI28-AH28) -> -1.0347324 | AK28: =IF($G28="","",(1+AE28)^(1/G28)-1) -> 0.069745217 | AL28: =IF($G28="","",(1+AF28)^(1/G28)-1) -> 0.050352093 | AM28: =IF($G28="","",AL28-AK28) -> -0.019393124 | AN28: =IF($G28="","",(1+AH28)^(1/G28)-1) -> 0.068 | AO28: =IF($G28="","",(1+AI28)^(1/G28)-1) -> 0.048416 | AP28: =IF($G28="","",AO28-AN28) -> -0.019584
B29: Annualized Return (Net) | C29: =_xlfn.XLOOKUP(C3,G:G,AL:AL) -> 0.050453112 | D29: =_xlfn.XLOOKUP(C3,G:G,AO:AO) -> 0.048416 | G29: 20 | H29: =IF(G29="","",SUMIFS(Add_Contributions[[#All],[Amount ($)]],Add_Contributions[[#All],[Year]],G29)) -> 0 | I29: =IF($G29="","",IF($G29=1,(($C$2+$H29)*I$3)*(1+(I$4-I$5)),((I28+($H29*I$3))*(1+(I$4-I$5))))) -> 27965743 | J29: =IF($G29="","",IF($G29=1,(($C$2+$H29)*J$3)*(1+(J$4-J$5)),((J28+($H29*J$3))*(1+(J$4-J$5))))) -> 19594377 | K29: =IF($G29="","",IF($G29=1,(($C$2+$H29)*K$3)*(1+(K$4-K$5)),((K28+($H29*K$3))*(1+(K$4-K$5))))) -> 0 | L29: =IF($G29="","",IF($G29=1,(($C$2+$H29)*L$3)*(1+(L$4-L$5)),((L28+($H29*L$3))*(1+(L$4-L$5))))) -> 0 | M29: =IF($G29="","",IF($G29=1,(($C$2+$H29)*M$3)*(1+(M$4-M$5)),((M28+($H29*M$3))*(1+(M$4-M$5))))) -> 10613191 | N29: =IF($G29="","",IF($G29=1,(($C$2+$H29)*N$3)*(1+(N$4-N$5)),((N28+($H29*N$3))*(1+(N$4-N$5))))) -> 7168539.3 | O29: =IF($G29="","",IF($G29=1,(($C$2+$H29)*O$3)*(1+(O$4-O$5)),((O28+($H29*O$3))*(1+(O$4-O$5))))) -> 0 | P29: =IF($G29="","",IF($G29=1,(($C$2+$H29)*P$3)*(1+(P$4-P$5)),((P28+($H29*P$3))*(1+(P$4-P$5))))) -> 0 | ... T29: =IF($G29="","",IF($G29=1,(($C$2+$H29)*T$3)*(1+(T$4-T$5)),((T28+($H29*T$3))*(1+(T$4-T$5))))) -> 0 | U29: =IF(G29="","",SUM(I29,K29,M29,O29,Q29,S29)) -> 38578934 | V29: =IF(H29="","",SUM(J29,L29,N29,P29,R29,T29)) -> 26762916 | W29: =IF($G29="","",IF($G29=1,(($C$2+$H29)*W$3)*(1+(W$4-W$5)),((W28+($H29*W$3))*(1+(W$4-W$5))))) -> 37275635 | X29: =IF($G29="","",IF($G29=1,(($C$2+$H29)*X$3)*(1+(X$4-X$5)),((X28+($H29*X$3))*(1+(X$4-X$5))))) -> 25743809 | Y29: =IF($G29="","",IF($G29=1,(U29-$C$2-H29)/($C$2+H29),(U29-U28-H29)/(U28+H29))) -> 0.071577302 | Z29: =IF($G29="","",IF($G29=1,(V29-$C$2-H29)/($C$2+H29),(V29-V28-H29)/(V28+H29))) -> 0.052374314 | AA29: =IF($G29="","",Z29-Y29) -> -0.019202988 | AB29: =IF($G29="","",IF($G29=1,(W29-$C$2-H29)/($C$2+H29),(W29-W28-H29)/(W28+H29))) -> 0.068 | AC29: =IF($G29="","",IF($G29=1,(X29-$C$2-H29)/($C$2+H29),(X29-X28-H29)/(X28+H29))) -> 0.048416 | AD29: =IF($G29="","",AC29-AB29) -> -0.019584 | AE29: =IF($G29="","",IF($G29=1,Y29,(1+Y29)*(1+AE28)-1)) -> 2.8578934 | AF29: =IF($G29="","",IF($G29=1,Z29,(1+Z29)*(1+AF28)-1)) -> 1.6762916 | AG29: =IF($G29="","",AF29-AE29) -> -1.1816017 | AH29: =IF($G29="","",IF($G29=1,AB29,(1+AB29)*(1+AH28)-1)) -> 2.7275635 | AI29: =IF($G29="","",IF($G29=1,AC29,(1+AC29)*(1+AI28)-1)) -> 1.5743809 | AJ29: =IF($G29="","",AI29-AH29) -> -1.1531826 | AK29: =IF($G29="","",(1+AE29)^(1/G29)-1) -> 0.069836747 | AL29: =IF($G29="","",(1+AF29)^(1/G29)-1) -> 0.050453112 | AM29: =IF($G29="","",AL29-AK29) -> -0.019383635 | AN29: =IF($G29="","",(1+AH29)^(1/G29)-1) -> 0.068 | AO29: =IF($G29="","",(1+AI29)^(1/G29)-1) -> 0.048416 | AP29: =IF($G29="","",AO29-AN29) -> -0.019584
B30: Annualized Return (Drag) | C30: =_xlfn.XLOOKUP(C3,G:G,AM:AM) -> -0.019383635 | D30: =_xlfn.XLOOKUP(C3,G:G,AP:AP) -> -0.019584 | H30: =IF(G30="","",SUMIFS(Add_Contributions[[#All],[Amount ($)]],Add_Contributions[[#All],[Year]],G30)) | I30: =IF($G30="","",IF($G30=1,(($C$2+$H30)*I$3)*(1+(I$4-I$5)),((I29+($H30*I$3))*(1+(I$4-I$5))))) | J30: =IF($G30="","",IF($G30=1,(($C$2+$H30)*J$3)*(1+(J$4-J$5)),((J29+($H30*J$3))*(1+(J$4-J$5))))) | K30: =IF($G30="","",IF($G30=1,(($C$2+$H30)*K$3)*(1+(K$4-K$5)),((K29+($H30*K$3))*(1+(K$4-K$5))))) | L30: =IF($G30="","",IF($G30=1,(($C$2+$H30)*L$3)*(1+(L$4-L$5)),((L29+($H30*L$3))*(1+(L$4-L$5))))) | M30: =IF($G30="","",IF($G30=1,(($C$2+$H30)*M$3)*(1+(M$4-M$5)),((M29+($H30*M$3))*(1+(M$4-M$5))))) | N30: =IF($G30="","",IF($G30=1,(($C$2+$H30)*N$3)*(1+(N$4-N$5)),((N29+($H30*N$3))*(1+(N$4-N$5))))) | O30: =IF($G30="","",IF($G30=1,(($C$2+$H30)*O$3)*(1+(O$4-O$5)),((O29+($H30*O$3))*(1+(O$4-O$5))))) | P30: =IF($G30="","",IF($G30=1,(($C$2+$H30)*P$3)*(1+(P$4-P$5)),((P29+($H30*P$3))*(1+(P$4-P$5))))) | ... T30: =IF($G30="","",IF($G30=1,(($C$2+$H30)*T$3)*(1+(T$4-T$5)),((T29+($H30*T$3))*(1+(T$4-T$5))))) | U30: =IF(G30="","",SUM(I30,K30,M30,O30,Q30,S30)) | V30: =IF(H30="","",SUM(J30,L30,N30,P30,R30,T30)) | W30: =IF($G30="","",IF($G30=1,(($C$2+$H30)*W$3)*(1+(W$4-W$5)),((W29+($H30*W$3))*(1+(W$4-W$5))))) | X30: =IF($G30="","",IF($G30=1,(($C$2+$H30)*X$3)*(1+(X$4-X$5)),((X29+($H30*X$3))*(1+(X$4-X$5))))) | Y30: =IF($G30="","",IF($G30=1,(U30-$C$2-H30)/($C$2+H30),(U30-U29-H30)/(U29+H30))) | Z30: =IF($G30="","",IF($G30=1,(V30-$C$2-H30)/($C$2+H30),(V30-V29-H30)/(V29+H30))) | AA30: =IF($G30="","",Z30-Y30) | AB30: =IF($G30="","",IF($G30=1,(W30-$C$2-H30)/($C$2+H30),(W30-W29-H30)/(W29+H30))) | AC30: =IF($G30="","",IF($G30=1,(X30-$C$2-H30)/($C$2+H30),(X30-X29-H30)/(X29+H30))) | AD30: =IF($G30="","",AC30-AB30) | AE30: =IF($G30="","",IF($G30=1,Y30,(1+Y30)*(1+AE29)-1)) | AF30: =IF($G30="","",IF($G30=1,Z30,(1+Z30)*(1+AF29)-1)) | AG30: =IF($G30="","",AF30-AE30) | AH30: =IF($G30="","",IF($G30=1,AB30,(1+AB30)*(1+AH29)-1)) | AI30: =IF($G30="","",IF($G30=1,AC30,(1+AC30)*(1+AI29)-1)) | AJ30: =IF($G30="","",AI30-AH30) | AK30: =IF($G30="","",(1+AE30)^(1/G30)-1) | AL30: =IF($G30="","",(1+AF30)^(1/G30)-1) | AM30: =IF($G30="","",AL30-AK30) | AN30: =IF($G30="","",(1+AH30)^(1/G30)-1) | AO30: =IF($G30="","",(1+AI30)^(1/G30)-1) | AP30: =IF($G30="","",AO30-AN30)
H31: =IF(G31="","",SUMIFS(Add_Contributions[[#All],[Amount ($)]],Add_Contributions[[#All],[Year]],G31)) | I31: =IF($G31="","",IF($G31=1,(($C$2+$H31)*I$3)*(1+(I$4-I$5)),((I30+($H31*I$3))*(1+(I$4-I$5))))) | J31: =IF($G31="","",IF($G31=1,(($C$2+$H31)*J$3)*(1+(J$4-J$5)),((J30+($H31*J$3))*(1+(J$4-J$5))))) | K31: =IF($G31="","",IF($G31=1,(($C$2+$H31)*K$3)*(1+(K$4-K$5)),((K30+($H31*K$3))*(1+(K$4-K$5))))) | L31: =IF($G31="","",IF($G31=1,(($C$2+$H31)*L$3)*(1+(L$4-L$5)),((L30+($H31*L$3))*(1+(L$4-L$5))))) | M31: =IF($G31="","",IF($G31=1,(($C$2+$H31)*M$3)*(1+(M$4-M$5)),((M30+($H31*M$3))*(1+(M$4-M$5))))) | N31: =IF($G31="","",IF($G31=1,(($C$2+$H31)*N$3)*(1+(N$4-N$5)),((N30+($H31*N$3))*(1+(N$4-N$5))))) | O31: =IF($G31="","",IF($G31=1,(($C$2+$H31)*O$3)*(1+(O$4-O$5)),((O30+($H31*O$3))*(1+(O$4-O$5))))) | P31: =IF($G31="","",IF($G31=1,(($C$2+$H31)*P$3)*(1+(P$4-P$5)),((P30+($H31*P$3))*(1+(P$4-P$5))))) | ... T31: =IF($G31="","",IF($G31=1,(($C$2+$H31)*T$3)*(1+(T$4-T$5)),((T30+($H31*T$3))*(1+(T$4-T$5))))) | U31: =IF(G31="","",SUM(I31,K31,M31,O31,Q31,S31)) | V31: =IF(H31="","",SUM(J31,L31,N31,P31,R31,T31)) | W31: =IF($G31="","",IF($G31=1,(($C$2+$H31)*W$3)*(1+(W$4-W$5)),((W30+($H31*W$3))*(1+(W$4-W$5))))) | X31: =IF($G31="","",IF($G31=1,(($C$2+$H31)*X$3)*(1+(X$4-X$5)),((X30+($H31*X$3))*(1+(X$4-X$5))))) | Y31: =IF($G31="","",IF($G31=1,(U31-$C$2-H31)/($C$2+H31),(U31-U30-H31)/(U30+H31))) | Z31: =IF($G31="","",IF($G31=1,(V31-$C$2-H31)/($C$2+H31),(V31-V30-H31)/(V30+H31))) | AA31: =IF($G31="","",Z31-Y31) | AB31: =IF($G31="","",IF($G31=1,(W31-$C$2-H31)/($C$2+H31),(W31-W30-H31)/(W30+H31))) | AC31: =IF($G31="","",IF($G31=1,(X31-$C$2-H31)/($C$2+H31),(X31-X30-H31)/(X30+H31))) | AD31: =IF($G31="","",AC31-AB31) | AE31: =IF($G31="","",IF($G31=1,Y31,(1+Y31)*(1+AE30)-1)) | AF31: =IF($G31="","",IF($G31=1,Z31,(1+Z31)*(1+AF30)-1)) | AG31: =IF($G31="","",AF31-AE31) | AH31: =IF($G31="","",IF($G31=1,AB31,(1+AB31)*(1+AH30)-1)) | AI31: =IF($G31="","",IF($G31=1,AC31,(1+AC31)*(1+AI30)-1)) | AJ31: =IF($G31="","",AI31-AH31) | AK31: =IF($G31="","",(1+AE31)^(1/G31)-1) | AL31: =IF($G31="","",(1+AF31)^(1/G31)-1) | AM31: =IF($G31="","",AL31-AK31) | AN31: =IF($G31="","",(1+AH31)^(1/G31)-1) | AO31: =IF($G31="","",(1+AI31)^(1/G31)-1) | AP31: =IF($G31="","",AO31-AN31)
H32: =IF(G32="","",SUMIFS(Add_Contributions[[#All],[Amount ($)]],Add_Contributions[[#All],[Year]],G32)) | I32: =IF($G32="","",IF($G32=1,(($C$2+$H32)*I$3)*(1+(I$4-I$5)),((I31+($H32*I$3))*(1+(I$4-I$5))))) | J32: =IF($G32="","",IF($G32=1,(($C$2+$H32)*J$3)*(1+(J$4-J$5)),((J31+($H32*J$3))*(1+(J$4-J$5))))) | K32: =IF($G32="","",IF($G32=1,(($C$2+$H32)*K$3)*(1+(K$4-K$5)),((K31+($H32*K$3))*(1+(K$4-K$5))))) | L32: =IF($G32="","",IF($G32=1,(($C$2+$H32)*L$3)*(1+(L$4-L$5)),((L31+($H32*L$3))*(1+(L$4-L$5))))) | M32: =IF($G32="","",IF($G32=1,(($C$2+$H32)*M$3)*(1+(M$4-M$5)),((M31+($H32*M$3))*(1+(M$4-M$5))))) | N32: =IF($G32="","",IF($G32=1,(($C$2+$H32)*N$3)*(1+(N$4-N$5)),((N31+($H32*N$3))*(1+(N$4-N$5))))) | O32: =IF($G32="","",IF($G32=1,(($C$2+$H32)*O$3)*(1+(O$4-O$5)),((O31+($H32*O$3))*(1+(O$4-O$5))))) | P32: =IF($G32="","",IF($G32=1,(($C$2+$H32)*P$3)*(1+(P$4-P$5)),((P31+($H32*P$3))*(1+(P$4-P$5))))) | ... T32: =IF($G32="","",IF($G32=1,(($C$2+$H32)*T$3)*(1+(T$4-T$5)),((T31+($H32*T$3))*(1+(T$4-T$5))))) | U32: =IF(G32="","",SUM(I32,K32,M32,O32,Q32,S32)) | V32: =IF(H32="","",SUM(J32,L32,N32,P32,R32,T32)) | W32: =IF($G32="","",IF($G32=1,(($C$2+$H32)*W$3)*(1+(W$4-W$5)),((W31+($H32*W$3))*(1+(W$4-W$5))))) | X32: =IF($G32="","",IF($G32=1,(($C$2+$H32)*X$3)*(1+(X$4-X$5)),((X31+($H32*X$3))*(1+(X$4-X$5))))) | Y32: =IF($G32="","",IF($G32=1,(U32-$C$2-H32)/($C$2+H32),(U32-U31-H32)/(U31+H32))) | Z32: =IF($G32="","",IF($G32=1,(V32-$C$2-H32)/($C$2+H32),(V32-V31-H32)/(V31+H32))) | AA32: =IF($G32="","",Z32-Y32) | AB32: =IF($G32="","",IF($G32=1,(W32-$C$2-H32)/($C$2+H32),(W32-W31-H32)/(W31+H32))) | AC32: =IF($G32="","",IF($G32=1,(X32-$C$2-H32)/($C$2+H32),(X32-X31-H32)/(X31+H32))) | AD32: =IF($G32="","",AC32-AB32) | AE32: =IF($G32="","",IF($G32=1,Y32,(1+Y32)*(1+AE31)-1)) | AF32: =IF($G32="","",IF($G32=1,Z32,(1+Z32)*(1+AF31)-1)) | AG32: =IF($G32="","",AF32-AE32) | AH32: =IF($G32="","",IF($G32=1,AB32,(1+AB32)*(1+AH31)-1)) | AI32: =IF($G32="","",IF($G32=1,AC32,(1+AC32)*(1+AI31)-1)) | AJ32: =IF($G32="","",AI32-AH32) | AK32: =IF($G32="","",(1+AE32)^(1/G32)-1) | AL32: =IF($G32="","",(1+AF32)^(1/G32)-1) | AM32: =IF($G32="","",AL32-AK32) | AN32: =IF($G32="","",(1+AH32)^(1/G32)-1) | AO32: =IF($G32="","",(1+AI32)^(1/G32)-1) | AP32: =IF($G32="","",AO32-AN32)
H33: =IF(G33="","",SUMIFS(Add_Contributions[[#All],[Amount ($)]],Add_Contributions[[#All],[Year]],G33)) | I33: =IF($G33="","",IF($G33=1,(($C$2+$H33)*I$3)*(1+(I$4-I$5)),((I32+($H33*I$3))*(1+(I$4-I$5))))) | J33: =IF($G33="","",IF($G33=1,(($C$2+$H33)*J$3)*(1+(J$4-J$5)),((J32+($H33*J$3))*(1+(J$4-J$5))))) | K33: =IF($G33="","",IF($G33=1,(($C$2+$H33)*K$3)*(1+(K$4-K$5)),((K32+($H33*K$3))*(1+(K$4-K$5))))) | L33: =IF($G33="","",IF($G33=1,(($C$2+$H33)*L$3)*(1+(L$4-L$5)),((L32+($H33*L$3))*(1+(L$4-L$5))))) | M33: =IF($G33="","",IF($G33=1,(($C$2+$H33)*M$3)*(1+(M$4-M$5)),((M32+($H33*M$3))*(1+(M$4-M$5))))) | N33: =IF($G33="","",IF($G33=1,(($C$2+$H33)*N$3)*(1+(N$4-N$5)),((N32+($H33*N$3))*(1+(N$4-N$5))))) | O33: =IF($G33="","",IF($G33=1,(($C$2+$H33)*O$3)*(1+(O$4-O$5)),((O32+($H33*O$3))*(1+(O$4-O$5))))) | P33: =IF($G33="","",IF($G33=1,(($C$2+$H33)*P$3)*(1+(P$4-P$5)),((P32+($H33*P$3))*(1+(P$4-P$5))))) | ... T33: =IF($G33="","",IF($G33=1,(($C$2+$H33)*T$3)*(1+(T$4-T$5)),((T32+($H33*T$3))*(1+(T$4-T$5))))) | U33: =IF(G33="","",SUM(I33,K33,M33,O33,Q33,S33)) | V33: =IF(H33="","",SUM(J33,L33,N33,P33,R33,T33)) | W33: =IF($G33="","",IF($G33=1,(($C$2+$H33)*W$3)*(1+(W$4-W$5)),((W32+($H33*W$3))*(1+(W$4-W$5))))) | X33: =IF($G33="","",IF($G33=1,(($C$2+$H33)*X$3)*(1+(X$4-X$5)),((X32+($H33*X$3))*(1+(X$4-X$5))))) | Y33: =IF($G33="","",IF($G33=1,(U33-$C$2-H33)/($C$2+H33),(U33-U32-H33)/(U32+H33))) | Z33: =IF($G33="","",IF($G33=1,(V33-$C$2-H33)/($C$2+H33),(V33-V32-H33)/(V32+H33))) | AA33: =IF($G33="","",Z33-Y33) | AB33: =IF($G33="","",IF($G33=1,(W33-$C$2-H33)/($C$2+H33),(W33-W32-H33)/(W32+H33))) | AC33: =IF($G33="","",IF($G33=1,(X33-$C$2-H33)/($C$2+H33),(X33-X32-H33)/(X32+H33))) | AD33: =IF($G33="","",AC33-AB33) | AE33: =IF($G33="","",IF($G33=1,Y33,(1+Y33)*(1+AE32)-1)) | AF33: =IF($G33="","",IF($G33=1,Z33,(1+Z33)*(1+AF32)-1)) | AG33: =IF($G33="","",AF33-AE33) | AH33: =IF($G33="","",IF($G33=1,AB33,(1+AB33)*(1+AH32)-1)) | AI33: =IF($G33="","",IF($G33=1,AC33,(1+AC33)*(1+AI32)-1)) | AJ33: =IF($G33="","",AI33-AH33) | AK33: =IF($G33="","",(1+AE33)^(1/G33)-1) | AL33: =IF($G33="","",(1+AF33)^(1/G33)-1) | AM33: =IF($G33="","",AL33-AK33) | AN33: =IF($G33="","",(1+AH33)^(1/G33)-1) | AO33: =IF($G33="","",(1+AI33)^(1/G33)-1) | AP33: =IF($G33="","",AO33-AN33)
H34: =IF(G34="","",SUMIFS(Add_Contributions[[#All],[Amount ($)]],Add_Contributions[[#All],[Year]],G34)) | I34: =IF($G34="","",IF($G34=1,(($C$2+$H34)*I$3)*(1+(I$4-I$5)),((I33+($H34*I$3))*(1+(I$4-I$5))))) | J34: =IF($G34="","",IF($G34=1,(($C$2+$H34)*J$3)*(1+(J$4-J$5)),((J33+($H34*J$3))*(1+(J$4-J$5))))) | K34: =IF($G34="","",IF($G34=1,(($C$2+$H34)*K$3)*(1+(K$4-K$5)),((K33+($H34*K$3))*(1+(K$4-K$5))))) | L34: =IF($G34="","",IF($G34=1,(($C$2+$H34)*L$3)*(1+(L$4-L$5)),((L33+($H34*L$3))*(1+(L$4-L$5))))) | M34: =IF($G34="","",IF($G34=1,(($C$2+$H34)*M$3)*(1+(M$4-M$5)),((M33+($H34*M$3))*(1+(M$4-M$5))))) | N34: =IF($G34="","",IF($G34=1,(($C$2+$H34)*N$3)*(1+(N$4-N$5)),((N33+($H34*N$3))*(1+(N$4-N$5))))) | O34: =IF($G34="","",IF($G34=1,(($C$2+$H34)*O$3)*(1+(O$4-O$5)),((O33+($H34*O$3))*(1+(O$4-O$5))))) | P34: =IF($G34="","",IF($G34=1,(($C$2+$H34)*P$3)*(1+(P$4-P$5)),((P33+($H34*P$3))*(1+(P$4-P$5))))) | ... T34: =IF($G34="","",IF($G34=1,(($C$2+$H34)*T$3)*(1+(T$4-T$5)),((T33+($H34*T$3))*(1+(T$4-T$5))))) | U34: =IF(G34="","",SUM(I34,K34,M34,O34,Q34,S34)) | V34: =IF(H34="","",SUM(J34,L34,N34,P34,R34,T34)) | W34: =IF($G34="","",IF($G34=1,(($C$2+$H34)*W$3)*(1+(W$4-W$5)),((W33+($H34*W$3))*(1+(W$4-W$5))))) | X34: =IF($G34="","",IF($G34=1,(($C$2+$H34)*X$3)*(1+(X$4-X$5)),((X33+($H34*X$3))*(1+(X$4-X$5))))) | Y34: =IF($G34="","",IF($G34=1,(U34-$C$2-H34)/($C$2+H34),(U34-U33-H34)/(U33+H34))) | Z34: =IF($G34="","",IF($G34=1,(V34-$C$2-H34)/($C$2+H34),(V34-V33-H34)/(V33+H34))) | AA34: =IF($G34="","",Z34-Y34) | AB34: =IF($G34="","",IF($G34=1,(W34-$C$2-H34)/($C$2+H34),(W34-W33-H34)/(W33+H34))) | AC34: =IF($G34="","",IF($G34=1,(X34-$C$2-H34)/($C$2+H34),(X34-X33-H34)/(X33+H34))) | AD34: =IF($G34="","",AC34-AB34) | AE34: =IF($G34="","",IF($G34=1,Y34,(1+Y34)*(1+AE33)-1)) | AF34: =IF($G34="","",IF($G34=1,Z34,(1+Z34)*(1+AF33)-1)) | AG34: =IF($G34="","",AF34-AE34) | AH34: =IF($G34="","",IF($G34=1,AB34,(1+AB34)*(1+AH33)-1)) | AI34: =IF($G34="","",IF($G34=1,AC34,(1+AC34)*(1+AI33)-1)) | AJ34: =IF($G34="","",AI34-AH34) | AK34: =IF($G34="","",(1+AE34)^(1/G34)-1) | AL34: =IF($G34="","",(1+AF34)^(1/G34)-1) | AM34: =IF($G34="","",AL34-AK34) | AN34: =IF($G34="","",(1+AH34)^(1/G34)-1) | AO34: =IF($G34="","",(1+AI34)^(1/G34)-1) | AP34: =IF($G34="","",AO34-AN34)
H35: =IF(G35="","",SUMIFS(Add_Contributions[[#All],[Amount ($)]],Add_Contributions[[#All],[Year]],G35)) | I35: =IF($G35="","",IF($G35=1,(($C$2+$H35)*I$3)*(1+(I$4-I$5)),((I34+($H35*I$3))*(1+(I$4-I$5))))) | J35: =IF($G35="","",IF($G35=1,(($C$2+$H35)*J$3)*(1+(J$4-J$5)),((J34+($H35*J$3))*(1+(J$4-J$5))))) | K35: =IF($G35="","",IF($G35=1,(($C$2+$H35)*K$3)*(1+(K$4-K$5)),((K34+($H35*K$3))*(1+(K$4-K$5))))) | L35: =IF($G35="","",IF($G35=1,(($C$2+$H35)*L$3)*(1+(L$4-L$5)),((L34+($H35*L$3))*(1+(L$4-L$5))))) | M35: =IF($G35="","",IF($G35=1,(($C$2+$H35)*M$3)*(1+(M$4-M$5)),((M34+($H35*M$3))*(1+(M$4-M$5))))) | N35: =IF($G35="","",IF($G35=1,(($C$2+$H35)*N$3)*(1+(N$4-N$5)),((N34+($H35*N$3))*(1+(N$4-N$5))))) | O35: =IF($G35="","",IF($G35=1,(($C$2+$H35)*O$3)*(1+(O$4-O$5)),((O34+($H35*O$3))*(1+(O$4-O$5))))) | P35: =IF($G35="","",IF($G35=1,(($C$2+$H35)*P$3)*(1+(P$4-P$5)),((P34+($H35*P$3))*(1+(P$4-P$5))))) | ... T35: =IF($G35="","",IF($G35=1,(($C$2+$H35)*T$3)*(1+(T$4-T$5)),((T34+($H35*T$3))*(1+(T$4-T$5))))) | U35: =IF(G35="","",SUM(I35,K35,M35,O35,Q35,S35)) | V35: =IF(H35="","",SUM(J35,L35,N35,P35,R35,T35)) | W35: =IF($G35="","",IF($G35=1,(($C$2+$H35)*W$3)*(1+(W$4-W$5)),((W34+($H35*W$3))*(1+(W$4-W$5))))) | X35: =IF($G35="","",IF($G35=1,(($C$2+$H35)*X$3)*(1+(X$4-X$5)),((X34+($H35*X$3))*(1+(X$4-X$5))))) | Y35: =IF($G35="","",IF($G35=1,(U35-$C$2-H35)/($C$2+H35),(U35-U34-H35)/(U34+H35))) | Z35: =IF($G35="","",IF($G35=1,(V35-$C$2-H35)/($C$2+H35),(V35-V34-H35)/(V34+H35))) | AA35: =IF($G35="","",Z35-Y35) | AB35: =IF($G35="","",IF($G35=1,(W35-$C$2-H35)/($C$2+H35),(W35-W34-H35)/(W34+H35))) | AC35: =IF($G35="","",IF($G35=1,(X35-$C$2-H35)/($C$2+H35),(X35-X34-H35)/(X34+H35))) | AD35: =IF($G35="","",AC35-AB35) | AE35: =IF($G35="","",IF($G35=1,Y35,(1+Y35)*(1+AE34)-1)) | AF35: =IF($G35="","",IF($G35=1,Z35,(1+Z35)*(1+AF34)-1)) | AG35: =IF($G35="","",AF35-AE35) | AH35: =IF($G35="","",IF($G35=1,AB35,(1+AB35)*(1+AH34)-1)) | AI35: =IF($G35="","",IF($G35=1,AC35,(1+AC35)*(1+AI34)-1)) | AJ35: =IF($G35="","",AI35-AH35) | AK35: =IF($G35="","",(1+AE35)^(1/G35)-1) | AL35: =IF($G35="","",(1+AF35)^(1/G35)-1) | AM35: =IF($G35="","",AL35-AK35) | AN35: =IF($G35="","",(1+AH35)^(1/G35)-1) | AO35: =IF($G35="","",(1+AI35)^(1/G35)-1) | AP35: =IF($G35="","",AO35-AN35)
H36: =IF(G36="","",SUMIFS(Add_Contributions[[#All],[Amount ($)]],Add_Contributions[[#All],[Year]],G36)) | I36: =IF($G36="","",IF($G36=1,(($C$2+$H36)*I$3)*(1+(I$4-I$5)),((I35+($H36*I$3))*(1+(I$4-I$5))))) | J36: =IF($G36="","",IF($G36=1,(($C$2+$H36)*J$3)*(1+(J$4-J$5)),((J35+($H36*J$3))*(1+(J$4-J$5))))) | K36: =IF($G36="","",IF($G36=1,(($C$2+$H36)*K$3)*(1+(K$4-K$5)),((K35+($H36*K$3))*(1+(K$4-K$5))))) | L36: =IF($G36="","",IF($G36=1,(($C$2+$H36)*L$3)*(1+(L$4-L$5)),((L35+($H36*L$3))*(1+(L$4-L$5))))) | M36: =IF($G36="","",IF($G36=1,(($C$2+$H36)*M$3)*(1+(M$4-M$5)),((M35+($H36*M$3))*(1+(M$4-M$5))))) | N36: =IF($G36="","",IF($G36=1,(($C$2+$H36)*N$3)*(1+(N$4-N$5)),((N35+($H36*N$3))*(1+(N$4-N$5))))) | O36: =IF($G36="","",IF($G36=1,(($C$2+$H36)*O$3)*(1+(O$4-O$5)),((O35+($H36*O$3))*(1+(O$4-O$5))))) | P36: =IF($G36="","",IF($G36=1,(($C$2+$H36)*P$3)*(1+(P$4-P$5)),((P35+($H36*P$3))*(1+(P$4-P$5))))) | ... T36: =IF($G36="","",IF($G36=1,(($C$2+$H36)*T$3)*(1+(T$4-T$5)),((T35+($H36*T$3))*(1+(T$4-T$5))))) | U36: =IF(G36="","",SUM(I36,K36,M36,O36,Q36,S36)) | V36: =IF(H36="","",SUM(J36,L36,N36,P36,R36,T36)) | W36: =IF($G36="","",IF($G36=1,(($C$2+$H36)*W$3)*(1+(W$4-W$5)),((W35+($H36*W$3))*(1+(W$4-W$5))))) | X36: =IF($G36="","",IF($G36=1,(($C$2+$H36)*X$3)*(1+(X$4-X$5)),((X35+($H36*X$3))*(1+(X$4-X$5))))) | Y36: =IF($G36="","",IF($G36=1,(U36-$C$2-H36)/($C$2+H36),(U36-U35-H36)/(U35+H36))) | Z36: =IF($G36="","",IF($G36=1,(V36-$C$2-H36)/($C$2+H36),(V36-V35-H36)/(V35+H36))) | AA36: =IF($G36="","",Z36-Y36) | AB36: =IF($G36="","",IF($G36=1,(W36-$C$2-H36)/($C$2+H36),(W36-W35-H36)/(W35+H36))) | AC36: =IF($G36="","",IF($G36=1,(X36-$C$2-H36)/($C$2+H36),(X36-X35-H36)/(X35+H36))) | AD36: =IF($G36="","",AC36-AB36) | AE36: =IF($G36="","",IF($G36=1,Y36,(1+Y36)*(1+AE35)-1)) | AF36: =IF($G36="","",IF($G36=1,Z36,(1+Z36)*(1+AF35)-1)) | AG36: =IF($G36="","",AF36-AE36) | AH36: =IF($G36="","",IF($G36=1,AB36,(1+AB36)*(1+AH35)-1)) | AI36: =IF($G36="","",IF($G36=1,AC36,(1+AC36)*(1+AI35)-1)) | AJ36: =IF($G36="","",AI36-AH36) | AK36: =IF($G36="","",(1+AE36)^(1/G36)-1) | AL36: =IF($G36="","",(1+AF36)^(1/G36)-1) | AM36: =IF($G36="","",AL36-AK36) | AN36: =IF($G36="","",(1+AH36)^(1/G36)-1) | AO36: =IF($G36="","",(1+AI36)^(1/G36)-1) | AP36: =IF($G36="","",AO36-AN36)
H37: =IF(G37="","",SUMIFS(Add_Contributions[[#All],[Amount ($)]],Add_Contributions[[#All],[Year]],G37)) | I37: =IF($G37="","",IF($G37=1,(($C$2+$H37)*I$3)*(1+(I$4-I$5)),((I36+($H37*I$3))*(1+(I$4-I$5))))) | J37: =IF($G37="","",IF($G37=1,(($C$2+$H37)*J$3)*(1+(J$4-J$5)),((J36+($H37*J$3))*(1+(J$4-J$5))))) | K37: =IF($G37="","",IF($G37=1,(($C$2+$H37)*K$3)*(1+(K$4-K$5)),((K36+($H37*K$3))*(1+(K$4-K$5))))) | L37: =IF($G37="","",IF($G37=1,(($C$2+$H37)*L$3)*(1+(L$4-L$5)),((L36+($H37*L$3))*(1+(L$4-L$5))))) | M37: =IF($G37="","",IF($G37=1,(($C$2+$H37)*M$3)*(1+(M$4-M$5)),((M36+($H37*M$3))*(1+(M$4-M$5))))) | N37: =IF($G37="","",IF($G37=1,(($C$2+$H37)*N$3)*(1+(N$4-N$5)),((N36+($H37*N$3))*(1+(N$4-N$5))))) | O37: =IF($G37="","",IF($G37=1,(($C$2+$H37)*O$3)*(1+(O$4-O$5)),((O36+($H37*O$3))*(1+(O$4-O$5))))) | P37: =IF($G37="","",IF($G37=1,(($C$2+$H37)*P$3)*(1+(P$4-P$5)),((P36+($H37*P$3))*(1+(P$4-P$5))))) | ... T37: =IF($G37="","",IF($G37=1,(($C$2+$H37)*T$3)*(1+(T$4-T$5)),((T36+($H37*T$3))*(1+(T$4-T$5))))) | U37: =IF(G37="","",SUM(I37,K37,M37,O37,Q37,S37)) | V37: =IF(H37="","",SUM(J37,L37,N37,P37,R37,T37)) | W37: =IF($G37="","",IF($G37=1,(($C$2+$H37)*W$3)*(1+(W$4-W$5)),((W36+($H37*W$3))*(1+(W$4-W$5))))) | X37: =IF($G37="","",IF($G37=1,(($C$2+$H37)*X$3)*(1+(X$4-X$5)),((X36+($H37*X$3))*(1+(X$4-X$5))))) | Y37: =IF($G37="","",IF($G37=1,(U37-$C$2-H37)/($C$2+H37),(U37-U36-H37)/(U36+H37))) | Z37: =IF($G37="","",IF($G37=1,(V37-$C$2-H37)/($C$2+H37),(V37-V36-H37)/(V36+H37))) | AA37: =IF($G37="","",Z37-Y37) | AB37: =IF($G37="","",IF($G37=1,(W37-$C$2-H37)/($C$2+H37),(W37-W36-H37)/(W36+H37))) | AC37: =IF($G37="","",IF($G37=1,(X37-$C$2-H37)/($C$2+H37),(X37-X36-H37)/(X36+H37))) | AD37: =IF($G37="","",AC37-AB37) | AE37: =IF($G37="","",IF($G37=1,Y37,(1+Y37)*(1+AE36)-1)) | AF37: =IF($G37="","",IF($G37=1,Z37,(1+Z37)*(1+AF36)-1)) | AG37: =IF($G37="","",AF37-AE37) | AH37: =IF($G37="","",IF($G37=1,AB37,(1+AB37)*(1+AH36)-1)) | AI37: =IF($G37="","",IF($G37=1,AC37,(1+AC37)*(1+AI36)-1)) | AJ37: =IF($G37="","",AI37-AH37) | AK37: =IF($G37="","",(1+AE37)^(1/G37)-1) | AL37: =IF($G37="","",(1+AF37)^(1/G37)-1) | AM37: =IF($G37="","",AL37-AK37) | AN37: =IF($G37="","",(1+AH37)^(1/G37)-1) | AO37: =IF($G37="","",(1+AI37)^(1/G37)-1) | AP37: =IF($G37="","",AO37-AN37)
H38: =IF(G38="","",SUMIFS(Add_Contributions[[#All],[Amount ($)]],Add_Contributions[[#All],[Year]],G38)) | I38: =IF($G38="","",IF($G38=1,(($C$2+$H38)*I$3)*(1+(I$4-I$5)),((I37+($H38*I$3))*(1+(I$4-I$5))))) | J38: =IF($G38="","",IF($G38=1,(($C$2+$H38)*J$3)*(1+(J$4-J$5)),((J37+($H38*J$3))*(1+(J$4-J$5))))) | K38: =IF($G38="","",IF($G38=1,(($C$2+$H38)*K$3)*(1+(K$4-K$5)),((K37+($H38*K$3))*(1+(K$4-K$5))))) | L38: =IF($G38="","",IF($G38=1,(($C$2+$H38)*L$3)*(1+(L$4-L$5)),((L37+($H38*L$3))*(1+(L$4-L$5))))) | M38: =IF($G38="","",IF($G38=1,(($C$2+$H38)*M$3)*(1+(M$4-M$5)),((M37+($H38*M$3))*(1+(M$4-M$5))))) | N38: =IF($G38="","",IF($G38=1,(($C$2+$H38)*N$3)*(1+(N$4-N$5)),((N37+($H38*N$3))*(1+(N$4-N$5))))) | O38: =IF($G38="","",IF($G38=1,(($C$2+$H38)*O$3)*(1+(O$4-O$5)),((O37+($H38*O$3))*(1+(O$4-O$5))))) | P38: =IF($G38="","",IF($G38=1,(($C$2+$H38)*P$3)*(1+(P$4-P$5)),((P37+($H38*P$3))*(1+(P$4-P$5))))) | ... T38: =IF($G38="","",IF($G38=1,(($C$2+$H38)*T$3)*(1+(T$4-T$5)),((T37+($H38*T$3))*(1+(T$4-T$5))))) | U38: =IF(G38="","",SUM(I38,K38,M38,O38,Q38,S38)) | V38: =IF(H38="","",SUM(J38,L38,N38,P38,R38,T38)) | W38: =IF($G38="","",IF($G38=1,(($C$2+$H38)*W$3)*(1+(W$4-W$5)),((W37+($H38*W$3))*(1+(W$4-W$5))))) | X38: =IF($G38="","",IF($G38=1,(($C$2+$H38)*X$3)*(1+(X$4-X$5)),((X37+($H38*X$3))*(1+(X$4-X$5))))) | Y38: =IF($G38="","",IF($G38=1,(U38-$C$2-H38)/($C$2+H38),(U38-U37-H38)/(U37+H38))) | Z38: =IF($G38="","",IF($G38=1,(V38-$C$2-H38)/($C$2+H38),(V38-V37-H38)/(V37+H38))) | AA38: =IF($G38="","",Z38-Y38) | AB38: =IF($G38="","",IF($G38=1,(W38-$C$2-H38)/($C$2+H38),(W38-W37-H38)/(W37+H38))) | AC38: =IF($G38="","",IF($G38=1,(X38-$C$2-H38)/($C$2+H38),(X38-X37-H38)/(X37+H38))) | AD38: =IF($G38="","",AC38-AB38) | AE38: =IF($G38="","",IF($G38=1,Y38,(1+Y38)*(1+AE37)-1)) | AF38: =IF($G38="","",IF($G38=1,Z38,(1+Z38)*(1+AF37)-1)) | AG38: =IF($G38="","",AF38-AE38) | AH38: =IF($G38="","",IF($G38=1,AB38,(1+AB38)*(1+AH37)-1)) | AI38: =IF($G38="","",IF($G38=1,AC38,(1+AC38)*(1+AI37)-1)) | AJ38: =IF($G38="","",AI38-AH38) | AK38: =IF($G38="","",(1+AE38)^(1/G38)-1) | AL38: =IF($G38="","",(1+AF38)^(1/G38)-1) | AM38: =IF($G38="","",AL38-AK38) | AN38: =IF($G38="","",(1+AH38)^(1/G38)-1) | AO38: =IF($G38="","",(1+AI38)^(1/G38)-1) | AP38: =IF($G38="","",AO38-AN38)
H39: =IF(G39="","",SUMIFS(Add_Contributions[[#All],[Amount ($)]],Add_Contributions[[#All],[Year]],G39)) | I39: =IF($G39="","",IF($G39=1,(($C$2+$H39)*I$3)*(1+(I$4-I$5)),((I38+($H39*I$3))*(1+(I$4-I$5))))) | J39: =IF($G39="","",IF($G39=1,(($C$2+$H39)*J$3)*(1+(J$4-J$5)),((J38+($H39*J$3))*(1+(J$4-J$5))))) | K39: =IF($G39="","",IF($G39=1,(($C$2+$H39)*K$3)*(1+(K$4-K$5)),((K38+($H39*K$3))*(1+(K$4-K$5))))) | L39: =IF($G39="","",IF($G39=1,(($C$2+$H39)*L$3)*(1+(L$4-L$5)),((L38+($H39*L$3))*(1+(L$4-L$5))))) | M39: =IF($G39="","",IF($G39=1,(($C$2+$H39)*M$3)*(1+(M$4-M$5)),((M38+($H39*M$3))*(1+(M$4-M$5))))) | N39: =IF($G39="","",IF($G39=1,(($C$2+$H39)*N$3)*(1+(N$4-N$5)),((N38+($H39*N$3))*(1+(N$4-N$5))))) | O39: =IF($G39="","",IF($G39=1,(($C$2+$H39)*O$3)*(1+(O$4-O$5)),((O38+($H39*O$3))*(1+(O$4-O$5))))) | P39: =IF($G39="","",IF($G39=1,(($C$2+$H39)*P$3)*(1+(P$4-P$5)),((P38+($H39*P$3))*(1+(P$4-P$5))))) | ... T39: =IF($G39="","",IF($G39=1,(($C$2+$H39)*T$3)*(1+(T$4-T$5)),((T38+($H39*T$3))*(1+(T$4-T$5))))) | U39: =IF(G39="","",SUM(I39,K39,M39,O39,Q39,S39)) | V39: =IF(H39="","",SUM(J39,L39,N39,P39,R39,T39)) | W39: =IF($G39="","",IF($G39=1,(($C$2+$H39)*W$3)*(1+(W$4-W$5)),((W38+($H39*W$3))*(1+(W$4-W$5))))) | X39: =IF($G39="","",IF($G39=1,(($C$2+$H39)*X$3)*(1+(X$4-X$5)),((X38+($H39*X$3))*(1+(X$4-X$5))))) | Y39: =IF($G39="","",IF($G39=1,(U39-$C$2-H39)/($C$2+H39),(U39-U38-H39)/(U38+H39))) | Z39: =IF($G39="","",IF($G39=1,(V39-$C$2-H39)/($C$2+H39),(V39-V38-H39)/(V38+H39))) | AA39: =IF($G39="","",Z39-Y39) | AB39: =IF($G39="","",IF($G39=1,(W39-$C$2-H39)/($C$2+H39),(W39-W38-H39)/(W38+H39))) | AC39: =IF($G39="","",IF($G39=1,(X39-$C$2-H39)/($C$2+H39),(X39-X38-H39)/(X38+H39))) | AD39: =IF($G39="","",AC39-AB39) | AE39: =IF($G39="","",IF($G39=1,Y39,(1+Y39)*(1+AE38)-1)) | AF39: =IF($G39="","",IF($G39=1,Z39,(1+Z39)*(1+AF38)-1)) | AG39: =IF($G39="","",AF39-AE39) | AH39: =IF($G39="","",IF($G39=1,AB39,(1+AB39)*(1+AH38)-1)) | AI39: =IF($G39="","",IF($G39=1,AC39,(1+AC39)*(1+AI38)-1)) | AJ39: =IF($G39="","",AI39-AH39) | AK39: =IF($G39="","",(1+AE39)^(1/G39)-1) | AL39: =IF($G39="","",(1+AF39)^(1/G39)-1) | AM39: =IF($G39="","",AL39-AK39) | AN39: =IF($G39="","",(1+AH39)^(1/G39)-1) | AO39: =IF($G39="","",(1+AI39)^(1/G39)-1) | AP39: =IF($G39="","",AO39-AN39)
H40: =IF(G40="","",SUMIFS(Add_Contributions[[#All],[Amount ($)]],Add_Contributions[[#All],[Year]],G40)) | I40: =IF($G40="","",IF($G40=1,(($C$2+$H40)*I$3)*(1+(I$4-I$5)),((I39+($H40*I$3))*(1+(I$4-I$5))))) | J40: =IF($G40="","",IF($G40=1,(($C$2+$H40)*J$3)*(1+(J$4-J$5)),((J39+($H40*J$3))*(1+(J$4-J$5))))) | K40: =IF($G40="","",IF($G40=1,(($C$2+$H40)*K$3)*(1+(K$4-K$5)),((K39+($H40*K$3))*(1+(K$4-K$5))))) | L40: =IF($G40="","",IF($G40=1,(($C$2+$H40)*L$3)*(1+(L$4-L$5)),((L39+($H40*L$3))*(1+(L$4-L$5))))) | M40: =IF($G40="","",IF($G40=1,(($C$2+$H40)*M$3)*(1+(M$4-M$5)),((M39+($H40*M$3))*(1+(M$4-M$5))))) | N40: =IF($G40="","",IF($G40=1,(($C$2+$H40)*N$3)*(1+(N$4-N$5)),((N39+($H40*N$3))*(1+(N$4-N$5))))) | O40: =IF($G40="","",IF($G40=1,(($C$2+$H40)*O$3)*(1+(O$4-O$5)),((O39+($H40*O$3))*(1+(O$4-O$5))))) | P40: =IF($G40="","",IF($G40=1,(($C$2+$H40)*P$3)*(1+(P$4-P$5)),((P39+($H40*P$3))*(1+(P$4-P$5))))) | ... T40: =IF($G40="","",IF($G40=1,(($C$2+$H40)*T$3)*(1+(T$4-T$5)),((T39+($H40*T$3))*(1+(T$4-T$5))))) | U40: =IF(G40="","",SUM(I40,K40,M40,O40,Q40,S40)) | V40: =IF(H40="","",SUM(J40,L40,N40,P40,R40,T40)) | W40: =IF($G40="","",IF($G40=1,(($C$2+$H40)*W$3)*(1+(W$4-W$5)),((W39+($H40*W$3))*(1+(W$4-W$5))))) | X40: =IF($G40="","",IF($G40=1,(($C$2+$H40)*X$3)*(1+(X$4-X$5)),((X39+($H40*X$3))*(1+(X$4-X$5))))) | Y40: =IF($G40="","",IF($G40=1,(U40-$C$2-H40)/($C$2+H40),(U40-U39-H40)/(U39+H40))) | Z40: =IF($G40="","",IF($G40=1,(V40-$C$2-H40)/($C$2+H40),(V40-V39-H40)/(V39+H40))) | AA40: =IF($G40="","",Z40-Y40) | AB40: =IF($G40="","",IF($G40=1,(W40-$C$2-H40)/($C$2+H40),(W40-W39-H40)/(W39+H40))) | AC40: =IF($G40="","",IF($G40=1,(X40-$C$2-H40)/($C$2+H40),(X40-X39-H40)/(X39+H40))) | AD40: =IF($G40="","",AC40-AB40) | AE40: =IF($G40="","",IF($G40=1,Y40,(1+Y40)*(1+AE39)-1)) | AF40: =IF($G40="","",IF($G40=1,Z40,(1+Z40)*(1+AF39)-1)) | AG40: =IF($G40="","",AF40-AE40) | AH40: =IF($G40="","",IF($G40=1,AB40,(1+AB40)*(1+AH39)-1)) | AI40: =IF($G40="","",IF($G40=1,AC40,(1+AC40)*(1+AI39)-1)) | AJ40: =IF($G40="","",AI40-AH40) | AK40: =IF($G40="","",(1+AE40)^(1/G40)-1) | AL40: =IF($G40="","",(1+AF40)^(1/G40)-1) | AM40: =IF($G40="","",AL40-AK40) | AN40: =IF($G40="","",(1+AH40)^(1/G40)-1) | AO40: =IF($G40="","",(1+AI40)^(1/G40)-1) | AP40: =IF($G40="","",AO40-AN40)
