Workbook
Name X_Axis: OFFSET(#REF!,0,0,'Return Simulator'!$D$48,1)

Sheet Diagram

Sheet Log-in
C4: "Platform Name"
J5: * Standalone log-in via our platform or integrated into RIA existing wealth platform
C7: Username
C10: Password
C15: Log-In

Sheet Suitability
C4: Client Profile | G4: * Final version would include a larger array of intake question/data (Data input here, would drive the similator snapshot of how Private Placement can impact future wealth)
C5: Client Name | D5: John Doe | G5: * AI driven results to show if client is/is not suitable with reasoning and other commentary
C6: Accredited Investor | D6: TRUE | G6: *Final version could be integrated to automatically pull client information from RIA Exisiting wealth platform
C7: Qualified Purchaser | D7: TRUE
C8: Interest in Private Placement | D8: TRUE | H8: * Sections (working)
I9: 1. Client Profile
C10: Investment Settings | I10: 2. Financial Snapshot
C11: Portfolio Value | D11: 10000000 | I11: 3. Legal & Compliance Qualification
C12: Time Horizon | D12: 20 | I12: 4. Exsiting Life Insurance/Annuities
I13: 5. Investment Allocation Preferences & Objectives
C14: Portfolio Allocation
C15: Stocks | D15: 0.48
C16: Bonds | D16: 0.32
C17: Alternative | D17: 0.2
C19: Return Assumptions
C20: Stocks | D20: 0.08
C21: Bonds | D21: 0.05
C22: Alternative | D22: 0.08
C25: =IF(D8=FALSE,"Not Suitable - Client Not Interested",IF(AND(D7=FALSE,D6=FALSE),"Not Suitable - Client Not An Accredited Investor/Qualified Purchaser","Client may be suitable")) -> Client may be suitable
C28: =IF(C25="Client may be suitable","Explore Impact of Private Placement","") -> Explore Impact of Private Placement

Sheet Return Simulator
B2: Back
W3: * Maybe include more unique comparison options (potentially driven by data/information from intake)
C4: Current Client Portfolio | W4: * e.g. - Comapare impact of housing solely alternatives into PPLI wrapper
C5: Projected Value | D5: ='1'!C22 -> 27153622
C6: Net | D6: ='1'!C29 -> 0.05121461
C10: 10% of Current Portfolio inside PPLI | F10: Compared to Base Case
C11: =C5 -> Projected Value | D11: ='2'!C22 -> 28098547 | F11: =_xlfn.CONCAT("+ ",TEXT(D11-$D$5,"$#,##0.00")) -> + $944,925.05
C12: =C6 -> Net | D12: ='2'!C29 -> 0.053014116 | F12: =_xlfn.CONCAT("+ ",TEXT(D12-$D$6,"0.00%")) -> + 0.18%
C14: 20% of Current Portfolio inside PPLI | F14: Compared to Base Case
C15: =C5 -> Projected Value | D15: ='3'!C22 -> 29043472 | F15: =_xlfn.CONCAT("+ ",TEXT(D15-$D$5,"$#,##0.00")) -> + $1,889,850.10
C16: =C12 -> Net | D16: ='3'!C29 -> 0.054757025 | F16: =_xlfn.CONCAT("+ ",TEXT(D16-$D$6,"0.00%")) -> + 0.35%
C18: 30% of Current Portfolio inside PPLI | F18: Compared to Base Case
C19: =C5 -> Projected Value | D19: ='4'!C22 -> 29988397 | F19: =_xlfn.CONCAT("+ ",TEXT(D19-$D$5,"$#,##0.00")) -> + $2,834,775.14
C20: =C16 -> Net | D20: ='4'!C29 -> 0.056446875 | F20: =_xlfn.CONCAT("+ ",TEXT(D20-$D$6,"0.00%")) -> + 0.52%
C22: 40% of Current Portfolio inside PPLI | F22: Compared to Base Case
C23: =C5 -> Projected Value | D23: ='5'!C22 -> 30933322 | F23: =_xlfn.CONCAT("+ ",TEXT(D23-$D$5,"$#,##0.00")) -> + $3,779,700.19
C24: =C20 -> Net | D24: ='5'!C29 -> 0.058086877 | F24: =_xlfn.CONCAT("+ ",TEXT(D24-$D$6,"0.00%")) -> + 0.69% | L24: Explore Carriers/Products
L28: Explore Education Portal
L32: Explore Other Service Providers
C46: Investment Settings | H46: Buy & Hold | W46: Rebalanced
C47: Starting Capital ($) | D47: =Suitability!D11 -> 10000000
C48: Investment Horizon (Years) | D48: =Suitability!D12 -> 20 | W48: Custom | Z48: Traditional (Taxable) | AC48: Traditional (PPLI) | AF48: Alternatives Enhanced (Taxable) | AI48: Alternatives Enhanced (PPLI)
W49: Projected Value | X49: ='1'!D22 -> 26313895 | Z49: =W49 -> Projected Value | AA49: ='2'!D22 -> 27119396 | AC49: =W49 -> Projected Value | AD49: ='3'!D22 -> 27948285 | AF49: =W49 -> Projected Value | AG49: ='4'!D22 -> 28801206 | AI49: =W49 -> Projected Value | AJ49: ='5'!D22 -> 29678817
C50: Portfolio Allocation (%) | F50: Allocation Check
C51: Stocks | D51: =Suitability!D15 -> 0.48 | F51: =IF(SUM(D51:D53)=1,"Good","Must Equal 100%") -> Good | H51: Total Return | K51: =H51 -> Total Return | N51: =K51 -> Total Return | Q51: =N51 -> Total Return | T51: =Q51 -> Total Return | W51: Total Return | Z51: =W51 -> Total Return | AC51: =Z51 -> Total Return | AF51: =AC51 -> Total Return | AI51: =AF51 -> Total Return
C52: Bonds | D52: =Suitability!D16 -> 0.32 | H52: Gross | I52: ='1'!C24 -> 3.0185061 | K52: =H52 -> Gross | L52: ='2'!C24 -> 3.0185061 | N52: =K52 -> Gross | O52: ='3'!C24 -> 3.0185061 | Q52: =N52 -> Gross | R52: ='4'!C24 -> 3.0185061 | T52: =Q52 -> Gross | U52: ='5'!C24 -> 3.0185061 | W52: Gross | X52: ='1'!D24 -> 2.8987197 | Z52: =W52 -> Gross | AA52: ='2'!D24 -> 2.8987197 | AC52: =Z52 -> Gross | AD52: ='3'!D24 -> 2.8987197 | AF52: =AC52 -> Gross | AG52: ='4'!D24 -> 2.8987197 | AI52: =AF52 -> Gross | AJ52: ='5'!D24 -> 2.8987197
C53: Alternatives | D53: =Suitability!D17 -> 0.2 | H53: Net | I53: ='1'!C25 -> 1.7153622 | K53: =H53 -> Net | L53: ='2'!C25 -> 1.8098547 | N53: =K53 -> Net | O53: ='3'!C25 -> 1.9043472 | Q53: =N53 -> Net | R53: ='4'!C25 -> 1.9988397 | T53: =Q53 -> Net | U53: ='5'!C25 -> 2.0933322 | W53: Net | X53: ='1'!D25 -> 1.6313895 | Z53: =W53 -> Net | AA53: ='2'!D25 -> 1.7119396 | AC53: =Z53 -> Net | AD53: ='3'!D25 -> 1.7948285 | AF53: =AC53 -> Net | AG53: ='4'!D25 -> 1.8801206 | AI53: =AF53 -> Net | AJ53: ='5'!D25 -> 1.9678817
H54: Drag | I54: ='1'!C26 -> -1.3031439 | K54: =H54 -> Drag | L54: ='2'!C26 -> -1.2086514 | N54: =K54 -> Drag | O54: ='3'!C26 -> -1.1141589 | Q54: =N54 -> Drag | R54: ='4'!C26 -> -1.0196664 | T54: =Q54 -> Drag | U54: ='5'!C26 -> -0.92517392 | W54: Drag | X54: ='1'!D26 -> -1.2673301 | Z54: =W54 -> Drag | AA54: ='2'!D26 -> -1.1867801 | AC54: =Z54 -> Drag | AD54: ='3'!D26 -> -1.1038911 | AF54: =AC54 -> Drag | AG54: ='4'!D26 -> -1.0185991 | AI54: =AF54 -> Drag | AJ54: ='5'!D26 -> -0.93083797
C55: Return Assumptions (%)
C56: Stocks | D56: =Suitability!D20 -> 0.08 | H56: Annualized Return | K56: =H56 -> Annualized Return | N56: =K56 -> Annualized Return | Q56: =N56 -> Annualized Return | T56: =Q56 -> Annualized Return | W56: Annualized Return | Z56: =W56 -> Annualized Return | AC56: =Z56 -> Annualized Return | AF56: =AC56 -> Annualized Return | AI56: =AF56 -> Annualized Return
C57: Bonds | D57: =Suitability!D21 -> 0.05 | H57: Gross | I57: ='1'!C28 -> 0.072020849 | K57: =H57 -> Gross | L57: ='2'!C28 -> 0.072020849 | N57: =K57 -> Gross | O57: ='3'!C28 -> 0.072020849 | Q57: =N57 -> Gross | R57: ='4'!C28 -> 0.072020849 | T57: =Q57 -> Gross | U57: ='5'!C28 -> 0.072020849 | W57: Gross | X57: ='1'!D28 -> 0.0704 | Z57: =W57 -> Gross | AA57: ='2'!D28 -> 0.0704 | AC57: =Z57 -> Gross | AD57: ='3'!D28 -> 0.0704 | AF57: =AC57 -> Gross | AG57: ='4'!D28 -> 0.0704 | AI57: =AF57 -> Gross | AJ57: ='5'!D28 -> 0.0704
C58: Alternatives | D58: =Suitability!D22 -> 0.08 | W58: Net | X58: ='1'!D29 -> 0.0495648 | Z58: =W58 -> Net | AA58: ='2'!D29 -> 0.05114832 | AC58: =Z58 -> Net | AD58: ='3'!D29 -> 0.05273184 | AF58: =AC58 -> Net | AG58: ='4'!D29 -> 0.05431536 | AI58: =AF58 -> Net | AJ58: ='5'!D29 -> 0.05589888
H59: Drag | I59: ='1'!C30 -> -0.020806239 | K59: =H59 -> Drag | L59: ='2'!C30 -> -0.019006733 | N59: =K59 -> Drag | O59: ='3'!C30 -> -0.017263824 | Q59: =N59 -> Drag | R59: ='4'!C30 -> -0.015573974 | T59: =Q59 -> Drag | U59: ='5'!C30 -> -0.013933972 | W59: Drag | X59: ='1'!D30 -> -0.0208352 | Z59: =W59 -> Drag | AA59: ='2'!D30 -> -0.01925168 | AC59: =Z59 -> Drag | AD59: ='3'!D30 -> -0.01766816 | AF59: =AC59 -> Drag | AG59: ='4'!D30 -> -0.01608464 | AI59: =AF59 -> Drag | AJ59: ='5'!D30 -> -0.01450112
C60: Tax Assumptions (%)
C61: Ordinary Income | D61: 0.37
C62: Capital Gains | D62: 0.2
C63: NIIT | D63: 0.038
C65: PPLI Allocation (%)
C66: Stocks | D66: 0
C67: Bonds | D67: 0
C68: Alternatives | D68: 0
C70: PPLI Costs (%)
C71: Policy Costs | D71: 0.005
C73: Additional Contributions
C74: Year | D74: Amount ($)
N90: Rank | O90: Strategy | Q90: Annualized Return (Net) | S90: Projected Value | AC90: Rank | AD90: Strategy | AF90: Annualized Return (Net) | AH90: Projected Value
N93: =Rank!M2 -> 1st | O93: =Rank!I2 -> 40% of Current Portfolio inside PPLI | Q93: =Rank!K2 -> 0.058086877 | R93: =_xlfn.CONCAT("+ ",TEXT(Q93-$Q$105,"0.00%")) -> + 0.69% | S93: =Rank!J2 -> 30933322 | U93: =_xlfn.CONCAT("+ ",TEXT(S93-$S$105,"$#,##0.00")) -> + $3,779,700.19 | AC93: =Rank!M10 -> 1st | AD93: =Rank!I10 -> 40% of Current Portfolio inside PPLI | AF93: =Rank!K10 -> 0.05589888 | AG93: =_xlfn.CONCAT("+ ",TEXT(AF93-$AF$105,"0.00%")) -> + 0.63% | AH93: =Rank!J10 -> 29678817 | AJ93: =_xlfn.CONCAT("+ ",TEXT(AH93-$AH$105,"$#,##0.00")) -> + $3,364,921.70
N96: =Rank!M3 -> 2nd | O96: =Rank!I3 -> 30% of Current Portfolio inside PPLI | Q96: =Rank!K3 -> 0.056446875 | R96: =_xlfn.CONCAT("+ ",TEXT(Q96-$Q$105,"0.00%")) -> + 0.52% | S96: =Rank!J3 -> 29988397 | U96: =_xlfn.CONCAT("+ ",TEXT(S96-$S$105,"$#,##0.00")) -> + $2,834,775.14 | AC96: =Rank!M11 -> 2nd | AD96: =Rank!I11 -> 30% of Current Portfolio inside PPLI | AF96: =Rank!K11 -> 0.05431536 | AG96: =_xlfn.CONCAT("+ ",TEXT(AF96-$AF$105,"0.00%")) -> + 0.48% | AH96: =Rank!J11 -> 28801206 | AJ96: =_xlfn.CONCAT("+ ",TEXT(AH96-$AH$105,"$#,##0.00")) -> + $2,487,310.80
N99: =Rank!M4 -> 3rd | O99: =Rank!I4 -> 20% of Current Portfolio inside PPLI | Q99: =Rank!K4 -> 0.054757025 | R99: =_xlfn.CONCAT("+ ",TEXT(Q99-$Q$105,"0.00%")) -> + 0.35% | S99: =Rank!J4 -> 29043472 | U99: =_xlfn.CONCAT("+ ",TEXT(S99-$S$105,"$#,##0.00")) -> + $1,889,850.10 | AC99: =Rank!M12 -> 3rd | AD99: =Rank!I12 -> 20% of Current Portfolio inside PPLI | AF99: =Rank!K12 -> 0.05273184 | AG99: =_xlfn.CONCAT("+ ",TEXT(AF99-$AF$105,"0.00%")) -> + 0.32% | AH99: =Rank!J12 -> 27948285 | AJ99: =_xlfn.CONCAT("+ ",TEXT(AH99-$AH$105,"$#,##0.00")) -> + $1,634,390.13
N102: =Rank!M5 -> 4th | O102: =Rank!I5 -> 10% of Current Portfolio inside PPLI | Q102: =Rank!K5 -> 0.053014116 | R102: =_xlfn.CONCAT("+ ",TEXT(Q102-$Q$105,"0.00%")) -> + 0.18% | S102: =Rank!J5 -> 28098547 | U102: =_xlfn.CONCAT("+ ",TEXT(S102-$S$105,"$#,##0.00")) -> + $944,925.05 | AC102: =Rank!M13 -> 4th | AD102: =Rank!I13 -> 10% of Current Portfolio inside PPLI | AF102: =Rank!K13 -> 0.05114832 | AG102: =_xlfn.CONCAT("+ ",TEXT(AF102-$AF$105,"0.00%")) -> + 0.16% | AH102: =Rank!J13 -> 27119396 | AJ102: =_xlfn.CONCAT("+ ",TEXT(AH102-$AH$105,"$#,##0.00")) -> + $805,500.67
N105: =Rank!M6 -> 5th | O105: =Rank!I6 -> Current Client Portfolio | Q105: =Rank!K6 -> 0.05121461 | R105: =_xlfn.CONCAT("+ ",TEXT(Q105-$Q$105,"0.00%")) -> + 0.00% | S105: =Rank!J6 -> 27153622 | U105: =_xlfn.CONCAT("+ ",TEXT(S105-$S$105,"$#,##0.00")) -> + $0.00 | AC105: =Rank!M14 -> 5th | AD105: =Rank!I14 -> Current Client Portfolio | AF105: =Rank!K14 -> 0.0495648 | AG105: =_xlfn.CONCAT("+ ",TEXT(AF105-$AF$105,"0.00%")) -> + 0.00% | AH105: =Rank!J14 -> 26313895 | AJ105: =_xlfn.CONCAT("+ ",TEXT(AH105-$AH$105,"$#,##0.00")) -> + $0.00

Sheet Carrier Portal
B2: Back
C4: Carrier | D4: Rating | E4: Policy Minimum | F4: Fund Name | G4: Fund Type | H4: Learn More | I4: Select Policy
C5: X | D5: 5 | E5: 1000000 | F5: A | G5: Private Equity | H5: Link | I5: FALSE
C6: X | D6: 5 | E6: 1000000 | F6: B | G6: Private Credit | H6: Link | I6: FALSE
C7: Y | D7: 3.5 | E7: 500000 | F7: C | G7: Real Estate | H7: Link | I7: FALSE
C8: Z | D8: 4.5 | E8: 2000000 | F8: D | G8: Fixed Income | H8: Link | I8: FALSE
C9: Z | D9: 4.5 | E9: 2000000 | F9: E | G9: Private Credit | H9: Link | I9: FALSE
C10: Z | D10: 4.5 | E10: 2000000 | F10: F | G10: S&P 500 Index | H10: Link | I10: FALSE
E12: Begin Policy Execution

Sheet Education Portal
B2: Back
G3: * Demo is simplified data room - Should be a place where advisors/clients can learn more about PPLI/PPVA and what it is, the steps involved, impact, legal & compliance concerns, etc.
C4: Type | D4: Learn More
C5: White Papers | D5: Link
C6: What is PPLI/PPVA | D6: Link
C7: PPLI/PPVA Compliance | D7: Link
C8: Taxes | D8: Link
C9: Estate/Trust | D9: Link

Sheet Service Providers
B2: Back
G3: * Demo is simplified - Should be a place where advisors/clients can connect to other services providers needed for the PPLI/PPVA process if not already available/provided
C4: Type | D4: Connect
C5: Estate Attornerys | D5: Link
C6: Trust Providers | D6: Link
C7: CPA's | D7: Link
C8: Taxes | D8: Link
C9: Estate/Trust | D9: Link

Sheet Policy Execution
C3: Workflow Steps
C4: 1. Advisor initiates connection with the selected carrier to start the process.
C5: 2. Carrier is notified automatically via the platform.
C6: 3. Platform facilitates secure document exchange and onboarding — including KYC, AML, and application uploads.
C7: 4. Advisor tracks underwriting progress in real time through the integrated platform dashboard.
C8: 5. Platform automatically creates a compliance trail for audit and recordkeeping, while maintaining a secure, encrypted data environment.
C9: 6. Once policy is activated, carrier data is pushed back into the platform through API connections for performance reporting and portfolio integration.
C13: * Steps are simplified for version 1 - Purpose is end-to-end integrated/streamlined process of policy selection/execution. The goal should be to make it as quick and easy as possible for the RIA/Client while offering a compliance ready and secure aduit trail

Sheet Portal-Widget
E3: Current Value | G3: 25000000 | K3: Resrouces | U3: * Standalone portal accessed via out platform or integrated into RIA Exisiting wealth platform
K5: Statements
E7: Metrics Table | K7: Policy Information
K9: Education
K11: Service Providers | W11: Carrier A | X11: =25%*$G$3 -> 6250000
W12: Carrier B | X12: =30%*$G$3 -> 7500000
K13: Contact Advisor/Carrier | W13: Carrier C | X13: =45%*$G$3 -> 11250000
O15: Chat with AI
W17: 1 | X17: 10000000
W18: 5 | X18: =X17*1.4 -> 14000000
W19: 10 | X19: =X18*1.4 -> 19600000
W20: 15 | X20: 25000000

Sheet Chart Feeder >

Sheet WA PIVOT
A1: Buy & Hold | I1: Rebalanced
D3: Current Client Portfolio | F3: 10% of Current Portfolio inside PPLI | H3: 20% of Current Portfolio inside PPLI | J3: 100% of Alternatives inside PPLI | L3: 100% of Bonds inside PPLI
A6: Row Labels | B6: Current Client Portfolio | C6: 10% of Current Portfolio inside PPLI | D6: 20% of Current Portfolio inside PPLI | E6: 30% of Current Portfolio inside PPLI | F6: 40% of Current Portfolio inside PPLI | I6: Row Labels | J6: Current Client Portfolio | K6: 10% of Current Portfolio inside PPLI | L6: 20% of Current Portfolio inside PPLI | M6: 30% of Current Portfolio inside PPLI | N6: 40% of Current Portfolio inside PPLI
A7: 1 | B7: 10495648 | C7: 10511483 | D7: 10527318 | E7: 10543154 | F7: 10558989 | I7: 1 | J7: 10495648 | K7: 10511483 | L7: 10527318 | M7: 10543154 | N7: 10558989
A8: 2 | B8: 11015863 | C8: 11049128 | D8: 11082443 | E8: 11115809 | F8: 11149224 | I8: 2 | J8: 11015863 | K8: 11049128 | L8: 11082443 | M8: 11115809 | N8: 11149224
A9: 3 | B9: 11561862 | C9: 11614272 | D9: 11666841 | E9: 11719568 | F9: 11772454 | I9: 3 | J9: 11561862 | K9: 11614272 | L9: 11666841 | M9: 11719568 | N9: 11772454
A10: 4 | B10: 12134923 | C10: 12208323 | D10: 12282055 | E10: 12356120 | F10: 12430521 | I10: 4 | J10: 12134923 | K10: 12208323 | L10: 12282055 | M10: 12356120 | N10: 12430521
A11: 5 | B11: 12736388 | C11: 12832758 | D11: 12929710 | E11: 13027248 | F11: 13125373 | I11: 5 | J11: 12736388 | K11: 12832758 | L11: 12929710 | M11: 13027248 | N11: 13125373
A12: 6 | B12: 13367665 | C12: 13489132 | D12: 13611518 | E12: 13734827 | F12: 13859066 | I12: 6 | J12: 13367665 | K12: 13489132 | L12: 13611518 | M12: 13734827 | N12: 13859066
A13: 7 | B13: 14030230 | C13: 14179078 | D13: 14329278 | E13: 14480839 | F13: 14633773 | I13: 7 | J13: 14030230 | K13: 14179078 | L13: 14329278 | M13: 14480839 | N13: 14633773
A14: 8 | B14: 14725636 | C14: 14904314 | D14: 15084887 | E14: 15267371 | F14: 15451784 | I14: 8 | J14: 14725636 | K14: 14904314 | L14: 15084887 | M14: 15267371 | N14: 15451784
A15: 9 | B15: 15455509 | C15: 15666645 | D15: 15880341 | E15: 16096624 | F15: 16315522 | I15: 9 | J15: 15455509 | K15: 15666645 | L15: 15880341 | M15: 16096624 | N15: 16315522
A16: 10 | B16: 16221558 | C16: 16467968 | D16: 16717741 | E16: 16970918 | F16: 17227541 | I16: 10 | J16: 16221558 | K16: 16467968 | L16: 16717741 | M16: 16970918 | N16: 17227541
A17: 11 | B17: 17025577 | C17: 17310277 | D17: 17599298 | E17: 17892700 | F17: 18190541 | I17: 11 | J17: 17025577 | K17: 17310277 | L17: 17599298 | M17: 17892700 | N17: 18190541
A18: 12 | B18: 17869446 | C18: 18195668 | D18: 18527341 | E18: 18864548 | F18: 19207372 | I18: 12 | J18: 17869446 | K18: 18195668 | L18: 18527341 | M18: 18864548 | N18: 19207372
... A26: 20 | B26: 26313895 | C26: 27119396 | D26: 27948285 | E26: 28801206 | F26: 29678817 | I26: 20 | J26: 26313895 | K26: 27119396 | L26: 27948285 | M26: 28801206 | N26: 29678817
A27: Grand Total | B27: 3.4545666e+08 | C27: 3.5182044e+08 | D27: 3.5831732e+08 | E27: 3.6495018e+08 | F27: 3.7172195e+08 | I27: Grand Total | J27: 3.4545666e+08 | K27: 3.5182044e+08 | L27: 3.5831732e+08 | M27: 3.6495018e+08 | N27: 3.7172195e+08

Sheet WA
A1: ='Return Simulator'!D48 -> 20 | B1: Buy & Hold | K1: =A1 -> 20 | L1: Rebalanced
A5: Year | B5: Custom_ | C5: Traditional (Taxable)_ | D5: Traditional (PPLI)_ | E5: Alternatives Enhanced (Taxable)_ | F5: Alternatives Enhanced (PPLI)_ | K5: Year | L5: Custom_ | M5: Traditional (Taxable)_ | N5: Traditional (PPLI)_ | O5: Alternatives Enhanced (Taxable)_ | P5: Alternatives Enhanced (PPLI)_
A6: {=_xlfn.SEQUENCE(A1,1,1,1)} -> 1 | B6: =IF(A6="","N/A",'1'!V10) -> 10495648 | C6: =IF(A6="","N/A",'2'!V10) -> 10511483 | D6: =IF(A6="","N/A",'3'!V10) -> 10527318 | E6: =IF(A6="","N/A",'4'!V10) -> 10543154 | F6: =IF(A6="","N/A",'5'!V10) -> 10558989 | K6: {=_xlfn.SEQUENCE(K1,1,1,1)} -> 1 | L6: =IF(K6="","N/A",'1'!X10) -> 10495648 | M6: =IF(K6="","N/A",'2'!X10) -> 10511483 | N6: =IF(K6="","N/A",'3'!X10) -> 10527318 | O6: =IF(K6="","N/A",'4'!X10) -> 10543154 | P6: =IF(K6="","N/A",'5'!X10) -> 10558989
A7: 2 | B7: =IF(A7="","N/A",'1'!V11) -> 11017804 | C7: =IF(A7="","N/A",'2'!V11) -> 11051296 | D7: =IF(A7="","N/A",'3'!V11) -> 11084789 | E7: =IF(A7="","N/A",'4'!V11) -> 11118282 | F7: =IF(A7="","N/A",'5'!V11) -> 11151774 | K7: 2 | L7: =IF(K7="","N/A",'1'!X11) -> 11015863 | M7: =IF(K7="","N/A",'2'!X11) -> 11049128 | N7: =IF(K7="","N/A",'3'!X11) -> 11082443 | O7: =IF(K7="","N/A",'4'!X11) -> 11115809 | P7: =IF(K7="","N/A",'5'!X11) -> 11149224
A8: 3 | B8: =IF(A8="","N/A",'1'!V12) -> 11567955 | C8: =IF(A8="","N/A",'2'!V12) -> 11621095 | D8: =IF(A8="","N/A",'3'!V12) -> 11674234 | E8: =IF(A8="","N/A",'4'!V12) -> 11727374 | F8: =IF(A8="","N/A",'5'!V12) -> 11780513 | K8: 3 | L8: =IF(K8="","N/A",'1'!X12) -> 11561862 | M8: =IF(K8="","N/A",'2'!X12) -> 11614272 | N8: =IF(K8="","N/A",'3'!X12) -> 11666841 | O8: =IF(K8="","N/A",'4'!X12) -> 11719568 | P8: =IF(K8="","N/A",'5'!X12) -> 11772454
A9: 4 | B9: =IF(A9="","N/A",'1'!V13) -> 12147677 | C9: =IF(A9="","N/A",'2'!V13) -> 12222634 | D9: =IF(A9="","N/A",'3'!V13) -> 12297591 | E9: =IF(A9="","N/A",'4'!V13) -> 12372548 | F9: =IF(A9="","N/A",'5'!V13) -> 12447506 | K9: 4 | L9: =IF(K9="","N/A",'1'!X13) -> 12134923 | M9: =IF(K9="","N/A",'2'!X13) -> 12208323 | N9: =IF(K9="","N/A",'3'!X13) -> 12282055 | O9: =IF(K9="","N/A",'4'!X13) -> 12356120 | P9: =IF(K9="","N/A",'5'!X13) -> 12430521
A10: 5 | B10: =IF(A10="","N/A",'1'!V14) -> 12758633 | C10: =IF(A10="","N/A",'2'!V14) -> 12857776 | D10: =IF(A10="","N/A",'3'!V14) -> 12956919 | E10: =IF(A10="","N/A",'4'!V14) -> 13056061 | F10: =IF(A10="","N/A",'5'!V14) -> 13155204 | K10: 5 | L10: =IF(K10="","N/A",'1'!X14) -> 12736388 | M10: =IF(K10="","N/A",'2'!X14) -> 12832758 | N10: =IF(K10="","N/A",'3'!X14) -> 12929710 | O10: =IF(K10="","N/A",'4'!X14) -> 13027248 | P10: =IF(K10="","N/A",'5'!X14) -> 13125373
A11: 6 | B11: =IF(A11="","N/A",'1'!V15) -> 13402585 | C11: =IF(A11="","N/A",'2'!V15) -> 13528495 | D11: =IF(A11="","N/A",'3'!V15) -> 13654405 | E11: =IF(A11="","N/A",'4'!V15) -> 13780315 | F11: =IF(A11="","N/A",'5'!V15) -> 13906224 | K11: 6 | L11: =IF(K11="","N/A",'1'!X15) -> 13367665 | M11: =IF(K11="","N/A",'2'!X15) -> 13489132 | N11: =IF(K11="","N/A",'3'!X15) -> 13611518 | O11: =IF(K11="","N/A",'4'!X15) -> 13734827 | P11: =IF(K11="","N/A",'5'!X15) -> 13859066
A12: 7 | B12: =IF(A12="","N/A",'1'!V16) -> 14081397 | C12: =IF(A12="","N/A",'2'!V16) -> 14236887 | D12: =IF(A12="","N/A",'3'!V16) -> 14392376 | E12: =IF(A12="","N/A",'4'!V16) -> 14547866 | F12: =IF(A12="","N/A",'5'!V16) -> 14703355 | K12: 7 | L12: =IF(K12="","N/A",'1'!X16) -> 14030230 | M12: =IF(K12="","N/A",'2'!X16) -> 14179078 | N12: =IF(K12="","N/A",'3'!X16) -> 14329278 | O12: =IF(K12="","N/A",'4'!X16) -> 14480839 | P12: =IF(K12="","N/A",'5'!X16) -> 14633773
A13: 8 | B13: =IF(A13="","N/A",'1'!V17) -> 14797041 | C13: =IF(A13="","N/A",'2'!V17) -> 14985174 | D13: =IF(A13="","N/A",'3'!V17) -> 15173307 | E13: =IF(A13="","N/A",'4'!V17) -> 15361440 | F13: =IF(A13="","N/A",'5'!V17) -> 15549573 | K13: 8 | L13: =IF(K13="","N/A",'1'!X17) -> 14725636 | M13: =IF(K13="","N/A",'2'!X17) -> 14904314 | N13: =IF(K13="","N/A",'3'!X17) -> 15084887 | O13: =IF(K13="","N/A",'4'!X17) -> 15267371 | P13: =IF(K13="","N/A",'5'!X17) -> 15451784
A14: 9 | B14: =IF(A14="","N/A",'1'!V18) -> 15551601 | C14: =IF(A14="","N/A",'2'!V18) -> 15775713 | D14: =IF(A14="","N/A",'3'!V18) -> 15999826 | E14: =IF(A14="","N/A",'4'!V18) -> 16223939 | F14: =IF(A14="","N/A",'5'!V18) -> 16448051 | K14: 9 | L14: =IF(K14="","N/A",'1'!X18) -> 15455509 | M14: =IF(K14="","N/A",'2'!X18) -> 15666645 | N14: =IF(K14="","N/A",'3'!X18) -> 15880341 | O14: =IF(K14="","N/A",'4'!X18) -> 16096624 | P14: =IF(K14="","N/A",'5'!X18) -> 16315522
A15: 10 | B15: =IF(A15="","N/A",'1'!V19) -> 16347284 | C15: =IF(A15="","N/A",'2'!V19) -> 16611007 | D15: =IF(A15="","N/A",'3'!V19) -> 16874731 | E15: =IF(A15="","N/A",'4'!V19) -> 17138454 | F15: =IF(A15="","N/A",'5'!V19) -> 17402177 | K15: 10 | L15: =IF(K15="","N/A",'1'!X19) -> 16221558 | M15: =IF(K15="","N/A",'2'!X19) -> 16467968 | N15: =IF(K15="","N/A",'3'!X19) -> 16717741 | O15: =IF(K15="","N/A",'4'!X19) -> 16970918 | P15: =IF(K15="","N/A",'5'!X19) -> 17227541
A16: 11 | B16: =IF(A16="","N/A",'1'!V20) -> 17186426 | C16: =IF(A16="","N/A",'2'!V20) -> 17493711 | D16: =IF(A16="","N/A",'3'!V20) -> 17800995 | E16: =IF(A16="","N/A",'4'!V20) -> 18108279 | F16: =IF(A16="","N/A",'5'!V20) -> 18415564 | K16: 11 | L16: =IF(K16="","N/A",'1'!X20) -> 17025577 | M16: =IF(K16="","N/A",'2'!X20) -> 17310277 | N16: =IF(K16="","N/A",'3'!X20) -> 17599298 | O16: =IF(K16="","N/A",'4'!X20) -> 17892700 | P16: =IF(K16="","N/A",'5'!X20) -> 18190541
A17: 12 | B17: =IF(A17="","N/A",'1'!V21) -> 18071498 | C17: =IF(A17="","N/A",'2'!V21) -> 18426640 | D17: =IF(A17="","N/A",'3'!V21) -> 18781782 | E17: =IF(A17="","N/A",'4'!V21) -> 19136925 | F17: =IF(A17="","N/A",'5'!V21) -> 19492067 | K17: 12 | L17: =IF(K17="","N/A",'1'!X21) -> 17869446 | M17: =IF(K17="","N/A",'2'!X21) -> 18195668 | N17: =IF(K17="","N/A",'3'!X21) -> 18527341 | O17: =IF(K17="","N/A",'4'!X21) -> 18864548 | P17: =IF(K17="","N/A",'5'!X21) -> 19207372
A18: 13 | B18: =IF(A18="","N/A",'1'!V22) -> 19005113 | C18: =IF(A18="","N/A",'2'!V22) -> 19412785 | D18: =IF(A18="","N/A",'3'!V22) -> 19820458 | E18: =IF(A18="","N/A",'4'!V22) -> 20228130 | F18: =IF(A18="","N/A",'5'!V22) -> 20635802 | K18: 13 | L18: =IF(K18="","N/A",'1'!X22) -> 18755141 | M18: =IF(K18="","N/A",'2'!X22) -> 19126346 | N18: =IF(K18="","N/A",'3'!X22) -> 19504322 | O18: =IF(K18="","N/A",'4'!X22) -> 19889183 | P18: =IF(K18="","N/A",'5'!X22) -> 20281043
... A25: 20 | B25: =IF(A25="","N/A",'1'!V29) -> 27153622 | C25: =IF(A25="","N/A",'2'!V29) -> 28098547 | D25: =IF(A25="","N/A",'3'!V29) -> 29043472 | E25: =IF(A25="","N/A",'4'!V29) -> 29988397 | F25: =IF(A25="","N/A",'5'!V29) -> 30933322 | K25: 20 | L25: =IF(K25="","N/A",'1'!X29) -> 26313895 | M25: =IF(K25="","N/A",'2'!X29) -> 27119396 | N25: =IF(K25="","N/A",'3'!X29) -> 27948285 | O25: =IF(K25="","N/A",'4'!X29) -> 28801206 | P25: =IF(K25="","N/A",'5'!X29) -> 29678817
B26: =IF(A26="","N/A",'1'!V30) -> N/A | C26: =IF(A26="","N/A",'2'!V30) -> N/A | D26: =IF(A26="","N/A",'3'!V30) -> N/A | E26: =IF(A26="","N/A",'4'!V30) -> N/A | F26: =IF(A26="","N/A",'5'!V30) -> N/A | L26: =IF(K26="","N/A",'1'!X30) -> N/A | M26: =IF(K26="","N/A",'2'!X30) -> N/A | N26: =IF(K26="","N/A",'3'!X30) -> N/A | O26: =IF(K26="","N/A",'4'!X30) -> N/A | P26: =IF(K26="","N/A",'5'!X30) -> N/A
B27: =IF(A27="","N/A",'1'!V31) -> N/A | C27: =IF(A27="","N/A",'2'!V31) -> N/A | D27: =IF(A27="","N/A",'3'!V31) -> N/A | E27: =IF(A27="","N/A",'4'!V31) -> N/A | F27: =IF(A27="","N/A",'5'!V31) -> N/A | L27: =IF(K27="","N/A",'1'!X31) -> N/A | M27: =IF(K27="","N/A",'2'!X31) -> N/A | N27: =IF(K27="","N/A",'3'!X31) -> N/A | O27: =IF(K27="","N/A",'4'!X31) -> N/A | P27: =IF(K27="","N/A",'5'!X31) -> N/A
B28: =IF(A28="","N/A",'1'!V32) -> N/A | C28: =IF(A28="","N/A",'2'!V32) -> N/A | D28: =IF(A28="","N/A",'3'!V32) -> N/A | E28: =IF(A28="","N/A",'4'!V32) -> N/A | F28: =IF(A28="","N/A",'5'!V32) -> N/A | L28: =IF(K28="","N/A",'1'!X32) -> N/A | M28: =IF(K28="","N/A",'2'!X32) -> N/A | N28: =IF(K28="","N/A",'3'!X32) -> N/A | O28: =IF(K28="","N/A",'4'!X32) -> N/A | P28: =IF(K28="","N/A",'5'!X32) -> N/A
B29: =IF(A29="","N/A",'1'!V33) -> N/A | C29: =IF(A29="","N/A",'2'!V33) -> N/A | D29: =IF(A29="","N/A",'3'!V33) -> N/A | E29: =IF(A29="","N/A",'4'!V33) -> N/A | F29: =IF(A29="","N/A",'5'!V33) -> N/A | L29: =IF(K29="","N/A",'1'!X33) -> N/A | M29: =IF(K29="","N/A",'2'!X33) -> N/A | N29: =IF(K29="","N/A",'3'!X33) -> N/A | O29: =IF(K29="","N/A",'4'!X33) -> N/A | P29: =IF(K29="","N/A",'5'!X33) -> N/A
B30: =IF(A30="","N/A",'1'!V34) -> N/A | C30: =IF(A30="","N/A",'2'!V34) -> N/A | D30: =IF(A30="","N/A",'3'!V34) -> N/A | E30: =IF(A30="","N/A",'4'!V34) -> N/A | F30: =IF(A30="","N/A",'5'!V34) -> N/A | L30: =IF(K30="","N/A",'1'!X34) -> N/A | M30: =IF(K30="","N/A",'2'!X34) -> N/A | N30: =IF(K30="","N/A",'3'!X34) -> N/A | O30: =IF(K30="","N/A",'4'!X34) -> N/A | P30: =IF(K30="","N/A",'5'!X34) -> N/A
B31: =IF(A31="","N/A",'1'!V35) -> N/A | C31: =IF(A31="","N/A",'2'!V35) -> N/A | D31: =IF(A31="","N/A",'3'!V35) -> N/A | E31: =IF(A31="","N/A",'4'!V35) -> N/A | F31: =IF(A31="","N/A",'5'!V35) -> N/A | L31: =IF(K31="","N/A",'1'!X35) -> N/A | M31: =IF(K31="","N/A",'2'!X35) -> N/A | N31: =IF(K31="","N/A",'3'!X35) -> N/A | O31: =IF(K31="","N/A",'4'!X35) -> N/A | P31: =IF(K31="","N/A",'5'!X35) -> N/A
B32: =IF(A32="","N/A",'1'!V36) -> N/A | C32: =IF(A32="","N/A",'2'!V36) -> N/A | D32: =IF(A32="","N/A",'3'!V36) -> N/A | E32: =IF(A32="","N/A",'4'!V36) -> N/A | F32: =IF(A32="","N/A",'5'!V36) -> N/A | L32: =IF(K32="","N/A",'1'!X36) -> N/A | M32: =IF(K32="","N/A",'2'!X36) -> N/A | N32: =IF(K32="","N/A",'3'!X36) -> N/A | O32: =IF(K32="","N/A",'4'!X36) -> N/A | P32: =IF(K32="","N/A",'5'!X36) -> N/A
B33: =IF(A33="","N/A",'1'!V37) -> N/A | C33: =IF(A33="","N/A",'2'!V37) -> N/A | D33: =IF(A33="","N/A",'3'!V37) -> N/A | E33: =IF(A33="","N/A",'4'!V37) -> N/A | F33: =IF(A33="","N/A",'5'!V37) -> N/A | L33: =IF(K33="","N/A",'1'!X37) -> N/A | M33: =IF(K33="","N/A",'2'!X37) -> N/A | N33: =IF(K33="","N/A",'3'!X37) -> N/A | O33: =IF(K33="","N/A",'4'!X37) -> N/A | P33: =IF(K33="","N/A",'5'!X37) -> N/A
B34: =IF(A34="","N/A",'1'!V38) -> N/A | C34: =IF(A34="","N/A",'2'!V38) -> N/A | D34: =IF(A34="","N/A",'3'!V38) -> N/A | E34: =IF(A34="","N/A",'4'!V38) -> N/A | F34: =IF(A34="","N/A",'5'!V38) -> N/A | L34: =IF(K34="","N/A",'1'!X38) -> N/A | M34: =IF(K34="","N/A",'2'!X38) -> N/A | N34: =IF(K34="","N/A",'3'!X38) -> N/A | O34: =IF(K34="","N/A",'4'!X38) -> N/A | P34: =IF(K34="","N/A",'5'!X38) -> N/A
B35: =IF(A35="","N/A",'1'!V39) -> N/A | C35: =IF(A35="","N/A",'2'!V39) -> N/A | D35: =IF(A35="","N/A",'3'!V39) -> N/A | E35: =IF(A35="","N/A",'4'!V39) -> N/A | F35: =IF(A35="","N/A",'5'!V39) -> N/A | L35: =IF(K35="","N/A",'1'!X39) -> N/A | M35: =IF(K35="","N/A",'2'!X39) -> N/A | N35: =IF(K35="","N/A",'3'!X39) -> N/A | O35: =IF(K35="","N/A",'4'!X39) -> N/A | P35: =IF(K35="","N/A",'5'!X39) -> N/A
B36: =IF(A36="","N/A",'1'!V40) -> N/A | C36: =IF(A36="","N/A",'2'!V40) -> N/A | D36: =IF(A36="","N/A",'3'!V40) -> N/A | E36: =IF(A36="","N/A",'4'!V40) -> N/A | F36: =IF(A36="","N/A",'5'!V40) -> N/A | L36: =IF(K36="","N/A",'1'!X40) -> N/A | M36: =IF(K36="","N/A",'2'!X40) -> N/A | N36: =IF(K36="","N/A",'3'!X40) -> N/A | O36: =IF(K36="","N/A",'4'!X40) -> N/A | P36: =IF(K36="","N/A",'5'!X40) -> N/A
B37: =IF(A37="","N/A",'1'!V41) -> N/A | C37: =IF(A37="","N/A",'2'!V41) -> N/A | D37: =IF(A37="","N/A",'3'!V41) -> N/A | E37: =IF(A37="","N/A",'4'!V41) -> N/A | F37: =IF(A37="","N/A",'5'!V41) -> N/A | L37: =IF(K37="","N/A",'1'!X41) -> N/A | M37: =IF(K37="","N/A",'2'!X41) -> N/A | N37: =IF(K37="","N/A",'3'!X41) -> N/A | O37: =IF(K37="","N/A",'4'!X41) -> N/A | P37: =IF(K37="","N/A",'5'!X41) -> N/A
... B105: =IF(A105="","N/A",'1'!V109) -> N/A | C105: =IF(A105="","N/A",'2'!V109) -> N/A | D105: =IF(A105="","N/A",'3'!V109) -> N/A | E105: =IF(A105="","N/A",'4'!V109) -> N/A | F105: =IF(A105="","N/A",'5'!V109) -> N/A | L105: =IF(K105="","N/A",'1'!X109) -> N/A | M105: =IF(K105="","N/A",'2'!X109) -> N/A | N105: =IF(K105="","N/A",'3'!X109) -> N/A | O105: =IF(K105="","N/A",'4'!X109) -> N/A | P105: =IF(K105="","N/A",'5'!X109) -> N/A

Sheet Rank
A1: Buy & Hold
A2: ='Return Simulator'!D48 -> 20 | C2: ='Return Simulator'!C4 -> Current Client Portfolio | D2: ='Return Simulator'!D5 -> 27153622 | E2: ='Return Simulator'!D6 -> 0.05121461 | F2: =_xlfn.RANK.EQ(D2,$D$2:$D$6,0) -> 5 | G2: =_xlfn.XLOOKUP(F2,$O$2:$O$6,$P$2:$P$6) -> 5th | I2: {=_xlfn._xlws.SORT(C2:G6,2,-1)} -> 40% of Current Portfolio inside PPLI | J2: 30933322 | K2: 0.058086877 | L2: 1 | M2: 1st | O2: 1 | P2: 1st
C3: ='Return Simulator'!C10 -> 10% of Current Portfolio inside PPLI | D3: ='Return Simulator'!D11 -> 28098547 | E3: ='Return Simulator'!D12 -> 0.053014116 | F3: =_xlfn.RANK.EQ(D3,$D$2:$D$6,0) -> 4 | G3: =_xlfn.XLOOKUP(F3,$O$2:$O$6,$P$2:$P$6) -> 4th | I3: 30% of Current Portfolio inside PPLI | J3: 29988397 | K3: 0.056446875 | L3: 2 | M3: 2nd | O3: 2 | P3: 2nd
C4: ='Return Simulator'!C14 -> 20% of Current Portfolio inside PPLI | D4: ='Return Simulator'!D15 -> 29043472 | E4: ='Return Simulator'!D16 -> 0.054757025 | F4: =_xlfn.RANK.EQ(D4,$D$2:$D$6,0) -> 3 | G4: =_xlfn.XLOOKUP(F4,$O$2:$O$6,$P$2:$P$6) -> 3rd | I4: 20% of Current Portfolio inside PPLI | J4: 29043472 | K4: 0.054757025 | L4: 3 | M4: 3rd | O4: 3 | P4: 3rd
C5: ='Return Simulator'!C18 -> 30% of Current Portfolio inside PPLI | D5: ='Return Simulator'!D19 -> 29988397 | E5: ='Return Simulator'!D20 -> 0.056446875 | F5: =_xlfn.RANK.EQ(D5,$D$2:$D$6,0) -> 2 | G5: =_xlfn.XLOOKUP(F5,$O$2:$O$6,$P$2:$P$6) -> 2nd | I5: 10% of Current Portfolio inside PPLI | J5: 28098547 | K5: 0.053014116 | L5: 4 | M5: 4th | O5: 4 | P5: 4th
C6: ='Return Simulator'!C22 -> 40% of Current Portfolio inside PPLI | D6: ='Return Simulator'!D23 -> 30933322 | E6: ='Return Simulator'!D24 -> 0.058086877 | F6: =_xlfn.RANK.EQ(D6,$D$2:$D$6,0) -> 1 | G6: =_xlfn.XLOOKUP(F6,$O$2:$O$6,$P$2:$P$6) -> 1st | I6: Current Client Portfolio | J6: 27153622 | K6: 0.05121461 | L6: 5 | M6: 5th | O6: 5 | P6: 5th
A9: Rebalanced
A10: =A2 -> 20 | C10: =C2 -> Current Client Portfolio | D10: ='Return Simulator'!X49 -> 26313895 | E10: ='Return Simulator'!X58 -> 0.0495648 | F10: =_xlfn.RANK.EQ(D10,$D$10:$D$14,0) -> 5 | G10: =_xlfn.XLOOKUP(F10,$O$2:$O$6,$P$2:$P$6) -> 5th | I10: {=_xlfn._xlws.SORT(C10:G14,2,-1)} -> 40% of Current Portfolio inside PPLI | J10: 29678817 | K10: 0.05589888 | L10: 1 | M10: 1st | O10: 1 | P10: 1st
C11: =C3 -> 10% of Current Portfolio inside PPLI | D11: ='Return Simulator'!AA49 -> 27119396 | E11: ='Return Simulator'!AA58 -> 0.05114832 | F11: =_xlfn.RANK.EQ(D11,$D$10:$D$14,0) -> 4 | G11: =_xlfn.XLOOKUP(F11,$O$2:$O$6,$P$2:$P$6) -> 4th | I11: 30% of Current Portfolio inside PPLI | J11: 28801206 | K11: 0.05431536 | L11: 2 | M11: 2nd | O11: 2 | P11: 2nd
C12: =C4 -> 20% of Current Portfolio inside PPLI | D12: ='Return Simulator'!AD49 -> 27948285 | E12: ='Return Simulator'!AD58 -> 0.05273184 | F12: =_xlfn.RANK.EQ(D12,$D$10:$D$14,0) -> 3 | G12: =_xlfn.XLOOKUP(F12,$O$2:$O$6,$P$2:$P$6) -> 3rd | I12: 20% of Current Portfolio inside PPLI | J12: 27948285 | K12: 0.05273184 | L12: 3 | M12: 3rd | O12: 3 | P12: 3rd
C13: =C5 -> 30% of Current Portfolio inside PPLI | D13: ='Return Simulator'!AG49 -> 28801206 | E13: ='Return Simulator'!AG58 -> 0.05431536 | F13: =_xlfn.RANK.EQ(D13,$D$10:$D$14,0) -> 2 | G13: =_xlfn.XLOOKUP(F13,$O$2:$O$6,$P$2:$P$6) -> 2nd | I13: 10% of Current Portfolio inside PPLI | J13: 27119396 | K13: 0.05114832 | L13: 4 | M13: 4th | O13: 4 | P13: 4th
C14: =C6 -> 40% of Current Portfolio inside PPLI | D14: ='Return Simulator'!AJ49 -> 29678817 | E14: ='Return Simulator'!AJ58 -> 0.05589888 | F14: =_xlfn.RANK.EQ(D14,$D$10:$D$14,0) -> 1 | G14: =_xlfn.XLOOKUP(F14,$O$2:$O$6,$P$2:$P$6) -> 1st | I14: Current Client Portfolio | J14: 26313895 | K14: 0.0495648 | L14: 5 | M14: 5th | O14: 5 | P14: 5th

Sheet Strategy Feeder >

Sheet 1
B2: Initial Capital ($) | C2: ='Return Simulator'!D47 -> 10000000 | I2: Stocks (Taxable) | J2: Stocks (Taxable) | K2: Stocks (PPLI) | L2: Stocks (PPLI) | M2: Bonds (Taxable) | N2: Bonds (Taxable) | O2: Bonds (PPLI) | P2: Bonds (PPLI) | Q2: Alternatives (Taxable) | R2: Alternatives (Taxable) | S2: Alternatives (PPLI) | T2: Alternatives (PPLI) | W2: Weighted Average | X2: Weighted Average
B3: Time Horizon (Years) | C3: ='Return Simulator'!D48 -> 20 | H3: Weight | I3: =$D$7*(1-$E$7) -> 0.48 | J3: =$D$7*(1-$E$7) -> 0.48 | K3: =$D$7*$E$7 -> 0 | L3: =$D$7*$E$7 -> 0 | M3: =$D$8*(1-$E$8) -> 0.32 | N3: =$D$8*(1-$E$8) -> 0.32 | O3: =$D$8*$E$8 -> 0 | P3: =$D$8*$E$8 -> 0 | Q3: =$D$9*(1-$E$9) -> 0.2 | R3: =$D$9*(1-$E$9) -> 0.2 | S3: =$D$9*$E$9 -> 0 | T3: =$D$9*$E$9 -> 0 | W3: =SUM(I3,K3,M3,O3,Q3,S3) -> 1 | X3: =SUM(J3,L3,N3,P3,R3,T3) -> 1
H4: Return | I4: =$C$7 -> 0.08 | J4: =$C$7 -> 0.08 | K4: =$C$7 -> 0.08 | L4: =$C$7 -> 0.08 | M4: =$C$8 -> 0.05 | N4: =$C$8 -> 0.05 | O4: =$C$8 -> 0.05 | P4: =$C$8 -> 0.05 | Q4: =$C$9 -> 0.08 | R4: =$C$9 -> 0.08 | S4: =$C$9 -> 0.08 | T4: =$C$9 -> 0.08 | W4: =SUMPRODUCT(I3:T3,I4:T4)/2 -> 0.0704 | X4: =SUMPRODUCT(I3:T3,I4:T4)/2 -> 0.0704
D5: =IF(SUM(D7:D9)<>1,"Error","Good") -> Good | H5: Drag | I5: 0 | J5: =$C$7*($C$15+$C$16) -> 0.01904 | K5: 0 | L5: =$C$11 -> 0.005 | M5: 0 | N5: =$C$8*($C$14+$C$16) -> 0.0204 | O5: 0 | P5: =$C$11 -> 0.005 | Q5: 0 | R5: =(50%*$C$9*($C$14+$C$16))+(50%*$C$9*($C$15+$C$16)) -> 0.02584 | S5: 0 | T5: =$C$11 -> 0.005 | W5: 0 | X5: =SUMPRODUCT(J3:T3,J5:T5) -> 0.0208352
C6: Returns | D6: Weight | E6: PPLI Allocation
B7: Stocks | C7: ='Return Simulator'!D56 -> 0.08 | D7: ='Return Simulator'!D51 -> 0.48 | E7: ='Return Simulator'!D66 -> 0 | U7: Buy & Hold | V7: Buy & Hold | W7: Rebalanced | X7: Rebalanced | Y7: Buy & Hold | Z7: Buy & Hold | AA7: Buy & Hold | AB7: Rebalanced | AC7: Rebalanced | AD7: Rebalanced | AE7: Buy & Hold | AF7: Buy & Hold | AG7: Buy & Hold | AH7: Rebalanced | AI7: Rebalanced | AJ7: Rebalanced | AK7: Buy & Hold | AL7: Buy & Hold | AM7: Buy & Hold | AN7: Rebalanced | AO7: Rebalanced | AP7: Rebalanced
B8: Bonds | C8: ='Return Simulator'!D57 -> 0.05 | D8: ='Return Simulator'!D52 -> 0.32 | E8: ='Return Simulator'!D67 -> 0 | I8: Gross | J8: Net | K8: Gross | L8: Net | M8: Gross | N8: Net | O8: Gross | P8: Net | Q8: Gross | R8: Net | S8: Gross | T8: Net | U8: Gross | V8: Net | W8: Gross | X8: Net | Y8: Gross | Z8: Net | AB8: Gross | AC8: Net | AE8: Gross | AF8: Net | AH8: Gross | AI8: Net | AK8: Gross | AL8: Net | AN8: Gross | AO8: Net
B9: Alternatives | C9: ='Return Simulator'!D58 -> 0.08 | D9: ='Return Simulator'!D53 -> 0.2 | E9: ='Return Simulator'!D68 -> 0 | G9: Year | H9: Contributions | I9: Stocks (Taxable) | J9: Stocks (Taxable) | K9: Stocks (PPLI) | L9: Stocks (PPLI) | M9: Bonds (Taxable) | N9: Bonds (Taxable) | O9: Bonds (PPLI) | P9: Bonds (PPLI) | Q9: Alternatives (Taxable) | R9: Alternatives (Taxable) | S9: Alternatives (PPLI) | T9: Alternatives (PPLI) | U9: Total | V9: Total | W9: Total | X9: Total | Y9: Period Return | Z9: Period Return | AA9: Period Drag | AB9: Period Return | AC9: Period Return | AD9: Period Drag | AE9: Total Return | AF9: Total Return | AG9: Total Drag | AH9: Total Return | AI9: Total Return | AJ9: Total Drag | AK9: Total Return (Annualized) | AL9: Total Return (Annualized) | AM9: Annaulized Drag | AN9: Total Return (Annualized) | AO9: Total Return (Annualized) | AP9: Annaulized Drag
G10: {=_xlfn.SEQUENCE(C3,1,1,1)} -> 1 | H10: =IF(G10="","",SUMIFS(Add_Contributions[[#All],[Amount ($)]],Add_Contributions[[#All],[Year]],G10)) -> 0 | I10: =IF($G10="","",IF($G10=1,(($C$2+$H10)*I$3)*(1+(I$4-I$5)),((I9+($H10*I$3))*(1+(I$4-I$5))))) -> 5184000 | J10: =IF($G10="","",IF($G10=1,(($C$2+$H10)*J$3)*(1+(J$4-J$5)),((J9+($H10*J$3))*(1+(J$4-J$5))))) -> 5092608 | K10: =IF($G10="","",IF($G10=1,(($C$2+$H10)*K$3)*(1+(K$4-K$5)),((K9+($H10*K$3))*(1+(K$4-K$5))))) -> 0 | L10: =IF($G10="","",IF($G10=1,(($C$2+$H10)*L$3)*(1+(L$4-L$5)),((L9+($H10*L$3))*(1+(L$4-L$5))))) -> 0 | M10: =IF($G10="","",IF($G10=1,(($C$2+$H10)*M$3)*(1+(M$4-M$5)),((M9+($H10*M$3))*(1+(M$4-M$5))))) -> 3360000 | N10: =IF($G10="","",IF($G10=1,(($C$2+$H10)*N$3)*(1+(N$4-N$5)),((N9+($H10*N$3))*(1+(N$4-N$5))))) -> 3294720 | O10: =IF($G10="","",IF($G10=1,(($C$2+$H10)*O$3)*(1+(O$4-O$5)),((O9+($H10*O$3))*(1+(O$4-O$5))))) -> 0 | P10: =IF($G10="","",IF($G10=1,(($C$2+$H10)*P$3)*(1+(P$4-P$5)),((P9+($H10*P$3))*(1+(P$4-P$5))))) -> 0 | ... T10: =IF($G10="","",IF($G10=1,(($C$2+$H10)*T$3)*(1+(T$4-T$5)),((T9+($H10*T$3))*(1+(T$4-T$5))))) -> 0 | U10: =IF(G10="","",SUM(I10,K10,M10,O10,Q10,S10)) -> 10704000 | V10: =IF(H10="","",SUM(J10,L10,N10,P10,R10,T10)) -> 10495648 | W10: =IF($G10="","",IF($G10=1,(($C$2+$H10)*W$3)*(1+(W$4-W$5)),((W9+($H10*W$3))*(1+(W$4-W$5))))) -> 10704000 | X10: =IF($G10="","",IF($G10=1,(($C$2+$H10)*X$3)*(1+(X$4-X$5)),((X9+($H10*X$3))*(1+(X$4-X$5))))) -> 10495648 | Y10: =IF($G10="","",IF($G10=1,(U10-$C$2-H10)/($C$2+H10),(U10-U9-H10)/(U9+H10))) -> 0.0704 | Z10: =IF($G10="","",IF($G10=1,(V10-$C$2-H10)/($C$2+H10),(V10-V9-H10)/(V9+H10))) -> 0.0495648 | AA10: =IF($G10="","",Z10-Y10) -> -0.0208352 | AB10: =IF($G10="","",IF($G10=1,(W10-$C$2-H10)/($C$2+H10),(W10-W9-H10)/(W9+H10))) -> 0.0704 | AC10: =IF($G10="","",IF($G10=1,(X10-$C$2-H10)/($C$2+H10),(X10-X9-H10)/(X9+H10))) -> 0.0495648 | AD10: =IF($G10="","",AC10-AB10) -> -0.0208352 | AE10: =IF($G10="","",IF($G10=1,Y10,(1+Y10)*(1+AE9)-1)) -> 0.0704 | AF10: =IF($G10="","",IF($G10=1,Z10,(1+Z10)*(1+AF9)-1)) -> 0.0495648 | AG10: =IF($G10="","",AF10-AE10) -> -0.0208352 | AH10: =IF($G10="","",IF($G10=1,AB10,(1+AB10)*(1+AH9)-1)) -> 0.0704 | AI10: =IF($G10="","",IF($G10=1,AC10,(1+AC10)*(1+AI9)-1)) -> 0.0495648 | AJ10: =IF($G10="","",AI10-AH10) -> -0.0208352 | AK10: =IF($G10="","",(1+AE10)^(1/G10)-1) -> 0.0704 | AL10: =IF($G10="","",(1+AF10)^(1/G10)-1) -> 0.0495648 | AM10: =IF($G10="","",AL10-AK10) -> -0.0208352 | AN10: =IF($G10="","",(1+AH10)^(1/G10)-1) -> 0.0704 | AO10: =IF($G10="","",(1+AI10)^(1/G10)-1) -> 0.0495648 | AP10: =IF($G10="","",AO10-AN10) -> -0.0208352
B11: PPLI Policy Costs | C11: ='Return Simulator'!D71 -> 0.005 | G11: 2 | H11: =IF(G11="","",SUMIFS(Add_Contributions[[#All],[Amount ($)]],Add_Contributions[[#All],[Year]],G11)) -> 0 | I11: =IF($G11="","",IF($G11=1,(($C$2+$H11)*I$3)*(1+(I$4-I$5)),((I10+($H11*I$3))*(1+(I$4-I$5))))) -> 5598720 | J11: =IF($G11="","",IF($G11=1,(($C$2+$H11)*J$3)*(1+(J$4-J$5)),((J10+($H11*J$3))*(1+(J$4-J$5))))) -> 5403053.4 | K11: =IF($G11="","",IF($G11=1,(($C$2+$H11)*K$3)*(1+(K$4-K$5)),((K10+($H11*K$3))*(1+(K$4-K$5))))) -> 0 | L11: =IF($G11="","",IF($G11=1,(($C$2+$H11)*L$3)*(1+(L$4-L$5)),((L10+($H11*L$3))*(1+(L$4-L$5))))) -> 0 | M11: =IF($G11="","",IF($G11=1,(($C$2+$H11)*M$3)*(1+(M$4-M$5)),((M10+($H11*M$3))*(1+(M$4-M$5))))) -> 3528000 | N11: =IF($G11="","",IF($G11=1,(($C$2+$H11)*N$3)*(1+(N$4-N$5)),((N10+($H11*N$3))*(1+(N$4-N$5))))) -> 3392243.7 | O11: =IF($G11="","",IF($G11=1,(($C$2+$H11)*O$3)*(1+(O$4-O$5)),((O10+($H11*O$3))*(1+(O$4-O$5))))) -> 0 | P11: =IF($G11="","",IF($G11=1,(($C$2+$H11)*P$3)*(1+(P$4-P$5)),((P10+($H11*P$3))*(1+(P$4-P$5))))) -> 0 | ... T11: =IF($G11="","",IF($G11=1,(($C$2+$H11)*T$3)*(1+(T$4-T$5)),((T10+($H11*T$3))*(1+(T$4-T$5))))) -> 0 | U11: =IF(G11="","",SUM(I11,K11,M11,O11,Q11,S11)) -> 11459520 | V11: =IF(H11="","",SUM(J11,L11,N11,P11,R11,T11)) -> 11017804 | W11: =IF($G11="","",IF($G11=1,(($C$2+$H11)*W$3)*(1+(W$4-W$5)),((W10+($H11*W$3))*(1+(W$4-W$5))))) -> 11457562 | X11: =IF($G11="","",IF($G11=1,(($C$2+$H11)*X$3)*(1+(X$4-X$5)),((X10+($H11*X$3))*(1+(X$4-X$5))))) -> 11015863 | Y11: =IF($G11="","",IF($G11=1,(U11-$C$2-H11)/($C$2+H11),(U11-U10-H11)/(U10+H11))) -> 0.07058296 | Z11: =IF($G11="","",IF($G11=1,(V11-$C$2-H11)/($C$2+H11),(V11-V10-H11)/(V10+H11))) -> 0.049749735 | AA11: =IF($G11="","",Z11-Y11) -> -0.020833225 | AB11: =IF($G11="","",IF($G11=1,(W11-$C$2-H11)/($C$2+H11),(W11-W10-H11)/(W10+H11))) -> 0.0704 | AC11: =IF($G11="","",IF($G11=1,(X11-$C$2-H11)/($C$2+H11),(X11-X10-H11)/(X10+H11))) -> 0.0495648 | AD11: =IF($G11="","",AC11-AB11) -> -0.0208352 | AE11: =IF($G11="","",IF($G11=1,Y11,(1+Y11)*(1+AE10)-1)) -> 0.145952 | AF11: =IF($G11="","",IF($G11=1,Z11,(1+Z11)*(1+AF10)-1)) -> 0.10178037 | AG11: =IF($G11="","",AF11-AE11) -> -0.044171629 | AH11: =IF($G11="","",IF($G11=1,AB11,(1+AB11)*(1+AH10)-1)) -> 0.14575616 | AI11: =IF($G11="","",IF($G11=1,AC11,(1+AC11)*(1+AI10)-1)) -> 0.10158627 | AJ11: =IF($G11="","",AI11-AH11) -> -0.044169891 | AK11: =IF($G11="","",(1+AE11)^(1/G11)-1) -> 0.070491476 | AL11: =IF($G11="","",(1+AF11)^(1/G11)-1) -> 0.049657263 | AM11: =IF($G11="","",AL11-AK11) -> -0.020834212 | AN11: =IF($G11="","",(1+AH11)^(1/G11)-1) -> 0.0704 | AO11: =IF($G11="","",(1+AI11)^(1/G11)-1) -> 0.0495648 | AP11: =IF($G11="","",AO11-AN11) -> -0.0208352
B12: PPLI Start Up Costs | G12: 3 | H12: =IF(G12="","",SUMIFS(Add_Contributions[[#All],[Amount ($)]],Add_Contributions[[#All],[Year]],G12)) -> 0 | I12: =IF($G12="","",IF($G12=1,(($C$2+$H12)*I$3)*(1+(I$4-I$5)),((I11+($H12*I$3))*(1+(I$4-I$5))))) -> 6046617.6 | J12: =IF($G12="","",IF($G12=1,(($C$2+$H12)*J$3)*(1+(J$4-J$5)),((J11+($H12*J$3))*(1+(J$4-J$5))))) -> 5732423.5 | K12: =IF($G12="","",IF($G12=1,(($C$2+$H12)*K$3)*(1+(K$4-K$5)),((K11+($H12*K$3))*(1+(K$4-K$5))))) -> 0 | L12: =IF($G12="","",IF($G12=1,(($C$2+$H12)*L$3)*(1+(L$4-L$5)),((L11+($H12*L$3))*(1+(L$4-L$5))))) -> 0 | M12: =IF($G12="","",IF($G12=1,(($C$2+$H12)*M$3)*(1+(M$4-M$5)),((M11+($H12*M$3))*(1+(M$4-M$5))))) -> 3704400 | N12: =IF($G12="","",IF($G12=1,(($C$2+$H12)*N$3)*(1+(N$4-N$5)),((N11+($H12*N$3))*(1+(N$4-N$5))))) -> 3492654.1 | O12: =IF($G12="","",IF($G12=1,(($C$2+$H12)*O$3)*(1+(O$4-O$5)),((O11+($H12*O$3))*(1+(O$4-O$5))))) -> 0 | P12: =IF($G12="","",IF($G12=1,(($C$2+$H12)*P$3)*(1+(P$4-P$5)),((P11+($H12*P$3))*(1+(P$4-P$5))))) -> 0 | ... T12: =IF($G12="","",IF($G12=1,(($C$2+$H12)*T$3)*(1+(T$4-T$5)),((T11+($H12*T$3))*(1+(T$4-T$5))))) -> 0 | U12: =IF(G12="","",SUM(I12,K12,M12,O12,Q12,S12)) -> 12270442 | V12: =IF(H12="","",SUM(J12,L12,N12,P12,R12,T12)) -> 11567955 | W12: =IF($G12="","",IF($G12=1,(($C$2+$H12)*W$3)*(1+(W$4-W$5)),((W11+($H12*W$3))*(1+(W$4-W$5))))) -> 12264174 | X12: =IF($G12="","",IF($G12=1,(($C$2+$H12)*X$3)*(1+(X$4-X$5)),((X11+($H12*X$3))*(1+(X$4-X$5))))) -> 11561862 | Y12: =IF($G12="","",IF($G12=1,(U12-$C$2-H12)/($C$2+H12),(U12-U11-H12)/(U11+H12))) -> 0.070764011 | Z12: =IF($G12="","",IF($G12=1,(V12-$C$2-H12)/($C$2+H12),(V12-V11-H12)/(V11+H12))) -> 0.049932956 | AA12: =IF($G12="","",Z12-Y12) -> -0.020831055 | AB12: =IF($G12="","",IF($G12=1,(W12-$C$2-H12)/($C$2+H12),(W12-W11-H12)/(W11+H12))) -> 0.0704 | AC12: =IF($G12="","",IF($G12=1,(X12-$C$2-H12)/($C$2+H12),(X12-X11-H12)/(X11+H12))) -> 0.0495648 | AD12: =IF($G12="","",AC12-AB12) -> -0.0208352 | AE12: =IF($G12="","",IF($G12=1,Y12,(1+Y12)*(1+AE11)-1)) -> 0.22704416 | AF12: =IF($G12="","",IF($G12=1,Z12,(1+Z12)*(1+AF11)-1)) -> 0.15679552 | AG12: =IF($G12="","",AF12-AE12) -> -0.070248639 | AH12: =IF($G12="","",IF($G12=1,AB12,(1+AB12)*(1+AH11)-1)) -> 0.22641739 | AI12: =IF($G12="","",IF($G12=1,AC12,(1+AC12)*(1+AI11)-1)) -> 0.15618617 | AJ12: =IF($G12="","",AI12-AH12) -> -0.070231221 | AK12: =IF($G12="","",(1+AE12)^(1/G12)-1) -> 0.070582313 | AL12: =IF($G12="","",(1+AF12)^(1/G12)-1) -> 0.049749153 | AM12: =IF($G12="","",AL12-AK12) -> -0.02083316 | AN12: =IF($G12="","",(1+AH12)^(1/G12)-1) -> 0.0704 | AO12: =IF($G12="","",(1+AI12)^(1/G12)-1) -> 0.0495648 | AP12: =IF($G12="","",AO12-AN12) -> -0.0208352
G13: 4 | H13: =IF(G13="","",SUMIFS(Add_Contributions[[#All],[Amount ($)]],Add_Contributions[[#All],[Year]],G13)) -> 0 | I13: =IF($G13="","",IF($G13=1,(($C$2+$H13)*I$3)*(1+(I$4-I$5)),((I12+($H13*I$3))*(1+(I$4-I$5))))) -> 6530347 | J13: =IF($G13="","",IF($G13=1,(($C$2+$H13)*J$3)*(1+(J$4-J$5)),((J12+($H13*J$3))*(1+(J$4-J$5))))) -> 6081872.1 | K13: =IF($G13="","",IF($G13=1,(($C$2+$H13)*K$3)*(1+(K$4-K$5)),((K12+($H13*K$3))*(1+(K$4-K$5))))) -> 0 | L13: =IF($G13="","",IF($G13=1,(($C$2+$H13)*L$3)*(1+(L$4-L$5)),((L12+($H13*L$3))*(1+(L$4-L$5))))) -> 0 | M13: =IF($G13="","",IF($G13=1,(($C$2+$H13)*M$3)*(1+(M$4-M$5)),((M12+($H13*M$3))*(1+(M$4-M$5))))) -> 3889620 | N13: =IF($G13="","",IF($G13=1,(($C$2+$H13)*N$3)*(1+(N$4-N$5)),((N12+($H13*N$3))*(1+(N$4-N$5))))) -> 3596036.7 | O13: =IF($G13="","",IF($G13=1,(($C$2+$H13)*O$3)*(1+(O$4-O$5)),((O12+($H13*O$3))*(1+(O$4-O$5))))) -> 0 | P13: =IF($G13="","",IF($G13=1,(($C$2+$H13)*P$3)*(1+(P$4-P$5)),((P12+($H13*P$3))*(1+(P$4-P$5))))) -> 0 | ... T13: =IF($G13="","",IF($G13=1,(($C$2+$H13)*T$3)*(1+(T$4-T$5)),((T12+($H13*T$3))*(1+(T$4-T$5))))) -> 0 | U13: =IF(G13="","",SUM(I13,K13,M13,O13,Q13,S13)) -> 13140945 | V13: =IF(H13="","",SUM(J13,L13,N13,P13,R13,T13)) -> 12147677 | W13: =IF($G13="","",IF($G13=1,(($C$2+$H13)*W$3)*(1+(W$4-W$5)),((W12+($H13*W$3))*(1+(W$4-W$5))))) -> 13127572 | X13: =IF($G13="","",IF($G13=1,(($C$2+$H13)*X$3)*(1+(X$4-X$5)),((X12+($H13*X$3))*(1+(X$4-X$5))))) -> 12134923 | Y13: =IF($G13="","",IF($G13=1,(U13-$C$2-H13)/($C$2+H13),(U13-U12-H13)/(U12+H13))) -> 0.070943113 | Z13: =IF($G13="","",IF($G13=1,(V13-$C$2-H13)/($C$2+H13),(V13-V12-H13)/(V12+H13))) -> 0.050114419 | AA13: =IF($G13="","",Z13-Y13) -> -0.020828695 | AB13: =IF($G13="","",IF($G13=1,(W13-$C$2-H13)/($C$2+H13),(W13-W12-H13)/(W12+H13))) -> 0.0704 | AC13: =IF($G13="","",IF($G13=1,(X13-$C$2-H13)/($C$2+H13),(X13-X12-H13)/(X12+H13))) -> 0.0495648 | AD13: =IF($G13="","",AC13-AB13) -> -0.0208352 | AE13: =IF($G13="","",IF($G13=1,Y13,(1+Y13)*(1+AE12)-1)) -> 0.31409449 | AF13: =IF($G13="","",IF($G13=1,Z13,(1+Z13)*(1+AF12)-1)) -> 0.21476766 | AG13: =IF($G13="","",AF13-AE13) -> -0.099326837 | AH13: =IF($G13="","",IF($G13=1,AB13,(1+AB13)*(1+AH12)-1)) -> 0.31275718 | AI13: =IF($G13="","",IF($G13=1,AC13,(1+AC13)*(1+AI12)-1)) -> 0.21349231 | AJ13: =IF($G13="","",AI13-AH13) -> -0.099264869 | AK13: =IF($G13="","",(1+AE13)^(1/G13)-1) -> 0.070672502 | AL13: =IF($G13="","",(1+AF13)^(1/G13)-1) -> 0.049840457 | AM13: =IF($G13="","",AL13-AK13) -> -0.020832044 | AN13: =IF($G13="","",(1+AH13)^(1/G13)-1) -> 0.0704 | AO13: =IF($G13="","",(1+AI13)^(1/G13)-1) -> 0.0495648 | AP13: =IF($G13="","",AO13-AN13) -> -0.0208352
B14: Federal Income Tax | C14: ='Return Simulator'!D61 -> 0.37 | G14: 5 | H14: =IF(G14="","",SUMIFS(Add_Contributions[[#All],[Amount ($)]],Add_Contributions[[#All],[Year]],G14)) -> 0 | I14: =IF($G14="","",IF($G14=1,(($C$2+$H14)*I$3)*(1+(I$4-I$5)),((I13+($H14*I$3))*(1+(I$4-I$5))))) -> 7052774.8 | J14: =IF($G14="","",IF($G14=1,(($C$2+$H14)*J$3)*(1+(J$4-J$5)),((J13+($H14*J$3))*(1+(J$4-J$5))))) -> 6452623 | K14: =IF($G14="","",IF($G14=1,(($C$2+$H14)*K$3)*(1+(K$4-K$5)),((K13+($H14*K$3))*(1+(K$4-K$5))))) -> 0 | L14: =IF($G14="","",IF($G14=1,(($C$2+$H14)*L$3)*(1+(L$4-L$5)),((L13+($H14*L$3))*(1+(L$4-L$5))))) -> 0 | M14: =IF($G14="","",IF($G14=1,(($C$2+$H14)*M$3)*(1+(M$4-M$5)),((M13+($H14*M$3))*(1+(M$4-M$5))))) -> 4084101 | N14: =IF($G14="","",IF($G14=1,(($C$2+$H14)*N$3)*(1+(N$4-N$5)),((N13+($H14*N$3))*(1+(N$4-N$5))))) -> 3702479.4 | O14: =IF($G14="","",IF($G14=1,(($C$2+$H14)*O$3)*(1+(O$4-O$5)),((O13+($H14*O$3))*(1+(O$4-O$5))))) -> 0 | P14: =IF($G14="","",IF($G14=1,(($C$2+$H14)*P$3)*(1+(P$4-P$5)),((P13+($H14*P$3))*(1+(P$4-P$5))))) -> 0 | ... T14: =IF($G14="","",IF($G14=1,(($C$2+$H14)*T$3)*(1+(T$4-T$5)),((T13+($H14*T$3))*(1+(T$4-T$5))))) -> 0 | U14: =IF(G14="","",SUM(I14,K14,M14,O14,Q14,S14)) -> 14075532 | V14: =IF(H14="","",SUM(J14,L14,N14,P14,R14,T14)) -> 12758633 | W14: =IF($G14="","",IF($G14=1,(($C$2+$H14)*W$3)*(1+(W$4-W$5)),((W13+($H14*W$3))*(1+(W$4-W$5))))) -> 14051753 | X14: =IF($G14="","",IF($G14=1,(($C$2+$H14)*X$3)*(1+(X$4-X$5)),((X13+($H14*X$3))*(1+(X$4-X$5))))) -> 12736388 | Y14: =IF($G14="","",IF($G14=1,(U14-$C$2-H14)/($C$2+H14),(U14-U13-H14)/(U13+H14))) -> 0.071120228 | Z14: =IF($G14="","",IF($G14=1,(V14-$C$2-H14)/($C$2+H14),(V14-V13-H14)/(V13+H14))) -> 0.050294081 | AA14: =IF($G14="","",Z14-Y14) -> -0.020826146 | AB14: =IF($G14="","",IF($G14=1,(W14-$C$2-H14)/($C$2+H14),(W14-W13-H14)/(W13+H14))) -> 0.0704 | AC14: =IF($G14="","",IF($G14=1,(X14-$C$2-H14)/($C$2+H14),(X14-X13-H14)/(X13+H14))) -> 0.0495648 | AD14: =IF($G14="","",AC14-AB14) -> -0.0208352 | AE14: =IF($G14="","",IF($G14=1,Y14,(1+Y14)*(1+AE13)-1)) -> 0.40755319 | AF14: =IF($G14="","",IF($G14=1,Z14,(1+Z14)*(1+AF13)-1)) -> 0.27586328 | AG14: =IF($G14="","",AF14-AE14) -> -0.13168991 | AH14: =IF($G14="","",IF($G14=1,AB14,(1+AB14)*(1+AH13)-1)) -> 0.40517528 | AI14: =IF($G14="","",IF($G14=1,AC14,(1+AC14)*(1+AI13)-1)) -> 0.27363881 | AJ14: =IF($G14="","",AI14-AH14) -> -0.13153647 | AK14: =IF($G14="","",(1+AE14)^(1/G14)-1) -> 0.070762032 | AL14: =IF($G14="","",(1+AF14)^(1/G14)-1) -> 0.049931166 | AM14: =IF($G14="","",AL14-AK14) -> -0.020830866 | AN14: =IF($G14="","",(1+AH14)^(1/G14)-1) -> 0.0704 | AO14: =IF($G14="","",(1+AI14)^(1/G14)-1) -> 0.0495648 | AP14: =IF($G14="","",AO14-AN14) -> -0.0208352
B15: Capital Gains Tax | C15: ='Return Simulator'!D62 -> 0.2 | G15: 6 | H15: =IF(G15="","",SUMIFS(Add_Contributions[[#All],[Amount ($)]],Add_Contributions[[#All],[Year]],G15)) -> 0 | I15: =IF($G15="","",IF($G15=1,(($C$2+$H15)*I$3)*(1+(I$4-I$5)),((I14+($H15*I$3))*(1+(I$4-I$5))))) -> 7616996.8 | J15: =IF($G15="","",IF($G15=1,(($C$2+$H15)*J$3)*(1+(J$4-J$5)),((J14+($H15*J$3))*(1+(J$4-J$5))))) -> 6845974.9 | K15: =IF($G15="","",IF($G15=1,(($C$2+$H15)*K$3)*(1+(K$4-K$5)),((K14+($H15*K$3))*(1+(K$4-K$5))))) -> 0 | L15: =IF($G15="","",IF($G15=1,(($C$2+$H15)*L$3)*(1+(L$4-L$5)),((L14+($H15*L$3))*(1+(L$4-L$5))))) -> 0 | M15: =IF($G15="","",IF($G15=1,(($C$2+$H15)*M$3)*(1+(M$4-M$5)),((M14+($H15*M$3))*(1+(M$4-M$5))))) -> 4288306 | N15: =IF($G15="","",IF($G15=1,(($C$2+$H15)*N$3)*(1+(N$4-N$5)),((N14+($H15*N$3))*(1+(N$4-N$5))))) -> 3812072.8 | O15: =IF($G15="","",IF($G15=1,(($C$2+$H15)*O$3)*(1+(O$4-O$5)),((O14+($H15*O$3))*(1+(O$4-O$5))))) -> 0 | P15: =IF($G15="","",IF($G15=1,(($C$2+$H15)*P$3)*(1+(P$4-P$5)),((P14+($H15*P$3))*(1+(P$4-P$5))))) -> 0 | ... T15: =IF($G15="","",IF($G15=1,(($C$2+$H15)*T$3)*(1+(T$4-T$5)),((T14+($H15*T$3))*(1+(T$4-T$5))))) -> 0 | U15: =IF(G15="","",SUM(I15,K15,M15,O15,Q15,S15)) -> 15079051 | V15: =IF(H15="","",SUM(J15,L15,N15,P15,R15,T15)) -> 13402585 | W15: =IF($G15="","",IF($G15=1,(($C$2+$H15)*W$3)*(1+(W$4-W$5)),((W14+($H15*W$3))*(1+(W$4-W$5))))) -> 15040996 | X15: =IF($G15="","",IF($G15=1,(($C$2+$H15)*X$3)*(1+(X$4-X$5)),((X14+($H15*X$3))*(1+(X$4-X$5))))) -> 13367665 | Y15: =IF($G15="","",IF($G15=1,(U15-$C$2-H15)/($C$2+H15),(U15-U14-H15)/(U14+H15))) -> 0.071295318 | Z15: =IF($G15="","",IF($G15=1,(V15-$C$2-H15)/($C$2+H15),(V15-V14-H15)/(V14+H15))) -> 0.050471904 | AA15: =IF($G15="","",Z15-Y15) -> -0.020823414 | AB15: =IF($G15="","",IF($G15=1,(W15-$C$2-H15)/($C$2+H15),(W15-W14-H15)/(W14+H15))) -> 0.0704 | AC15: =IF($G15="","",IF($G15=1,(X15-$C$2-H15)/($C$2+H15),(X15-X14-H15)/(X14+H15))) -> 0.0495648 | AD15: =IF($G15="","",AC15-AB15) -> -0.0208352 | AE15: =IF($G15="","",IF($G15=1,Y15,(1+Y15)*(1+AE14)-1)) -> 0.50790514 | AF15: =IF($G15="","",IF($G15=1,Z15,(1+Z15)*(1+AF14)-1)) -> 0.34025853 | AG15: =IF($G15="","",AF15-AE15) -> -0.16764662 | AH15: =IF($G15="","",IF($G15=1,AB15,(1+AB15)*(1+AH14)-1)) -> 0.50409962 | AI15: =IF($G15="","",IF($G15=1,AC15,(1+AC15)*(1+AI14)-1)) -> 0.33676647 | AJ15: =IF($G15="","",AI15-AH15) -> -0.16733316 | AK15: =IF($G15="","",(1+AE15)^(1/G15)-1) -> 0.070850895 | AL15: =IF($G15="","",(1+AF15)^(1/G15)-1) -> 0.05002127 | AM15: =IF($G15="","",AL15-AK15) -> -0.020829624 | AN15: =IF($G15="","",(1+AH15)^(1/G15)-1) -> 0.0704 | AO15: =IF($G15="","",(1+AI15)^(1/G15)-1) -> 0.0495648 | AP15: =IF($G15="","",AO15-AN15) -> -0.0208352
B16: Net Investment Income Tax | C16: ='Return Simulator'!D63 -> 0.038 | G16: 7 | H16: =IF(G16="","",SUMIFS(Add_Contributions[[#All],[Amount ($)]],Add_Contributions[[#All],[Year]],G16)) -> 0 | I16: =IF($G16="","",IF($G16=1,(($C$2+$H16)*I$3)*(1+(I$4-I$5)),((I15+($H16*I$3))*(1+(I$4-I$5))))) -> 8226356.5 | J16: =IF($G16="","",IF($G16=1,(($C$2+$H16)*J$3)*(1+(J$4-J$5)),((J15+($H16*J$3))*(1+(J$4-J$5))))) -> 7263305.5 | K16: =IF($G16="","",IF($G16=1,(($C$2+$H16)*K$3)*(1+(K$4-K$5)),((K15+($H16*K$3))*(1+(K$4-K$5))))) -> 0 | L16: =IF($G16="","",IF($G16=1,(($C$2+$H16)*L$3)*(1+(L$4-L$5)),((L15+($H16*L$3))*(1+(L$4-L$5))))) -> 0 | M16: =IF($G16="","",IF($G16=1,(($C$2+$H16)*M$3)*(1+(M$4-M$5)),((M15+($H16*M$3))*(1+(M$4-M$5))))) -> 4502721.4 | N16: =IF($G16="","",IF($G16=1,(($C$2+$H16)*N$3)*(1+(N$4-N$5)),((N15+($H16*N$3))*(1+(N$4-N$5))))) -> 3924910.1 | O16: =IF($G16="","",IF($G16=1,(($C$2+$H16)*O$3)*(1+(O$4-O$5)),((O15+($H16*O$3))*(1+(O$4-O$5))))) -> 0 | P16: =IF($G16="","",IF($G16=1,(($C$2+$H16)*P$3)*(1+(P$4-P$5)),((P15+($H16*P$3))*(1+(P$4-P$5))))) -> 0 | ... T16: =IF($G16="","",IF($G16=1,(($C$2+$H16)*T$3)*(1+(T$4-T$5)),((T15+($H16*T$3))*(1+(T$4-T$5))))) -> 0 | U16: =IF(G16="","",SUM(I16,K16,M16,O16,Q16,S16)) -> 16156726 | V16: =IF(H16="","",SUM(J16,L16,N16,P16,R16,T16)) -> 14081397 | W16: =IF($G16="","",IF($G16=1,(($C$2+$H16)*W$3)*(1+(W$4-W$5)),((W15+($H16*W$3))*(1+(W$4-W$5))))) -> 16099882 | X16: =IF($G16="","",IF($G16=1,(($C$2+$H16)*X$3)*(1+(X$4-X$5)),((X15+($H16*X$3))*(1+(X$4-X$5))))) -> 14030230 | Y16: =IF($G16="","",IF($G16=1,(U16-$C$2-H16)/($C$2+H16),(U16-U15-H16)/(U15+H16))) -> 0.071468351 | Z16: =IF($G16="","",IF($G16=1,(V16-$C$2-H16)/($C$2+H16),(V16-V15-H16)/(V15+H16))) -> 0.050647851 | AA16: =IF($G16="","",Z16-Y16) -> -0.0208205 | AB16: =IF($G16="","",IF($G16=1,(W16-$C$2-H16)/($C$2+H16),(W16-W15-H16)/(W15+H16))) -> 0.0704 | AC16: =IF($G16="","",IF($G16=1,(X16-$C$2-H16)/($C$2+H16),(X16-X15-H16)/(X15+H16))) -> 0.0495648 | AD16: =IF($G16="","",AC16-AB16) -> -0.0208352 | AE16: =IF($G16="","",IF($G16=1,Y16,(1+Y16)*(1+AE15)-1)) -> 0.61567264 | AF16: =IF($G16="","",IF($G16=1,Z16,(1+Z16)*(1+AF15)-1)) -> 0.40813974 | AG16: =IF($G16="","",AF16-AE16) -> -0.2075329 | AH16: =IF($G16="","",IF($G16=1,AB16,(1+AB16)*(1+AH15)-1)) -> 0.60998824 | AI16: =IF($G16="","",IF($G16=1,AC16,(1+AC16)*(1+AI15)-1)) -> 0.40302303 | AJ16: =IF($G16="","",AI16-AH16) -> -0.20696521 | AK16: =IF($G16="","",(1+AE16)^(1/G16)-1) -> 0.070939081 | AL16: =IF($G16="","",(1+AF16)^(1/G16)-1) -> 0.050110759 | AM16: =IF($G16="","",AL16-AK16) -> -0.020828322 | AN16: =IF($G16="","",(1+AH16)^(1/G16)-1) -> 0.0704 | AO16: =IF($G16="","",(1+AI16)^(1/G16)-1) -> 0.0495648 | AP16: =IF($G16="","",AO16-AN16) -> -0.0208352
B17: State Income Tax | G17: 8 | H17: =IF(G17="","",SUMIFS(Add_Contributions[[#All],[Amount ($)]],Add_Contributions[[#All],[Year]],G17)) -> 0 | I17: =IF($G17="","",IF($G17=1,(($C$2+$H17)*I$3)*(1+(I$4-I$5)),((I16+($H17*I$3))*(1+(I$4-I$5))))) -> 8884465 | J17: =IF($G17="","",IF($G17=1,(($C$2+$H17)*J$3)*(1+(J$4-J$5)),((J16+($H17*J$3))*(1+(J$4-J$5))))) -> 7706076.6 | K17: =IF($G17="","",IF($G17=1,(($C$2+$H17)*K$3)*(1+(K$4-K$5)),((K16+($H17*K$3))*(1+(K$4-K$5))))) -> 0 | L17: =IF($G17="","",IF($G17=1,(($C$2+$H17)*L$3)*(1+(L$4-L$5)),((L16+($H17*L$3))*(1+(L$4-L$5))))) -> 0 | M17: =IF($G17="","",IF($G17=1,(($C$2+$H17)*M$3)*(1+(M$4-M$5)),((M16+($H17*M$3))*(1+(M$4-M$5))))) -> 4727857.4 | N17: =IF($G17="","",IF($G17=1,(($C$2+$H17)*N$3)*(1+(N$4-N$5)),((N16+($H17*N$3))*(1+(N$4-N$5))))) -> 4041087.5 | O17: =IF($G17="","",IF($G17=1,(($C$2+$H17)*O$3)*(1+(O$4-O$5)),((O16+($H17*O$3))*(1+(O$4-O$5))))) -> 0 | P17: =IF($G17="","",IF($G17=1,(($C$2+$H17)*P$3)*(1+(P$4-P$5)),((P16+($H17*P$3))*(1+(P$4-P$5))))) -> 0 | ... T17: =IF($G17="","",IF($G17=1,(($C$2+$H17)*T$3)*(1+(T$4-T$5)),((T16+($H17*T$3))*(1+(T$4-T$5))))) -> 0 | U17: =IF(G17="","",SUM(I17,K17,M17,O17,Q17,S17)) -> 17314183 | V17: =IF(H17="","",SUM(J17,L17,N17,P17,R17,T17)) -> 14797041 | W17: =IF($G17="","",IF($G17=1,(($C$2+$H17)*W$3)*(1+(W$4-W$5)),((W16+($H17*W$3))*(1+(W$4-W$5))))) -> 17233314 | X17: =IF($G17="","",IF($G17=1,(($C$2+$H17)*X$3)*(1+(X$4-X$5)),((X16+($H17*X$3))*(1+(X$4-X$5))))) -> 14725636 | Y17: =IF($G17="","",IF($G17=1,(U17-$C$2-H17)/($C$2+H17),(U17-U16-H17)/(U16+H17))) -> 0.071639294 | Z17: =IF($G17="","",IF($G17=1,(V17-$C$2-H17)/($C$2+H17),(V17-V16-H17)/(V16+H17))) -> 0.050821886 | AA17: =IF($G17="","",Z17-Y17) -> -0.020817408 | AB17: =IF($G17="","",IF($G17=1,(W17-$C$2-H17)/($C$2+H17),(W17-W16-H17)/(W16+H17))) -> 0.0704 | AC17: =IF($G17="","",IF($G17=1,(X17-$C$2-H17)/($C$2+H17),(X17-X16-H17)/(X16+H17))) -> 0.0495648 | AD17: =IF($G17="","",AC17-AB17) -> -0.0208352 | AE17: =IF($G17="","",IF($G17=1,Y17,(1+Y17)*(1+AE16)-1)) -> 0.73141829 | AF17: =IF($G17="","",IF($G17=1,Z17,(1+Z17)*(1+AF16)-1)) -> 0.47970406 | AG17: =IF($G17="","",AF17-AE17) -> -0.25171423 | AH17: =IF($G17="","",IF($G17=1,AB17,(1+AB17)*(1+AH16)-1)) -> 0.72333141 | AI17: =IF($G17="","",IF($G17=1,AC17,(1+AC17)*(1+AI16)-1)) -> 0.47256358 | AJ17: =IF($G17="","",AI17-AH17) -> -0.25076783 | AK17: =IF($G17="","",(1+AE17)^(1/G17)-1) -> 0.071026582 | AL17: =IF($G17="","",(1+AF17)^(1/G17)-1) -> 0.050199623 | AM17: =IF($G17="","",AL17-AK17) -> -0.020826959 | AN17: =IF($G17="","",(1+AH17)^(1/G17)-1) -> 0.0704 | AO17: =IF($G17="","",(1+AI17)^(1/G17)-1) -> 0.0495648 | AP17: =IF($G17="","",AO17-AN17) -> -0.0208352
G18: 9 | H18: =IF(G18="","",SUMIFS(Add_Contributions[[#All],[Amount ($)]],Add_Contributions[[#All],[Year]],G18)) -> 0 | I18: =IF($G18="","",IF($G18=1,(($C$2+$H18)*I$3)*(1+(I$4-I$5)),((I17+($H18*I$3))*(1+(I$4-I$5))))) -> 9595222.2 | J18: =IF($G18="","",IF($G18=1,(($C$2+$H18)*J$3)*(1+(J$4-J$5)),((J17+($H18*J$3))*(1+(J$4-J$5))))) -> 8175839 | K18: =IF($G18="","",IF($G18=1,(($C$2+$H18)*K$3)*(1+(K$4-K$5)),((K17+($H18*K$3))*(1+(K$4-K$5))))) -> 0 | L18: =IF($G18="","",IF($G18=1,(($C$2+$H18)*L$3)*(1+(L$4-L$5)),((L17+($H18*L$3))*(1+(L$4-L$5))))) -> 0 | M18: =IF($G18="","",IF($G18=1,(($C$2+$H18)*M$3)*(1+(M$4-M$5)),((M17+($H18*M$3))*(1+(M$4-M$5))))) -> 4964250.3 | N18: =IF($G18="","",IF($G18=1,(($C$2+$H18)*N$3)*(1+(N$4-N$5)),((N17+($H18*N$3))*(1+(N$4-N$5))))) -> 4160703.6 | O18: =IF($G18="","",IF($G18=1,(($C$2+$H18)*O$3)*(1+(O$4-O$5)),((O17+($H18*O$3))*(1+(O$4-O$5))))) -> 0 | P18: =IF($G18="","",IF($G18=1,(($C$2+$H18)*P$3)*(1+(P$4-P$5)),((P17+($H18*P$3))*(1+(P$4-P$5))))) -> 0 | ... T18: =IF($G18="","",IF($G18=1,(($C$2+$H18)*T$3)*(1+(T$4-T$5)),((T17+($H18*T$3))*(1+(T$4-T$5))))) -> 0 | U18: =IF(G18="","",SUM(I18,K18,M18,O18,Q18,S18)) -> 18557482 | V18: =IF(H18="","",SUM(J18,L18,N18,P18,R18,T18)) -> 15551601 | W18: =IF($G18="","",IF($G18=1,(($C$2+$H18)*W$3)*(1+(W$4-W$5)),((W17+($H18*W$3))*(1+(W$4-W$5))))) -> 18446539 | X18: =IF($G18="","",IF($G18=1,(($C$2+$H18)*X$3)*(1+(X$4-X$5)),((X17+($H18*X$3))*(1+(X$4-X$5))))) -> 15455509 | Y18: =IF($G18="","",IF($G18=1,(U18-$C$2-H18)/($C$2+H18),(U18-U17-H18)/(U17+H18))) -> 0.071808119 | Z18: =IF($G18="","",IF($G18=1,(V18-$C$2-H18)/($C$2+H18),(V18-V17-H18)/(V17+H18))) -> 0.050993976 | AA18: =IF($G18="","",Z18-Y18) -> -0.020814143 | AB18: =IF($G18="","",IF($G18=1,(W18-$C$2-H18)/($C$2+H18),(W18-W17-H18)/(W17+H18))) -> 0.0704 | AC18: =IF($G18="","",IF($G18=1,(X18-$C$2-H18)/($C$2+H18),(X18-X17-H18)/(X17+H18))) -> 0.0495648 | AD18: =IF($G18="","",AC18-AB18) -> -0.0208352 | AE18: =IF($G18="","",IF($G18=1,Y18,(1+Y18)*(1+AE17)-1)) -> 0.85574818 | AF18: =IF($G18="","",IF($G18=1,Z18,(1+Z18)*(1+AF17)-1)) -> 0.55516005 | AG18: =IF($G18="","",AF18-AE18) -> -0.30058812 | AH18: =IF($G18="","",IF($G18=1,AB18,(1+AB18)*(1+AH17)-1)) -> 0.84465394 | AI18: =IF($G18="","",IF($G18=1,AC18,(1+AC18)*(1+AI17)-1)) -> 0.5455509 | AJ18: =IF($G18="","",AI18-AH18) -> -0.29910304 | AK18: =IF($G18="","",(1+AE18)^(1/G18)-1) -> 0.071113392 | AL18: =IF($G18="","",(1+AF18)^(1/G18)-1) -> 0.050287855 | AM18: =IF($G18="","",AL18-AK18) -> -0.020825537 | AN18: =IF($G18="","",(1+AH18)^(1/G18)-1) -> 0.0704 | AO18: =IF($G18="","",(1+AI18)^(1/G18)-1) -> 0.0495648 | AP18: =IF($G18="","",AO18-AN18) -> -0.0208352
G19: 10 | H19: =IF(G19="","",SUMIFS(Add_Contributions[[#All],[Amount ($)]],Add_Contributions[[#All],[Year]],G19)) -> 0 | I19: =IF($G19="","",IF($G19=1,(($C$2+$H19)*I$3)*(1+(I$4-I$5)),((I18+($H19*I$3))*(1+(I$4-I$5))))) -> 10362840 | J19: =IF($G19="","",IF($G19=1,(($C$2+$H19)*J$3)*(1+(J$4-J$5)),((J18+($H19*J$3))*(1+(J$4-J$5))))) -> 8674238.2 | K19: =IF($G19="","",IF($G19=1,(($C$2+$H19)*K$3)*(1+(K$4-K$5)),((K18+($H19*K$3))*(1+(K$4-K$5))))) -> 0 | L19: =IF($G19="","",IF($G19=1,(($C$2+$H19)*L$3)*(1+(L$4-L$5)),((L18+($H19*L$3))*(1+(L$4-L$5))))) -> 0 | M19: =IF($G19="","",IF($G19=1,(($C$2+$H19)*M$3)*(1+(M$4-M$5)),((M18+($H19*M$3))*(1+(M$4-M$5))))) -> 5212462.8 | N19: =IF($G19="","",IF($G19=1,(($C$2+$H19)*N$3)*(1+(N$4-N$5)),((N18+($H19*N$3))*(1+(N$4-N$5))))) -> 4283860.5 | O19: =IF($G19="","",IF($G19=1,(($C$2+$H19)*O$3)*(1+(O$4-O$5)),((O18+($H19*O$3))*(1+(O$4-O$5))))) -> 0 | P19: =IF($G19="","",IF($G19=1,(($C$2+$H19)*P$3)*(1+(P$4-P$5)),((P18+($H19*P$3))*(1+(P$4-P$5))))) -> 0 | ... T19: =IF($G19="","",IF($G19=1,(($C$2+$H19)*T$3)*(1+(T$4-T$5)),((T18+($H19*T$3))*(1+(T$4-T$5))))) -> 0 | U19: =IF(G19="","",SUM(I19,K19,M19,O19,Q19,S19)) -> 19893153 | V19: =IF(H19="","",SUM(J19,L19,N19,P19,R19,T19)) -> 16347284 | W19: =IF($G19="","",IF($G19=1,(($C$2+$H19)*W$3)*(1+(W$4-W$5)),((W18+($H19*W$3))*(1+(W$4-W$5))))) -> 19745176 | X19: =IF($G19="","",IF($G19=1,(($C$2+$H19)*X$3)*(1+(X$4-X$5)),((X18+($H19*X$3))*(1+(X$4-X$5))))) -> 16221558 | Y19: =IF($G19="","",IF($G19=1,(U19-$C$2-H19)/($C$2+H19),(U19-U18-H19)/(U18+H19))) -> 0.0719748 | Z19: =IF($G19="","",IF($G19=1,(V19-$C$2-H19)/($C$2+H19),(V19-V18-H19)/(V18+H19))) -> 0.051164091 | AA19: =IF($G19="","",Z19-Y19) -> -0.020810708 | AB19: =IF($G19="","",IF($G19=1,(W19-$C$2-H19)/($C$2+H19),(W19-W18-H19)/(W18+H19))) -> 0.0704 | AC19: =IF($G19="","",IF($G19=1,(X19-$C$2-H19)/($C$2+H19),(X19-X18-H19)/(X18+H19))) -> 0.0495648 | AD19: =IF($G19="","",AC19-AB19) -> -0.0208352 | AE19: =IF($G19="","",IF($G19=1,Y19,(1+Y19)*(1+AE18)-1)) -> 0.98931528 | AF19: =IF($G19="","",IF($G19=1,Z19,(1+Z19)*(1+AF18)-1)) -> 0.6347284 | AG19: =IF($G19="","",AF19-AE19) -> -0.35458687 | AH19: =IF($G19="","",IF($G19=1,AB19,(1+AB19)*(1+AH18)-1)) -> 0.97451758 | AI19: =IF($G19="","",IF($G19=1,AC19,(1+AC19)*(1+AI18)-1)) -> 0.62215582 | AJ19: =IF($G19="","",AI19-AH19) -> -0.35236175 | AK19: =IF($G19="","",(1+AE19)^(1/G19)-1) -> 0.071199501 | AL19: =IF($G19="","",(1+AF19)^(1/G19)-1) -> 0.050375446 | AM19: =IF($G19="","",AL19-AK19) -> -0.020824056 | AN19: =IF($G19="","",(1+AH19)^(1/G19)-1) -> 0.0704 | AO19: =IF($G19="","",(1+AI19)^(1/G19)-1) -> 0.0495648 | AP19: =IF($G19="","",AO19-AN19) -> -0.0208352
G20: 11 | H20: =IF(G20="","",SUMIFS(Add_Contributions[[#All],[Amount ($)]],Add_Contributions[[#All],[Year]],G20)) -> 0 | I20: =IF($G20="","",IF($G20=1,(($C$2+$H20)*I$3)*(1+(I$4-I$5)),((I19+($H20*I$3))*(1+(I$4-I$5))))) -> 11191867 | J20: =IF($G20="","",IF($G20=1,(($C$2+$H20)*J$3)*(1+(J$4-J$5)),((J19+($H20*J$3))*(1+(J$4-J$5))))) -> 9203019.7 | K20: =IF($G20="","",IF($G20=1,(($C$2+$H20)*K$3)*(1+(K$4-K$5)),((K19+($H20*K$3))*(1+(K$4-K$5))))) -> 0 | L20: =IF($G20="","",IF($G20=1,(($C$2+$H20)*L$3)*(1+(L$4-L$5)),((L19+($H20*L$3))*(1+(L$4-L$5))))) -> 0 | M20: =IF($G20="","",IF($G20=1,(($C$2+$H20)*M$3)*(1+(M$4-M$5)),((M19+($H20*M$3))*(1+(M$4-M$5))))) -> 5473085.9 | N20: =IF($G20="","",IF($G20=1,(($C$2+$H20)*N$3)*(1+(N$4-N$5)),((N19+($H20*N$3))*(1+(N$4-N$5))))) -> 4410662.7 | O20: =IF($G20="","",IF($G20=1,(($C$2+$H20)*O$3)*(1+(O$4-O$5)),((O19+($H20*O$3))*(1+(O$4-O$5))))) -> 0 | P20: =IF($G20="","",IF($G20=1,(($C$2+$H20)*P$3)*(1+(P$4-P$5)),((P19+($H20*P$3))*(1+(P$4-P$5))))) -> 0 | ... T20: =IF($G20="","",IF($G20=1,(($C$2+$H20)*T$3)*(1+(T$4-T$5)),((T19+($H20*T$3))*(1+(T$4-T$5))))) -> 0 | U20: =IF(G20="","",SUM(I20,K20,M20,O20,Q20,S20)) -> 21328231 | V20: =IF(H20="","",SUM(J20,L20,N20,P20,R20,T20)) -> 17186426 | W20: =IF($G20="","",IF($G20=1,(($C$2+$H20)*W$3)*(1+(W$4-W$5)),((W19+($H20*W$3))*(1+(W$4-W$5))))) -> 21135236 | X20: =IF($G20="","",IF($G20=1,(($C$2+$H20)*X$3)*(1+(X$4-X$5)),((X19+($H20*X$3))*(1+(X$4-X$5))))) -> 17025577 | Y20: =IF($G20="","",IF($G20=1,(U20-$C$2-H20)/($C$2+H20),(U20-U19-H20)/(U19+H20))) -> 0.072139311 | Z20: =IF($G20="","",IF($G20=1,(V20-$C$2-H20)/($C$2+H20),(V20-V19-H20)/(V19+H20))) -> 0.051332203 | AA20: =IF($G20="","",Z20-Y20) -> -0.020807108 | AB20: =IF($G20="","",IF($G20=1,(W20-$C$2-H20)/($C$2+H20),(W20-W19-H20)/(W19+H20))) -> 0.0704 | AC20: =IF($G20="","",IF($G20=1,(X20-$C$2-H20)/($C$2+H20),(X20-X19-H20)/(X19+H20))) -> 0.0495648 | AD20: =IF($G20="","",AC20-AB20) -> -0.0208352 | AE20: =IF($G20="","",IF($G20=1,Y20,(1+Y20)*(1+AE19)-1)) -> 1.1328231 | AF20: =IF($G20="","",IF($G20=1,Z20,(1+Z20)*(1+AF19)-1)) -> 0.71864261 | AG20: =IF($G20="","",AF20-AE20) -> -0.4141805 | AH20: =IF($G20="","",IF($G20=1,AB20,(1+AB20)*(1+AH19)-1)) -> 1.1135236 | AI20: =IF($G20="","",IF($G20=1,AC20,(1+AC20)*(1+AI19)-1)) -> 0.70255765 | AJ20: =IF($G20="","",AI20-AH20) -> -0.41096596 | AK20: =IF($G20="","",(1+AE20)^(1/G20)-1) -> 0.071284905 | AL20: =IF($G20="","",(1+AF20)^(1/G20)-1) -> 0.050462388 | AM20: =IF($G20="","",AL20-AK20) -> -0.020822517 | AN20: =IF($G20="","",(1+AH20)^(1/G20)-1) -> 0.0704 | AO20: =IF($G20="","",(1+AI20)^(1/G20)-1) -> 0.0495648 | AP20: =IF($G20="","",AO20-AN20) -> -0.0208352
B21: Metrics | C21: Buy & Hold | D21: Rebalanced | G21: 12 | H21: =IF(G21="","",SUMIFS(Add_Contributions[[#All],[Amount ($)]],Add_Contributions[[#All],[Year]],G21)) -> 0 | I21: =IF($G21="","",IF($G21=1,(($C$2+$H21)*I$3)*(1+(I$4-I$5)),((I20+($H21*I$3))*(1+(I$4-I$5))))) -> 12087217 | J21: =IF($G21="","",IF($G21=1,(($C$2+$H21)*J$3)*(1+(J$4-J$5)),((J20+($H21*J$3))*(1+(J$4-J$5))))) -> 9764035.8 | K21: =IF($G21="","",IF($G21=1,(($C$2+$H21)*K$3)*(1+(K$4-K$5)),((K20+($H21*K$3))*(1+(K$4-K$5))))) -> 0 | L21: =IF($G21="","",IF($G21=1,(($C$2+$H21)*L$3)*(1+(L$4-L$5)),((L20+($H21*L$3))*(1+(L$4-L$5))))) -> 0 | M21: =IF($G21="","",IF($G21=1,(($C$2+$H21)*M$3)*(1+(M$4-M$5)),((M20+($H21*M$3))*(1+(M$4-M$5))))) -> 5746740.2 | N21: =IF($G21="","",IF($G21=1,(($C$2+$H21)*N$3)*(1+(N$4-N$5)),((N20+($H21*N$3))*(1+(N$4-N$5))))) -> 4541218.4 | O21: =IF($G21="","",IF($G21=1,(($C$2+$H21)*O$3)*(1+(O$4-O$5)),((O20+($H21*O$3))*(1+(O$4-O$5))))) -> 0 | P21: =IF($G21="","",IF($G21=1,(($C$2+$H21)*P$3)*(1+(P$4-P$5)),((P20+($H21*P$3))*(1+(P$4-P$5))))) -> 0 | ... T21: =IF($G21="","",IF($G21=1,(($C$2+$H21)*T$3)*(1+(T$4-T$5)),((T20+($H21*T$3))*(1+(T$4-T$5))))) -> 0 | U21: =IF(G21="","",SUM(I21,K21,M21,O21,Q21,S21)) -> 22870297 | V21: =IF(H21="","",SUM(J21,L21,N21,P21,R21,T21)) -> 18071498 | W21: =IF($G21="","",IF($G21=1,(($C$2+$H21)*W$3)*(1+(W$4-W$5)),((W20+($H21*W$3))*(1+(W$4-W$5))))) -> 22623157 | X21: =IF($G21="","",IF($G21=1,(($C$2+$H21)*X$3)*(1+(X$4-X$5)),((X20+($H21*X$3))*(1+(X$4-X$5))))) -> 17869446 | Y21: =IF($G21="","",IF($G21=1,(U21-$C$2-H21)/($C$2+H21),(U21-U20-H21)/(U20+H21))) -> 0.072301632 | Z21: =IF($G21="","",IF($G21=1,(V21-$C$2-H21)/($C$2+H21),(V21-V20-H21)/(V20+H21))) -> 0.051498286 | AA21: =IF($G21="","",Z21-Y21) -> -0.020803345 | AB21: =IF($G21="","",IF($G21=1,(W21-$C$2-H21)/($C$2+H21),(W21-W20-H21)/(W20+H21))) -> 0.0704 | AC21: =IF($G21="","",IF($G21=1,(X21-$C$2-H21)/($C$2+H21),(X21-X20-H21)/(X20+H21))) -> 0.0495648 | AD21: =IF($G21="","",AC21-AB21) -> -0.0208352 | AE21: =IF($G21="","",IF($G21=1,Y21,(1+Y21)*(1+AE20)-1)) -> 1.2870297 | AF21: =IF($G21="","",IF($G21=1,Z21,(1+Z21)*(1+AF20)-1)) -> 0.80714976 | AG21: =IF($G21="","",AF21-AE21) -> -0.47987994 | AH21: =IF($G21="","",IF($G21=1,AB21,(1+AB21)*(1+AH20)-1)) -> 1.2623157 | AI21: =IF($G21="","",IF($G21=1,AC21,(1+AC21)*(1+AI20)-1)) -> 0.78694458 | AJ21: =IF($G21="","",AI21-AH21) -> -0.47537109 | AK21: =IF($G21="","",(1+AE21)^(1/G21)-1) -> 0.071369595 | AL21: =IF($G21="","",(1+AF21)^(1/G21)-1) -> 0.050548674 | AM21: =IF($G21="","",AL21-AK21) -> -0.020820921 | AN21: =IF($G21="","",(1+AH21)^(1/G21)-1) -> 0.0704 | AO21: =IF($G21="","",(1+AI21)^(1/G21)-1) -> 0.0495648 | AP21: =IF($G21="","",AO21-AN21) -> -0.0208352
B22: Projected Value | C22: =_xlfn.XLOOKUP(C3,G:G,V:V) -> 27153622 | D22: =_xlfn.XLOOKUP(C3,G:G,X:X) -> 26313895 | G22: 13 | H22: =IF(G22="","",SUMIFS(Add_Contributions[[#All],[Amount ($)]],Add_Contributions[[#All],[Year]],G22)) -> 0 | I22: =IF($G22="","",IF($G22=1,(($C$2+$H22)*I$3)*(1+(I$4-I$5)),((I21+($H22*I$3))*(1+(I$4-I$5))))) -> 13054194 | J22: =IF($G22="","",IF($G22=1,(($C$2+$H22)*J$3)*(1+(J$4-J$5)),((J21+($H22*J$3))*(1+(J$4-J$5))))) -> 10359251 | K22: =IF($G22="","",IF($G22=1,(($C$2+$H22)*K$3)*(1+(K$4-K$5)),((K21+($H22*K$3))*(1+(K$4-K$5))))) -> 0 | L22: =IF($G22="","",IF($G22=1,(($C$2+$H22)*L$3)*(1+(L$4-L$5)),((L21+($H22*L$3))*(1+(L$4-L$5))))) -> 0 | M22: =IF($G22="","",IF($G22=1,(($C$2+$H22)*M$3)*(1+(M$4-M$5)),((M21+($H22*M$3))*(1+(M$4-M$5))))) -> 6034077.3 | N22: =IF($G22="","",IF($G22=1,(($C$2+$H22)*N$3)*(1+(N$4-N$5)),((N21+($H22*N$3))*(1+(N$4-N$5))))) -> 4675638.4 | O22: =IF($G22="","",IF($G22=1,(($C$2+$H22)*O$3)*(1+(O$4-O$5)),((O21+($H22*O$3))*(1+(O$4-O$5))))) -> 0 | P22: =IF($G22="","",IF($G22=1,(($C$2+$H22)*P$3)*(1+(P$4-P$5)),((P21+($H22*P$3))*(1+(P$4-P$5))))) -> 0 | ... T22: =IF($G22="","",IF($G22=1,(($C$2+$H22)*T$3)*(1+(T$4-T$5)),((T21+($H22*T$3))*(1+(T$4-T$5))))) -> 0 | U22: =IF(G22="","",SUM(I22,K22,M22,O22,Q22,S22)) -> 24527519 | V22: =IF(H22="","",SUM(J22,L22,N22,P22,R22,T22)) -> 19005113 | W22: =IF($G22="","",IF($G22=1,(($C$2+$H22)*W$3)*(1+(W$4-W$5)),((W21+($H22*W$3))*(1+(W$4-W$5))))) -> 24215827 | X22: =IF($G22="","",IF($G22=1,(($C$2+$H22)*X$3)*(1+(X$4-X$5)),((X21+($H22*X$3))*(1+(X$4-X$5))))) -> 18755141 | Y22: =IF($G22="","",IF($G22=1,(U22-$C$2-H22)/($C$2+H22),(U22-U21-H22)/(U21+H22))) -> 0.072461742 | Z22: =IF($G22="","",IF($G22=1,(V22-$C$2-H22)/($C$2+H22),(V22-V21-H22)/(V21+H22))) -> 0.051662317 | AA22: =IF($G22="","",Z22-Y22) -> -0.020799425 | AB22: =IF($G22="","",IF($G22=1,(W22-$C$2-H22)/($C$2+H22),(W22-W21-H22)/(W21+H22))) -> 0.0704 | AC22: =IF($G22="","",IF($G22=1,(X22-$C$2-H22)/($C$2+H22),(X22-X21-H22)/(X21+H22))) -> 0.0495648 | AD22: =IF($G22="","",AC22-AB22) -> -0.0208352 | AE22: =IF($G22="","",IF($G22=1,Y22,(1+Y22)*(1+AE21)-1)) -> 1.4527519 | AF22: =IF($G22="","",IF($G22=1,Z22,(1+Z22)*(1+AF21)-1)) -> 0.90051131 | AG22: =IF($G22="","",AF22-AE22) -> -0.55224055 | AH22: =IF($G22="","",IF($G22=1,AB22,(1+AB22)*(1+AH21)-1)) -> 1.4215827 | AI22: =IF($G22="","",IF($G22=1,AC22,(1+AC22)*(1+AI21)-1)) -> 0.87551413 | AJ22: =IF($G22="","",AI22-AH22) -> -0.54606857 | AK22: =IF($G22="","",(1+AE22)^(1/G22)-1) -> 0.071453567 | AL22: =IF($G22="","",(1+AF22)^(1/G22)-1) -> 0.050634297 | AM22: =IF($G22="","",AL22-AK22) -> -0.02081927 | AN22: =IF($G22="","",(1+AH22)^(1/G22)-1) -> 0.0704 | AO22: =IF($G22="","",(1+AI22)^(1/G22)-1) -> 0.0495648 | AP22: =IF($G22="","",AO22-AN22) -> -0.0208352
G23: 14 | H23: =IF(G23="","",SUMIFS(Add_Contributions[[#All],[Amount ($)]],Add_Contributions[[#All],[Year]],G23)) -> 0 | I23: =IF($G23="","",IF($G23=1,(($C$2+$H23)*I$3)*(1+(I$4-I$5)),((I22+($H23*I$3))*(1+(I$4-I$5))))) -> 14098529 | J23: =IF($G23="","",IF($G23=1,(($C$2+$H23)*J$3)*(1+(J$4-J$5)),((J22+($H23*J$3))*(1+(J$4-J$5))))) -> 10990751 | K23: =IF($G23="","",IF($G23=1,(($C$2+$H23)*K$3)*(1+(K$4-K$5)),((K22+($H23*K$3))*(1+(K$4-K$5))))) -> 0 | L23: =IF($G23="","",IF($G23=1,(($C$2+$H23)*L$3)*(1+(L$4-L$5)),((L22+($H23*L$3))*(1+(L$4-L$5))))) -> 0 | M23: =IF($G23="","",IF($G23=1,(($C$2+$H23)*M$3)*(1+(M$4-M$5)),((M22+($H23*M$3))*(1+(M$4-M$5))))) -> 6335781.1 | N23: =IF($G23="","",IF($G23=1,(($C$2+$H23)*N$3)*(1+(N$4-N$5)),((N22+($H23*N$3))*(1+(N$4-N$5))))) -> 4814037.3 | O23: =IF($G23="","",IF($G23=1,(($C$2+$H23)*O$3)*(1+(O$4-O$5)),((O22+($H23*O$3))*(1+(O$4-O$5))))) -> 0 | P23: =IF($G23="","",IF($G23=1,(($C$2+$H23)*P$3)*(1+(P$4-P$5)),((P22+($H23*P$3))*(1+(P$4-P$5))))) -> 0 | ... T23: =IF($G23="","",IF($G23=1,(($C$2+$H23)*T$3)*(1+(T$4-T$5)),((T22+($H23*T$3))*(1+(T$4-T$5))))) -> 0 | U23: =IF(G23="","",SUM(I23,K23,M23,O23,Q23,S23)) -> 26308698 | V23: =IF(H23="","",SUM(J23,L23,N23,P23,R23,T23)) -> 19990039 | W23: =IF($G23="","",IF($G23=1,(($C$2+$H23)*W$3)*(1+(W$4-W$5)),((W22+($H23*W$3))*(1+(W$4-W$5))))) -> 25920621 | X23: =IF($G23="","",IF($G23=1,(($C$2+$H23)*X$3)*(1+(X$4-X$5)),((X22+($H23*X$3))*(1+(X$4-X$5))))) -> 19684736 | Y23: =IF($G23="","",IF($G23=1,(U23-$C$2-H23)/($C$2+H23),(U23-U22-H23)/(U22+H23))) -> 0.072619624 | Z23: =IF($G23="","",IF($G23=1,(V23-$C$2-H23)/($C$2+H23),(V23-V22-H23)/(V22+H23))) -> 0.051824272 | AA23: =IF($G23="","",Z23-Y23) -> -0.020795351 | AB23: =IF($G23="","",IF($G23=1,(W23-$C$2-H23)/($C$2+H23),(W23-W22-H23)/(W22+H23))) -> 0.0704 | AC23: =IF($G23="","",IF($G23=1,(X23-$C$2-H23)/($C$2+H23),(X23-X22-H23)/(X22+H23))) -> 0.0495648 | AD23: =IF($G23="","",AC23-AB23) -> -0.0208352 | AE23: =IF($G23="","",IF($G23=1,Y23,(1+Y23)*(1+AE22)-1)) -> 1.6308698 | AF23: =IF($G23="","",IF($G23=1,Z23,(1+Z23)*(1+AF22)-1)) -> 0.99900392 | AG23: =IF($G23="","",AF23-AE23) -> -0.63186585 | AH23: =IF($G23="","",IF($G23=1,AB23,(1+AB23)*(1+AH22)-1)) -> 1.5920621 | AI23: =IF($G23="","",IF($G23=1,AC23,(1+AC23)*(1+AI22)-1)) -> 0.96847362 | AJ23: =IF($G23="","",AI23-AH23) -> -0.62358851 | AK23: =IF($G23="","",(1+AE23)^(1/G23)-1) -> 0.071536814 | AL23: =IF($G23="","",(1+AF23)^(1/G23)-1) -> 0.05071925 | AM23: =IF($G23="","",AL23-AK23) -> -0.020817564 | AN23: =IF($G23="","",(1+AH23)^(1/G23)-1) -> 0.0704 | AO23: =IF($G23="","",(1+AI23)^(1/G23)-1) -> 0.0495648 | AP23: =IF($G23="","",AO23-AN23) -> -0.0208352
B24: Total Return (Gross) | C24: =_xlfn.XLOOKUP(C3,G:G,AE:AE) -> 3.0185061 | D24: =_xlfn.XLOOKUP(C3,G:G,AH:AH) -> 2.8987197 | G24: 15 | H24: =IF(G24="","",SUMIFS(Add_Contributions[[#All],[Amount ($)]],Add_Contributions[[#All],[Year]],G24)) -> 0 | I24: =IF($G24="","",IF($G24=1,(($C$2+$H24)*I$3)*(1+(I$4-I$5)),((I23+($H24*I$3))*(1+(I$4-I$5))))) -> 15226412 | J24: =IF($G24="","",IF($G24=1,(($C$2+$H24)*J$3)*(1+(J$4-J$5)),((J23+($H24*J$3))*(1+(J$4-J$5))))) -> 11660748 | K24: =IF($G24="","",IF($G24=1,(($C$2+$H24)*K$3)*(1+(K$4-K$5)),((K23+($H24*K$3))*(1+(K$4-K$5))))) -> 0 | L24: =IF($G24="","",IF($G24=1,(($C$2+$H24)*L$3)*(1+(L$4-L$5)),((L23+($H24*L$3))*(1+(L$4-L$5))))) -> 0 | M24: =IF($G24="","",IF($G24=1,(($C$2+$H24)*M$3)*(1+(M$4-M$5)),((M23+($H24*M$3))*(1+(M$4-M$5))))) -> 6652570.2 | N24: =IF($G24="","",IF($G24=1,(($C$2+$H24)*N$3)*(1+(N$4-N$5)),((N23+($H24*N$3))*(1+(N$4-N$5))))) -> 4956532.8 | O24: =IF($G24="","",IF($G24=1,(($C$2+$H24)*O$3)*(1+(O$4-O$5)),((O23+($H24*O$3))*(1+(O$4-O$5))))) -> 0 | P24: =IF($G24="","",IF($G24=1,(($C$2+$H24)*P$3)*(1+(P$4-P$5)),((P23+($H24*P$3))*(1+(P$4-P$5))))) -> 0 | ... T24: =IF($G24="","",IF($G24=1,(($C$2+$H24)*T$3)*(1+(T$4-T$5)),((T23+($H24*T$3))*(1+(T$4-T$5))))) -> 0 | U24: =IF(G24="","",SUM(I24,K24,M24,O24,Q24,S24)) -> 28223320 | V24: =IF(H24="","",SUM(J24,L24,N24,P24,R24,T24)) -> 21029204 | W24: =IF($G24="","",IF($G24=1,(($C$2+$H24)*W$3)*(1+(W$4-W$5)),((W23+($H24*W$3))*(1+(W$4-W$5))))) -> 27745433 | X24: =IF($G24="","",IF($G24=1,(($C$2+$H24)*X$3)*(1+(X$4-X$5)),((X23+($H24*X$3))*(1+(X$4-X$5))))) -> 20660406 | Y24: =IF($G24="","",IF($G24=1,(U24-$C$2-H24)/($C$2+H24),(U24-U23-H24)/(U23+H24))) -> 0.072775263 | Z24: =IF($G24="","",IF($G24=1,(V24-$C$2-H24)/($C$2+H24),(V24-V23-H24)/(V23+H24))) -> 0.051984134 | AA24: =IF($G24="","",Z24-Y24) -> -0.020791129 | AB24: =IF($G24="","",IF($G24=1,(W24-$C$2-H24)/($C$2+H24),(W24-W23-H24)/(W23+H24))) -> 0.0704 | AC24: =IF($G24="","",IF($G24=1,(X24-$C$2-H24)/($C$2+H24),(X24-X23-H24)/(X23+H24))) -> 0.0495648 | AD24: =IF($G24="","",AC24-AB24) -> -0.0208352 | AE24: =IF($G24="","",IF($G24=1,Y24,(1+Y24)*(1+AE23)-1)) -> 1.822332 | AF24: =IF($G24="","",IF($G24=1,Z24,(1+Z24)*(1+AF23)-1)) -> 1.1029204 | AG24: =IF($G24="","",AF24-AE24) -> -0.7194116 | AH24: =IF($G24="","",IF($G24=1,AB24,(1+AB24)*(1+AH23)-1)) -> 1.7745433 | AI24: =IF($G24="","",IF($G24=1,AC24,(1+AC24)*(1+AI23)-1)) -> 1.0660406 | AJ24: =IF($G24="","",AI24-AH24) -> -0.70850268 | AK24: =IF($G24="","",(1+AE24)^(1/G24)-1) -> 0.071619333 | AL24: =IF($G24="","",(1+AF24)^(1/G24)-1) -> 0.050803528 | AM24: =IF($G24="","",AL24-AK24) -> -0.020815805 | AN24: =IF($G24="","",(1+AH24)^(1/G24)-1) -> 0.0704 | AO24: =IF($G24="","",(1+AI24)^(1/G24)-1) -> 0.0495648 | AP24: =IF($G24="","",AO24-AN24) -> -0.0208352
B25: Total Return (Net) | C25: =_xlfn.XLOOKUP(C3,G:G,AF:AF) -> 1.7153622 | D25: =_xlfn.XLOOKUP(C3,G:G,AI:AI) -> 1.6313895 | G25: 16 | H25: =IF(G25="","",SUMIFS(Add_Contributions[[#All],[Amount ($)]],Add_Contributions[[#All],[Year]],G25)) -> 0 | I25: =IF($G25="","",IF($G25=1,(($C$2+$H25)*I$3)*(1+(I$4-I$5)),((I24+($H25*I$3))*(1+(I$4-I$5))))) -> 16444525 | J25: =IF($G25="","",IF($G25=1,(($C$2+$H25)*J$3)*(1+(J$4-J$5)),((J24+($H25*J$3))*(1+(J$4-J$5))))) -> 12371587 | K25: =IF($G25="","",IF($G25=1,(($C$2+$H25)*K$3)*(1+(K$4-K$5)),((K24+($H25*K$3))*(1+(K$4-K$5))))) -> 0 | L25: =IF($G25="","",IF($G25=1,(($C$2+$H25)*L$3)*(1+(L$4-L$5)),((L24+($H25*L$3))*(1+(L$4-L$5))))) -> 0 | M25: =IF($G25="","",IF($G25=1,(($C$2+$H25)*M$3)*(1+(M$4-M$5)),((M24+($H25*M$3))*(1+(M$4-M$5))))) -> 6985198.7 | N25: =IF($G25="","",IF($G25=1,(($C$2+$H25)*N$3)*(1+(N$4-N$5)),((N24+($H25*N$3))*(1+(N$4-N$5))))) -> 5103246.2 | O25: =IF($G25="","",IF($G25=1,(($C$2+$H25)*O$3)*(1+(O$4-O$5)),((O24+($H25*O$3))*(1+(O$4-O$5))))) -> 0 | P25: =IF($G25="","",IF($G25=1,(($C$2+$H25)*P$3)*(1+(P$4-P$5)),((P24+($H25*P$3))*(1+(P$4-P$5))))) -> 0 | ... T25: =IF($G25="","",IF($G25=1,(($C$2+$H25)*T$3)*(1+(T$4-T$5)),((T24+($H25*T$3))*(1+(T$4-T$5))))) -> 0 | U25: =IF(G25="","",SUM(I25,K25,M25,O25,Q25,S25)) -> 30281609 | V25: =IF(H25="","",SUM(J25,L25,N25,P25,R25,T25)) -> 22125706 | W25: =IF($G25="","",IF($G25=1,(($C$2+$H25)*W$3)*(1+(W$4-W$5)),((W24+($H25*W$3))*(1+(W$4-W$5))))) -> 29698711 | X25: =IF($G25="","",IF($G25=1,(($C$2+$H25)*X$3)*(1+(X$4-X$5)),((X24+($H25*X$3))*(1+(X$4-X$5))))) -> 21684435 | Y25: =IF($G25="","",IF($G25=1,(U25-$C$2-H25)/($C$2+H25),(U25-U24-H25)/(U24+H25))) -> 0.072928645 | Z25: =IF($G25="","",IF($G25=1,(V25-$C$2-H25)/($C$2+H25),(V25-V24-H25)/(V24+H25))) -> 0.052141885 | AA25: =IF($G25="","",Z25-Y25) -> -0.020786761 | AB25: =IF($G25="","",IF($G25=1,(W25-$C$2-H25)/($C$2+H25),(W25-W24-H25)/(W24+H25))) -> 0.0704 | AC25: =IF($G25="","",IF($G25=1,(X25-$C$2-H25)/($C$2+H25),(X25-X24-H25)/(X24+H25))) -> 0.0495648 | AD25: =IF($G25="","",AC25-AB25) -> -0.0208352 | AE25: =IF($G25="","",IF($G25=1,Y25,(1+Y25)*(1+AE24)-1)) -> 2.0281609 | AF25: =IF($G25="","",IF($G25=1,Z25,(1+Z25)*(1+AF24)-1)) -> 1.2125706 | AG25: =IF($G25="","",AF25-AE25) -> -0.81559022 | AH25: =IF($G25="","",IF($G25=1,AB25,(1+AB25)*(1+AH24)-1)) -> 1.9698711 | AI25: =IF($G25="","",IF($G25=1,AC25,(1+AC25)*(1+AI24)-1)) -> 1.1684435 | AJ25: =IF($G25="","",AI25-AH25) -> -0.80142764 | AK25: =IF($G25="","",(1+AE25)^(1/G25)-1) -> 0.071701118 | AL25: =IF($G25="","",(1+AF25)^(1/G25)-1) -> 0.050887126 | AM25: =IF($G25="","",AL25-AK25) -> -0.020813993 | AN25: =IF($G25="","",(1+AH25)^(1/G25)-1) -> 0.0704 | AO25: =IF($G25="","",(1+AI25)^(1/G25)-1) -> 0.0495648 | AP25: =IF($G25="","",AO25-AN25) -> -0.0208352
B26: Total Return (Drag) | C26: =_xlfn.XLOOKUP(C3,G:G,AG:AG) -> -1.3031439 | D26: =_xlfn.XLOOKUP(C3,G:G,AJ:AJ) -> -1.2673301 | G26: 17 | H26: =IF(G26="","",SUMIFS(Add_Contributions[[#All],[Amount ($)]],Add_Contributions[[#All],[Year]],G26)) -> 0 | I26: =IF($G26="","",IF($G26=1,(($C$2+$H26)*I$3)*(1+(I$4-I$5)),((I25+($H26*I$3))*(1+(I$4-I$5))))) -> 17760087 | J26: =IF($G26="","",IF($G26=1,(($C$2+$H26)*J$3)*(1+(J$4-J$5)),((J25+($H26*J$3))*(1+(J$4-J$5))))) -> 13125759 | K26: =IF($G26="","",IF($G26=1,(($C$2+$H26)*K$3)*(1+(K$4-K$5)),((K25+($H26*K$3))*(1+(K$4-K$5))))) -> 0 | L26: =IF($G26="","",IF($G26=1,(($C$2+$H26)*L$3)*(1+(L$4-L$5)),((L25+($H26*L$3))*(1+(L$4-L$5))))) -> 0 | M26: =IF($G26="","",IF($G26=1,(($C$2+$H26)*M$3)*(1+(M$4-M$5)),((M25+($H26*M$3))*(1+(M$4-M$5))))) -> 7334458.6 | N26: =IF($G26="","",IF($G26=1,(($C$2+$H26)*N$3)*(1+(N$4-N$5)),((N25+($H26*N$3))*(1+(N$4-N$5))))) -> 5254302.3 | O26: =IF($G26="","",IF($G26=1,(($C$2+$H26)*O$3)*(1+(O$4-O$5)),((O25+($H26*O$3))*(1+(O$4-O$5))))) -> 0 | P26: =IF($G26="","",IF($G26=1,(($C$2+$H26)*P$3)*(1+(P$4-P$5)),((P25+($H26*P$3))*(1+(P$4-P$5))))) -> 0 | ... T26: =IF($G26="","",IF($G26=1,(($C$2+$H26)*T$3)*(1+(T$4-T$5)),((T25+($H26*T$3))*(1+(T$4-T$5))))) -> 0 | U26: =IF(G26="","",SUM(I26,K26,M26,O26,Q26,S26)) -> 32494581 | V26: =IF(H26="","",SUM(J26,L26,N26,P26,R26,T26)) -> 23282826 | W26: =IF($G26="","",IF($G26=1,(($C$2+$H26)*W$3)*(1+(W$4-W$5)),((W25+($H26*W$3))*(1+(W$4-W$5))))) -> 31789501 | X26: =IF($G26="","",IF($G26=1,(($C$2+$H26)*X$3)*(1+(X$4-X$5)),((X25+($H26*X$3))*(1+(X$4-X$5))))) -> 22759220 | Y26: =IF($G26="","",IF($G26=1,(U26-$C$2-H26)/($C$2+H26),(U26-U25-H26)/(U25+H26))) -> 0.073079761 | Z26: =IF($G26="","",IF($G26=1,(V26-$C$2-H26)/($C$2+H26),(V26-V25-H26)/(V25+H26))) -> 0.052297509 | AA26: =IF($G26="","",Z26-Y26) -> -0.020782253 | AB26: =IF($G26="","",IF($G26=1,(W26-$C$2-H26)/($C$2+H26),(W26-W25-H26)/(W25+H26))) -> 0.0704 | AC26: =IF($G26="","",IF($G26=1,(X26-$C$2-H26)/($C$2+H26),(X26-X25-H26)/(X25+H26))) -> 0.0495648 | AD26: =IF($G26="","",AC26-AB26) -> -0.0208352 | AE26: =IF($G26="","",IF($G26=1,Y26,(1+Y26)*(1+AE25)-1)) -> 2.2494581 | AF26: =IF($G26="","",IF($G26=1,Z26,(1+Z26)*(1+AF25)-1)) -> 1.3282826 | AG26: =IF($G26="","",AF26-AE26) -> -0.92117556 | AH26: =IF($G26="","",IF($G26=1,AB26,(1+AB26)*(1+AH25)-1)) -> 2.1789501 | AI26: =IF($G26="","",IF($G26=1,AC26,(1+AC26)*(1+AI25)-1)) -> 1.275922 | AJ26: =IF($G26="","",AI26-AH26) -> -0.9030281 | AK26: =IF($G26="","",(1+AE26)^(1/G26)-1) -> 0.071782166 | AL26: =IF($G26="","",(1+AF26)^(1/G26)-1) -> 0.050970037 | AM26: =IF($G26="","",AL26-AK26) -> -0.020812129 | AN26: =IF($G26="","",(1+AH26)^(1/G26)-1) -> 0.0704 | AO26: =IF($G26="","",(1+AI26)^(1/G26)-1) -> 0.0495648 | AP26: =IF($G26="","",AO26-AN26) -> -0.0208352
G27: 18 | H27: =IF(G27="","",SUMIFS(Add_Contributions[[#All],[Amount ($)]],Add_Contributions[[#All],[Year]],G27)) -> 0 | I27: =IF($G27="","",IF($G27=1,(($C$2+$H27)*I$3)*(1+(I$4-I$5)),((I26+($H27*I$3))*(1+(I$4-I$5))))) -> 19180894 | J27: =IF($G27="","",IF($G27=1,(($C$2+$H27)*J$3)*(1+(J$4-J$5)),((J26+($H27*J$3))*(1+(J$4-J$5))))) -> 13925905 | K27: =IF($G27="","",IF($G27=1,(($C$2+$H27)*K$3)*(1+(K$4-K$5)),((K26+($H27*K$3))*(1+(K$4-K$5))))) -> 0 | L27: =IF($G27="","",IF($G27=1,(($C$2+$H27)*L$3)*(1+(L$4-L$5)),((L26+($H27*L$3))*(1+(L$4-L$5))))) -> 0 | M27: =IF($G27="","",IF($G27=1,(($C$2+$H27)*M$3)*(1+(M$4-M$5)),((M26+($H27*M$3))*(1+(M$4-M$5))))) -> 7701181.5 | N27: =IF($G27="","",IF($G27=1,(($C$2+$H27)*N$3)*(1+(N$4-N$5)),((N26+($H27*N$3))*(1+(N$4-N$5))))) -> 5409829.6 | O27: =IF($G27="","",IF($G27=1,(($C$2+$H27)*O$3)*(1+(O$4-O$5)),((O26+($H27*O$3))*(1+(O$4-O$5))))) -> 0 | P27: =IF($G27="","",IF($G27=1,(($C$2+$H27)*P$3)*(1+(P$4-P$5)),((P26+($H27*P$3))*(1+(P$4-P$5))))) -> 0 | ... T27: =IF($G27="","",IF($G27=1,(($C$2+$H27)*T$3)*(1+(T$4-T$5)),((T26+($H27*T$3))*(1+(T$4-T$5))))) -> 0 | U27: =IF(G27="","",SUM(I27,K27,M27,O27,Q27,S27)) -> 34874114 | V27: =IF(H27="","",SUM(J27,L27,N27,P27,R27,T27)) -> 24504033 | W27: =IF($G27="","",IF($G27=1,(($C$2+$H27)*W$3)*(1+(W$4-W$5)),((W26+($H27*W$3))*(1+(W$4-W$5))))) -> 34027482 | X27: =IF($G27="","",IF($G27=1,(($C$2+$H27)*X$3)*(1+(X$4-X$5)),((X26+($H27*X$3))*(1+(X$4-X$5))))) -> 23887276 | Y27: =IF($G27="","",IF($G27=1,(U27-$C$2-H27)/($C$2+H27),(U27-U26-H27)/(U26+H27))) -> 0.073228602 | Z27: =IF($G27="","",IF($G27=1,(V27-$C$2-H27)/($C$2+H27),(V27-V26-H27)/(V26+H27))) -> 0.052450993 | AA27: =IF($G27="","",Z27-Y27) -> -0.020777608 | AB27: =IF($G27="","",IF($G27=1,(W27-$C$2-H27)/($C$2+H27),(W27-W26-H27)/(W26+H27))) -> 0.0704 | AC27: =IF($G27="","",IF($G27=1,(X27-$C$2-H27)/($C$2+H27),(X27-X26-H27)/(X26+H27))) -> 0.0495648 | AD27: =IF($G27="","",AC27-AB27) -> -0.0208352 | AE27: =IF($G27="","",IF($G27=1,Y27,(1+Y27)*(1+AE26)-1)) -> 2.4874114 | AF27: =IF($G27="","",IF($G27=1,Z27,(1+Z27)*(1+AF26)-1)) -> 1.4504033 | AG27: =IF($G27="","",AF27-AE27) -> -1.0370081 | AH27: =IF($G27="","",IF($G27=1,AB27,(1+AB27)*(1+AH26)-1)) -> 2.4027482 | AI27: =IF($G27="","",IF($G27=1,AC27,(1+AC27)*(1+AI26)-1)) -> 1.3887276 | AJ27: =IF($G27="","",AI27-AH27) -> -1.0140206 | AK27: =IF($G27="","",(1+AE27)^(1/G27)-1) -> 0.071862472 | AL27: =IF($G27="","",(1+AF27)^(1/G27)-1) -> 0.051052258 | AM27: =IF($G27="","",AL27-AK27) -> -0.020810214 | AN27: =IF($G27="","",(1+AH27)^(1/G27)-1) -> 0.0704 | AO27: =IF($G27="","",(1+AI27)^(1/G27)-1) -> 0.0495648 | AP27: =IF($G27="","",AO27-AN27) -> -0.0208352
B28: Annualized Return (Gross) | C28: =_xlfn.XLOOKUP(C3,G:G,AK:AK) -> 0.072020849 | D28: =_xlfn.XLOOKUP(C3,G:G,AN:AN) -> 0.0704 | G28: 19 | H28: =IF(G28="","",SUMIFS(Add_Contributions[[#All],[Amount ($)]],Add_Contributions[[#All],[Year]],G28)) -> 0 | I28: =IF($G28="","",IF($G28=1,(($C$2+$H28)*I$3)*(1+(I$4-I$5)),((I27+($H28*I$3))*(1+(I$4-I$5))))) -> 20715365 | J28: =IF($G28="","",IF($G28=1,(($C$2+$H28)*J$3)*(1+(J$4-J$5)),((J27+($H28*J$3))*(1+(J$4-J$5))))) -> 14774828 | K28: =IF($G28="","",IF($G28=1,(($C$2+$H28)*K$3)*(1+(K$4-K$5)),((K27+($H28*K$3))*(1+(K$4-K$5))))) -> 0 | L28: =IF($G28="","",IF($G28=1,(($C$2+$H28)*L$3)*(1+(L$4-L$5)),((L27+($H28*L$3))*(1+(L$4-L$5))))) -> 0 | M28: =IF($G28="","",IF($G28=1,(($C$2+$H28)*M$3)*(1+(M$4-M$5)),((M27+($H28*M$3))*(1+(M$4-M$5))))) -> 8086240.6 | N28: =IF($G28="","",IF($G28=1,(($C$2+$H28)*N$3)*(1+(N$4-N$5)),((N27+($H28*N$3))*(1+(N$4-N$5))))) -> 5569960.6 | O28: =IF($G28="","",IF($G28=1,(($C$2+$H28)*O$3)*(1+(O$4-O$5)),((O27+($H28*O$3))*(1+(O$4-O$5))))) -> 0 | P28: =IF($G28="","",IF($G28=1,(($C$2+$H28)*P$3)*(1+(P$4-P$5)),((P27+($H28*P$3))*(1+(P$4-P$5))))) -> 0 | ... T28: =IF($G28="","",IF($G28=1,(($C$2+$H28)*T$3)*(1+(T$4-T$5)),((T27+($H28*T$3))*(1+(T$4-T$5))))) -> 0 | U28: =IF(G28="","",SUM(I28,K28,M28,O28,Q28,S28)) -> 37433008 | V28: =IF(H28="","",SUM(J28,L28,N28,P28,R28,T28)) -> 25793002 | W28: =IF($G28="","",IF($G28=1,(($C$2+$H28)*W$3)*(1+(W$4-W$5)),((W27+($H28*W$3))*(1+(W$4-W$5))))) -> 36423016 | X28: =IF($G28="","",IF($G28=1,(($C$2+$H28)*X$3)*(1+(X$4-X$5)),((X27+($H28*X$3))*(1+(X$4-X$5))))) -> 25071244 | Y28: =IF($G28="","",IF($G28=1,(U28-$C$2-H28)/($C$2+H28),(U28-U27-H28)/(U27+H28))) -> 0.073375159 | Z28: =IF($G28="","",IF($G28=1,(V28-$C$2-H28)/($C$2+H28),(V28-V27-H28)/(V27+H28))) -> 0.052602327 | AA28: =IF($G28="","",Z28-Y28) -> -0.020772832 | AB28: =IF($G28="","",IF($G28=1,(W28-$C$2-H28)/($C$2+H28),(W28-W27-H28)/(W27+H28))) -> 0.0704 | AC28: =IF($G28="","",IF($G28=1,(X28-$C$2-H28)/($C$2+H28),(X28-X27-H28)/(X27+H28))) -> 0.0495648 | AD28: =IF($G28="","",AC28-AB28) -> -0.0208352 | AE28: =IF($G28="","",IF($G28=1,Y28,(1+Y28)*(1+AE27)-1)) -> 2.7433008 | AF28: =IF($G28="","",IF($G28=1,Z28,(1+Z28)*(1+AF27)-1)) -> 1.5793002 | AG28: =IF($G28="","",AF28-AE28) -> -1.1640006 | AH28: =IF($G28="","",IF($G28=1,AB28,(1+AB28)*(1+AH27)-1)) -> 2.6423016 | AI28: =IF($G28="","",IF($G28=1,AC28,(1+AC28)*(1+AI27)-1)) -> 1.5071244 | AJ28: =IF($G28="","",AI28-AH28) -> -1.1351772 | AK28: =IF($G28="","",(1+AE28)^(1/G28)-1) -> 0.071942034 | AL28: =IF($G28="","",(1+AF28)^(1/G28)-1) -> 0.051133783 | AM28: =IF($G28="","",AL28-AK28) -> -0.020808251 | AN28: =IF($G28="","",(1+AH28)^(1/G28)-1) -> 0.0704 | AO28: =IF($G28="","",(1+AI28)^(1/G28)-1) -> 0.0495648 | AP28: =IF($G28="","",AO28-AN28) -> -0.0208352
B29: Annualized Return (Net) | C29: =_xlfn.XLOOKUP(C3,G:G,AL:AL) -> 0.05121461 | D29: =_xlfn.XLOOKUP(C3,G:G,AO:AO) -> 0.0495648 | G29: 20 | H29: =IF(G29="","",SUMIFS(Add_Contributions[[#All],[Amount ($)]],Add_Contributions[[#All],[Year]],G29)) -> 0 | I29: =IF($G29="","",IF($G29=1,(($C$2+$H29)*I$3)*(1+(I$4-I$5)),((I28+($H29*I$3))*(1+(I$4-I$5))))) -> 22372594 | J29: =IF($G29="","",IF($G29=1,(($C$2+$H29)*J$3)*(1+(J$4-J$5)),((J28+($H29*J$3))*(1+(J$4-J$5))))) -> 15675502 | K29: =IF($G29="","",IF($G29=1,(($C$2+$H29)*K$3)*(1+(K$4-K$5)),((K28+($H29*K$3))*(1+(K$4-K$5))))) -> 0 | L29: =IF($G29="","",IF($G29=1,(($C$2+$H29)*L$3)*(1+(L$4-L$5)),((L28+($H29*L$3))*(1+(L$4-L$5))))) -> 0 | M29: =IF($G29="","",IF($G29=1,(($C$2+$H29)*M$3)*(1+(M$4-M$5)),((M28+($H29*M$3))*(1+(M$4-M$5))))) -> 8490552.7 | N29: =IF($G29="","",IF($G29=1,(($C$2+$H29)*N$3)*(1+(N$4-N$5)),((N28+($H29*N$3))*(1+(N$4-N$5))))) -> 5734831.4 | O29: =IF($G29="","",IF($G29=1,(($C$2+$H29)*O$3)*(1+(O$4-O$5)),((O28+($H29*O$3))*(1+(O$4-O$5))))) -> 0 | P29: =IF($G29="","",IF($G29=1,(($C$2+$H29)*P$3)*(1+(P$4-P$5)),((P28+($H29*P$3))*(1+(P$4-P$5))))) -> 0 | ... T29: =IF($G29="","",IF($G29=1,(($C$2+$H29)*T$3)*(1+(T$4-T$5)),((T28+($H29*T$3))*(1+(T$4-T$5))))) -> 0 | U29: =IF(G29="","",SUM(I29,K29,M29,O29,Q29,S29)) -> 40185061 | V29: =IF(H29="","",SUM(J29,L29,N29,P29,R29,T29)) -> 27153622 | W29: =IF($G29="","",IF($G29=1,(($C$2+$H29)*W$3)*(1+(W$4-W$5)),((W28+($H29*W$3))*(1+(W$4-W$5))))) -> 38987197 | X29: =IF($G29="","",IF($G29=1,(($C$2+$H29)*X$3)*(1+(X$4-X$5)),((X28+($H29*X$3))*(1+(X$4-X$5))))) -> 26313895 | Y29: =IF($G29="","",IF($G29=1,(U29-$C$2-H29)/($C$2+H29),(U29-U28-H29)/(U28+H29))) -> 0.07351943 | Z29: =IF($G29="","",IF($G29=1,(V29-$C$2-H29)/($C$2+H29),(V29-V28-H29)/(V28+H29))) -> 0.052751502 | AA29: =IF($G29="","",Z29-Y29) -> -0.020767929 | AB29: =IF($G29="","",IF($G29=1,(W29-$C$2-H29)/($C$2+H29),(W29-W28-H29)/(W28+H29))) -> 0.0704 | AC29: =IF($G29="","",IF($G29=1,(X29-$C$2-H29)/($C$2+H29),(X29-X28-H29)/(X28+H29))) -> 0.0495648 | AD29: =IF($G29="","",AC29-AB29) -> -0.0208352 | AE29: =IF($G29="","",IF($G29=1,Y29,(1+Y29)*(1+AE28)-1)) -> 3.0185061 | AF29: =IF($G29="","",IF($G29=1,Z29,(1+Z29)*(1+AF28)-1)) -> 1.7153622 | AG29: =IF($G29="","",AF29-AE29) -> -1.3031439 | AH29: =IF($G29="","",IF($G29=1,AB29,(1+AB29)*(1+AH28)-1)) -> 2.8987197 | AI29: =IF($G29="","",IF($G29=1,AC29,(1+AC29)*(1+AI28)-1)) -> 1.6313895 | AJ29: =IF($G29="","",AI29-AH29) -> -1.2673301 | AK29: =IF($G29="","",(1+AE29)^(1/G29)-1) -> 0.072020849 | AL29: =IF($G29="","",(1+AF29)^(1/G29)-1) -> 0.05121461 | AM29: =IF($G29="","",AL29-AK29) -> -0.020806239 | AN29: =IF($G29="","",(1+AH29)^(1/G29)-1) -> 0.0704 | AO29: =IF($G29="","",(1+AI29)^(1/G29)-1) -> 0.0495648 | AP29: =IF($G29="","",AO29-AN29) -> -0.0208352
B30: Annualized Return (Drag) | C30: =_xlfn.XLOOKUP(C3,G:G,AM:AM) -> -0.020806239 | D30: =_xlfn.XLOOKUP(C3,G:G,AP:AP) -> -0.0208352 | H30: =IF(G30="","",SUMIFS(Add_Contributions[[#All],[Amount ($)]],Add_Contributions[[#All],[Year]],G30)) | I30: =IF($G30="","",IF($G30=1,(($C$2+$H30)*I$3)*(1+(I$4-I$5)),((I29+($H30*I$3))*(1+(I$4-I$5))))) | J30: =IF($G30="","",IF($G30=1,(($C$2+$H30)*J$3)*(1+(J$4-J$5)),((J29+($H30*J$3))*(1+(J$4-J$5))))) | K30: =IF($G30="","",IF($G30=1,(($C$2+$H30)*K$3)*(1+(K$4-K$5)),((K29+($H30*K$3))*(1+(K$4-K$5))))) | L30: =IF($G30="","",IF($G30=1,(($C$2+$H30)*L$3)*(1+(L$4-L$5)),((L29+($H30*L$3))*(1+(L$4-L$5))))) | M30: =IF($G30="","",IF($G30=1,(($C$2+$H30)*M$3)*(1+(M$4-M$5)),((M29+($H30*M$3))*(1+(M$4-M$5))))) | N30: =IF($G30="","",IF($G30=1,(($C$2+$H30)*N$3)*(1+(N$4-N$5)),((N29+($H30*N$3))*(1+(N$4-N$5))))) | O30: =IF($G30="","",IF($G30=1,(($C$2+$H30)*O$3)*(1+(O$4-O$5)),((O29+($H30*O$3))*(1+(O$4-O$5))))) | P30: =IF($G30="","",IF($G30=1,(($C$2+$H30)*P$3)*(1+(P$4-P$5)),((P29+($H30*P$3))*(1+(P$4-P$5))))) | ... T30: =IF($G30="","",IF($G30=1,(($C$2+$H30)*T$3)*(1+(T$4-T$5)),((T29+($H30*T$3))*(1+(T$4-T$5))))) | U30: =IF(G30="","",SUM(I30,K30,M30,O30,Q30,S30)) | V30: =IF(H30="","",SUM(J30,L30,N30,P30,R30,T30)) | W30: =IF($G30="","",IF($G30=1,(($C$2+$H30)*W$3)*(1+(W$4-W$5)),((W29+($H30*W$3))*(1+(W$4-W$5))))) | X30: =IF($G30="","",IF($G30=1,(($C$2+$H30)*X$3)*(1+(X$4-X$5)),((X29+($H30*X$3))*(1+(X$4-X$5))))) | Y30: =IF($G30="","",IF($G30=1,(U30-$C$2-H30)/($C$2+H30),(U30-U29-H30)/(U29+H30))) | Z30: =IF($G30="","",IF($G30=1,(V30-$C$2-H30)/($C$2+H30),(V30-V29-H30)/(V29+H30))) | AA30: =IF($G30="","",Z30-Y30) | AB30: =IF($G30="","",IF($G30=1,(W30-$C$2-H30)/($C$2+H30),(W30-W29-H30)/(W29+H30))) | AC30: =IF($G30="","",IF($G30=1,(X30-$C$2-H30)/($C$2+H30),(X30-X29-H30)/(X29+H30))) | AD30: =IF($G30="","",AC30-AB30) | AE30: =IF($G30="","",IF($G30=1,Y30,(1+Y30)*(1+AE29)-1)) | AF30: =IF($G30="","",IF($G30=1,Z30,(1+Z30)*(1+AF29)-1)) | AG30: =IF($G30="","",AF30-AE30) | AH30: =IF($G30="","",IF($G30=1,AB30,(1+AB30)*(1+AH29)-1)) | AI30: =IF($G30="","",IF($G30=1,AC30,(1+AC30)*(1+AI29)-1)) | AJ30: =IF($G30="","",AI30-AH30) | AK30: =IF($G30="","",(1+AE30)^(1/G30)-1) | AL30: =IF($G30="","",(1+AF30)^(1/G30)-1) | AM30: =IF($G30="","",AL30-AK30) | AN30: =IF($G30="","",(1+AH30)^(1/G30)-1) | AO30: =IF($G30="","",(1+AI30)^(1/G30)-1) | AP30: =IF($G30="","",AO30-AN30)
H31: =IF(G31="","",SUMIFS(Add_Contributions[[#All],[Amount ($)]],Add_Contributions[[#All],[Year]],G31)) | I31: =IF($G31="","",IF($G31=1,(($C$2+$H31)*I$3)*(1+(I$4-I$5)),((I30+($H31*I$3))*(1+(I$4-I$5))))) | J31: =IF($G31="","",IF($G31=1,(($C$2+$H31)*J$3)*(1+(J$4-J$5)),((J30+($H31*J$3))*(1+(J$4-J$5))))) | K31: =IF($G31="","",IF($G31=1,(($C$2+$H31)*K$3)*(1+(K$4-K$5)),((K30+($H31*K$3))*(1+(K$4-K$5))))) | L31: =IF($G31="","",IF($G31=1,(($C$2+$H31)*L$3)*(1+(L$4-L$5)),((L30+($H31*L$3))*(1+(L$4-L$5))))) | M31: =IF($G31="","",IF($G31=1,(($C$2+$H31)*M$3)*(1+(M$4-M$5)),((M30+($H31*M$3))*(1+(M$4-M$5))))) | N31: =IF($G31="","",IF($G31=1,(($C$2+$H31)*N$3)*(1+(N$4-N$5)),((N30+($H31*N$3))*(1+(N$4-N$5))))) | O31: =IF($G31="","",IF($G31=1,(($C$2+$H31)*O$3)*(1+(O$4-O$5)),((O30+($H31*O$3))*(1+(O$4-O$5))))) | P31: =IF($G31="","",IF($G31=1,(($C$2+$H31)*P$3)*(1+(P$4-P$5)),((P30+($H31*P$3))*(1+(P$4-P$5))))) | ... T31: =IF($G31="","",IF($G31=1,(($C$2+$H31)*T$3)*(1+(T$4-T$5)),((T30+($H31*T$3))*(1+(T$4-T$5))))) | U31: =IF(G31="","",SUM(I31,K31,M31,O31,Q31,S31)) | V31: =IF(H31="","",SUM(J31,L31,N31,P31,R31,T31)) | W31: =IF($G31="","",IF($G31=1,(($C$2+$H31)*W$3)*(1+(W$4-W$5)),((W30+($H31*W$3))*(1+(W$4-W$5))))) | X31: =IF($G31="","",IF($G31=1,(($C$2+$H31)*X$3)*(1+(X$4-X$5)),((X30+($H31*X$3))*(1+(X$4-X$5))))) | Y31: =IF($G31="","",IF($G31=1,(U31-$C$2-H31)/($C$2+H31),(U31-U30-H31)/(U30+H31))) | Z31: =IF($G31="","",IF($G31=1,(V31-$C$2-H31)/($C$2+H31),(V31-V30-H31)/(V30+H31))) | AA31: =IF($G31="","",Z31-Y31) | AB31: =IF($G31="","",IF($G31=1,(W31-$C$2-H31)/($C$2+H31),(W31-W30-H31)/(W30+H31))) | AC31: =IF($G31="","",IF($G31=1,(X31-$C$2-H31)/($C$2+H31),(X31-X30-H31)/(X30+H31))) | AD31: =IF($G31="","",AC31-AB31) | AE31: =IF($G31="","",IF($G31=1,Y31,(1+Y31)*(1+AE30)-1)) | AF31: =IF($G31="","",IF($G31=1,Z31,(1+Z31)*(1+AF30)-1)) | AG31: =IF($G31="","",AF31-AE31) | AH31: =IF($G31="","",IF($G31=1,AB31,(1+AB31)*(1+AH30)-1)) | AI31: =IF($G31="","",IF($G31=1,AC31,(1+AC31)*(1+AI30)-1)) | AJ31: =IF($G31="","",AI31-AH31) | AK31: =IF($G31="","",(1+AE31)^(1/G31)-1) | AL31: =IF($G31="","",(1+AF31)^(1/G31)-1) | AM31: =IF($G31="","",AL31-AK31) | AN31: =IF($G31="","",(1+AH31)^(1/G31)-1) | AO31: =IF($G31="","",(1+AI31)^(1/G31)-1) | AP31: =IF($G31="","",AO31-AN31)
H32: =IF(G32="","",SUMIFS(Add_Contributions[[#All],[Amount ($)]],Add_Contributions[[#All],[Year]],G32)) | I32: =IF($G32="","",IF($G32=1,(($C$2+$H32)*I$3)*(1+(I$4-I$5)),((I31+($H32*I$3))*(1+(I$4-I$5))))) | J32: =IF($G32="","",IF($G32=1,(($C$2+$H32)*J$3)*(1+(J$4-J$5)),((J31+($H32*J$3))*(1+(J$4-J$5))))) | K32: =IF($G32="","",IF($G32=1,(($C$2+$H32)*K$3)*(1+(K$4-K$5)),((K31+($H32*K$3))*(1+(K$4-K$5))))) | L32: =IF($G32="","",IF($G32=1,(($C$2+$H32)*L$3)*(1+(L$4-L$5)),((L31+($H32*L$3))*(1+(L$4-L$5))))) | M32: =IF($G32="","",IF($G32=1,(($C$2+$H32)*M$3)*(1+(M$4-M$5)),((M31+($H32*M$3))*(1+(M$4-M$5))))) | N32: =IF($G32="","",IF($G32=1,(($C$2+$H32)*N$3)*(1+(N$4-N$5)),((N31+($H32*N$3))*(1+(N$4-N$5))))) | O32: =IF($G32="","",IF($G32=1,(($C$2+$H32)*O$3)*(1+(O$4-O$5)),((O31+($H32*O$3))*(1+(O$4-O$5))))) | P32: =IF($G32="","",IF($G32=1,(($C$2+$H32)*P$3)*(1+(P$4-P$5)),((P31+($H32*P$3))*(1+(P$4-P$5))))) | ... T32: =IF($G32="","",IF($G32=1,(($C$2+$H32)*T$3)*(1+(T$4-T$5)),((T31+($H32*T$3))*(1+(T$4-T$5))))) | U32: =IF(G32="","",SUM(I32,K32,M32,O32,Q32,S32)) | V32: =IF(H32="","",SUM(J32,L32,N32,P32,R32,T32)) | W32: =IF($G32="","",IF($G32=1,(($C$2+$H32)*W$3)*(1+(W$4-W$5)),((W31+($H32*W$3))*(1+(W$4-W$5))))) | X32: =IF($G32="","",IF($G32=1,(($C$2+$H32)*X$3)*(1+(X$4-X$5)),((X31+($H32*X$3))*(1+(X$4-X$5))))) | Y32: =IF($G32="","",IF($G32=1,(U32-$C$2-H32)/($C$2+H32),(U32-U31-H32)/(U31+H32))) | Z32: =IF($G32="","",IF($G32=1,(V32-$C$2-H32)/($C$2+H32),(V32-V31-H32)/(V31+H32))) | AA32: =IF($G32="","",Z32-Y32) | AB32: =IF($G32="","",IF($G32=1,(W32-$C$2-H32)/($C$2+H32),(W32-W31-H32)/(W31+H32))) | AC32: =IF($G32="","",IF($G32=1,(X32-$C$2-H32)/($C$2+H32),(X32-X31-H32)/(X31+H32))) | AD32: =IF($G32="","",AC32-AB32) | AE32: =IF($G32="","",IF($G32=1,Y32,(1+Y32)*(1+AE31)-1)) | AF32: =IF($G32="","",IF($G32=1,Z32,(1+Z32)*(1+AF31)-1)) | AG32: =IF($G32="","",AF32-AE32) | AH32: =IF($G32="","",IF($G32=1,AB32,(1+AB32)*(1+AH31)-1)) | AI32: =IF($G32="","",IF($G32=1,AC32,(1+AC32)*(1+AI31)-1)) | AJ32: =IF($G32="","",AI32-AH32) | AK32: =IF($G32="","",(1+AE32)^(1/G32)-1) | AL32: =IF($G32="","",(1+AF32)^(1/G32)-1) | AM32: =IF($G32="","",AL32-AK32) | AN32: =IF($G32="","",(1+AH32)^(1/G32)-1) | AO32: =IF($G32="","",(1+AI32)^(1/G32)-1) | AP32: =IF($G32="","",AO32-AN32)
H33: =IF(G33="","",SUMIFS(Add_Contributions[[#All],[Amount ($)]],Add_Contributions[[#All],[Year]],G33)) | I33: =IF($G33="","",IF($G33=1,(($C$2+$H33)*I$3)*(1+(I$4-I$5)),((I32+($H33*I$3))*(1+(I$4-I$5))))) | J33: =IF($G33="","",IF($G33=1,(($C$2+$H33)*J$3)*(1+(J$4-J$5)),((J32+($H33*J$3))*(1+(J$4-J$5))))) | K33: =IF($G33="","",IF($G33=1,(($C$2+$H33)*K$3)*(1+(K$4-K$5)),((K32+($H33*K$3))*(1+(K$4-K$5))))) | L33: =IF($G33="","",IF($G33=1,(($C$2+$H33)*L$3)*(1+(L$4-L$5)),((L32+($H33*L$3))*(1+(L$4-L$5))))) | M33: =IF($G33="","",IF($G33=1,(($C$2+$H33)*M$3)*(1+(M$4-M$5)),((M32+($H33*M$3))*(1+(M$4-M$5))))) | N33: =IF($G33="","",IF($G33=1,(($C$2+$H33)*N$3)*(1+(N$4-N$5)),((N32+($H33*N$3))*(1+(N$4-N$5))))) | O33: =IF($G33="","",IF($G33=1,(($C$2+$H33)*O$3)*(1+(O$4-O$5)),((O32+($H33*O$3))*(1+(O$4-O$5))))) | P33: =IF($G33="","",IF($G33=1,(($C$2+$H33)*P$3)*(1+(P$4-P$5)),((P32+($H33*P$3))*(1+(P$4-P$5))))) | ... T33: =IF($G33="","",IF($G33=1,(($C$2+$H33)*T$3)*(1+(T$4-T$5)),((T32+($H33*T$3))*(1+(T$4-T$5))))) | U33: =IF(G33="","",SUM(I33,K33,M33,O33,Q33,S33)) | V33: =IF(H33="","",SUM(J33,L33,N33,P33,R33,T33)) | W33: =IF($G33="","",IF($G33=1,(($C$2+$H33)*W$3)*(1+(W$4-W$5)),((W32+($H33*W$3))*(1+(W$4-W$5))))) | X33: =IF($G33="","",IF($G33=1,(($C$2+$H33)*X$3)*(1+(X$4-X$5)),((X32+($H33*X$3))*(1+(X$4-X$5))))) | Y33: =IF($G33="","",IF($G33=1,(U33-$C$2-H33)/($C$2+H33),(U33-U32-H33)/(U32+H33))) | Z33: =IF($G33="","",IF($G33=1,(V33-$C$2-H33)/($C$2+H33),(V33-V32-H33)/(V32+H33))) | AA33: =IF($G33="","",Z33-Y33) | AB33: =IF($G33="","",IF($G33=1,(W33-$C$2-H33)/($C$2+H33),(W33-W32-H33)/(W32+H33))) | AC33: =IF($G33="","",IF($G33=1,(X33-$C$2-H33)/($C$2+H33),(X33-X32-H33)/(X32+H33))) | AD33: =IF($G33="","",AC33-AB33) | AE33: =IF($G33="","",IF($G33=1,Y33,(1+Y33)*(1+AE32)-1)) | AF33: =IF($G33="","",IF($G33=1,Z33,(1+Z33)*(1+AF32)-1)) | AG33: =IF($G33="","",AF33-AE33) | AH33: =IF($G33="","",IF($G33=1,AB33,(1+AB33)*(1+AH32)-1)) | AI33: =IF($G33="","",IF($G33=1,AC33,(1+AC33)*(1+AI32)-1)) | AJ33: =IF($G33="","",AI33-AH33) | AK33: =IF($G33="","",(1+AE33)^(1/G33)-1) | AL33: =IF($G33="","",(1+AF33)^(1/G33)-1) | AM33: =IF($G33="","",AL33-AK33) | AN33: =IF($G33="","",(1+AH33)^(1/G33)-1) | AO33: =IF($G33="","",(1+AI33)^(1/G33)-1) | AP33: =IF($G33="","",AO33-AN33)
H34: =IF(G34="","",SUMIFS(Add_Contributions[[#All],[Amount ($)]],Add_Contributions[[#All],[Year]],G34)) | I34: =IF($G34="","",IF($G34=1,(($C$2+$H34)*I$3)*(1+(I$4-I$5)),((I33+($H34*I$3))*(1+(I$4-I$5))))) | J34: =IF($G34="","",IF($G34=1,(($C$2+$H34)*J$3)*(1+(J$4-J$5)),((J33+($H34*J$3))*(1+(J$4-J$5))))) | K34: =IF($G34="","",IF($G34=1,(($C$2+$H34)*K$3)*(1+(K$4-K$5)),((K33+($H34*K$3))*(1+(K$4-K$5))))) | L34: =IF($G34="","",IF($G34=1,(($C$2+$H34)*L$3)*(1+(L$4-L$5)),((L33+($H34*L$3))*(1+(L$4-L$5))))) | M34: =IF($G34="","",IF($G34=1,(($C$2+$H34)*M$3)*(1+(M$4-M$5)),((M33+($H34*M$3))*(1+(M$4-M$5))))) | N34: =IF($G34="","",IF($G34=1,(($C$2+$H34)*N$3)*(1+(N$4-N$5)),((N33+($H34*N$3))*(1+(N$4-N$5))))) | O34: =IF($G34="","",IF($G34=1,(($C$2+$H34)*O$3)*(1+(O$4-O$5)),((O33+($H34*O$3))*(1+(O$4-O$5))))) | P34: =IF($G34="","",IF($G34=1,(($C$2+$H34)*P$3)*(1+(P$4-P$5)),((P33+($H34*P$3))*(1+(P$4-P$5))))) | ... T34: =IF($G34="","",IF($G34=1,(($C$2+$H34)*T$3)*(1+(T$4-T$5)),((T33+($H34*T$3))*(1+(T$4-T$5))))) | U34: =IF(G34="","",SUM(I34,K34,M34,O34,Q34,S34)) | V34: =IF(H34="","",SUM(J34,L34,N34,P34,R34,T34)) | W34: =IF($G34="","",IF($G34=1,(($C$2+$H34)*W$3)*(1+(W$4-W$5)),((W33+($H34*W$3))*(1+(W$4-W$5))))) | X34: =IF($G34="","",IF($G34=1,(($C$2+$H34)*X$3)*(1+(X$4-X$5)),((X33+($H34*X$3))*(1+(X$4-X$5))))) | Y34: =IF($G34="","",IF($G34=1,(U34-$C$2-H34)/($C$2+H34),(U34-U33-H34)/(U33+H34))) | Z34: =IF($G34="","",IF($G34=1,(V34-$C$2-H34)/($C$2+H34),(V34-V33-H34)/(V33+H34))) | AA34: =IF($G34="","",Z34-Y34) | AB34: =IF($G34="","",IF($G34=1,(W34-$C$2-H34)/($C$2+H34),(W34-W33-H34)/(W33+H34))) | AC34: =IF($G34="","",IF($G34=1,(X34-$C$2-H34)/($C$2+H34),(X34-X33-H34)/(X33+H34))) | AD34: =IF($G34="","",AC34-AB34) | AE34: =IF($G34="","",IF($G34=1,Y34,(1+Y34)*(1+AE33)-1)) | AF34: =IF($G34="","",IF($G34=1,Z34,(1+Z34)*(1+AF33)-1)) | AG34: =IF($G34="","",AF34-AE34) | AH34: =IF($G34="","",IF($G34=1,AB34,(1+AB34)*(1+AH33)-1)) | AI34: =IF($G34="","",IF($G34=1,AC34,(1+AC34)*(1+AI33)-1)) | AJ34: =IF($G34="","",AI34-AH34) | AK34: =IF($G34="","",(1+AE34)^(1/G34)-1) | AL34: =IF($G34="","",(1+AF34)^(1/G34)-1) | AM34: =IF($G34="","",AL34-AK34) | AN34: =IF($G34="","",(1+AH34)^(1/G34)-1) | AO34: =IF($G34="","",(1+AI34)^(1/G34)-1) | AP34: =IF($G34="","",AO34-AN34)
H35: =IF(G35="","",SUMIFS(Add_Contributions[[#All],[Amount ($)]],Add_Contributions[[#All],[Year]],G35)) | I35: =IF($G35="","",IF($G35=1,(($C$2+$H35)*I$3)*(1+(I$4-I$5)),((I34+($H35*I$3))*(1+(I$4-I$5))))) | J35: =IF($G35="","",IF($G35=1,(($C$2+$H35)*J$3)*(1+(J$4-J$5)),((J34+($H35*J$3))*(1+(J$4-J$5))))) | K35: =IF($G35="","",IF($G35=1,(($C$2+$H35)*K$3)*(1+(K$4-K$5)),((K34+($H35*K$3))*(1+(K$4-K$5))))) | L35: =IF($G35="","",IF($G35=1,(($C$2+$H35)*L$3)*(1+(L$4-L$5)),((L34+($H35*L$3))*(1+(L$4-L$5))))) | M35: =IF($G35="","",IF($G35=1,(($C$2+$H35)*M$3)*(1+(M$4-M$5)),((M34+($H35*M$3))*(1+(M$4-M$5))))) | N35: =IF($G35="","",IF($G35=1,(($C$2+$H35)*N$3)*(1+(N$4-N$5)),((N34+($H35*N$3))*(1+(N$4-N$5))))) | O35: =IF($G35="","",IF($G35=1,(($C$2+$H35)*O$3)*(1+(O$4-O$5)),((O34+($H35*O$3))*(1+(O$4-O$5))))) | P35: =IF($G35="","",IF($G35=1,(($C$2+$H35)*P$3)*(1+(P$4-P$5)),((P34+($H35*P$3))*(1+(P$4-P$5))))) | ... T35: =IF($G35="","",IF($G35=1,(($C$2+$H35)*T$3)*(1+(T$4-T$5)),((T34+($H35*T$3))*(1+(T$4-T$5))))) | U35: =IF(G35="","",SUM(I35,K35,M35,O35,Q35,S35)) | V35: =IF(H35="","",SUM(J35,L35,N35,P35,R35,T35)) | W35: =IF($G35="","",IF($G35=1,(($C$2+$H35)*W$3)*(1+(W$4-W$5)),((W34+($H35*W$3))*(1+(W$4-W$5))))) | X35: =IF($G35="","",IF($G35=1,(($C$2+$H35)*X$3)*(1+(X$4-X$5)),((X34+($H35*X$3))*(1+(X$4-X$5))))) | Y35: =IF($G35="","",IF($G35=1,(U35-$C$2-H35)/($C$2+H35),(U35-U34-H35)/(U34+H35))) | Z35: =IF($G35="","",IF($G35=1,(V35-$C$2-H35)/($C$2+H35),(V35-V34-H35)/(V34+H35))) | AA35: =IF($G35="","",Z35-Y35) | AB35: =IF($G35="","",IF($G35=1,(W35-$C$2-H35)/($C$2+H35),(W35-W34-H35)/(W34+H35))) | AC35: =IF($G35="","",IF($G35=1,(X35-$C$2-H35)/($C$2+H35),(X35-X34-H35)/(X34+H35))) | AD35: =IF($G35="","",AC35-AB35) | AE35: =IF($G35="","",IF($G35=1,Y35,(1+Y35)*(1+AE34)-1)) | AF35: =IF($G35="","",IF($G35=1,Z35,(1+Z35)*(1+AF34)-1)) | AG35: =IF($G35="","",AF35-AE35) | AH35: =IF($G35="","",IF($G35=1,AB35,(1+AB35)*(1+AH34)-1)) | AI35: =IF($G35="","",IF($G35=1,AC35,(1+AC35)*(1+AI34)-1)) | AJ35: =IF($G35="","",AI35-AH35) | AK35: =IF($G35="","",(1+AE35)^(1/G35)-1) | AL35: =IF($G35="","",(1+AF35)^(1/G35)-1) | AM35: =IF($G35="","",AL35-AK35) | AN35: =IF($G35="","",(1+AH35)^(1/G35)-1) | AO35: =IF($G35="","",(1+AI35)^(1/G35)-1) | AP35: =IF($G35="","",AO35-AN35)
H36: =IF(G36="","",SUMIFS(Add_Contributions[[#All],[Amount ($)]],Add_Contributions[[#All],[Year]],G36)) | I36: =IF($G36="","",IF($G36=1,(($C$2+$H36)*I$3)*(1+(I$4-I$5)),((I35+($H36*I$3))*(1+(I$4-I$5))))) | J36: =IF($G36="","",IF($G36=1,(($C$2+$H36)*J$3)*(1+(J$4-J$5)),((J35+($H36*J$3))*(1+(J$4-J$5))))) | K36: =IF($G36="","",IF($G36=1,(($C$2+$H36)*K$3)*(1+(K$4-K$5)),((K35+($H36*K$3))*(1+(K$4-K$5))))) | L36: =IF($G36="","",IF($G36=1,(($C$2+$H36)*L$3)*(1+(L$4-L$5)),((L35+($H36*L$3))*(1+(L$4-L$5))))) | M36: =IF($G36="","",IF($G36=1,(($C$2+$H36)*M$3)*(1+(M$4-M$5)),((M35+($H36*M$3))*(1+(M$4-M$5))))) | N36: =IF($G36="","",IF($G36=1,(($C$2+$H36)*N$3)*(1+(N$4-N$5)),((N35+($H36*N$3))*(1+(N$4-N$5))))) | O36: =IF($G36="","",IF($G36=1,(($C$2+$H36)*O$3)*(1+(O$4-O$5)),((O35+($H36*O$3))*(1+(O$4-O$5))))) | P36: =IF($G36="","",IF($G36=1,(($C$2+$H36)*P$3)*(1+(P$4-P$5)),((P35+($H36*P$3))*(1+(P$4-P$5))))) | ... T36: =IF($G36="","",IF($G36=1,(($C$2+$H36)*T$3)*(1+(T$4-T$5)),((T35+($H36*T$3))*(1+(T$4-T$5))))) | U36: =IF(G36="","",SUM(I36,K36,M36,O36,Q36,S36)) | V36: =IF(H36="","",SUM(J36,L36,N36,P36,R36,T36)) | W36: =IF($G36="","",IF($G36=1,(($C$2+$H36)*W$3)*(1+(W$4-W$5)),((W35+($H36*W$3))*(1+(W$4-W$5))))) | X36: =IF($G36="","",IF($G36=1,(($C$2+$H36)*X$3)*(1+(X$4-X$5)),((X35+($H36*X$3))*(1+(X$4-X$5))))) | Y36: =IF($G36="","",IF($G36=1,(U36-$C$2-H36)/($C$2+H36),(U36-U35-H36)/(U35+H36))) | Z36: =IF($G36="","",IF($G36=1,(V36-$C$2-H36)/($C$2+H36),(V36-V35-H36)/(V35+H36))) | AA36: =IF($G36="","",Z36-Y36) | AB36: =IF($G36="","",IF($G36=1,(W36-$C$2-H36)/($C$2+H36),(W36-W35-H36)/(W35+H36))) | AC36: =IF($G36="","",IF($G36=1,(X36-$C$2-H36)/($C$2+H36),(X36-X35-H36)/(X35+H36))) | AD36: =IF($G36="","",AC36-AB36) | AE36: =IF($G36="","",IF($G36=1,Y36,(1+Y36)*(1+AE35)-1)) | AF36: =IF($G36="","",IF($G36=1,Z36,(1+Z36)*(1+AF35)-1)) | AG36: =IF($G36="","",AF36-AE36) | AH36: =IF($G36="","",IF($G36=1,AB36,(1+AB36)*(1+AH35)-1)) | AI36: =IF($G36="","",IF($G36=1,AC36,(1+AC36)*(1+AI35)-1)) | AJ36: =IF($G36="","",AI36-AH36) | AK36: =IF($G36="","",(1+AE36)^(1/G36)-1) | AL36: =IF($G36="","",(1+AF36)^(1/G36)-1) | AM36: =IF($G36="","",AL36-AK36) | AN36: =IF($G36="","",(1+AH36)^(1/G36)-1) | AO36: =IF($G36="","",(1+AI36)^(1/G36)-1) | AP36: =IF($G36="","",AO36-AN36)
H37: =IF(G37="","",SUMIFS(Add_Contributions[[#All],[Amount ($)]],Add_Contributions[[#All],[Year]],G37)) | I37: =IF($G37="","",IF($G37=1,(($C$2+$H37)*I$3)*(1+(I$4-I$5)),((I36+($H37*I$3))*(1+(I$4-I$5))))) | J37: =IF($G37="","",IF($G37=1,(($C$2+$H37)*J$3)*(1+(J$4-J$5)),((J36+($H37*J$3))*(1+(J$4-J$5))))) | K37: =IF($G37="","",IF($G37=1,(($C$2+$H37)*K$3)*(1+(K$4-K$5)),((K36+($H37*K$3))*(1+(K$4-K$5))))) | L37: =IF($G37="","",IF($G37=1,(($C$2+$H37)*L$3)*(1+(L$4-L$5)),((L36+($H37*L$3))*(1+(L$4-L$5))))) | M37: =IF($G37="","",IF($G37=1,(($C$2+$H37)*M$3)*(1+(M$4-M$5)),((M36+($H37*M$3))*(1+(M$4-M$5))))) | N37: =IF($G37="","",IF($G37=1,(($C$2+$H37)*N$3)*(1+(N$4-N$5)),((N36+($H37*N$3))*(1+(N$4-N$5))))) | O37: =IF($G37="","",IF($G37=1,(($C$2+$H37)*O$3)*(1+(O$4-O$5)),((O36+($H37*O$3))*(1+(O$4-O$5))))) | P37: =IF($G37="","",IF($G37=1,(($C$2+$H37)*P$3)*(1+(P$4-P$5)),((P36+($H37*P$3))*(1+(P$4-P$5))))) | ... T37: =IF($G37="","",IF($G37=1,(($C$2+$H37)*T$3)*(1+(T$4-T$5)),((T36+($H37*T$3))*(1+(T$4-T$5))))) | U37: =IF(G37="","",SUM(I37,K37,M37,O37,Q37,S37)) | V37: =IF(H37="","",SUM(J37,L37,N37,P37,R37,T37)) | W37: =IF($G37="","",IF($G37=1,(($C$2+$H37)*W$3)*(1+(W$4-W$5)),((W36+($H37*W$3))*(1+(W$4-W$5))))) | X37: =IF($G37="","",IF($G37=1,(($C$2+$H37)*X$3)*(1+(X$4-X$5)),((X36+($H37*X$3))*(1+(X$4-X$5))))) | Y37: =IF($G37="","",IF($G37=1,(U37-$C$2-H37)/($C$2+H37),(U37-U36-H37)/(U36+H37))) | Z37: =IF($G37="","",IF($G37=1,(V37-$C$2-H37)/($C$2+H37),(V37-V36-H37)/(V36+H37))) | AA37: =IF($G37="","",Z37-Y37) | AB37: =IF($G37="","",IF($G37=1,(W37-$C$2-H37)/($C$2+H37),(W37-W36-H37)/(W36+H37))) | AC37: =IF($G37="","",IF($G37=1,(X37-$C$2-H37)/($C$2+H37),(X37-X36-H37)/(X36+H37))) | AD37: =IF($G37="","",AC37-AB37) | AE37: =IF($G37="","",IF($G37=1,Y37,(1+Y37)*(1+AE36)-1)) | AF37: =IF($G37="","",IF($G37=1,Z37,(1+Z37)*(1+AF36)-1)) | AG37: =IF($G37="","",AF37-AE37) | AH37: =IF($G37="","",IF($G37=1,AB37,(1+AB37)*(1+AH36)-1)) | AI37: =IF($G37="","",IF($G37=1,AC37,(1+AC37)*(1+AI36)-1)) | AJ37: =IF($G37="","",AI37-AH37) | AK37: =IF($G37="","",(1+AE37)^(1/G37)-1) | AL37: =IF($G37="","",(1+AF37)^(1/G37)-1) | AM37: =IF($G37="","",AL37-AK37) | AN37: =IF($G37="","",(1+AH37)^(1/G37)-1) | AO37: =IF($G37="","",(1+AI37)^(1/G37)-1) | AP37: =IF($G37="","",AO37-AN37)
H38: =IF(G38="","",SUMIFS(Add_Contributions[[#All],[Amount ($)]],Add_Contributions[[#All],[Year]],G38)) | I38: =IF($G38="","",IF($G38=1,(($C$2+$H38)*I$3)*(1+(I$4-I$5)),((I37+($H38*I$3))*(1+(I$4-I$5))))) | J38: =IF($G38="","",IF($G38=1,(($C$2+$H38)*J$3)*(1+(J$4-J$5)),((J37+($H38*J$3))*(1+(J$4-J$5))))) | K38: =IF($G38="","",IF($G38=1,(($C$2+$H38)*K$3)*(1+(K$4-K$5)),((K37+($H38*K$3))*(1+(K$4-K$5))))) | L38: =IF($G38="","",IF($G38=1,(($C$2+$H38)*L$3)*(1+(L$4-L$5)),((L37+($H38*L$3))*(1+(L$4-L$5))))) | M38: =IF($G38="","",IF($G38=1,(($C$2+$H38)*M$3)*(1+(M$4-M$5)),((M37+($H38*M$3))*(1+(M$4-M$5))))) | N38: =IF($G38="","",IF($G38=1,(($C$2+$H38)*N$3)*(1+(N$4-N$5)),((N37+($H38*N$3))*(1+(N$4-N$5))))) | O38: =IF($G38="","",IF($G38=1,(($C$2+$H38)*O$3)*(1+(O$4-O$5)),((O37+($H38*O$3))*(1+(O$4-O$5))))) | P38: =IF($G38="","",IF($G38=1,(($C$2+$H38)*P$3)*(1+(P$4-P$5)),((P37+($H38*P$3))*(1+(P$4-P$5))))) | ... T38: =IF($G38="","",IF($G38=1,(($C$2+$H38)*T$3)*(1+(T$4-T$5)),((T37+($H38*T$3))*(1+(T$4-T$5))))) | U38: =IF(G38="","",SUM(I38,K38,M38,O38,Q38,S38)) | V38: =IF(H38="","",SUM(J38,L38,N38,P38,R38,T38)) | W38: =IF($G38="","",IF($G38=1,(($C$2+$H38)*W$3)*(1+(W$4-W$5)),((W37+($H38*W$3))*(1+(W$4-W$5))))) | X38: =IF($G38="","",IF($G38=1,(($C$2+$H38)*X$3)*(1+(X$4-X$5)),((X37+($H38*X$3))*(1+(X$4-X$5))))) | Y38: =IF($G38="","",IF($G38=1,(U38-$C$2-H38)/($C$2+H38),(U38-U37-H38)/(U37+H38))) | Z38: =IF($G38="","",IF($G38=1,(V38-$C$2-H38)/($C$2+H38),(V38-V37-H38)/(V37+H38))) | AA38: =IF($G38="","",Z38-Y38) | AB38: =IF($G38="","",IF($G38=1,(W38-$C$2-H38)/($C$2+H38),(W38-W37-H38)/(W37+H38))) | AC38: =IF($G38="","",IF($G38=1,(X38-$C$2-H38)/($C$2+H38),(X38-X37-H38)/(X37+H38))) | AD38: =IF($G38="","",AC38-AB38) | AE38: =IF($G38="","",IF($G38=1,Y38,(1+Y38)*(1+AE37)-1)) | AF38: =IF($G38="","",IF($G38=1,Z38,(1+Z38)*(1+AF37)-1)) | AG38: =IF($G38="","",AF38-AE38) | AH38: =IF($G38="","",IF($G38=1,AB38,(1+AB38)*(1+AH37)-1)) | AI38: =IF($G38="","",IF($G38=1,AC38,(1+AC38)*(1+AI37)-1)) | AJ38: =IF($G38="","",AI38-AH38) | AK38: =IF($G38="","",(1+AE38)^(1/G38)-1) | AL38: =IF($G38="","",(1+AF38)^(1/G38)-1) | AM38: =IF($G38="","",AL38-AK38) | AN38: =IF($G38="","",(1+AH38)^(1/G38)-1) | AO38: =IF($G38="","",(1+AI38)^(1/G38)-1) | AP38: =IF($G38="","",AO38-AN38)
H39: =IF(G39="","",SUMIFS(Add_Contributions[[#All],[Amount ($)]],Add_Contributions[[#All],[Year]],G39)) | I39: =IF($G39="","",IF($G39=1,(($C$2+$H39)*I$3)*(1+(I$4-I$5)),((I38+($H39*I$3))*(1+(I$4-I$5))))) | J39: =IF($G39="","",IF($G39=1,(($C$2+$H39)*J$3)*(1+(J$4-J$5)),((J38+($H39*J$3))*(1+(J$4-J$5))))) | K39: =IF($G39="","",IF($G39=1,(($C$2+$H39)*K$3)*(1+(K$4-K$5)),((K38+($H39*K$3))*(1+(K$4-K$5))))) | L39: =IF($G39="","",IF($G39=1,(($C$2+$H39)*L$3)*(1+(L$4-L$5)),((L38+($H39*L$3))*(1+(L$4-L$5))))) | M39: =IF($G39="","",IF($G39=1,(($C$2+$H39)*M$3)*(1+(M$4-M$5)),((M38+($H39*M$3))*(1+(M$4-M$5))))) | N39: =IF($G39="","",IF($G39=1,(($C$2+$H39)*N$3)*(1+(N$4-N$5)),((N38+($H39*N$3))*(1+(N$4-N$5))))) | O39: =IF($G39="","",IF($G39=1,(($C$2+$H39)*O$3)*(1+(O$4-O$5)),((O38+($H39*O$3))*(1+(O$4-O$5))))) | P39: =IF($G39="","",IF($G39=1,(($C$2+$H39)*P$3)*(1+(P$4-P$5)),((P38+($H39*P$3))*(1+(P$4-P$5))))) | ... T39: =IF($G39="","",IF($G39=1,(($C$2+$H39)*T$3)*(1+(T$4-T$5)),((T38+($H39*T$3))*(1+(T$4-T$5))))) | U39: =IF(G39="","",SUM(I39,K39,M39,O39,Q39,S39)) | V39: =IF(H39="","",SUM(J39,L39,N39,P39,R39,T39)) | W39: =IF($G39="","",IF($G39=1,(($C$2+$H39)*W$3)*(1+(W$4-W$5)),((W38+($H39*W$3))*(1+(W$4-W$5))))) | X39: =IF($G39="","",IF($G39=1,(($C$2+$H39)*X$3)*(1+(X$4-X$5)),((X38+($H39*X$3))*(1+(X$4-X$5))))) | Y39: =IF($G39="","",IF($G39=1,(U39-$C$2-H39)/($C$2+H39),(U39-U38-H39)/(U38+H39))) | Z39: =IF($G39="","",IF($G39=1,(V39-$C$2-H39)/($C$2+H39),(V39-V38-H39)/(V38+H39))) | AA39: =IF($G39="","",Z39-Y39) | AB39: =IF($G39="","",IF($G39=1,(W39-$C$2-H39)/($C$2+H39),(W39-W38-H39)/(W38+H39))) | AC39: =IF($G39="","",IF($G39=1,(X39-$C$2-H39)/($C$2+H39),(X39-X38-H39)/(X38+H39))) | AD39: =IF($G39="","",AC39-AB39) | AE39: =IF($G39="","",IF($G39=1,Y39,(1+Y39)*(1+AE38)-1)) | AF39: =IF($G39="","",IF($G39=1,Z39,(1+Z39)*(1+AF38)-1)) | AG39: =IF($G39="","",AF39-AE39) | AH39: =IF($G39="","",IF($G39=1,AB39,(1+AB39)*(1+AH38)-1)) | AI39: =IF($G39="","",IF($G39=1,AC39,(1+AC39)*(1+AI38)-1)) | AJ39: =IF($G39="","",AI39-AH39) | AK39: =IF($G39="","",(1+AE39)^(1/G39)-1) | AL39: =IF($G39="","",(1+AF39)^(1/G39)-1) | AM39: =IF($G39="","",AL39-AK39) | AN39: =IF($G39="","",(1+AH39)^(1/G39)-1) | AO39: =IF($G39="","",(1+AI39)^(1/G39)-1) | AP39: =IF($G39="","",AO39-AN39)
H40: =IF(G40="","",SUMIFS(Add_Contributions[[#All],[Amount ($)]],Add_Contributions[[#All],[Year]],G40)) | I40: =IF($G40="","",IF($G40=1,(($C$2+$H40)*I$3)*(1+(I$4-I$5)),((I39+($H40*I$3))*(1+(I$4-I$5))))) | J40: =IF($G40="","",IF($G40=1,(($C$2+$H40)*J$3)*(1+(J$4-J$5)),((J39+($H40*J$3))*(1+(J$4-J$5))))) | K40: =IF($G40="","",IF($G40=1,(($C$2+$H40)*K$3)*(1+(K$4-K$5)),((K39+($H40*K$3))*(1+(K$4-K$5))))) | L40: =IF($G40="","",IF($G40=1,(($C$2+$H40)*L$3)*(1+(L$4-L$5)),((L39+($H40*L$3))*(1+(L$4-L$5))))) | M40: =IF($G40="","",IF($G40=1,(($C$2+$H40)*M$3)*(1+(M$4-M$5)),((M39+($H40*M$3))*(1+(M$4-M$5))))) | N40: =IF($G40="","",IF($G40=1,(($C$2+$H40)*N$3)*(1+(N$4-N$5)),((N39+($H40*N$3))*(1+(N$4-N$5))))) | O40: =IF($G40="","",IF($G40=1,(($C$2+$H40)*O$3)*(1+(O$4-O$5)),((O39+($H40*O$3))*(1+(O$4-O$5))))) | P40: =IF($G40="","",IF($G40=1,(($C$2+$H40)*P$3)*(1+(P$4-P$5)),((P39+($H40*P$3))*(1+(P$4-P$5))))) | ... T40: =IF($G40="","",IF($G40=1,(($C$2+$H40)*T$3)*(1+(T$4-T$5)),((T39+($H40*T$3))*(1+(T$4-T$5))))) | U40: =IF(G40="","",SUM(I40,K40,M40,O40,Q40,S40)) | V40: =IF(H40="","",SUM(J40,L40,N40,P40,R40,T40)) | W40: =IF($G40="","",IF($G40=1,(($C$2+$H40)*W$3)*(1+(W$4-W$5)),((W39+($H40*W$3))*(1+(W$4-W$5))))) | X40: =IF($G40="","",IF($G40=1,(($C$2+$H40)*X$3)*(1+(X$4-X$5)),((X39+($H40*X$3))*(1+(X$4-X$5))))) | Y40: =IF($G40="","",IF($G40=1,(U40-$C$2-H40)/($C$2+H40),(U40-U39-H40)/(U39+H40))) | Z40: =IF($G40="","",IF($G40=1,(V40-$C$2-H40)/($C$2+H40),(V40-V39-H40)/(V39+H40))) | AA40: =IF($G40="","",Z40-Y40) | AB40: =IF($G40="","",IF($G40=1,(W40-$C$2-H40)/($C$2+H40),(W40-W39-H40)/(W39+H40))) | AC40: =IF($G40="","",IF($G40=1,(X40-$C$2-H40)/($C$2+H40),(X40-X39-H40)/(X39+H40))) | AD40: =IF($G40="","",AC40-AB40) | AE40: =IF($G40="","",IF($G40=1,Y40,(1+Y40)*(1+AE39)-1)) | AF40: =IF($G40="","",IF($G40=1,Z40,(1+Z40)*(1+AF39)-1)) | AG40: =IF($G40="","",AF40-AE40) | AH40: =IF($G40="","",IF($G40=1,AB40,(1+AB40)*(1+AH39)-1)) | AI40: =IF($G40="","",IF($G40=1,AC40,(1+AC40)*(1+AI39)-1)) | AJ40: =IF($G40="","",AI40-AH40) | AK40: =IF($G40="","",(1+AE40)^(1/G40)-1) | AL40: =IF($G40="","",(1+AF40)^(1/G40)-1) | AM40: =IF($G40="","",AL40-AK40) | AN40: =IF($G40="","",(1+AH40)^(1/G40)-1) | AO40: =IF($G40="","",(1+AI40)^(1/G40)-1) | AP40: =IF($G40="","",AO40-AN40)
H41: =IF(G41="","",SUMIFS(Add_Contributions[[#All],[Amount ($)]],Add_Contributions[[#All],[Year]],G41)) | I41: =IF($G41="","",IF($G41=1,(($C$2+$H41)*I$3)*(1+(I$4-I$5)),((I40+($H41*I$3))*(1+(I$4-I$5))))) | J41: =IF($G41="","",IF($G41=1,(($C$2+$H41)*J$3)*(1+(J$4-J$5)),((J40+($H41*J$3))*(1+(J$4-J$5))))) | K41: =IF($G41="","",IF($G41=1,(($C$2+$H41)*K$3)*(1+(K$4-K$5)),((K40+($H41*K$3))*(1+(K$4-K$5))))) | L41: =IF($G41="","",IF($G41=1,(($C$2+$H41)*L$3)*(1+(L$4-L$5)),((L40+($H41*L$3))*(1+(L$4-L$5))))) | M41: =IF($G41="","",IF($G41=1,(($C$2+$H41)*M$3)*(1+(M$4-M$5)),((M40+($H41*M$3))*(1+(M$4-M$5))))) | N41: =IF($G41="","",IF($G41=1,(($C$2+$H41)*N$3)*(1+(N$4-N$5)),((N40+($H41*N$3))*(1+(N$4-N$5))))) | O41: =IF($G41="","",IF($G41=1,(($C$2+$H41)*O$3)*(1+(O$4-O$5)),((O40+($H41*O$3))*(1+(O$4-O$5))))) | P41: =IF($G41="","",IF($G41=1,(($C$2+$H41)*P$3)*(1+(P$4-P$5)),((P40+($H41*P$3))*(1+(P$4-P$5))))) | ... T41: =IF($G41="","",IF($G41=1,(($C$2+$H41)*T$3)*(1+(T$4-T$5)),((T40+($H41*T$3))*(1+(T$4-T$5))))) | U41: =IF(G41="","",SUM(I41,K41,M41,O41,Q41,S41)) | V41: =IF(H41="","",SUM(J41,L41,N41,P41,R41,T41)) | W41: =IF($G41="","",IF($G41=1,(($C$2+$H41)*W$3)*(1+(W$4-W$5)),((W40+($H41*W$3))*(1+(W$4-W$5))))) | X41: =IF($G41="","",IF($G41=1,(($C$2+$H41)*X$3)*(1+(X$4-X$5)),((X40+($H41*X$3))*(1+(X$4-X$5))))) | Y41: =IF($G41="","",IF($G41=1,(U41-$C$2-H41)/($C$2+H41),(U41-U40-H41)/(U40+H41))) | Z41: =IF($G41="","",IF($G41=1,(V41-$C$2-H41)/($C$2+H41),(V41-V40-H41)/(V40+H41))) | AA41: =IF($G41="","",Z41-Y41) | AB41: =IF($G41="","",IF($G41=1,(W41-$C$2-H41)/($C$2+H41),(W41-W40-H41)/(W40+H41))) | AC41: =IF($G41="","",IF($G41=1,(X41-$C$2-H41)/($C$2+H41),(X41-X40-H41)/(X40+H41))) | AD41: =IF($G41="","",AC41-AB41) | AE41: =IF($G41="","",IF($G41=1,Y41,(1+Y41)*(1+AE40)-1)) | AF41: =IF($G41="","",IF($G41=1,Z41,(1+Z41)*(1+AF40)-1)) | AG41: =IF($G41="","",AF41-AE41) | AH41: =IF($G41="","",IF($G41=1,AB41,(1+AB41)*(1+AH40)-1)) | AI41: =IF($G41="","",IF($G41=1,AC41,(1+AC41)*(1+AI40)-1)) | AJ41: =IF($G41="","",AI41-AH41) | AK41: =IF($G41="","",(1+AE41)^(1/G41)-1) | AL41: =IF($G41="","",(1+AF41)^(1/G41)-1) | AM41: =IF($G41="","",AL41-AK41) | AN41: =IF($G41="","",(1+AH41)^(1/G41)-1) | AO41: =IF($G41="","",(1+AI41)^(1/G41)-1) | AP41: =IF($G41="","",AO41-AN41)
H42: =IF(G42="","",SUMIFS(Add_Contributions[[#All],[Amount ($)]],Add_Contributions[[#All],[Year]],G42)) | I42: =IF($G42="","",IF($G42=1,(($C$2+$H42)*I$3)*(1+(I$4-I$5)),((I41+($H42*I$3))*(1+(I$4-I$5))))) | J42: =IF($G42="","",IF($G42=1,(($C$2+$H42)*J$3)*(1+(J$4-J$5)),((J41+($H42*J$3))*(1+(J$4-J$5))))) | K42: =IF($G42="","",IF($G42=1,(($C$2+$H42)*K$3)*(1+(K$4-K$5)),((K41+($H42*K$3))*(1+(K$4-K$5))))) | L42: =IF($G42="","",IF($G42=1,(($C$2+$H42)*L$3)*(1+(L$4-L$5)),((L41+($H42*L$3))*(1+(L$4-L$5))))) | M42: =IF($G42="","",IF($G42=1,(($C$2+$H42)*M$3)*(1+(M$4-M$5)),((M41+($H42*M$3))*(1+(M$4-M$5))))) | N42: =IF($G42="","",IF($G42=1,(($C$2+$H42)*N$3)*(1+(N$4-N$5)),((N41+($H42*N$3))*(1+(N$4-N$5))))) | O42: =IF($G42="","",IF($G42=1,(($C$2+$H42)*O$3)*(1+(O$4-O$5)),((O41+($H42*O$3))*(1+(O$4-O$5))))) | P42: =IF($G42="","",IF($G42=1,(($C$2+$H42)*P$3)*(1+(P$4-P$5)),((P41+($H42*P$3))*(1+(P$4-P$5))))) | ... T42: =IF($G42="","",IF($G42=1,(($C$2+$H42)*T$3)*(1+(T$4-T$5)),((T41+($H42*T$3))*(1+(T$4-T$5))))) | U42: =IF(G42="","",SUM(I42,K42,M42,O42,Q42,S42)) | V42: =IF(H42="","",SUM(J42,L42,N42,P42,R42,T42)) | W42: =IF($G42="","",IF($G42=1,(($C$2+$H42)*W$3)*(1+(W$4-W$5)),((W41+($H42*W$3))*(1+(W$4-W$5))))) | X42: =IF($G42="","",IF($G42=1,(($C$2+$H42)*X$3)*(1+(X$4-X$5)),((X41+($H42*X$3))*(1+(X$4-X$5))))) | Y42: =IF($G42="","",IF($G42=1,(U42-$C$2-H42)/($C$2+H42),(U42-U41-H42)/(U41+H42))) | Z42: =IF($G42="","",IF($G42=1,(V42-$C$2-H42)/($C$2+H42),(V42-V41-H42)/(V41+H42))) | AA42: =IF($G42="","",Z42-Y42) | AB42: =IF($G42="","",IF($G42=1,(W42-$C$2-H42)/($C$2+H42),(W42-W41-H42)/(W41+H42))) | AC42: =IF($G42="","",IF($G42=1,(X42-$C$2-H42)/($C$2+H42),(X42-X41-H42)/(X41+H42))) | AD42: =IF($G42="","",AC42-AB42) | AE42: =IF($G42="","",IF($G42=1,Y42,(1+Y42)*(1+AE41)-1)) | AF42: =IF($G42="","",IF($G42=1,Z42,(1+Z42)*(1+AF41)-1)) | AG42: =IF($G42="","",AF42-AE42) | AH42: =IF($G42="","",IF($G42=1,AB42,(1+AB42)*(1+AH41)-1)) | AI42: =IF($G42="","",IF($G42=1,AC42,(1+AC42)*(1+AI41)-1)) | AJ42: =IF($G42="","",AI42-AH42) | AK42: =IF($G42="","",(1+AE42)^(1/G42)-1) | AL42: =IF($G42="","",(1+AF42)^(1/G42)-1) | AM42: =IF($G42="","",AL42-AK42) | AN42: =IF($G42="","",(1+AH42)^(1/G42)-1) | AO42: =IF($G42="","",(1+AI42)^(1/G42)-1) | AP42: =IF($G42="","",AO42-AN42)
... H109: =IF(G109="","",SUMIFS(Add_Contributions[[#All],[Amount ($)]],Add_Contributions[[#All],[Year]],G109)) | I109: =IF($G109="","",IF($G109=1,(($C$2+$H109)*I$3)*(1+(I$4-I$5)),((I108+($H109*I$3))*(1+(I$4-I$5))))) | J109: =IF($G109="","",IF($G109=1,(($C$2+$H109)*J$3)*(1+(J$4-J$5)),((J108+($H109*J$3))*(1+(J$4-J$5))))) | K109: =IF($G109="","",IF($G109=1,(($C$2+$H109)*K$3)*(1+(K$4-K$5)),((K108+($H109*K$3))*(1+(K$4-K$5))))) | L109: =IF($G109="","",IF($G109=1,(($C$2+$H109)*L$3)*(1+(L$4-L$5)),((L108+($H109*L$3))*(1+(L$4-L$5))))) | M109: =IF($G109="","",IF($G109=1,(($C$2+$H109)*M$3)*(1+(M$4-M$5)),((M108+($H109*M$3))*(1+(M$4-M$5))))) | N109: =IF($G109="","",IF($G109=1,(($C$2+$H109)*N$3)*(1+(N$4-N$5)),((N108+($H109*N$3))*(1+(N$4-N$5))))) | O109: =IF($G109="","",IF($G109=1,(($C$2+$H109)*O$3)*(1+(O$4-O$5)),((O108+($H109*O$3))*(1+(O$4-O$5))))) | P109: =IF($G109="","",IF($G109=1,(($C$2+$H109)*P$3)*(1+(P$4-P$5)),((P108+($H109*P$3))*(1+(P$4-P$5))))) | ... T109: =IF($G109="","",IF($G109=1,(($C$2+$H109)*T$3)*(1+(T$4-T$5)),((T108+($H109*T$3))*(1+(T$4-T$5))))) | U109: =IF(G109="","",SUM(I109,K109,M109,O109,Q109,S109)) | V109: =IF(H109="","",SUM(J109,L109,N109,P109,R109,T109)) | W109: =IF($G109="","",IF($G109=1,(($C$2+$H109)*W$3)*(1+(W$4-W$5)),((W108+($H109*W$3))*(1+(W$4-W$5))))) | X109: =IF($G109="","",IF($G109=1,(($C$2+$H109)*X$3)*(1+(X$4-X$5)),((X108+($H109*X$3))*(1+(X$4-X$5))))) | Y109: =IF($G109="","",IF($G109=1,(U109-$C$2-H109)/($C$2+H109),(U109-U108-H109)/(U108+H109))) | Z109: =IF($G109="","",IF($G109=1,(V109-$C$2-H109)/($C$2+H109),(V109-V108-H109)/(V108+H109))) | AA109: =IF($G109="","",Z109-Y109) | AB109: =IF($G109="","",IF($G109=1,(W109-$C$2-H109)/($C$2+H109),(W109-W108-H109)/(W108+H109))) | AC109: =IF($G109="","",IF($G109=1,(X109-$C$2-H109)/($C$2+H109),(X109-X108-H109)/(X108+H109))) | AD109: =IF($G109="","",AC109-AB109) | AE109: =IF($G109="","",IF($G109=1,Y109,(1+Y109)*(1+AE108)-1)) | AF109: =IF($G109="","",IF($G109=1,Z109,(1+Z109)*(1+AF108)-1)) | AG109: =IF($G109="","",AF109-AE109) | AH109: =IF($G109="","",IF($G109=1,AB109,(1+AB109)*(1+AH108)-1)) | AI109: =IF($G109="","",IF($G109=1,AC109,(1+AC109)*(1+AI108)-1)) | AJ109: =IF($G109="","",AI109-AH109) | AK109: =IF($G109="","",(1+AE109)^(1/G109)-1) | AL109: =IF($G109="","",(1+AF109)^(1/G109)-1) | AM109: =IF($G109="","",AL109-AK109) | AN109: =IF($G109="","",(1+AH109)^(1/G109)-1) | AO109: =IF($G109="","",(1+AI109)^(1/G109)-1) | AP109: =IF($G109="","",AO109-AN109)

Sheet 2
B2: Initial Capital ($) | C2: ='Return Simulator'!D47 -> 10000000 | I2: Stocks (Taxable) | J2: Stocks (Taxable) | K2: Stocks (PPLI) | L2: Stocks (PPLI) | M2: Bonds (Taxable) | N2: Bonds (Taxable) | O2: Bonds (PPLI) | P2: Bonds (PPLI) | Q2: Alternatives (Taxable) | R2: Alternatives (Taxable) | S2: Alternatives (PPLI) | T2: Alternatives (PPLI) | W2: Weighted Average | X2: Weighted Average
B3: Time Horizon (Years) | C3: ='Return Simulator'!D48 -> 20 | H3: Weight | I3: =$D$7*(1-$E$7) -> 0.432 | J3: =$D$7*(1-$E$7) -> 0.432 | K3: =$D$7*$E$7 -> 0.048 | L3: =$D$7*$E$7 -> 0.048 | M3: =$D$8*(1-$E$8) -> 0.288 | N3: =$D$8*(1-$E$8) -> 0.288 | O3: =$D$8*$E$8 -> 0.032 | P3: =$D$8*$E$8 -> 0.032 | Q3: =$D$9*(1-$E$9) -> 0.18 | R3: =$D$9*(1-$E$9) -> 0.18 | S3: =$D$9*$E$9 -> 0.02 | T3: =$D$9*$E$9 -> 0.02 | W3: =SUM(I3,K3,M3,O3,Q3,S3) -> 1 | X3: =SUM(J3,L3,N3,P3,R3,T3) -> 1
H4: Return | I4: =$C$7 -> 0.08 | J4: =$C$7 -> 0.08 | K4: =$C$7 -> 0.08 | L4: =$C$7 -> 0.08 | M4: =$C$8 -> 0.05 | N4: =$C$8 -> 0.05 | O4: =$C$8 -> 0.05 | P4: =$C$8 -> 0.05 | Q4: =$C$9 -> 0.08 | R4: =$C$9 -> 0.08 | S4: =$C$9 -> 0.08 | T4: =$C$9 -> 0.08 | W4: =SUMPRODUCT(I3:T3,I4:T4)/2 -> 0.0704 | X4: =SUMPRODUCT(I3:T3,I4:T4)/2 -> 0.0704
D5: =IF(SUM(D7:D9)<>1,"Error","Good") -> Good | H5: Drag | I5: 0 | J5: =$C$7*($C$15+$C$16) -> 0.01904 | K5: 0 | L5: =$C$11 -> 0.005 | M5: 0 | N5: =$C$8*($C$14+$C$16) -> 0.0204 | O5: 0 | P5: =$C$11 -> 0.005 | Q5: 0 | R5: =(50%*$C$9*($C$14+$C$16))+(50%*$C$9*($C$15+$C$16)) -> 0.02584 | S5: 0 | T5: =$C$11 -> 0.005 | W5: 0 | X5: =SUMPRODUCT(J3:T3,J5:T5) -> 0.01925168
C6: Returns | D6: Weight | E6: PPLI Allocation
B7: Stocks | C7: ='Return Simulator'!D56 -> 0.08 | D7: ='Return Simulator'!D51 -> 0.48 | E7: 0.1 | U7: Buy & Hold | V7: Buy & Hold | W7: Rebalanced | X7: Rebalanced | Y7: Buy & Hold | Z7: Buy & Hold | AA7: Buy & Hold | AB7: Rebalanced | AC7: Rebalanced | AD7: Rebalanced | AE7: Buy & Hold | AF7: Buy & Hold | AG7: Buy & Hold | AH7: Rebalanced | AI7: Rebalanced | AJ7: Rebalanced | AK7: Buy & Hold | AL7: Buy & Hold | AM7: Buy & Hold | AN7: Rebalanced | AO7: Rebalanced | AP7: Rebalanced
B8: Bonds | C8: ='Return Simulator'!D57 -> 0.05 | D8: ='Return Simulator'!D52 -> 0.32 | E8: 0.1 | I8: Gross | J8: Net | K8: Gross | L8: Net | M8: Gross | N8: Net | O8: Gross | P8: Net | Q8: Gross | R8: Net | S8: Gross | T8: Net | U8: Gross | V8: Net | W8: Gross | X8: Net | Y8: Gross | Z8: Net | AB8: Gross | AC8: Net | AE8: Gross | AF8: Net | AH8: Gross | AI8: Net | AK8: Gross | AL8: Net | AN8: Gross | AO8: Net
B9: Alternatives | C9: ='Return Simulator'!D58 -> 0.08 | D9: ='Return Simulator'!D53 -> 0.2 | E9: 0.1 | G9: Year | H9: Contributions | I9: Stocks (Taxable) | J9: Stocks (Taxable) | K9: Stocks (PPLI) | L9: Stocks (PPLI) | M9: Bonds (Taxable) | N9: Bonds (Taxable) | O9: Bonds (PPLI) | P9: Bonds (PPLI) | Q9: Alternatives (Taxable) | R9: Alternatives (Taxable) | S9: Alternatives (PPLI) | T9: Alternatives (PPLI) | U9: Total | V9: Total | W9: Total | X9: Total | Y9: Period Return | Z9: Period Return | AA9: Period Drag | AB9: Period Return | AC9: Period Return | AD9: Period Drag | AE9: Total Return | AF9: Total Return | AG9: Total Drag | AH9: Total Return | AI9: Total Return | AJ9: Total Drag | AK9: Total Return (Annualized) | AL9: Total Return (Annualized) | AM9: Annaulized Drag | AN9: Total Return (Annualized) | AO9: Total Return (Annualized) | AP9: Annaulized Drag
D10: * Weights Static | E10: * Weights Static | G10: {=_xlfn.SEQUENCE(C3,1,1,1)} -> 1 | H10: =IF(G10="","",SUMIFS(Add_Contributions[[#All],[Amount ($)]],Add_Contributions[[#All],[Year]],G10)) -> 0 | I10: =IF($G10="","",IF($G10=1,(($C$2+$H10)*I$3)*(1+(I$4-I$5)),((I9+($H10*I$3))*(1+(I$4-I$5))))) -> 4665600 | J10: =IF($G10="","",IF($G10=1,(($C$2+$H10)*J$3)*(1+(J$4-J$5)),((J9+($H10*J$3))*(1+(J$4-J$5))))) -> 4583347.2 | K10: =IF($G10="","",IF($G10=1,(($C$2+$H10)*K$3)*(1+(K$4-K$5)),((K9+($H10*K$3))*(1+(K$4-K$5))))) -> 518400 | L10: =IF($G10="","",IF($G10=1,(($C$2+$H10)*L$3)*(1+(L$4-L$5)),((L9+($H10*L$3))*(1+(L$4-L$5))))) -> 516000 | M10: =IF($G10="","",IF($G10=1,(($C$2+$H10)*M$3)*(1+(M$4-M$5)),((M9+($H10*M$3))*(1+(M$4-M$5))))) -> 3024000 | N10: =IF($G10="","",IF($G10=1,(($C$2+$H10)*N$3)*(1+(N$4-N$5)),((N9+($H10*N$3))*(1+(N$4-N$5))))) -> 2965248 | O10: =IF($G10="","",IF($G10=1,(($C$2+$H10)*O$3)*(1+(O$4-O$5)),((O9+($H10*O$3))*(1+(O$4-O$5))))) -> 336000 | P10: =IF($G10="","",IF($G10=1,(($C$2+$H10)*P$3)*(1+(P$4-P$5)),((P9+($H10*P$3))*(1+(P$4-P$5))))) -> 334400 | ... T10: =IF($G10="","",IF($G10=1,(($C$2+$H10)*T$3)*(1+(T$4-T$5)),((T9+($H10*T$3))*(1+(T$4-T$5))))) -> 215000 | U10: =IF(G10="","",SUM(I10,K10,M10,O10,Q10,S10)) -> 10704000 | V10: =IF(H10="","",SUM(J10,L10,N10,P10,R10,T10)) -> 10511483 | W10: =IF($G10="","",IF($G10=1,(($C$2+$H10)*W$3)*(1+(W$4-W$5)),((W9+($H10*W$3))*(1+(W$4-W$5))))) -> 10704000 | X10: =IF($G10="","",IF($G10=1,(($C$2+$H10)*X$3)*(1+(X$4-X$5)),((X9+($H10*X$3))*(1+(X$4-X$5))))) -> 10511483 | Y10: =IF($G10="","",IF($G10=1,(U10-$C$2-H10)/($C$2+H10),(U10-U9-H10)/(U9+H10))) -> 0.0704 | Z10: =IF($G10="","",IF($G10=1,(V10-$C$2-H10)/($C$2+H10),(V10-V9-H10)/(V9+H10))) -> 0.05114832 | AA10: =IF($G10="","",Z10-Y10) -> -0.01925168 | AB10: =IF($G10="","",IF($G10=1,(W10-$C$2-H10)/($C$2+H10),(W10-W9-H10)/(W9+H10))) -> 0.0704 | AC10: =IF($G10="","",IF($G10=1,(X10-$C$2-H10)/($C$2+H10),(X10-X9-H10)/(X9+H10))) -> 0.05114832 | AD10: =IF($G10="","",AC10-AB10) -> -0.01925168 | AE10: =IF($G10="","",IF($G10=1,Y10,(1+Y10)*(1+AE9)-1)) -> 0.0704 | AF10: =IF($G10="","",IF($G10=1,Z10,(1+Z10)*(1+AF9)-1)) -> 0.05114832 | AG10: =IF($G10="","",AF10-AE10) -> -0.01925168 | AH10: =IF($G10="","",IF($G10=1,AB10,(1+AB10)*(1+AH9)-1)) -> 0.0704 | AI10: =IF($G10="","",IF($G10=1,AC10,(1+AC10)*(1+AI9)-1)) -> 0.05114832 | AJ10: =IF($G10="","",AI10-AH10) -> -0.01925168 | AK10: =IF($G10="","",(1+AE10)^(1/G10)-1) -> 0.0704 | AL10: =IF($G10="","",(1+AF10)^(1/G10)-1) -> 0.05114832 | AM10: =IF($G10="","",AL10-AK10) -> -0.01925168 | AN10: =IF($G10="","",(1+AH10)^(1/G10)-1) -> 0.0704 | AO10: =IF($G10="","",(1+AI10)^(1/G10)-1) -> 0.05114832 | AP10: =IF($G10="","",AO10-AN10) -> -0.01925168
B11: PPLI Policy Costs | C11: ='Return Simulator'!D71 -> 0.005 | G11: 2 | H11: =IF(G11="","",SUMIFS(Add_Contributions[[#All],[Amount ($)]],Add_Contributions[[#All],[Year]],G11)) -> 0 | I11: =IF($G11="","",IF($G11=1,(($C$2+$H11)*I$3)*(1+(I$4-I$5)),((I10+($H11*I$3))*(1+(I$4-I$5))))) -> 5038848 | J11: =IF($G11="","",IF($G11=1,(($C$2+$H11)*J$3)*(1+(J$4-J$5)),((J10+($H11*J$3))*(1+(J$4-J$5))))) -> 4862748 | K11: =IF($G11="","",IF($G11=1,(($C$2+$H11)*K$3)*(1+(K$4-K$5)),((K10+($H11*K$3))*(1+(K$4-K$5))))) -> 559872 | L11: =IF($G11="","",IF($G11=1,(($C$2+$H11)*L$3)*(1+(L$4-L$5)),((L10+($H11*L$3))*(1+(L$4-L$5))))) -> 554700 | M11: =IF($G11="","",IF($G11=1,(($C$2+$H11)*M$3)*(1+(M$4-M$5)),((M10+($H11*M$3))*(1+(M$4-M$5))))) -> 3175200 | N11: =IF($G11="","",IF($G11=1,(($C$2+$H11)*N$3)*(1+(N$4-N$5)),((N10+($H11*N$3))*(1+(N$4-N$5))))) -> 3053019.3 | O11: =IF($G11="","",IF($G11=1,(($C$2+$H11)*O$3)*(1+(O$4-O$5)),((O10+($H11*O$3))*(1+(O$4-O$5))))) -> 352800 | P11: =IF($G11="","",IF($G11=1,(($C$2+$H11)*P$3)*(1+(P$4-P$5)),((P10+($H11*P$3))*(1+(P$4-P$5))))) -> 349448 | ... T11: =IF($G11="","",IF($G11=1,(($C$2+$H11)*T$3)*(1+(T$4-T$5)),((T10+($H11*T$3))*(1+(T$4-T$5))))) -> 231125 | U11: =IF(G11="","",SUM(I11,K11,M11,O11,Q11,S11)) -> 11459520 | V11: =IF(H11="","",SUM(J11,L11,N11,P11,R11,T11)) -> 11051296 | W11: =IF($G11="","",IF($G11=1,(($C$2+$H11)*W$3)*(1+(W$4-W$5)),((W10+($H11*W$3))*(1+(W$4-W$5))))) -> 11457562 | X11: =IF($G11="","",IF($G11=1,(($C$2+$H11)*X$3)*(1+(X$4-X$5)),((X10+($H11*X$3))*(1+(X$4-X$5))))) -> 11049128 | Y11: =IF($G11="","",IF($G11=1,(U11-$C$2-H11)/($C$2+H11),(U11-U10-H11)/(U10+H11))) -> 0.07058296 | Z11: =IF($G11="","",IF($G11=1,(V11-$C$2-H11)/($C$2+H11),(V11-V10-H11)/(V10+H11))) -> 0.051354612 | AA11: =IF($G11="","",Z11-Y11) -> -0.019228348 | AB11: =IF($G11="","",IF($G11=1,(W11-$C$2-H11)/($C$2+H11),(W11-W10-H11)/(W10+H11))) -> 0.0704 | AC11: =IF($G11="","",IF($G11=1,(X11-$C$2-H11)/($C$2+H11),(X11-X10-H11)/(X10+H11))) -> 0.05114832 | AD11: =IF($G11="","",AC11-AB11) -> -0.01925168 | AE11: =IF($G11="","",IF($G11=1,Y11,(1+Y11)*(1+AE10)-1)) -> 0.145952 | AF11: =IF($G11="","",IF($G11=1,Z11,(1+Z11)*(1+AF10)-1)) -> 0.10512963 | AG11: =IF($G11="","",AF11-AE11) -> -0.040822366 | AH11: =IF($G11="","",IF($G11=1,AB11,(1+AB11)*(1+AH10)-1)) -> 0.14575616 | AI11: =IF($G11="","",IF($G11=1,AC11,(1+AC11)*(1+AI10)-1)) -> 0.10491279 | AJ11: =IF($G11="","",AI11-AH11) -> -0.040843369 | AK11: =IF($G11="","",(1+AE11)^(1/G11)-1) -> 0.070491476 | AL11: =IF($G11="","",(1+AF11)^(1/G11)-1) -> 0.051251461 | AM11: =IF($G11="","",AL11-AK11) -> -0.019240015 | AN11: =IF($G11="","",(1+AH11)^(1/G11)-1) -> 0.0704 | AO11: =IF($G11="","",(1+AI11)^(1/G11)-1) -> 0.05114832 | AP11: =IF($G11="","",AO11-AN11) -> -0.01925168
B12: PPLI Start Up Costs | G12: 3 | H12: =IF(G12="","",SUMIFS(Add_Contributions[[#All],[Amount ($)]],Add_Contributions[[#All],[Year]],G12)) -> 0 | I12: =IF($G12="","",IF($G12=1,(($C$2+$H12)*I$3)*(1+(I$4-I$5)),((I11+($H12*I$3))*(1+(I$4-I$5))))) -> 5441955.8 | J12: =IF($G12="","",IF($G12=1,(($C$2+$H12)*J$3)*(1+(J$4-J$5)),((J11+($H12*J$3))*(1+(J$4-J$5))))) -> 5159181.2 | K12: =IF($G12="","",IF($G12=1,(($C$2+$H12)*K$3)*(1+(K$4-K$5)),((K11+($H12*K$3))*(1+(K$4-K$5))))) -> 604661.76 | L12: =IF($G12="","",IF($G12=1,(($C$2+$H12)*L$3)*(1+(L$4-L$5)),((L11+($H12*L$3))*(1+(L$4-L$5))))) -> 596302.5 | M12: =IF($G12="","",IF($G12=1,(($C$2+$H12)*M$3)*(1+(M$4-M$5)),((M11+($H12*M$3))*(1+(M$4-M$5))))) -> 3333960 | N12: =IF($G12="","",IF($G12=1,(($C$2+$H12)*N$3)*(1+(N$4-N$5)),((N11+($H12*N$3))*(1+(N$4-N$5))))) -> 3143388.7 | O12: =IF($G12="","",IF($G12=1,(($C$2+$H12)*O$3)*(1+(O$4-O$5)),((O11+($H12*O$3))*(1+(O$4-O$5))))) -> 370440 | P12: =IF($G12="","",IF($G12=1,(($C$2+$H12)*P$3)*(1+(P$4-P$5)),((P11+($H12*P$3))*(1+(P$4-P$5))))) -> 365173.16 | ... T12: =IF($G12="","",IF($G12=1,(($C$2+$H12)*T$3)*(1+(T$4-T$5)),((T11+($H12*T$3))*(1+(T$4-T$5))))) -> 248459.38 | U12: =IF(G12="","",SUM(I12,K12,M12,O12,Q12,S12)) -> 12270442 | V12: =IF(H12="","",SUM(J12,L12,N12,P12,R12,T12)) -> 11621095 | W12: =IF($G12="","",IF($G12=1,(($C$2+$H12)*W$3)*(1+(W$4-W$5)),((W11+($H12*W$3))*(1+(W$4-W$5))))) -> 12264174 | X12: =IF($G12="","",IF($G12=1,(($C$2+$H12)*X$3)*(1+(X$4-X$5)),((X11+($H12*X$3))*(1+(X$4-X$5))))) -> 11614272 | Y12: =IF($G12="","",IF($G12=1,(U12-$C$2-H12)/($C$2+H12),(U12-U11-H12)/(U11+H12))) -> 0.070764011 | Z12: =IF($G12="","",IF($G12=1,(V12-$C$2-H12)/($C$2+H12),(V12-V11-H12)/(V11+H12))) -> 0.051559416 | AA12: =IF($G12="","",Z12-Y12) -> -0.019204595 | AB12: =IF($G12="","",IF($G12=1,(W12-$C$2-H12)/($C$2+H12),(W12-W11-H12)/(W11+H12))) -> 0.0704 | AC12: =IF($G12="","",IF($G12=1,(X12-$C$2-H12)/($C$2+H12),(X12-X11-H12)/(X11+H12))) -> 0.05114832 | AD12: =IF($G12="","",AC12-AB12) -> -0.01925168 | AE12: =IF($G12="","",IF($G12=1,Y12,(1+Y12)*(1+AE11)-1)) -> 0.22704416 | AF12: =IF($G12="","",IF($G12=1,Z12,(1+Z12)*(1+AF11)-1)) -> 0.16210947 | AG12: =IF($G12="","",AF12-AE12) -> -0.064934687 | AH12: =IF($G12="","",IF($G12=1,AB12,(1+AB12)*(1+AH11)-1)) -> 0.22641739 | AI12: =IF($G12="","",IF($G12=1,AC12,(1+AC12)*(1+AI11)-1)) -> 0.16142722 | AJ12: =IF($G12="","",AI12-AH12) -> -0.06499017 | AK12: =IF($G12="","",(1+AE12)^(1/G12)-1) -> 0.070582313 | AL12: =IF($G12="","",(1+AF12)^(1/G12)-1) -> 0.051354103 | AM12: =IF($G12="","",AL12-AK12) -> -0.019228211 | AN12: =IF($G12="","",(1+AH12)^(1/G12)-1) -> 0.0704 | AO12: =IF($G12="","",(1+AI12)^(1/G12)-1) -> 0.05114832 | AP12: =IF($G12="","",AO12-AN12) -> -0.01925168
G13: 4 | H13: =IF(G13="","",SUMIFS(Add_Contributions[[#All],[Amount ($)]],Add_Contributions[[#All],[Year]],G13)) -> 0 | I13: =IF($G13="","",IF($G13=1,(($C$2+$H13)*I$3)*(1+(I$4-I$5)),((I12+($H13*I$3))*(1+(I$4-I$5))))) -> 5877312.3 | J13: =IF($G13="","",IF($G13=1,(($C$2+$H13)*J$3)*(1+(J$4-J$5)),((J12+($H13*J$3))*(1+(J$4-J$5))))) -> 5473684.9 | K13: =IF($G13="","",IF($G13=1,(($C$2+$H13)*K$3)*(1+(K$4-K$5)),((K12+($H13*K$3))*(1+(K$4-K$5))))) -> 653034.7 | L13: =IF($G13="","",IF($G13=1,(($C$2+$H13)*L$3)*(1+(L$4-L$5)),((L12+($H13*L$3))*(1+(L$4-L$5))))) -> 641025.19 | M13: =IF($G13="","",IF($G13=1,(($C$2+$H13)*M$3)*(1+(M$4-M$5)),((M12+($H13*M$3))*(1+(M$4-M$5))))) -> 3500658 | N13: =IF($G13="","",IF($G13=1,(($C$2+$H13)*N$3)*(1+(N$4-N$5)),((N12+($H13*N$3))*(1+(N$4-N$5))))) -> 3236433 | O13: =IF($G13="","",IF($G13=1,(($C$2+$H13)*O$3)*(1+(O$4-O$5)),((O12+($H13*O$3))*(1+(O$4-O$5))))) -> 388962 | P13: =IF($G13="","",IF($G13=1,(($C$2+$H13)*P$3)*(1+(P$4-P$5)),((P12+($H13*P$3))*(1+(P$4-P$5))))) -> 381605.95 | ... T13: =IF($G13="","",IF($G13=1,(($C$2+$H13)*T$3)*(1+(T$4-T$5)),((T12+($H13*T$3))*(1+(T$4-T$5))))) -> 267093.83 | U13: =IF(G13="","",SUM(I13,K13,M13,O13,Q13,S13)) -> 13140945 | V13: =IF(H13="","",SUM(J13,L13,N13,P13,R13,T13)) -> 12222634 | W13: =IF($G13="","",IF($G13=1,(($C$2+$H13)*W$3)*(1+(W$4-W$5)),((W12+($H13*W$3))*(1+(W$4-W$5))))) -> 13127572 | X13: =IF($G13="","",IF($G13=1,(($C$2+$H13)*X$3)*(1+(X$4-X$5)),((X12+($H13*X$3))*(1+(X$4-X$5))))) -> 12208323 | Y13: =IF($G13="","",IF($G13=1,(U13-$C$2-H13)/($C$2+H13),(U13-U12-H13)/(U12+H13))) -> 0.070943113 | Z13: =IF($G13="","",IF($G13=1,(V13-$C$2-H13)/($C$2+H13),(V13-V12-H13)/(V12+H13))) -> 0.051762692 | AA13: =IF($G13="","",Z13-Y13) -> -0.019180421 | AB13: =IF($G13="","",IF($G13=1,(W13-$C$2-H13)/($C$2+H13),(W13-W12-H13)/(W12+H13))) -> 0.0704 | AC13: =IF($G13="","",IF($G13=1,(X13-$C$2-H13)/($C$2+H13),(X13-X12-H13)/(X12+H13))) -> 0.05114832 | AD13: =IF($G13="","",AC13-AB13) -> -0.01925168 | AE13: =IF($G13="","",IF($G13=1,Y13,(1+Y13)*(1+AE12)-1)) -> 0.31409449 | AF13: =IF($G13="","",IF($G13=1,Z13,(1+Z13)*(1+AF12)-1)) -> 0.22226339 | AG13: =IF($G13="","",AF13-AE13) -> -0.091831105 | AH13: =IF($G13="","",IF($G13=1,AB13,(1+AB13)*(1+AH12)-1)) -> 0.31275718 | AI13: =IF($G13="","",IF($G13=1,AC13,(1+AC13)*(1+AI12)-1)) -> 0.22083227 | AJ13: =IF($G13="","",AI13-AH13) -> -0.091924903 | AK13: =IF($G13="","",(1+AE13)^(1/G13)-1) -> 0.070672502 | AL13: =IF($G13="","",(1+AF13)^(1/G13)-1) -> 0.051456235 | AM13: =IF($G13="","",AL13-AK13) -> -0.019216267 | AN13: =IF($G13="","",(1+AH13)^(1/G13)-1) -> 0.0704 | AO13: =IF($G13="","",(1+AI13)^(1/G13)-1) -> 0.05114832 | AP13: =IF($G13="","",AO13-AN13) -> -0.01925168
B14: Federal Income Tax | C14: ='Return Simulator'!D61 -> 0.37 | G14: 5 | H14: =IF(G14="","",SUMIFS(Add_Contributions[[#All],[Amount ($)]],Add_Contributions[[#All],[Year]],G14)) -> 0 | I14: =IF($G14="","",IF($G14=1,(($C$2+$H14)*I$3)*(1+(I$4-I$5)),((I13+($H14*I$3))*(1+(I$4-I$5))))) -> 6347497.3 | J14: =IF($G14="","",IF($G14=1,(($C$2+$H14)*J$3)*(1+(J$4-J$5)),((J13+($H14*J$3))*(1+(J$4-J$5))))) -> 5807360.7 | K14: =IF($G14="","",IF($G14=1,(($C$2+$H14)*K$3)*(1+(K$4-K$5)),((K13+($H14*K$3))*(1+(K$4-K$5))))) -> 705277.48 | L14: =IF($G14="","",IF($G14=1,(($C$2+$H14)*L$3)*(1+(L$4-L$5)),((L13+($H14*L$3))*(1+(L$4-L$5))))) -> 689102.08 | M14: =IF($G14="","",IF($G14=1,(($C$2+$H14)*M$3)*(1+(M$4-M$5)),((M13+($H14*M$3))*(1+(M$4-M$5))))) -> 3675690.9 | N14: =IF($G14="","",IF($G14=1,(($C$2+$H14)*N$3)*(1+(N$4-N$5)),((N13+($H14*N$3))*(1+(N$4-N$5))))) -> 3332231.4 | O14: =IF($G14="","",IF($G14=1,(($C$2+$H14)*O$3)*(1+(O$4-O$5)),((O13+($H14*O$3))*(1+(O$4-O$5))))) -> 408410.1 | P14: =IF($G14="","",IF($G14=1,(($C$2+$H14)*P$3)*(1+(P$4-P$5)),((P13+($H14*P$3))*(1+(P$4-P$5))))) -> 398778.22 | ... T14: =IF($G14="","",IF($G14=1,(($C$2+$H14)*T$3)*(1+(T$4-T$5)),((T13+($H14*T$3))*(1+(T$4-T$5))))) -> 287125.87 | U14: =IF(G14="","",SUM(I14,K14,M14,O14,Q14,S14)) -> 14075532 | V14: =IF(H14="","",SUM(J14,L14,N14,P14,R14,T14)) -> 12857776 | W14: =IF($G14="","",IF($G14=1,(($C$2+$H14)*W$3)*(1+(W$4-W$5)),((W13+($H14*W$3))*(1+(W$4-W$5))))) -> 14051753 | X14: =IF($G14="","",IF($G14=1,(($C$2+$H14)*X$3)*(1+(X$4-X$5)),((X13+($H14*X$3))*(1+(X$4-X$5))))) -> 12832758 | Y14: =IF($G14="","",IF($G14=1,(U14-$C$2-H14)/($C$2+H14),(U14-U13-H14)/(U13+H14))) -> 0.071120228 | Z14: =IF($G14="","",IF($G14=1,(V14-$C$2-H14)/($C$2+H14),(V14-V13-H14)/(V13+H14))) -> 0.051964397 | AA14: =IF($G14="","",Z14-Y14) -> -0.01915583 | AB14: =IF($G14="","",IF($G14=1,(W14-$C$2-H14)/($C$2+H14),(W14-W13-H14)/(W13+H14))) -> 0.0704 | AC14: =IF($G14="","",IF($G14=1,(X14-$C$2-H14)/($C$2+H14),(X14-X13-H14)/(X13+H14))) -> 0.05114832 | AD14: =IF($G14="","",AC14-AB14) -> -0.01925168 | AE14: =IF($G14="","",IF($G14=1,Y14,(1+Y14)*(1+AE13)-1)) -> 0.40755319 | AF14: =IF($G14="","",IF($G14=1,Z14,(1+Z14)*(1+AF13)-1)) -> 0.28577757 | AG14: =IF($G14="","",AF14-AE14) -> -0.12177562 | AH14: =IF($G14="","",IF($G14=1,AB14,(1+AB14)*(1+AH13)-1)) -> 0.40517528 | AI14: =IF($G14="","",IF($G14=1,AC14,(1+AC14)*(1+AI13)-1)) -> 0.28327579 | AJ14: =IF($G14="","",AI14-AH14) -> -0.12189949 | AK14: =IF($G14="","",(1+AE14)^(1/G14)-1) -> 0.070762032 | AL14: =IF($G14="","",(1+AF14)^(1/G14)-1) -> 0.051557848 | AM14: =IF($G14="","",AL14-AK14) -> -0.019204184 | AN14: =IF($G14="","",(1+AH14)^(1/G14)-1) -> 0.0704 | AO14: =IF($G14="","",(1+AI14)^(1/G14)-1) -> 0.05114832 | AP14: =IF($G14="","",AO14-AN14) -> -0.01925168
B15: Capital Gains Tax | C15: ='Return Simulator'!D62 -> 0.2 | G15: 6 | H15: =IF(G15="","",SUMIFS(Add_Contributions[[#All],[Amount ($)]],Add_Contributions[[#All],[Year]],G15)) -> 0 | I15: =IF($G15="","",IF($G15=1,(($C$2+$H15)*I$3)*(1+(I$4-I$5)),((I14+($H15*I$3))*(1+(I$4-I$5))))) -> 6855297.1 | J15: =IF($G15="","",IF($G15=1,(($C$2+$H15)*J$3)*(1+(J$4-J$5)),((J14+($H15*J$3))*(1+(J$4-J$5))))) -> 6161377.4 | K15: =IF($G15="","",IF($G15=1,(($C$2+$H15)*K$3)*(1+(K$4-K$5)),((K14+($H15*K$3))*(1+(K$4-K$5))))) -> 761699.68 | L15: =IF($G15="","",IF($G15=1,(($C$2+$H15)*L$3)*(1+(L$4-L$5)),((L14+($H15*L$3))*(1+(L$4-L$5))))) -> 740784.73 | M15: =IF($G15="","",IF($G15=1,(($C$2+$H15)*M$3)*(1+(M$4-M$5)),((M14+($H15*M$3))*(1+(M$4-M$5))))) -> 3859475.4 | N15: =IF($G15="","",IF($G15=1,(($C$2+$H15)*N$3)*(1+(N$4-N$5)),((N14+($H15*N$3))*(1+(N$4-N$5))))) -> 3430865.5 | O15: =IF($G15="","",IF($G15=1,(($C$2+$H15)*O$3)*(1+(O$4-O$5)),((O14+($H15*O$3))*(1+(O$4-O$5))))) -> 428830.61 | P15: =IF($G15="","",IF($G15=1,(($C$2+$H15)*P$3)*(1+(P$4-P$5)),((P14+($H15*P$3))*(1+(P$4-P$5))))) -> 416723.24 | ... T15: =IF($G15="","",IF($G15=1,(($C$2+$H15)*T$3)*(1+(T$4-T$5)),((T14+($H15*T$3))*(1+(T$4-T$5))))) -> 308660.31 | U15: =IF(G15="","",SUM(I15,K15,M15,O15,Q15,S15)) -> 15079051 | V15: =IF(H15="","",SUM(J15,L15,N15,P15,R15,T15)) -> 13528495 | W15: =IF($G15="","",IF($G15=1,(($C$2+$H15)*W$3)*(1+(W$4-W$5)),((W14+($H15*W$3))*(1+(W$4-W$5))))) -> 15040996 | X15: =IF($G15="","",IF($G15=1,(($C$2+$H15)*X$3)*(1+(X$4-X$5)),((X14+($H15*X$3))*(1+(X$4-X$5))))) -> 13489132 | Y15: =IF($G15="","",IF($G15=1,(U15-$C$2-H15)/($C$2+H15),(U15-U14-H15)/(U14+H15))) -> 0.071295318 | Z15: =IF($G15="","",IF($G15=1,(V15-$C$2-H15)/($C$2+H15),(V15-V14-H15)/(V14+H15))) -> 0.052164494 | AA15: =IF($G15="","",Z15-Y15) -> -0.019130824 | AB15: =IF($G15="","",IF($G15=1,(W15-$C$2-H15)/($C$2+H15),(W15-W14-H15)/(W14+H15))) -> 0.0704 | AC15: =IF($G15="","",IF($G15=1,(X15-$C$2-H15)/($C$2+H15),(X15-X14-H15)/(X14+H15))) -> 0.05114832 | AD15: =IF($G15="","",AC15-AB15) -> -0.01925168 | AE15: =IF($G15="","",IF($G15=1,Y15,(1+Y15)*(1+AE14)-1)) -> 0.50790514 | AF15: =IF($G15="","",IF($G15=1,Z15,(1+Z15)*(1+AF14)-1)) -> 0.3528495 | AG15: =IF($G15="","",AF15-AE15) -> -0.15505564 | AH15: =IF($G15="","",IF($G15=1,AB15,(1+AB15)*(1+AH14)-1)) -> 0.50409962 | AI15: =IF($G15="","",IF($G15=1,AC15,(1+AC15)*(1+AI14)-1)) -> 0.3489132 | AJ15: =IF($G15="","",AI15-AH15) -> -0.15518643 | AK15: =IF($G15="","",(1+AE15)^(1/G15)-1) -> 0.070850895 | AL15: =IF($G15="","",(1+AF15)^(1/G15)-1) -> 0.051658931 | AM15: =IF($G15="","",AL15-AK15) -> -0.019191963 | AN15: =IF($G15="","",(1+AH15)^(1/G15)-1) -> 0.0704 | AO15: =IF($G15="","",(1+AI15)^(1/G15)-1) -> 0.05114832 | AP15: =IF($G15="","",AO15-AN15) -> -0.01925168
B16: Net Investment Income Tax | C16: ='Return Simulator'!D63 -> 0.038 | G16: 7 | H16: =IF(G16="","",SUMIFS(Add_Contributions[[#All],[Amount ($)]],Add_Contributions[[#All],[Year]],G16)) -> 0 | I16: =IF($G16="","",IF($G16=1,(($C$2+$H16)*I$3)*(1+(I$4-I$5)),((I15+($H16*I$3))*(1+(I$4-I$5))))) -> 7403720.8 | J16: =IF($G16="","",IF($G16=1,(($C$2+$H16)*J$3)*(1+(J$4-J$5)),((J15+($H16*J$3))*(1+(J$4-J$5))))) -> 6536975 | K16: =IF($G16="","",IF($G16=1,(($C$2+$H16)*K$3)*(1+(K$4-K$5)),((K15+($H16*K$3))*(1+(K$4-K$5))))) -> 822635.65 | L16: =IF($G16="","",IF($G16=1,(($C$2+$H16)*L$3)*(1+(L$4-L$5)),((L15+($H16*L$3))*(1+(L$4-L$5))))) -> 796343.59 | M16: =IF($G16="","",IF($G16=1,(($C$2+$H16)*M$3)*(1+(M$4-M$5)),((M15+($H16*M$3))*(1+(M$4-M$5))))) -> 4052449.2 | N16: =IF($G16="","",IF($G16=1,(($C$2+$H16)*N$3)*(1+(N$4-N$5)),((N15+($H16*N$3))*(1+(N$4-N$5))))) -> 3532419.1 | O16: =IF($G16="","",IF($G16=1,(($C$2+$H16)*O$3)*(1+(O$4-O$5)),((O15+($H16*O$3))*(1+(O$4-O$5))))) -> 450272.14 | P16: =IF($G16="","",IF($G16=1,(($C$2+$H16)*P$3)*(1+(P$4-P$5)),((P15+($H16*P$3))*(1+(P$4-P$5))))) -> 435475.79 | ... T16: =IF($G16="","",IF($G16=1,(($C$2+$H16)*T$3)*(1+(T$4-T$5)),((T15+($H16*T$3))*(1+(T$4-T$5))))) -> 331809.83 | U16: =IF(G16="","",SUM(I16,K16,M16,O16,Q16,S16)) -> 16156726 | V16: =IF(H16="","",SUM(J16,L16,N16,P16,R16,T16)) -> 14236887 | W16: =IF($G16="","",IF($G16=1,(($C$2+$H16)*W$3)*(1+(W$4-W$5)),((W15+($H16*W$3))*(1+(W$4-W$5))))) -> 16099882 | X16: =IF($G16="","",IF($G16=1,(($C$2+$H16)*X$3)*(1+(X$4-X$5)),((X15+($H16*X$3))*(1+(X$4-X$5))))) -> 14179078 | Y16: =IF($G16="","",IF($G16=1,(U16-$C$2-H16)/($C$2+H16),(U16-U15-H16)/(U15+H16))) -> 0.071468351 | Z16: =IF($G16="","",IF($G16=1,(V16-$C$2-H16)/($C$2+H16),(V16-V15-H16)/(V15+H16))) -> 0.052362946 | AA16: =IF($G16="","",Z16-Y16) -> -0.019105405 | AB16: =IF($G16="","",IF($G16=1,(W16-$C$2-H16)/($C$2+H16),(W16-W15-H16)/(W15+H16))) -> 0.0704 | AC16: =IF($G16="","",IF($G16=1,(X16-$C$2-H16)/($C$2+H16),(X16-X15-H16)/(X15+H16))) -> 0.05114832 | AD16: =IF($G16="","",AC16-AB16) -> -0.01925168 | AE16: =IF($G16="","",IF($G16=1,Y16,(1+Y16)*(1+AE15)-1)) -> 0.61567264 | AF16: =IF($G16="","",IF($G16=1,Z16,(1+Z16)*(1+AF15)-1)) -> 0.42368869 | AG16: =IF($G16="","",AF16-AE16) -> -0.19198395 | AH16: =IF($G16="","",IF($G16=1,AB16,(1+AB16)*(1+AH15)-1)) -> 0.60998824 | AI16: =IF($G16="","",IF($G16=1,AC16,(1+AC16)*(1+AI15)-1)) -> 0.41790784 | AJ16: =IF($G16="","",AI16-AH16) -> -0.1920804 | AK16: =IF($G16="","",(1+AE16)^(1/G16)-1) -> 0.070939081 | AL16: =IF($G16="","",(1+AF16)^(1/G16)-1) -> 0.051759476 | AM16: =IF($G16="","",AL16-AK16) -> -0.019179605 | AN16: =IF($G16="","",(1+AH16)^(1/G16)-1) -> 0.0704 | AO16: =IF($G16="","",(1+AI16)^(1/G16)-1) -> 0.05114832 | AP16: =IF($G16="","",AO16-AN16) -> -0.01925168
B17: State Income Tax | G17: 8 | H17: =IF(G17="","",SUMIFS(Add_Contributions[[#All],[Amount ($)]],Add_Contributions[[#All],[Year]],G17)) -> 0 | I17: =IF($G17="","",IF($G17=1,(($C$2+$H17)*I$3)*(1+(I$4-I$5)),((I16+($H17*I$3))*(1+(I$4-I$5))))) -> 7996018.5 | J17: =IF($G17="","",IF($G17=1,(($C$2+$H17)*J$3)*(1+(J$4-J$5)),((J16+($H17*J$3))*(1+(J$4-J$5))))) -> 6935468.9 | K17: =IF($G17="","",IF($G17=1,(($C$2+$H17)*K$3)*(1+(K$4-K$5)),((K16+($H17*K$3))*(1+(K$4-K$5))))) -> 888446.5 | L17: =IF($G17="","",IF($G17=1,(($C$2+$H17)*L$3)*(1+(L$4-L$5)),((L16+($H17*L$3))*(1+(L$4-L$5))))) -> 856069.36 | M17: =IF($G17="","",IF($G17=1,(($C$2+$H17)*M$3)*(1+(M$4-M$5)),((M16+($H17*M$3))*(1+(M$4-M$5))))) -> 4255071.7 | N17: =IF($G17="","",IF($G17=1,(($C$2+$H17)*N$3)*(1+(N$4-N$5)),((N16+($H17*N$3))*(1+(N$4-N$5))))) -> 3636978.7 | O17: =IF($G17="","",IF($G17=1,(($C$2+$H17)*O$3)*(1+(O$4-O$5)),((O16+($H17*O$3))*(1+(O$4-O$5))))) -> 472785.74 | P17: =IF($G17="","",IF($G17=1,(($C$2+$H17)*P$3)*(1+(P$4-P$5)),((P16+($H17*P$3))*(1+(P$4-P$5))))) -> 455072.2 | ... T17: =IF($G17="","",IF($G17=1,(($C$2+$H17)*T$3)*(1+(T$4-T$5)),((T16+($H17*T$3))*(1+(T$4-T$5))))) -> 356695.57 | U17: =IF(G17="","",SUM(I17,K17,M17,O17,Q17,S17)) -> 17314183 | V17: =IF(H17="","",SUM(J17,L17,N17,P17,R17,T17)) -> 14985174 | W17: =IF($G17="","",IF($G17=1,(($C$2+$H17)*W$3)*(1+(W$4-W$5)),((W16+($H17*W$3))*(1+(W$4-W$5))))) -> 17233314 | X17: =IF($G17="","",IF($G17=1,(($C$2+$H17)*X$3)*(1+(X$4-X$5)),((X16+($H17*X$3))*(1+(X$4-X$5))))) -> 14904314 | Y17: =IF($G17="","",IF($G17=1,(U17-$C$2-H17)/($C$2+H17),(U17-U16-H17)/(U16+H17))) -> 0.071639294 | Z17: =IF($G17="","",IF($G17=1,(V17-$C$2-H17)/($C$2+H17),(V17-V16-H17)/(V16+H17))) -> 0.052559719 | AA17: =IF($G17="","",Z17-Y17) -> -0.019079575 | AB17: =IF($G17="","",IF($G17=1,(W17-$C$2-H17)/($C$2+H17),(W17-W16-H17)/(W16+H17))) -> 0.0704 | AC17: =IF($G17="","",IF($G17=1,(X17-$C$2-H17)/($C$2+H17),(X17-X16-H17)/(X16+H17))) -> 0.05114832 | AD17: =IF($G17="","",AC17-AB17) -> -0.01925168 | AE17: =IF($G17="","",IF($G17=1,Y17,(1+Y17)*(1+AE16)-1)) -> 0.73141829 | AF17: =IF($G17="","",IF($G17=1,Z17,(1+Z17)*(1+AF16)-1)) -> 0.49851737 | AG17: =IF($G17="","",AF17-AE17) -> -0.23290092 | AH17: =IF($G17="","",IF($G17=1,AB17,(1+AB17)*(1+AH16)-1)) -> 0.72333141 | AI17: =IF($G17="","",IF($G17=1,AC17,(1+AC17)*(1+AI16)-1)) -> 0.49043144 | AJ17: =IF($G17="","",AI17-AH17) -> -0.23289997 | AK17: =IF($G17="","",(1+AE17)^(1/G17)-1) -> 0.071026582 | AL17: =IF($G17="","",(1+AF17)^(1/G17)-1) -> 0.051859473 | AM17: =IF($G17="","",AL17-AK17) -> -0.019167109 | AN17: =IF($G17="","",(1+AH17)^(1/G17)-1) -> 0.0704 | AO17: =IF($G17="","",(1+AI17)^(1/G17)-1) -> 0.05114832 | AP17: =IF($G17="","",AO17-AN17) -> -0.01925168
G18: 9 | H18: =IF(G18="","",SUMIFS(Add_Contributions[[#All],[Amount ($)]],Add_Contributions[[#All],[Year]],G18)) -> 0 | I18: =IF($G18="","",IF($G18=1,(($C$2+$H18)*I$3)*(1+(I$4-I$5)),((I17+($H18*I$3))*(1+(I$4-I$5))))) -> 8635700 | J18: =IF($G18="","",IF($G18=1,(($C$2+$H18)*J$3)*(1+(J$4-J$5)),((J17+($H18*J$3))*(1+(J$4-J$5))))) -> 7358255.1 | K18: =IF($G18="","",IF($G18=1,(($C$2+$H18)*K$3)*(1+(K$4-K$5)),((K17+($H18*K$3))*(1+(K$4-K$5))))) -> 959522.22 | L18: =IF($G18="","",IF($G18=1,(($C$2+$H18)*L$3)*(1+(L$4-L$5)),((L17+($H18*L$3))*(1+(L$4-L$5))))) -> 920274.56 | M18: =IF($G18="","",IF($G18=1,(($C$2+$H18)*M$3)*(1+(M$4-M$5)),((M17+($H18*M$3))*(1+(M$4-M$5))))) -> 4467825.3 | N18: =IF($G18="","",IF($G18=1,(($C$2+$H18)*N$3)*(1+(N$4-N$5)),((N17+($H18*N$3))*(1+(N$4-N$5))))) -> 3744633.3 | O18: =IF($G18="","",IF($G18=1,(($C$2+$H18)*O$3)*(1+(O$4-O$5)),((O17+($H18*O$3))*(1+(O$4-O$5))))) -> 496425.03 | P18: =IF($G18="","",IF($G18=1,(($C$2+$H18)*P$3)*(1+(P$4-P$5)),((P17+($H18*P$3))*(1+(P$4-P$5))))) -> 475550.44 | ... T18: =IF($G18="","",IF($G18=1,(($C$2+$H18)*T$3)*(1+(T$4-T$5)),((T17+($H18*T$3))*(1+(T$4-T$5))))) -> 383447.73 | U18: =IF(G18="","",SUM(I18,K18,M18,O18,Q18,S18)) -> 18557482 | V18: =IF(H18="","",SUM(J18,L18,N18,P18,R18,T18)) -> 15775713 | W18: =IF($G18="","",IF($G18=1,(($C$2+$H18)*W$3)*(1+(W$4-W$5)),((W17+($H18*W$3))*(1+(W$4-W$5))))) -> 18446539 | X18: =IF($G18="","",IF($G18=1,(($C$2+$H18)*X$3)*(1+(X$4-X$5)),((X17+($H18*X$3))*(1+(X$4-X$5))))) -> 15666645 | Y18: =IF($G18="","",IF($G18=1,(U18-$C$2-H18)/($C$2+H18),(U18-U17-H18)/(U17+H18))) -> 0.071808119 | Z18: =IF($G18="","",IF($G18=1,(V18-$C$2-H18)/($C$2+H18),(V18-V17-H18)/(V17+H18))) -> 0.052754781 | AA18: =IF($G18="","",Z18-Y18) -> -0.019053338 | AB18: =IF($G18="","",IF($G18=1,(W18-$C$2-H18)/($C$2+H18),(W18-W17-H18)/(W17+H18))) -> 0.0704 | AC18: =IF($G18="","",IF($G18=1,(X18-$C$2-H18)/($C$2+H18),(X18-X17-H18)/(X17+H18))) -> 0.05114832 | AD18: =IF($G18="","",AC18-AB18) -> -0.01925168 | AE18: =IF($G18="","",IF($G18=1,Y18,(1+Y18)*(1+AE17)-1)) -> 0.85574818 | AF18: =IF($G18="","",IF($G18=1,Z18,(1+Z18)*(1+AF17)-1)) -> 0.57757132 | AG18: =IF($G18="","",AF18-AE18) -> -0.27817685 | AH18: =IF($G18="","",IF($G18=1,AB18,(1+AB18)*(1+AH17)-1)) -> 0.84465394 | AI18: =IF($G18="","",IF($G18=1,AC18,(1+AC18)*(1+AI17)-1)) -> 0.56666451 | AJ18: =IF($G18="","",AI18-AH18) -> -0.27798943 | AK18: =IF($G18="","",(1+AE18)^(1/G18)-1) -> 0.071113392 | AL18: =IF($G18="","",(1+AF18)^(1/G18)-1) -> 0.051958914 | AM18: =IF($G18="","",AL18-AK18) -> -0.019154478 | AN18: =IF($G18="","",(1+AH18)^(1/G18)-1) -> 0.0704 | AO18: =IF($G18="","",(1+AI18)^(1/G18)-1) -> 0.05114832 | AP18: =IF($G18="","",AO18-AN18) -> -0.01925168
G19: 10 | H19: =IF(G19="","",SUMIFS(Add_Contributions[[#All],[Amount ($)]],Add_Contributions[[#All],[Year]],G19)) -> 0 | I19: =IF($G19="","",IF($G19=1,(($C$2+$H19)*I$3)*(1+(I$4-I$5)),((I18+($H19*I$3))*(1+(I$4-I$5))))) -> 9326556 | J19: =IF($G19="","",IF($G19=1,(($C$2+$H19)*J$3)*(1+(J$4-J$5)),((J18+($H19*J$3))*(1+(J$4-J$5))))) -> 7806814.4 | K19: =IF($G19="","",IF($G19=1,(($C$2+$H19)*K$3)*(1+(K$4-K$5)),((K18+($H19*K$3))*(1+(K$4-K$5))))) -> 1036284 | L19: =IF($G19="","",IF($G19=1,(($C$2+$H19)*L$3)*(1+(L$4-L$5)),((L18+($H19*L$3))*(1+(L$4-L$5))))) -> 989295.15 | M19: =IF($G19="","",IF($G19=1,(($C$2+$H19)*M$3)*(1+(M$4-M$5)),((M18+($H19*M$3))*(1+(M$4-M$5))))) -> 4691216.5 | N19: =IF($G19="","",IF($G19=1,(($C$2+$H19)*N$3)*(1+(N$4-N$5)),((N18+($H19*N$3))*(1+(N$4-N$5))))) -> 3855474.4 | O19: =IF($G19="","",IF($G19=1,(($C$2+$H19)*O$3)*(1+(O$4-O$5)),((O18+($H19*O$3))*(1+(O$4-O$5))))) -> 521246.28 | P19: =IF($G19="","",IF($G19=1,(($C$2+$H19)*P$3)*(1+(P$4-P$5)),((P18+($H19*P$3))*(1+(P$4-P$5))))) -> 496950.21 | ... T19: =IF($G19="","",IF($G19=1,(($C$2+$H19)*T$3)*(1+(T$4-T$5)),((T18+($H19*T$3))*(1+(T$4-T$5))))) -> 412206.31 | U19: =IF(G19="","",SUM(I19,K19,M19,O19,Q19,S19)) -> 19893153 | V19: =IF(H19="","",SUM(J19,L19,N19,P19,R19,T19)) -> 16611007 | W19: =IF($G19="","",IF($G19=1,(($C$2+$H19)*W$3)*(1+(W$4-W$5)),((W18+($H19*W$3))*(1+(W$4-W$5))))) -> 19745176 | X19: =IF($G19="","",IF($G19=1,(($C$2+$H19)*X$3)*(1+(X$4-X$5)),((X18+($H19*X$3))*(1+(X$4-X$5))))) -> 16467968 | Y19: =IF($G19="","",IF($G19=1,(U19-$C$2-H19)/($C$2+H19),(U19-U18-H19)/(U18+H19))) -> 0.0719748 | Z19: =IF($G19="","",IF($G19=1,(V19-$C$2-H19)/($C$2+H19),(V19-V18-H19)/(V18+H19))) -> 0.052948104 | AA19: =IF($G19="","",Z19-Y19) -> -0.019026696 | AB19: =IF($G19="","",IF($G19=1,(W19-$C$2-H19)/($C$2+H19),(W19-W18-H19)/(W18+H19))) -> 0.0704 | AC19: =IF($G19="","",IF($G19=1,(X19-$C$2-H19)/($C$2+H19),(X19-X18-H19)/(X18+H19))) -> 0.05114832 | AD19: =IF($G19="","",AC19-AB19) -> -0.01925168 | AE19: =IF($G19="","",IF($G19=1,Y19,(1+Y19)*(1+AE18)-1)) -> 0.98931528 | AF19: =IF($G19="","",IF($G19=1,Z19,(1+Z19)*(1+AF18)-1)) -> 0.66110073 | AG19: =IF($G19="","",AF19-AE19) -> -0.32821455 | AH19: =IF($G19="","",IF($G19=1,AB19,(1+AB19)*(1+AH18)-1)) -> 0.97451758 | AI19: =IF($G19="","",IF($G19=1,AC19,(1+AC19)*(1+AI18)-1)) -> 0.64679677 | AJ19: =IF($G19="","",AI19-AH19) -> -0.32772081 | AK19: =IF($G19="","",(1+AE19)^(1/G19)-1) -> 0.071199501 | AL19: =IF($G19="","",(1+AF19)^(1/G19)-1) -> 0.052057791 | AM19: =IF($G19="","",AL19-AK19) -> -0.01914171 | AN19: =IF($G19="","",(1+AH19)^(1/G19)-1) -> 0.0704 | AO19: =IF($G19="","",(1+AI19)^(1/G19)-1) -> 0.05114832 | AP19: =IF($G19="","",AO19-AN19) -> -0.01925168
G20: 11 | H20: =IF(G20="","",SUMIFS(Add_Contributions[[#All],[Amount ($)]],Add_Contributions[[#All],[Year]],G20)) -> 0 | I20: =IF($G20="","",IF($G20=1,(($C$2+$H20)*I$3)*(1+(I$4-I$5)),((I19+($H20*I$3))*(1+(I$4-I$5))))) -> 10072680 | J20: =IF($G20="","",IF($G20=1,(($C$2+$H20)*J$3)*(1+(J$4-J$5)),((J19+($H20*J$3))*(1+(J$4-J$5))))) -> 8282717.8 | K20: =IF($G20="","",IF($G20=1,(($C$2+$H20)*K$3)*(1+(K$4-K$5)),((K19+($H20*K$3))*(1+(K$4-K$5))))) -> 1119186.7 | L20: =IF($G20="","",IF($G20=1,(($C$2+$H20)*L$3)*(1+(L$4-L$5)),((L19+($H20*L$3))*(1+(L$4-L$5))))) -> 1063492.3 | M20: =IF($G20="","",IF($G20=1,(($C$2+$H20)*M$3)*(1+(M$4-M$5)),((M19+($H20*M$3))*(1+(M$4-M$5))))) -> 4925777.4 | N20: =IF($G20="","",IF($G20=1,(($C$2+$H20)*N$3)*(1+(N$4-N$5)),((N19+($H20*N$3))*(1+(N$4-N$5))))) -> 3969596.5 | O20: =IF($G20="","",IF($G20=1,(($C$2+$H20)*O$3)*(1+(O$4-O$5)),((O19+($H20*O$3))*(1+(O$4-O$5))))) -> 547308.59 | P20: =IF($G20="","",IF($G20=1,(($C$2+$H20)*P$3)*(1+(P$4-P$5)),((P19+($H20*P$3))*(1+(P$4-P$5))))) -> 519312.97 | ... T20: =IF($G20="","",IF($G20=1,(($C$2+$H20)*T$3)*(1+(T$4-T$5)),((T19+($H20*T$3))*(1+(T$4-T$5))))) -> 443121.79 | U20: =IF(G20="","",SUM(I20,K20,M20,O20,Q20,S20)) -> 21328231 | V20: =IF(H20="","",SUM(J20,L20,N20,P20,R20,T20)) -> 17493711 | W20: =IF($G20="","",IF($G20=1,(($C$2+$H20)*W$3)*(1+(W$4-W$5)),((W19+($H20*W$3))*(1+(W$4-W$5))))) -> 21135236 | X20: =IF($G20="","",IF($G20=1,(($C$2+$H20)*X$3)*(1+(X$4-X$5)),((X19+($H20*X$3))*(1+(X$4-X$5))))) -> 17310277 | Y20: =IF($G20="","",IF($G20=1,(U20-$C$2-H20)/($C$2+H20),(U20-U19-H20)/(U19+H20))) -> 0.072139311 | Z20: =IF($G20="","",IF($G20=1,(V20-$C$2-H20)/($C$2+H20),(V20-V19-H20)/(V19+H20))) -> 0.053139659 | AA20: =IF($G20="","",Z20-Y20) -> -0.018999652 | AB20: =IF($G20="","",IF($G20=1,(W20-$C$2-H20)/($C$2+H20),(W20-W19-H20)/(W19+H20))) -> 0.0704 | AC20: =IF($G20="","",IF($G20=1,(X20-$C$2-H20)/($C$2+H20),(X20-X19-H20)/(X19+H20))) -> 0.05114832 | AD20: =IF($G20="","",AC20-AB20) -> -0.01925168 | AE20: =IF($G20="","",IF($G20=1,Y20,(1+Y20)*(1+AE19)-1)) -> 1.1328231 | AF20: =IF($G20="","",IF($G20=1,Z20,(1+Z20)*(1+AF19)-1)) -> 0.74937106 | AG20: =IF($G20="","",AF20-AE20) -> -0.38345205 | AH20: =IF($G20="","",IF($G20=1,AB20,(1+AB20)*(1+AH19)-1)) -> 1.1135236 | AI20: =IF($G20="","",IF($G20=1,AC20,(1+AC20)*(1+AI19)-1)) -> 0.73102765 | AJ20: =IF($G20="","",AI20-AH20) -> -0.38249596 | AK20: =IF($G20="","",(1+AE20)^(1/G20)-1) -> 0.071284905 | AL20: =IF($G20="","",(1+AF20)^(1/G20)-1) -> 0.052156097 | AM20: =IF($G20="","",AL20-AK20) -> -0.019128808 | AN20: =IF($G20="","",(1+AH20)^(1/G20)-1) -> 0.0704 | AO20: =IF($G20="","",(1+AI20)^(1/G20)-1) -> 0.05114832 | AP20: =IF($G20="","",AO20-AN20) -> -0.01925168
B21: Metrics | C21: Buy & Hold | D21: Rebalanced | G21: 12 | H21: =IF(G21="","",SUMIFS(Add_Contributions[[#All],[Amount ($)]],Add_Contributions[[#All],[Year]],G21)) -> 0 | I21: =IF($G21="","",IF($G21=1,(($C$2+$H21)*I$3)*(1+(I$4-I$5)),((I20+($H21*I$3))*(1+(I$4-I$5))))) -> 10878495 | J21: =IF($G21="","",IF($G21=1,(($C$2+$H21)*J$3)*(1+(J$4-J$5)),((J20+($H21*J$3))*(1+(J$4-J$5))))) -> 8787632.2 | K21: =IF($G21="","",IF($G21=1,(($C$2+$H21)*K$3)*(1+(K$4-K$5)),((K20+($H21*K$3))*(1+(K$4-K$5))))) -> 1208721.7 | L21: =IF($G21="","",IF($G21=1,(($C$2+$H21)*L$3)*(1+(L$4-L$5)),((L20+($H21*L$3))*(1+(L$4-L$5))))) -> 1143254.2 | M21: =IF($G21="","",IF($G21=1,(($C$2+$H21)*M$3)*(1+(M$4-M$5)),((M20+($H21*M$3))*(1+(M$4-M$5))))) -> 5172066.2 | N21: =IF($G21="","",IF($G21=1,(($C$2+$H21)*N$3)*(1+(N$4-N$5)),((N20+($H21*N$3))*(1+(N$4-N$5))))) -> 4087096.5 | O21: =IF($G21="","",IF($G21=1,(($C$2+$H21)*O$3)*(1+(O$4-O$5)),((O20+($H21*O$3))*(1+(O$4-O$5))))) -> 574674.02 | P21: =IF($G21="","",IF($G21=1,(($C$2+$H21)*P$3)*(1+(P$4-P$5)),((P20+($H21*P$3))*(1+(P$4-P$5))))) -> 542682.06 | ... T21: =IF($G21="","",IF($G21=1,(($C$2+$H21)*T$3)*(1+(T$4-T$5)),((T20+($H21*T$3))*(1+(T$4-T$5))))) -> 476355.92 | U21: =IF(G21="","",SUM(I21,K21,M21,O21,Q21,S21)) -> 22870297 | V21: =IF(H21="","",SUM(J21,L21,N21,P21,R21,T21)) -> 18426640 | W21: =IF($G21="","",IF($G21=1,(($C$2+$H21)*W$3)*(1+(W$4-W$5)),((W20+($H21*W$3))*(1+(W$4-W$5))))) -> 22623157 | X21: =IF($G21="","",IF($G21=1,(($C$2+$H21)*X$3)*(1+(X$4-X$5)),((X20+($H21*X$3))*(1+(X$4-X$5))))) -> 18195668 | Y21: =IF($G21="","",IF($G21=1,(U21-$C$2-H21)/($C$2+H21),(U21-U20-H21)/(U20+H21))) -> 0.072301632 | Z21: =IF($G21="","",IF($G21=1,(V21-$C$2-H21)/($C$2+H21),(V21-V20-H21)/(V20+H21))) -> 0.053329423 | AA21: =IF($G21="","",Z21-Y21) -> -0.018972209 | AB21: =IF($G21="","",IF($G21=1,(W21-$C$2-H21)/($C$2+H21),(W21-W20-H21)/(W20+H21))) -> 0.0704 | AC21: =IF($G21="","",IF($G21=1,(X21-$C$2-H21)/($C$2+H21),(X21-X20-H21)/(X20+H21))) -> 0.05114832 | AD21: =IF($G21="","",AC21-AB21) -> -0.01925168 | AE21: =IF($G21="","",IF($G21=1,Y21,(1+Y21)*(1+AE20)-1)) -> 1.2870297 | AF21: =IF($G21="","",IF($G21=1,Z21,(1+Z21)*(1+AF20)-1)) -> 0.84266401 | AG21: =IF($G21="","",AF21-AE21) -> -0.4443657 | AH21: =IF($G21="","",IF($G21=1,AB21,(1+AB21)*(1+AH20)-1)) -> 1.2623157 | AI21: =IF($G21="","",IF($G21=1,AC21,(1+AC21)*(1+AI20)-1)) -> 0.81956681 | AJ21: =IF($G21="","",AI21-AH21) -> -0.44274887 | AK21: =IF($G21="","",(1+AE21)^(1/G21)-1) -> 0.071369595 | AL21: =IF($G21="","",(1+AF21)^(1/G21)-1) -> 0.052253824 | AM21: =IF($G21="","",AL21-AK21) -> -0.019115771 | AN21: =IF($G21="","",(1+AH21)^(1/G21)-1) -> 0.0704 | AO21: =IF($G21="","",(1+AI21)^(1/G21)-1) -> 0.05114832 | AP21: =IF($G21="","",AO21-AN21) -> -0.01925168
B22: Projected Value | C22: =_xlfn.XLOOKUP(C3,G:G,V:V) -> 28098547 | D22: =_xlfn.XLOOKUP(C3,G:G,X:X) -> 27119396 | G22: 13 | H22: =IF(G22="","",SUMIFS(Add_Contributions[[#All],[Amount ($)]],Add_Contributions[[#All],[Year]],G22)) -> 0 | I22: =IF($G22="","",IF($G22=1,(($C$2+$H22)*I$3)*(1+(I$4-I$5)),((I21+($H22*I$3))*(1+(I$4-I$5))))) -> 11748774 | J22: =IF($G22="","",IF($G22=1,(($C$2+$H22)*J$3)*(1+(J$4-J$5)),((J21+($H22*J$3))*(1+(J$4-J$5))))) -> 9323326.3 | K22: =IF($G22="","",IF($G22=1,(($C$2+$H22)*K$3)*(1+(K$4-K$5)),((K21+($H22*K$3))*(1+(K$4-K$5))))) -> 1305419.4 | L22: =IF($G22="","",IF($G22=1,(($C$2+$H22)*L$3)*(1+(L$4-L$5)),((L21+($H22*L$3))*(1+(L$4-L$5))))) -> 1228998.3 | M22: =IF($G22="","",IF($G22=1,(($C$2+$H22)*M$3)*(1+(M$4-M$5)),((M21+($H22*M$3))*(1+(M$4-M$5))))) -> 5430669.5 | N22: =IF($G22="","",IF($G22=1,(($C$2+$H22)*N$3)*(1+(N$4-N$5)),((N21+($H22*N$3))*(1+(N$4-N$5))))) -> 4208074.6 | O22: =IF($G22="","",IF($G22=1,(($C$2+$H22)*O$3)*(1+(O$4-O$5)),((O21+($H22*O$3))*(1+(O$4-O$5))))) -> 603407.73 | P22: =IF($G22="","",IF($G22=1,(($C$2+$H22)*P$3)*(1+(P$4-P$5)),((P21+($H22*P$3))*(1+(P$4-P$5))))) -> 567102.75 | ... T22: =IF($G22="","",IF($G22=1,(($C$2+$H22)*T$3)*(1+(T$4-T$5)),((T21+($H22*T$3))*(1+(T$4-T$5))))) -> 512082.61 | U22: =IF(G22="","",SUM(I22,K22,M22,O22,Q22,S22)) -> 24527519 | V22: =IF(H22="","",SUM(J22,L22,N22,P22,R22,T22)) -> 19412785 | W22: =IF($G22="","",IF($G22=1,(($C$2+$H22)*W$3)*(1+(W$4-W$5)),((W21+($H22*W$3))*(1+(W$4-W$5))))) -> 24215827 | X22: =IF($G22="","",IF($G22=1,(($C$2+$H22)*X$3)*(1+(X$4-X$5)),((X21+($H22*X$3))*(1+(X$4-X$5))))) -> 19126346 | Y22: =IF($G22="","",IF($G22=1,(U22-$C$2-H22)/($C$2+H22),(U22-U21-H22)/(U21+H22))) -> 0.072461742 | Z22: =IF($G22="","",IF($G22=1,(V22-$C$2-H22)/($C$2+H22),(V22-V21-H22)/(V21+H22))) -> 0.053517372 | AA22: =IF($G22="","",Z22-Y22) -> -0.01894437 | AB22: =IF($G22="","",IF($G22=1,(W22-$C$2-H22)/($C$2+H22),(W22-W21-H22)/(W21+H22))) -> 0.0704 | AC22: =IF($G22="","",IF($G22=1,(X22-$C$2-H22)/($C$2+H22),(X22-X21-H22)/(X21+H22))) -> 0.05114832 | AD22: =IF($G22="","",AC22-AB22) -> -0.01925168 | AE22: =IF($G22="","",IF($G22=1,Y22,(1+Y22)*(1+AE21)-1)) -> 1.4527519 | AF22: =IF($G22="","",IF($G22=1,Z22,(1+Z22)*(1+AF21)-1)) -> 0.94127854 | AG22: =IF($G22="","",AF22-AE22) -> -0.51147332 | AH22: =IF($G22="","",IF($G22=1,AB22,(1+AB22)*(1+AH21)-1)) -> 1.4215827 | AI22: =IF($G22="","",IF($G22=1,AC22,(1+AC22)*(1+AI21)-1)) -> 0.9126346 | AJ22: =IF($G22="","",AI22-AH22) -> -0.50894811 | AK22: =IF($G22="","",(1+AE22)^(1/G22)-1) -> 0.071453567 | AL22: =IF($G22="","",(1+AF22)^(1/G22)-1) -> 0.052350966 | AM22: =IF($G22="","",AL22-AK22) -> -0.019102601 | AN22: =IF($G22="","",(1+AH22)^(1/G22)-1) -> 0.0704 | AO22: =IF($G22="","",(1+AI22)^(1/G22)-1) -> 0.05114832 | AP22: =IF($G22="","",AO22-AN22) -> -0.01925168
G23: 14 | H23: =IF(G23="","",SUMIFS(Add_Contributions[[#All],[Amount ($)]],Add_Contributions[[#All],[Year]],G23)) -> 0 | I23: =IF($G23="","",IF($G23=1,(($C$2+$H23)*I$3)*(1+(I$4-I$5)),((I22+($H23*I$3))*(1+(I$4-I$5))))) -> 12688676 | J23: =IF($G23="","",IF($G23=1,(($C$2+$H23)*J$3)*(1+(J$4-J$5)),((J22+($H23*J$3))*(1+(J$4-J$5))))) -> 9891676.3 | K23: =IF($G23="","",IF($G23=1,(($C$2+$H23)*K$3)*(1+(K$4-K$5)),((K22+($H23*K$3))*(1+(K$4-K$5))))) -> 1409852.9 | L23: =IF($G23="","",IF($G23=1,(($C$2+$H23)*L$3)*(1+(L$4-L$5)),((L22+($H23*L$3))*(1+(L$4-L$5))))) -> 1321173.1 | M23: =IF($G23="","",IF($G23=1,(($C$2+$H23)*M$3)*(1+(M$4-M$5)),((M22+($H23*M$3))*(1+(M$4-M$5))))) -> 5702203 | N23: =IF($G23="","",IF($G23=1,(($C$2+$H23)*N$3)*(1+(N$4-N$5)),((N22+($H23*N$3))*(1+(N$4-N$5))))) -> 4332633.6 | O23: =IF($G23="","",IF($G23=1,(($C$2+$H23)*O$3)*(1+(O$4-O$5)),((O22+($H23*O$3))*(1+(O$4-O$5))))) -> 633578.11 | P23: =IF($G23="","",IF($G23=1,(($C$2+$H23)*P$3)*(1+(P$4-P$5)),((P22+($H23*P$3))*(1+(P$4-P$5))))) -> 592622.37 | ... T23: =IF($G23="","",IF($G23=1,(($C$2+$H23)*T$3)*(1+(T$4-T$5)),((T22+($H23*T$3))*(1+(T$4-T$5))))) -> 550488.81 | U23: =IF(G23="","",SUM(I23,K23,M23,O23,Q23,S23)) -> 26308698 | V23: =IF(H23="","",SUM(J23,L23,N23,P23,R23,T23)) -> 20455320 | W23: =IF($G23="","",IF($G23=1,(($C$2+$H23)*W$3)*(1+(W$4-W$5)),((W22+($H23*W$3))*(1+(W$4-W$5))))) -> 25920621 | X23: =IF($G23="","",IF($G23=1,(($C$2+$H23)*X$3)*(1+(X$4-X$5)),((X22+($H23*X$3))*(1+(X$4-X$5))))) -> 20104626 | Y23: =IF($G23="","",IF($G23=1,(U23-$C$2-H23)/($C$2+H23),(U23-U22-H23)/(U22+H23))) -> 0.072619624 | Z23: =IF($G23="","",IF($G23=1,(V23-$C$2-H23)/($C$2+H23),(V23-V22-H23)/(V22+H23))) -> 0.053703485 | AA23: =IF($G23="","",Z23-Y23) -> -0.018916139 | AB23: =IF($G23="","",IF($G23=1,(W23-$C$2-H23)/($C$2+H23),(W23-W22-H23)/(W22+H23))) -> 0.0704 | AC23: =IF($G23="","",IF($G23=1,(X23-$C$2-H23)/($C$2+H23),(X23-X22-H23)/(X22+H23))) -> 0.05114832 | AD23: =IF($G23="","",AC23-AB23) -> -0.01925168 | AE23: =IF($G23="","",IF($G23=1,Y23,(1+Y23)*(1+AE22)-1)) -> 1.6308698 | AF23: =IF($G23="","",IF($G23=1,Z23,(1+Z23)*(1+AF22)-1)) -> 1.045532 | AG23: =IF($G23="","",AF23-AE23) -> -0.58533781 | AH23: =IF($G23="","",IF($G23=1,AB23,(1+AB23)*(1+AH22)-1)) -> 1.5920621 | AI23: =IF($G23="","",IF($G23=1,AC23,(1+AC23)*(1+AI22)-1)) -> 1.0104626 | AJ23: =IF($G23="","",AI23-AH23) -> -0.58159948 | AK23: =IF($G23="","",(1+AE23)^(1/G23)-1) -> 0.071536814 | AL23: =IF($G23="","",(1+AF23)^(1/G23)-1) -> 0.052447517 | AM23: =IF($G23="","",AL23-AK23) -> -0.019089297 | AN23: =IF($G23="","",(1+AH23)^(1/G23)-1) -> 0.0704 | AO23: =IF($G23="","",(1+AI23)^(1/G23)-1) -> 0.05114832 | AP23: =IF($G23="","",AO23-AN23) -> -0.01925168
B24: Total Return (Gross) | C24: =_xlfn.XLOOKUP(C3,G:G,AE:AE) -> 3.0185061 | D24: =_xlfn.XLOOKUP(C3,G:G,AH:AH) -> 2.8987197 | G24: 15 | H24: =IF(G24="","",SUMIFS(Add_Contributions[[#All],[Amount ($)]],Add_Contributions[[#All],[Year]],G24)) -> 0 | I24: =IF($G24="","",IF($G24=1,(($C$2+$H24)*I$3)*(1+(I$4-I$5)),((I23+($H24*I$3))*(1+(I$4-I$5))))) -> 13703771 | J24: =IF($G24="","",IF($G24=1,(($C$2+$H24)*J$3)*(1+(J$4-J$5)),((J23+($H24*J$3))*(1+(J$4-J$5))))) -> 10494673 | K24: =IF($G24="","",IF($G24=1,(($C$2+$H24)*K$3)*(1+(K$4-K$5)),((K23+($H24*K$3))*(1+(K$4-K$5))))) -> 1522641.2 | L24: =IF($G24="","",IF($G24=1,(($C$2+$H24)*L$3)*(1+(L$4-L$5)),((L23+($H24*L$3))*(1+(L$4-L$5))))) -> 1420261.1 | M24: =IF($G24="","",IF($G24=1,(($C$2+$H24)*M$3)*(1+(M$4-M$5)),((M23+($H24*M$3))*(1+(M$4-M$5))))) -> 5987313.2 | N24: =IF($G24="","",IF($G24=1,(($C$2+$H24)*N$3)*(1+(N$4-N$5)),((N23+($H24*N$3))*(1+(N$4-N$5))))) -> 4460879.5 | O24: =IF($G24="","",IF($G24=1,(($C$2+$H24)*O$3)*(1+(O$4-O$5)),((O23+($H24*O$3))*(1+(O$4-O$5))))) -> 665257.02 | P24: =IF($G24="","",IF($G24=1,(($C$2+$H24)*P$3)*(1+(P$4-P$5)),((P23+($H24*P$3))*(1+(P$4-P$5))))) -> 619290.38 | ... T24: =IF($G24="","",IF($G24=1,(($C$2+$H24)*T$3)*(1+(T$4-T$5)),((T23+($H24*T$3))*(1+(T$4-T$5))))) -> 591775.47 | U24: =IF(G24="","",SUM(I24,K24,M24,O24,Q24,S24)) -> 28223320 | V24: =IF(H24="","",SUM(J24,L24,N24,P24,R24,T24)) -> 21557611 | W24: =IF($G24="","",IF($G24=1,(($C$2+$H24)*W$3)*(1+(W$4-W$5)),((W23+($H24*W$3))*(1+(W$4-W$5))))) -> 27745433 | X24: =IF($G24="","",IF($G24=1,(($C$2+$H24)*X$3)*(1+(X$4-X$5)),((X23+($H24*X$3))*(1+(X$4-X$5))))) -> 21132944 | Y24: =IF($G24="","",IF($G24=1,(U24-$C$2-H24)/($C$2+H24),(U24-U23-H24)/(U23+H24))) -> 0.072775263 | Z24: =IF($G24="","",IF($G24=1,(V24-$C$2-H24)/($C$2+H24),(V24-V23-H24)/(V23+H24))) -> 0.053887745 | AA24: =IF($G24="","",Z24-Y24) -> -0.018887518 | AB24: =IF($G24="","",IF($G24=1,(W24-$C$2-H24)/($C$2+H24),(W24-W23-H24)/(W23+H24))) -> 0.0704 | AC24: =IF($G24="","",IF($G24=1,(X24-$C$2-H24)/($C$2+H24),(X24-X23-H24)/(X23+H24))) -> 0.05114832 | AD24: =IF($G24="","",AC24-AB24) -> -0.01925168 | AE24: =IF($G24="","",IF($G24=1,Y24,(1+Y24)*(1+AE23)-1)) -> 1.822332 | AF24: =IF($G24="","",IF($G24=1,Z24,(1+Z24)*(1+AF23)-1)) -> 1.1557611 | AG24: =IF($G24="","",AF24-AE24) -> -0.66657095 | AH24: =IF($G24="","",IF($G24=1,AB24,(1+AB24)*(1+AH23)-1)) -> 1.7745433 | AI24: =IF($G24="","",IF($G24=1,AC24,(1+AC24)*(1+AI23)-1)) -> 1.1132944 | AJ24: =IF($G24="","",AI24-AH24) -> -0.66124887 | AK24: =IF($G24="","",(1+AE24)^(1/G24)-1) -> 0.071619333 | AL24: =IF($G24="","",(1+AF24)^(1/G24)-1) -> 0.052543471 | AM24: =IF($G24="","",AL24-AK24) -> -0.019075862 | AN24: =IF($G24="","",(1+AH24)^(1/G24)-1) -> 0.0704 | AO24: =IF($G24="","",(1+AI24)^(1/G24)-1) -> 0.05114832 | AP24: =IF($G24="","",AO24-AN24) -> -0.01925168
B25: Total Return (Net) | C25: =_xlfn.XLOOKUP(C3,G:G,AF:AF) -> 1.8098547 | D25: =_xlfn.XLOOKUP(C3,G:G,AI:AI) -> 1.7119396 | G25: 16 | H25: =IF(G25="","",SUMIFS(Add_Contributions[[#All],[Amount ($)]],Add_Contributions[[#All],[Year]],G25)) -> 0 | I25: =IF($G25="","",IF($G25=1,(($C$2+$H25)*I$3)*(1+(I$4-I$5)),((I24+($H25*I$3))*(1+(I$4-I$5))))) -> 14800072 | J25: =IF($G25="","",IF($G25=1,(($C$2+$H25)*J$3)*(1+(J$4-J$5)),((J24+($H25*J$3))*(1+(J$4-J$5))))) -> 11134428 | K25: =IF($G25="","",IF($G25=1,(($C$2+$H25)*K$3)*(1+(K$4-K$5)),((K24+($H25*K$3))*(1+(K$4-K$5))))) -> 1644452.5 | L25: =IF($G25="","",IF($G25=1,(($C$2+$H25)*L$3)*(1+(L$4-L$5)),((L24+($H25*L$3))*(1+(L$4-L$5))))) -> 1526780.7 | M25: =IF($G25="","",IF($G25=1,(($C$2+$H25)*M$3)*(1+(M$4-M$5)),((M24+($H25*M$3))*(1+(M$4-M$5))))) -> 6286678.8 | N25: =IF($G25="","",IF($G25=1,(($C$2+$H25)*N$3)*(1+(N$4-N$5)),((N24+($H25*N$3))*(1+(N$4-N$5))))) -> 4592921.6 | O25: =IF($G25="","",IF($G25=1,(($C$2+$H25)*O$3)*(1+(O$4-O$5)),((O24+($H25*O$3))*(1+(O$4-O$5))))) -> 698519.87 | P25: =IF($G25="","",IF($G25=1,(($C$2+$H25)*P$3)*(1+(P$4-P$5)),((P24+($H25*P$3))*(1+(P$4-P$5))))) -> 647158.45 | ... T25: =IF($G25="","",IF($G25=1,(($C$2+$H25)*T$3)*(1+(T$4-T$5)),((T24+($H25*T$3))*(1+(T$4-T$5))))) -> 636158.63 | U25: =IF(G25="","",SUM(I25,K25,M25,O25,Q25,S25)) -> 30281609 | V25: =IF(H25="","",SUM(J25,L25,N25,P25,R25,T25)) -> 22723234 | W25: =IF($G25="","",IF($G25=1,(($C$2+$H25)*W$3)*(1+(W$4-W$5)),((W24+($H25*W$3))*(1+(W$4-W$5))))) -> 29698711 | X25: =IF($G25="","",IF($G25=1,(($C$2+$H25)*X$3)*(1+(X$4-X$5)),((X24+($H25*X$3))*(1+(X$4-X$5))))) -> 22213859 | Y25: =IF($G25="","",IF($G25=1,(U25-$C$2-H25)/($C$2+H25),(U25-U24-H25)/(U24+H25))) -> 0.072928645 | Z25: =IF($G25="","",IF($G25=1,(V25-$C$2-H25)/($C$2+H25),(V25-V24-H25)/(V24+H25))) -> 0.054070135 | AA25: =IF($G25="","",Z25-Y25) -> -0.018858511 | AB25: =IF($G25="","",IF($G25=1,(W25-$C$2-H25)/($C$2+H25),(W25-W24-H25)/(W24+H25))) -> 0.0704 | AC25: =IF($G25="","",IF($G25=1,(X25-$C$2-H25)/($C$2+H25),(X25-X24-H25)/(X24+H25))) -> 0.05114832 | AD25: =IF($G25="","",AC25-AB25) -> -0.01925168 | AE25: =IF($G25="","",IF($G25=1,Y25,(1+Y25)*(1+AE24)-1)) -> 2.0281609 | AF25: =IF($G25="","",IF($G25=1,Z25,(1+Z25)*(1+AF24)-1)) -> 1.2723234 | AG25: =IF($G25="","",AF25-AE25) -> -0.75583751 | AH25: =IF($G25="","",IF($G25=1,AB25,(1+AB25)*(1+AH24)-1)) -> 1.9698711 | AI25: =IF($G25="","",IF($G25=1,AC25,(1+AC25)*(1+AI24)-1)) -> 1.2213859 | AJ25: =IF($G25="","",AI25-AH25) -> -0.74848526 | AK25: =IF($G25="","",(1+AE25)^(1/G25)-1) -> 0.071701118 | AL25: =IF($G25="","",(1+AF25)^(1/G25)-1) -> 0.052638823 | AM25: =IF($G25="","",AL25-AK25) -> -0.019062296 | AN25: =IF($G25="","",(1+AH25)^(1/G25)-1) -> 0.0704 | AO25: =IF($G25="","",(1+AI25)^(1/G25)-1) -> 0.05114832 | AP25: =IF($G25="","",AO25-AN25) -> -0.01925168
B26: Total Return (Drag) | C26: =_xlfn.XLOOKUP(C3,G:G,AG:AG) -> -1.2086514 | D26: =_xlfn.XLOOKUP(C3,G:G,AJ:AJ) -> -1.1867801 | G26: 17 | H26: =IF(G26="","",SUMIFS(Add_Contributions[[#All],[Amount ($)]],Add_Contributions[[#All],[Year]],G26)) -> 0 | I26: =IF($G26="","",IF($G26=1,(($C$2+$H26)*I$3)*(1+(I$4-I$5)),((I25+($H26*I$3))*(1+(I$4-I$5))))) -> 15984078 | J26: =IF($G26="","",IF($G26=1,(($C$2+$H26)*J$3)*(1+(J$4-J$5)),((J25+($H26*J$3))*(1+(J$4-J$5))))) -> 11813183 | K26: =IF($G26="","",IF($G26=1,(($C$2+$H26)*K$3)*(1+(K$4-K$5)),((K25+($H26*K$3))*(1+(K$4-K$5))))) -> 1776008.7 | L26: =IF($G26="","",IF($G26=1,(($C$2+$H26)*L$3)*(1+(L$4-L$5)),((L25+($H26*L$3))*(1+(L$4-L$5))))) -> 1641289.3 | M26: =IF($G26="","",IF($G26=1,(($C$2+$H26)*M$3)*(1+(M$4-M$5)),((M25+($H26*M$3))*(1+(M$4-M$5))))) -> 6601012.8 | N26: =IF($G26="","",IF($G26=1,(($C$2+$H26)*N$3)*(1+(N$4-N$5)),((N25+($H26*N$3))*(1+(N$4-N$5))))) -> 4728872.1 | O26: =IF($G26="","",IF($G26=1,(($C$2+$H26)*O$3)*(1+(O$4-O$5)),((O25+($H26*O$3))*(1+(O$4-O$5))))) -> 733445.86 | P26: =IF($G26="","",IF($G26=1,(($C$2+$H26)*P$3)*(1+(P$4-P$5)),((P25+($H26*P$3))*(1+(P$4-P$5))))) -> 676280.58 | ... T26: =IF($G26="","",IF($G26=1,(($C$2+$H26)*T$3)*(1+(T$4-T$5)),((T25+($H26*T$3))*(1+(T$4-T$5))))) -> 683870.53 | U26: =IF(G26="","",SUM(I26,K26,M26,O26,Q26,S26)) -> 32494581 | V26: =IF(H26="","",SUM(J26,L26,N26,P26,R26,T26)) -> 23955984 | W26: =IF($G26="","",IF($G26=1,(($C$2+$H26)*W$3)*(1+(W$4-W$5)),((W25+($H26*W$3))*(1+(W$4-W$5))))) -> 31789501 | X26: =IF($G26="","",IF($G26=1,(($C$2+$H26)*X$3)*(1+(X$4-X$5)),((X25+($H26*X$3))*(1+(X$4-X$5))))) -> 23350060 | Y26: =IF($G26="","",IF($G26=1,(U26-$C$2-H26)/($C$2+H26),(U26-U25-H26)/(U25+H26))) -> 0.073079761 | Z26: =IF($G26="","",IF($G26=1,(V26-$C$2-H26)/($C$2+H26),(V26-V25-H26)/(V25+H26))) -> 0.05425064 | AA26: =IF($G26="","",Z26-Y26) -> -0.018829121 | AB26: =IF($G26="","",IF($G26=1,(W26-$C$2-H26)/($C$2+H26),(W26-W25-H26)/(W25+H26))) -> 0.0704 | AC26: =IF($G26="","",IF($G26=1,(X26-$C$2-H26)/($C$2+H26),(X26-X25-H26)/(X25+H26))) -> 0.05114832 | AD26: =IF($G26="","",AC26-AB26) -> -0.01925168 | AE26: =IF($G26="","",IF($G26=1,Y26,(1+Y26)*(1+AE25)-1)) -> 2.2494581 | AF26: =IF($G26="","",IF($G26=1,Z26,(1+Z26)*(1+AF25)-1)) -> 1.3955984 | AG26: =IF($G26="","",AF26-AE26) -> -0.85385978 | AH26: =IF($G26="","",IF($G26=1,AB26,(1+AB26)*(1+AH25)-1)) -> 2.1789501 | AI26: =IF($G26="","",IF($G26=1,AC26,(1+AC26)*(1+AI25)-1)) -> 1.335006 | AJ26: =IF($G26="","",AI26-AH26) -> -0.84394403 | AK26: =IF($G26="","",(1+AE26)^(1/G26)-1) -> 0.071782166 | AL26: =IF($G26="","",(1+AF26)^(1/G26)-1) -> 0.052733567 | AM26: =IF($G26="","",AL26-AK26) -> -0.019048599 | AN26: =IF($G26="","",(1+AH26)^(1/G26)-1) -> 0.0704 | AO26: =IF($G26="","",(1+AI26)^(1/G26)-1) -> 0.05114832 | AP26: =IF($G26="","",AO26-AN26) -> -0.01925168
G27: 18 | H27: =IF(G27="","",SUMIFS(Add_Contributions[[#All],[Amount ($)]],Add_Contributions[[#All],[Year]],G27)) -> 0 | I27: =IF($G27="","",IF($G27=1,(($C$2+$H27)*I$3)*(1+(I$4-I$5)),((I26+($H27*I$3))*(1+(I$4-I$5))))) -> 17262804 | J27: =IF($G27="","",IF($G27=1,(($C$2+$H27)*J$3)*(1+(J$4-J$5)),((J26+($H27*J$3))*(1+(J$4-J$5))))) -> 12533314 | K27: =IF($G27="","",IF($G27=1,(($C$2+$H27)*K$3)*(1+(K$4-K$5)),((K26+($H27*K$3))*(1+(K$4-K$5))))) -> 1918089.4 | L27: =IF($G27="","",IF($G27=1,(($C$2+$H27)*L$3)*(1+(L$4-L$5)),((L26+($H27*L$3))*(1+(L$4-L$5))))) -> 1764386 | M27: =IF($G27="","",IF($G27=1,(($C$2+$H27)*M$3)*(1+(M$4-M$5)),((M26+($H27*M$3))*(1+(M$4-M$5))))) -> 6931063.4 | N27: =IF($G27="","",IF($G27=1,(($C$2+$H27)*N$3)*(1+(N$4-N$5)),((N26+($H27*N$3))*(1+(N$4-N$5))))) -> 4868846.7 | O27: =IF($G27="","",IF($G27=1,(($C$2+$H27)*O$3)*(1+(O$4-O$5)),((O26+($H27*O$3))*(1+(O$4-O$5))))) -> 770118.15 | P27: =IF($G27="","",IF($G27=1,(($C$2+$H27)*P$3)*(1+(P$4-P$5)),((P26+($H27*P$3))*(1+(P$4-P$5))))) -> 706713.21 | ... T27: =IF($G27="","",IF($G27=1,(($C$2+$H27)*T$3)*(1+(T$4-T$5)),((T26+($H27*T$3))*(1+(T$4-T$5))))) -> 735160.82 | U27: =IF(G27="","",SUM(I27,K27,M27,O27,Q27,S27)) -> 34874114 | V27: =IF(H27="","",SUM(J27,L27,N27,P27,R27,T27)) -> 25259890 | W27: =IF($G27="","",IF($G27=1,(($C$2+$H27)*W$3)*(1+(W$4-W$5)),((W26+($H27*W$3))*(1+(W$4-W$5))))) -> 34027482 | X27: =IF($G27="","",IF($G27=1,(($C$2+$H27)*X$3)*(1+(X$4-X$5)),((X26+($H27*X$3))*(1+(X$4-X$5))))) -> 24544377 | Y27: =IF($G27="","",IF($G27=1,(U27-$C$2-H27)/($C$2+H27),(U27-U26-H27)/(U26+H27))) -> 0.073228602 | Z27: =IF($G27="","",IF($G27=1,(V27-$C$2-H27)/($C$2+H27),(V27-V26-H27)/(V26+H27))) -> 0.05442925 | AA27: =IF($G27="","",Z27-Y27) -> -0.018799352 | AB27: =IF($G27="","",IF($G27=1,(W27-$C$2-H27)/($C$2+H27),(W27-W26-H27)/(W26+H27))) -> 0.0704 | AC27: =IF($G27="","",IF($G27=1,(X27-$C$2-H27)/($C$2+H27),(X27-X26-H27)/(X26+H27))) -> 0.05114832 | AD27: =IF($G27="","",AC27-AB27) -> -0.01925168 | AE27: =IF($G27="","",IF($G27=1,Y27,(1+Y27)*(1+AE26)-1)) -> 2.4874114 | AF27: =IF($G27="","",IF($G27=1,Z27,(1+Z27)*(1+AF26)-1)) -> 1.525989 | AG27: =IF($G27="","",AF27-AE27) -> -0.96142244 | AH27: =IF($G27="","",IF($G27=1,AB27,(1+AB27)*(1+AH26)-1)) -> 2.4027482 | AI27: =IF($G27="","",IF($G27=1,AC27,(1+AC27)*(1+AI26)-1)) -> 1.4544377 | AJ27: =IF($G27="","",AI27-AH27) -> -0.94831048 | AK27: =IF($G27="","",(1+AE27)^(1/G27)-1) -> 0.071862472 | AL27: =IF($G27="","",(1+AF27)^(1/G27)-1) -> 0.0528277 | AM27: =IF($G27="","",AL27-AK27) -> -0.019034772 | AN27: =IF($G27="","",(1+AH27)^(1/G27)-1) -> 0.0704 | AO27: =IF($G27="","",(1+AI27)^(1/G27)-1) -> 0.05114832 | AP27: =IF($G27="","",AO27-AN27) -> -0.01925168
B28: Annualized Return (Gross) | C28: =_xlfn.XLOOKUP(C3,G:G,AK:AK) -> 0.072020849 | D28: =_xlfn.XLOOKUP(C3,G:G,AN:AN) -> 0.0704 | G28: 19 | H28: =IF(G28="","",SUMIFS(Add_Contributions[[#All],[Amount ($)]],Add_Contributions[[#All],[Year]],G28)) -> 0 | I28: =IF($G28="","",IF($G28=1,(($C$2+$H28)*I$3)*(1+(I$4-I$5)),((I27+($H28*I$3))*(1+(I$4-I$5))))) -> 18643829 | J28: =IF($G28="","",IF($G28=1,(($C$2+$H28)*J$3)*(1+(J$4-J$5)),((J27+($H28*J$3))*(1+(J$4-J$5))))) -> 13297345 | K28: =IF($G28="","",IF($G28=1,(($C$2+$H28)*K$3)*(1+(K$4-K$5)),((K27+($H28*K$3))*(1+(K$4-K$5))))) -> 2071536.5 | L28: =IF($G28="","",IF($G28=1,(($C$2+$H28)*L$3)*(1+(L$4-L$5)),((L27+($H28*L$3))*(1+(L$4-L$5))))) -> 1896714.9 | M28: =IF($G28="","",IF($G28=1,(($C$2+$H28)*M$3)*(1+(M$4-M$5)),((M27+($H28*M$3))*(1+(M$4-M$5))))) -> 7277616.6 | N28: =IF($G28="","",IF($G28=1,(($C$2+$H28)*N$3)*(1+(N$4-N$5)),((N27+($H28*N$3))*(1+(N$4-N$5))))) -> 5012964.5 | O28: =IF($G28="","",IF($G28=1,(($C$2+$H28)*O$3)*(1+(O$4-O$5)),((O27+($H28*O$3))*(1+(O$4-O$5))))) -> 808624.06 | P28: =IF($G28="","",IF($G28=1,(($C$2+$H28)*P$3)*(1+(P$4-P$5)),((P27+($H28*P$3))*(1+(P$4-P$5))))) -> 738515.3 | ... T28: =IF($G28="","",IF($G28=1,(($C$2+$H28)*T$3)*(1+(T$4-T$5)),((T27+($H28*T$3))*(1+(T$4-T$5))))) -> 790297.88 | U28: =IF(G28="","",SUM(I28,K28,M28,O28,Q28,S28)) -> 37433008 | V28: =IF(H28="","",SUM(J28,L28,N28,P28,R28,T28)) -> 26639230 | W28: =IF($G28="","",IF($G28=1,(($C$2+$H28)*W$3)*(1+(W$4-W$5)),((W27+($H28*W$3))*(1+(W$4-W$5))))) -> 36423016 | X28: =IF($G28="","",IF($G28=1,(($C$2+$H28)*X$3)*(1+(X$4-X$5)),((X27+($H28*X$3))*(1+(X$4-X$5))))) -> 25799780 | Y28: =IF($G28="","",IF($G28=1,(U28-$C$2-H28)/($C$2+H28),(U28-U27-H28)/(U27+H28))) -> 0.073375159 | Z28: =IF($G28="","",IF($G28=1,(V28-$C$2-H28)/($C$2+H28),(V28-V27-H28)/(V27+H28))) -> 0.054605953 | AA28: =IF($G28="","",Z28-Y28) -> -0.018769206 | AB28: =IF($G28="","",IF($G28=1,(W28-$C$2-H28)/($C$2+H28),(W28-W27-H28)/(W27+H28))) -> 0.0704 | AC28: =IF($G28="","",IF($G28=1,(X28-$C$2-H28)/($C$2+H28),(X28-X27-H28)/(X27+H28))) -> 0.05114832 | AD28: =IF($G28="","",AC28-AB28) -> -0.01925168 | AE28: =IF($G28="","",IF($G28=1,Y28,(1+Y28)*(1+AE27)-1)) -> 2.7433008 | AF28: =IF($G28="","",IF($G28=1,Z28,(1+Z28)*(1+AF27)-1)) -> 1.663923 | AG28: =IF($G28="","",AF28-AE28) -> -1.0793778 | AH28: =IF($G28="","",IF($G28=1,AB28,(1+AB28)*(1+AH27)-1)) -> 2.6423016 | AI28: =IF($G28="","",IF($G28=1,AC28,(1+AC28)*(1+AI27)-1)) -> 1.579978 | AJ28: =IF($G28="","",AI28-AH28) -> -1.0623236 | AK28: =IF($G28="","",(1+AE28)^(1/G28)-1) -> 0.071942034 | AL28: =IF($G28="","",(1+AF28)^(1/G28)-1) -> 0.052921218 | AM28: =IF($G28="","",AL28-AK28) -> -0.019020817 | AN28: =IF($G28="","",(1+AH28)^(1/G28)-1) -> 0.0704 | AO28: =IF($G28="","",(1+AI28)^(1/G28)-1) -> 0.05114832 | AP28: =IF($G28="","",AO28-AN28) -> -0.01925168
B29: Annualized Return (Net) | C29: =_xlfn.XLOOKUP(C3,G:G,AL:AL) -> 0.053014116 | D29: =_xlfn.XLOOKUP(C3,G:G,AO:AO) -> 0.05114832 | G29: 20 | H29: =IF(G29="","",SUMIFS(Add_Contributions[[#All],[Amount ($)]],Add_Contributions[[#All],[Year]],G29)) -> 0 | I29: =IF($G29="","",IF($G29=1,(($C$2+$H29)*I$3)*(1+(I$4-I$5)),((I28+($H29*I$3))*(1+(I$4-I$5))))) -> 20135335 | J29: =IF($G29="","",IF($G29=1,(($C$2+$H29)*J$3)*(1+(J$4-J$5)),((J28+($H29*J$3))*(1+(J$4-J$5))))) -> 14107952 | K29: =IF($G29="","",IF($G29=1,(($C$2+$H29)*K$3)*(1+(K$4-K$5)),((K28+($H29*K$3))*(1+(K$4-K$5))))) -> 2237259.4 | L29: =IF($G29="","",IF($G29=1,(($C$2+$H29)*L$3)*(1+(L$4-L$5)),((L28+($H29*L$3))*(1+(L$4-L$5))))) -> 2038968.5 | M29: =IF($G29="","",IF($G29=1,(($C$2+$H29)*M$3)*(1+(M$4-M$5)),((M28+($H29*M$3))*(1+(M$4-M$5))))) -> 7641497.4 | N29: =IF($G29="","",IF($G29=1,(($C$2+$H29)*N$3)*(1+(N$4-N$5)),((N28+($H29*N$3))*(1+(N$4-N$5))))) -> 5161348.3 | O29: =IF($G29="","",IF($G29=1,(($C$2+$H29)*O$3)*(1+(O$4-O$5)),((O28+($H29*O$3))*(1+(O$4-O$5))))) -> 849055.27 | P29: =IF($G29="","",IF($G29=1,(($C$2+$H29)*P$3)*(1+(P$4-P$5)),((P28+($H29*P$3))*(1+(P$4-P$5))))) -> 771748.49 | ... T29: =IF($G29="","",IF($G29=1,(($C$2+$H29)*T$3)*(1+(T$4-T$5)),((T28+($H29*T$3))*(1+(T$4-T$5))))) -> 849570.22 | U29: =IF(G29="","",SUM(I29,K29,M29,O29,Q29,S29)) -> 40185061 | V29: =IF(H29="","",SUM(J29,L29,N29,P29,R29,T29)) -> 28098547 | W29: =IF($G29="","",IF($G29=1,(($C$2+$H29)*W$3)*(1+(W$4-W$5)),((W28+($H29*W$3))*(1+(W$4-W$5))))) -> 38987197 | X29: =IF($G29="","",IF($G29=1,(($C$2+$H29)*X$3)*(1+(X$4-X$5)),((X28+($H29*X$3))*(1+(X$4-X$5))))) -> 27119396 | Y29: =IF($G29="","",IF($G29=1,(U29-$C$2-H29)/($C$2+H29),(U29-U28-H29)/(U28+H29))) -> 0.07351943 | Z29: =IF($G29="","",IF($G29=1,(V29-$C$2-H29)/($C$2+H29),(V29-V28-H29)/(V28+H29))) -> 0.054780742 | AA29: =IF($G29="","",Z29-Y29) -> -0.018738688 | AB29: =IF($G29="","",IF($G29=1,(W29-$C$2-H29)/($C$2+H29),(W29-W28-H29)/(W28+H29))) -> 0.0704 | AC29: =IF($G29="","",IF($G29=1,(X29-$C$2-H29)/($C$2+H29),(X29-X28-H29)/(X28+H29))) -> 0.05114832 | AD29: =IF($G29="","",AC29-AB29) -> -0.01925168 | AE29: =IF($G29="","",IF($G29=1,Y29,(1+Y29)*(1+AE28)-1)) -> 3.0185061 | AF29: =IF($G29="","",IF($G29=1,Z29,(1+Z29)*(1+AF28)-1)) -> 1.8098547 | AG29: =IF($G29="","",AF29-AE29) -> -1.2086514 | AH29: =IF($G29="","",IF($G29=1,AB29,(1+AB29)*(1+AH28)-1)) -> 2.8987197 | AI29: =IF($G29="","",IF($G29=1,AC29,(1+AC29)*(1+AI28)-1)) -> 1.7119396 | AJ29: =IF($G29="","",AI29-AH29) -> -1.1867801 | AK29: =IF($G29="","",(1+AE29)^(1/G29)-1) -> 0.072020849 | AL29: =IF($G29="","",(1+AF29)^(1/G29)-1) -> 0.053014116 | AM29: =IF($G29="","",AL29-AK29) -> -0.019006733 | AN29: =IF($G29="","",(1+AH29)^(1/G29)-1) -> 0.0704 | AO29: =IF($G29="","",(1+AI29)^(1/G29)-1) -> 0.05114832 | AP29: =IF($G29="","",AO29-AN29) -> -0.01925168
B30: Annualized Return (Drag) | C30: =_xlfn.XLOOKUP(C3,G:G,AM:AM) -> -0.019006733 | D30: =_xlfn.XLOOKUP(C3,G:G,AP:AP) -> -0.01925168 | H30: =IF(G30="","",SUMIFS(Add_Contributions[[#All],[Amount ($)]],Add_Contributions[[#All],[Year]],G30)) | I30: =IF($G30="","",IF($G30=1,(($C$2+$H30)*I$3)*(1+(I$4-I$5)),((I29+($H30*I$3))*(1+(I$4-I$5))))) | J30: =IF($G30="","",IF($G30=1,(($C$2+$H30)*J$3)*(1+(J$4-J$5)),((J29+($H30*J$3))*(1+(J$4-J$5))))) | K30: =IF($G30="","",IF($G30=1,(($C$2+$H30)*K$3)*(1+(K$4-K$5)),((K29+($H30*K$3))*(1+(K$4-K$5))))) | L30: =IF($G30="","",IF($G30=1,(($C$2+$H30)*L$3)*(1+(L$4-L$5)),((L29+($H30*L$3))*(1+(L$4-L$5))))) | M30: =IF($G30="","",IF($G30=1,(($C$2+$H30)*M$3)*(1+(M$4-M$5)),((M29+($H30*M$3))*(1+(M$4-M$5))))) | N30: =IF($G30="","",IF($G30=1,(($C$2+$H30)*N$3)*(1+(N$4-N$5)),((N29+($H30*N$3))*(1+(N$4-N$5))))) | O30: =IF($G30="","",IF($G30=1,(($C$2+$H30)*O$3)*(1+(O$4-O$5)),((O29+($H30*O$3))*(1+(O$4-O$5))))) | P30: =IF($G30="","",IF($G30=1,(($C$2+$H30)*P$3)*(1+(P$4-P$5)),((P29+($H30*P$3))*(1+(P$4-P$5))))) | ... T30: =IF($G30="","",IF($G30=1,(($C$2+$H30)*T$3)*(1+(T$4-T$5)),((T29+($H30*T$3))*(1+(T$4-T$5))))) | U30: =IF(G30="","",SUM(I30,K30,M30,O30,Q30,S30)) | V30: =IF(H30="","",SUM(J30,L30,N30,P30,R30,T30)) | W30: =IF($G30="","",IF($G30=1,(($C$2+$H30)*W$3)*(1+(W$4-W$5)),((W29+($H30*W$3))*(1+(W$4-W$5))))) | X30: =IF($G30="","",IF($G30=1,(($C$2+$H30)*X$3)*(1+(X$4-X$5)),((X29+($H30*X$3))*(1+(X$4-X$5))))) | Y30: =IF($G30="","",IF($G30=1,(U30-$C$2-H30)/($C$2+H30),(U30-U29-H30)/(U29+H30))) | Z30: =IF($G30="","",IF($G30=1,(V30-$C$2-H30)/($C$2+H30),(V30-V29-H30)/(V29+H30))) | AA30: =IF($G30="","",Z30-Y30) | AB30: =IF($G30="","",IF($G30=1,(W30-$C$2-H30)/($C$2+H30),(W30-W29-H30)/(W29+H30))) | AC30: =IF($G30="","",IF($G30=1,(X30-$C$2-H30)/($C$2+H30),(X30-X29-H30)/(X29+H30))) | AD30: =IF($G30="","",AC30-AB30) | AE30: =IF($G30="","",IF($G30=1,Y30,(1+Y30)*(1+AE29)-1)) | AF30: =IF($G30="","",IF($G30=1,Z30,(1+Z30)*(1+AF29)-1)) | AG30: =IF($G30="","",AF30-AE30) | AH30: =IF($G30="","",IF($G30=1,AB30,(1+AB30)*(1+AH29)-1)) | AI30: =IF($G30="","",IF($G30=1,AC30,(1+AC30)*(1+AI29)-1)) | AJ30: =IF($G30="","",AI30-AH30) | AK30: =IF($G30="","",(1+AE30)^(1/G30)-1) | AL30: =IF($G30="","",(1+AF30)^(1/G30)-1) | AM30: =IF($G30="","",AL30-AK30) | AN30: =IF($G30="","",(1+AH30)^(1/G30)-1) | AO30: =IF($G30="","",(1+AI30)^(1/G30)-1) | AP30: =IF($G30="","",AO30-AN30)
H31: =IF(G31="","",SUMIFS(Add_Contributions[[#All],[Amount ($)]],Add_Contributions[[#All],[Year]],G31)) | I31: =IF($G31="","",IF($G31=1,(($C$2+$H31)*I$3)*(1+(I$4-I$5)),((I30+($H31*I$3))*(1+(I$4-I$5))))) | J31: =IF($G31="","",IF($G31=1,(($C$2+$H31)*J$3)*(1+(J$4-J$5)),((J30+($H31*J$3))*(1+(J$4-J$5))))) | K31: =IF($G31="","",IF($G31=1,(($C$2+$H31)*K$3)*(1+(K$4-K$5)),((K30+($H31*K$3))*(1+(K$4-K$5))))) | L31: =IF($G31="","",IF($G31=1,(($C$2+$H31)*L$3)*(1+(L$4-L$5)),((L30+($H31*L$3))*(1+(L$4-L$5))))) | M31: =IF($G31="","",IF($G31=1,(($C$2+$H31)*M$3)*(1+(M$4-M$5)),((M30+($H31*M$3))*(1+(M$4-M$5))))) | N31: =IF($G31="","",IF($G31=1,(($C$2+$H31)*N$3)*(1+(N$4-N$5)),((N30+($H31*N$3))*(1+(N$4-N$5))))) | O31: =IF($G31="","",IF($G31=1,(($C$2+$H31)*O$3)*(1+(O$4-O$5)),((O30+($H31*O$3))*(1+(O$4-O$5))))) | P31: =IF($G31="","",IF($G31=1,(($C$2+$H31)*P$3)*(1+(P$4-P$5)),((P30+($H31*P$3))*(1+(P$4-P$5))))) | ... T31: =IF($G31="","",IF($G31=1,(($C$2+$H31)*T$3)*(1+(T$4-T$5)),((T30+($H31*T$3))*(1+(T$4-T$5))))) | U31: =IF(G31="","",SUM(I31,K31,M31,O31,Q31,S31)) | V31: =IF(H31="","",SUM(J31,L31,N31,P31,R31,T31)) | W31: =IF($G31="","",IF($G31=1,(($C$2+$H31)*W$3)*(1+(W$4-W$5)),((W30+($H31*W$3))*(1+(W$4-W$5))))) | X31: =IF($G31="","",IF($G31=1,(($C$2+$H31)*X$3)*(1+(X$4-X$5)),((X30+($H31*X$3))*(1+(X$4-X$5))))) | Y31: =IF($G31="","",IF($G31=1,(U31-$C$2-H31)/($C$2+H31),(U31-U30-H31)/(U30+H31))) | Z31: =IF($G31="","",IF($G31=1,(V31-$C$2-H31)/($C$2+H31),(V31-V30-H31)/(V30+H31))) | AA31: =IF($G31="","",Z31-Y31) | AB31: =IF($G31="","",IF($G31=1,(W31-$C$2-H31)/($C$2+H31),(W31-W30-H31)/(W30+H31))) | AC31: =IF($G31="","",IF($G31=1,(X31-$C$2-H31)/($C$2+H31),(X31-X30-H31)/(X30+H31))) | AD31: =IF($G31="","",AC31-AB31) | AE31: =IF($G31="","",IF($G31=1,Y31,(1+Y31)*(1+AE30)-1)) | AF31: =IF($G31="","",IF($G31=1,Z31,(1+Z31)*(1+AF30)-1)) | AG31: =IF($G31="","",AF31-AE31) | AH31: =IF($G31="","",IF($G31=1,AB31,(1+AB31)*(1+AH30)-1)) | AI31: =IF($G31="","",IF($G31=1,AC31,(1+AC31)*(1+AI30)-1)) | AJ31: =IF($G31="","",AI31-AH31) | AK31: =IF($G31="","",(1+AE31)^(1/G31)-1) | AL31: =IF($G31="","",(1+AF31)^(1/G31)-1) | AM31: =IF($G31="","",AL31-AK31) | AN31: =IF($G31="","",(1+AH31)^(1/G31)-1) | AO31: =IF($G31="","",(1+AI31)^(1/G31)-1) | AP31: =IF($G31="","",AO31-AN31)
H32: =IF(G32="","",SUMIFS(Add_Contributions[[#All],[Amount ($)]],Add_Contributions[[#All],[Year]],G32)) | I32: =IF($G32="","",IF($G32=1,(($C$2+$H32)*I$3)*(1+(I$4-I$5)),((I31+($H32*I$3))*(1+(I$4-I$5))))) | J32: =IF($G32="","",IF($G32=1,(($C$2+$H32)*J$3)*(1+(J$4-J$5)),((J31+($H32*J$3))*(1+(J$4-J$5))))) | K32: =IF($G32="","",IF($G32=1,(($C$2+$H32)*K$3)*(1+(K$4-K$5)),((K31+($H32*K$3))*(1+(K$4-K$5))))) | L32: =IF($G32="","",IF($G32=1,(($C$2+$H32)*L$3)*(1+(L$4-L$5)),((L31+($H32*L$3))*(1+(L$4-L$5))))) | M32: =IF($G32="","",IF($G32=1,(($C$2+$H32)*M$3)*(1+(M$4-M$5)),((M31+($H32*M$3))*(1+(M$4-M$5))))) | N32: =IF($G32="","",IF($G32=1,(($C$2+$H32)*N$3)*(1+(N$4-N$5)),((N31+($H32*N$3))*(1+(N$4-N$5))))) | O32: =IF($G32="","",IF($G32=1,(($C$2+$H32)*O$3)*(1+(O$4-O$5)),((O31+($H32*O$3))*(1+(O$4-O$5))))) | P32: =IF($G32="","",IF($G32=1,(($C$2+$H32)*P$3)*(1+(P$4-P$5)),((P31+($H32*P$3))*(1+(P$4-P$5))))) | ... T32: =IF($G32="","",IF($G32=1,(($C$2+$H32)*T$3)*(1+(T$4-T$5)),((T31+($H32*T$3))*(1+(T$4-T$5))))) | U32: =IF(G32="","",SUM(I32,K32,M32,O32,Q32,S32)) | V32: =IF(H32="","",SUM(J32,L32,N32,P32,R32,T32)) | W32: =IF($G32="","",IF($G32=1,(($C$2+$H32)*W$3)*(1+(W$4-W$5)),((W31+($H32*W$3))*(1+(W$4-W$5))))) | X32: =IF($G32="","",IF($G32=1,(($C$2+$H32)*X$3)*(1+(X$4-X$5)),((X31+($H32*X$3))*(1+(X$4-X$5))))) | Y32: =IF($G32="","",IF($G32=1,(U32-$C$2-H32)/($C$2+H32),(U32-U31-H32)/(U31+H32))) | Z32: =IF($G32="","",IF($G32=1,(V32-$C$2-H32)/($C$2+H32),(V32-V31-H32)/(V31+H32))) | AA32: =IF($G32="","",Z32-Y32) | AB32: =IF($G32="","",IF($G32=1,(W32-$C$2-H32)/($C$2+H32),(W32-W31-H32)/(W31+H32))) | AC32: =IF($G32="","",IF($G32=1,(X32-$C$2-H32)/($C$2+H32),(X32-X31-H32)/(X31+H32))) | AD32: =IF($G32="","",AC32-AB32) | AE32: =IF($G32="","",IF($G32=1,Y32,(1+Y32)*(1+AE31)-1)) | AF32: =IF($G32="","",IF($G32=1,Z32,(1+Z32)*(1+AF31)-1)) | AG32: =IF($G32="","",AF32-AE32) | AH32: =IF($G32="","",IF($G32=1,AB32,(1+AB32)*(1+AH31)-1)) | AI32: =IF($G32="","",IF($G32=1,AC32,(1+AC32)*(1+AI31)-1)) | AJ32: =IF($G32="","",AI32-AH32) | AK32: =IF($G32="","",(1+AE32)^(1/G32)-1) | AL32: =IF($G32="","",(1+AF32)^(1/G32)-1) | AM32: =IF($G32="","",AL32-AK32) | AN32: =IF($G32="","",(1+AH32)^(1/G32)-1) | AO32: =IF($G32="","",(1+AI32)^(1/G32)-1) | AP32: =IF($G32="","",AO32-AN32)
H33: =IF(G33="","",SUMIFS(Add_Contributions[[#All],[Amount ($)]],Add_Contributions[[#All],[Year]],G33)) | I33: =IF($G33="","",IF($G33=1,(($C$2+$H33)*I$3)*(1+(I$4-I$5)),((I32+($H33*I$3))*(1+(I$4-I$5))))) | J33: =IF($G33="","",IF($G33=1,(($C$2+$H33)*J$3)*(1+(J$4-J$5)),((J32+($H33*J$3))*(1+(J$4-J$5))))) | K33: =IF($G33="","",IF($G33=1,(($C$2+$H33)*K$3)*(1+(K$4-K$5)),((K32+($H33*K$3))*(1+(K$4-K$5))))) | L33: =IF($G33="","",IF($G33=1,(($C$2+$H33)*L$3)*(1+(L$4-L$5)),((L32+($H33*L$3))*(1+(L$4-L$5))))) | M33: =IF($G33="","",IF($G33=1,(($C$2+$H33)*M$3)*(1+(M$4-M$5)),((M32+($H33*M$3))*(1+(M$4-M$5))))) | N33: =IF($G33="","",IF($G33=1,(($C$2+$H33)*N$3)*(1+(N$4-N$5)),((N32+($H33*N$3))*(1+(N$4-N$5))))) | O33: =IF($G33="","",IF($G33=1,(($C$2+$H33)*O$3)*(1+(O$4-O$5)),((O32+($H33*O$3))*(1+(O$4-O$5))))) | P33: =IF($G33="","",IF($G33=1,(($C$2+$H33)*P$3)*(1+(P$4-P$5)),((P32+($H33*P$3))*(1+(P$4-P$5))))) | ... T33: =IF($G33="","",IF($G33=1,(($C$2+$H33)*T$3)*(1+(T$4-T$5)),((T32+($H33*T$3))*(1+(T$4-T$5))))) | U33: =IF(G33="","",SUM(I33,K33,M33,O33,Q33,S33)) | V33: =IF(H33="","",SUM(J33,L33,N33,P33,R33,T33)) | W33: =IF($G33="","",IF($G33=1,(($C$2+$H33)*W$3)*(1+(W$4-W$5)),((W32+($H33*W$3))*(1+(W$4-W$5))))) | X33: =IF($G33="","",IF($G33=1,(($C$2+$H33)*X$3)*(1+(X$4-X$5)),((X32+($H33*X$3))*(1+(X$4-X$5))))) | Y33: =IF($G33="","",IF($G33=1,(U33-$C$2-H33)/($C$2+H33),(U33-U32-H33)/(U32+H33))) | Z33: =IF($G33="","",IF($G33=1,(V33-$C$2-H33)/($C$2+H33),(V33-V32-H33)/(V32+H33))) | AA33: =IF($G33="","",Z33-Y33) | AB33: =IF($G33="","",IF($G33=1,(W33-$C$2-H33)/($C$2+H33),(W33-W32-H33)/(W32+H33))) | AC33: =IF($G33="","",IF($G33=1,(X33-$C$2-H33)/($C$2+H33),(X33-X32-H33)/(X32+H33))) | AD33: =IF($G33="","",AC33-AB33) | AE33: =IF($G33="","",IF($G33=1,Y33,(1+Y33)*(1+AE32)-1)) | AF33: =IF($G33="","",IF($G33=1,Z33,(1+Z33)*(1+AF32)-1)) | AG33: =IF($G33="","",AF33-AE33) | AH33: =IF($G33="","",IF($G33=1,AB33,(1+AB33)*(1+AH32)-1)) | AI33: =IF($G33="","",IF($G33=1,AC33,(1+AC33)*(1+AI32)-1)) | AJ33: =IF($G33="","",AI33-AH33) | AK33: =IF($G33="","",(1+AE33)^(1/G33)-1) | AL33: =IF($G33="","",(1+AF33)^(1/G33)-1) | AM33: =IF($G33="","",AL33-AK33) | AN33: =IF($G33="","",(1+AH33)^(1/G33)-1) | AO33: =IF($G33="","",(1+AI33)^(1/G33)-1) | AP33: =IF($G33="","",AO33-AN33)
H34: =IF(G34="","",SUMIFS(Add_Contributions[[#All],[Amount ($)]],Add_Contributions[[#All],[Year]],G34)) | I34: =IF($G34="","",IF($G34=1,(($C$2+$H34)*I$3)*(1+(I$4-I$5)),((I33+($H34*I$3))*(1+(I$4-I$5))))) | J34: =IF($G34="","",IF($G34=1,(($C$2+$H34)*J$3)*(1+(J$4-J$5)),((J33+($H34*J$3))*(1+(J$4-J$5))))) | K34: =IF($G34="","",IF($G34=1,(($C$2+$H34)*K$3)*(1+(K$4-K$5)),((K33+($H34*K$3))*(1+(K$4-K$5))))) | L34: =IF($G34="","",IF($G34=1,(($C$2+$H34)*L$3)*(1+(L$4-L$5)),((L33+($H34*L$3))*(1+(L$4-L$5))))) | M34: =IF($G34="","",IF($G34=1,(($C$2+$H34)*M$3)*(1+(M$4-M$5)),((M33+($H34*M$3))*(1+(M$4-M$5))))) | N34: =IF($G34="","",IF($G34=1,(($C$2+$H34)*N$3)*(1+(N$4-N$5)),((N33+($H34*N$3))*(1+(N$4-N$5))))) | O34: =IF($G34="","",IF($G34=1,(($C$2+$H34)*O$3)*(1+(O$4-O$5)),((O33+($H34*O$3))*(1+(O$4-O$5))))) | P34: =IF($G34="","",IF($G34=1,(($C$2+$H34)*P$3)*(1+(P$4-P$5)),((P33+($H34*P$3))*(1+(P$4-P$5))))) | ... T34: =IF($G34="","",IF($G34=1,(($C$2+$H34)*T$3)*(1+(T$4-T$5)),((T33+($H34*T$3))*(1+(T$4-T$5))))) | U34: =IF(G34="","",SUM(I34,K34,M34,O34,Q34,S34)) | V34: =IF(H34="","",SUM(J34,L34,N34,P34,R34,T34)) | W34: =IF($G34="","",IF($G34=1,(($C$2+$H34)*W$3)*(1+(W$4-W$5)),((W33+($H34*W$3))*(1+(W$4-W$5))))) | X34: =IF($G34="","",IF($G34=1,(($C$2+$H34)*X$3)*(1+(X$4-X$5)),((X33+($H34*X$3))*(1+(X$4-X$5))))) | Y34: =IF($G34="","",IF($G34=1,(U34-$C$2-H34)/($C$2+H34),(U34-U33-H34)/(U33+H34))) | Z34: =IF($G34="","",IF($G34=1,(V34-$C$2-H34)/($C$2+H34),(V34-V33-H34)/(V33+H34))) | AA34: =IF($G34="","",Z34-Y34) | AB34: =IF($G34="","",IF($G34=1,(W34-$C$2-H34)/($C$2+H34),(W34-W33-H34)/(W33+H34))) | AC34: =IF($G34="","",IF($G34=1,(X34-$C$2-H34)/($C$2+H34),(X34-X33-H34)/(X33+H34))) | AD34: =IF($G34="","",AC34-AB34) | AE34: =IF($G34="","",IF($G34=1,Y34,(1+Y34)*(1+AE33)-1)) | AF34: =IF($G34="","",IF($G34=1,Z34,(1+Z34)*(1+AF33)-1)) | AG34: =IF($G34="","",AF34-AE34) | AH34: =IF($G34="","",IF($G34=1,AB34,(1+AB34)*(1+AH33)-1)) | AI34: =IF($G34="","",IF($G34=1,AC34,(1+AC34)*(1+AI33)-1)) | AJ34: =IF($G34="","",AI34-AH34) | AK34: =IF($G34="","",(1+AE34)^(1/G34)-1) | AL34: =IF($G34="","",(1+AF34)^(1/G34)-1) | AM34: =IF($G34="","",AL34-AK34) | AN34: =IF($G34="","",(1+AH34)^(1/G34)-1) | AO34: =IF($G34="","",(1+AI34)^(1/G34)-1) | AP34: =IF($G34="","",AO34-AN34)
H35: =IF(G35="","",SUMIFS(Add_Contributions[[#All],[Amount ($)]],Add_Contributions[[#All],[Year]],G35)) | I35: =IF($G35="","",IF($G35=1,(($C$2+$H35)*I$3)*(1+(I$4-I$5)),((I34+($H35*I$3))*(1+(I$4-I$5))))) | J35: =IF($G35="","",IF($G35=1,(($C$2+$H35)*J$3)*(1+(J$4-J$5)),((J34+($H35*J$3))*(1+(J$4-J$5))))) | K35: =IF($G35="","",IF($G35=1,(($C$2+$H35)*K$3)*(1+(K$4-K$5)),((K34+($H35*K$3))*(1+(K$4-K$5))))) | L35: =IF($G35="","",IF($G35=1,(($C$2+$H35)*L$3)*(1+(L$4-L$5)),((L34+($H35*L$3))*(1+(L$4-L$5))))) | M35: =IF($G35="","",IF($G35=1,(($C$2+$H35)*M$3)*(1+(M$4-M$5)),((M34+($H35*M$3))*(1+(M$4-M$5))))) | N35: =IF($G35="","",IF($G35=1,(($C$2+$H35)*N$3)*(1+(N$4-N$5)),((N34+($H35*N$3))*(1+(N$4-N$5))))) | O35: =IF($G35="","",IF($G35=1,(($C$2+$H35)*O$3)*(1+(O$4-O$5)),((O34+($H35*O$3))*(1+(O$4-O$5))))) | P35: =IF($G35="","",IF($G35=1,(($C$2+$H35)*P$3)*(1+(P$4-P$5)),((P34+($H35*P$3))*(1+(P$4-P$5))))) | ... T35: =IF($G35="","",IF($G35=1,(($C$2+$H35)*T$3)*(1+(T$4-T$5)),((T34+($H35*T$3))*(1+(T$4-T$5))))) | U35: =IF(G35="","",SUM(I35,K35,M35,O35,Q35,S35)) | V35: =IF(H35="","",SUM(J35,L35,N35,P35,R35,T35)) | W35: =IF($G35="","",IF($G35=1,(($C$2+$H35)*W$3)*(1+(W$4-W$5)),((W34+($H35*W$3))*(1+(W$4-W$5))))) | X35: =IF($G35="","",IF($G35=1,(($C$2+$H35)*X$3)*(1+(X$4-X$5)),((X34+($H35*X$3))*(1+(X$4-X$5))))) | Y35: =IF($G35="","",IF($G35=1,(U35-$C$2-H35)/($C$2+H35),(U35-U34-H35)/(U34+H35))) | Z35: =IF($G35="","",IF($G35=1,(V35-$C$2-H35)/($C$2+H35),(V35-V34-H35)/(V34+H35))) | AA35: =IF($G35="","",Z35-Y35) | AB35: =IF($G35="","",IF($G35=1,(W35-$C$2-H35)/($C$2+H35),(W35-W34-H35)/(W34+H35))) | AC35: =IF($G35="","",IF($G35=1,(X35-$C$2-H35)/($C$2+H35),(X35-X34-H35)/(X34+H35))) | AD35: =IF($G35="","",AC35-AB35) | AE35: =IF($G35="","",IF($G35=1,Y35,(1+Y35)*(1+AE34)-1)) | AF35: =IF($G35="","",IF($G35=1,Z35,(1+Z35)*(1+AF34)-1)) | AG35: =IF($G35="","",AF35-AE35) | AH35: =IF($G35="","",IF($G35=1,AB35,(1+AB35)*(1+AH34)-1)) | AI35: =IF($G35="","",IF($G35=1,AC35,(1+AC35)*(1+AI34)-1)) | AJ35: =IF($G35="","",AI35-AH35) | AK35: =IF($G35="","",(1+AE35)^(1/G35)-1) | AL35: =IF($G35="","",(1+AF35)^(1/G35)-1) | AM35: =IF($G35="","",AL35-AK35) | AN35: =IF($G35="","",(1+AH35)^(1/G35)-1) | AO35: =IF($G35="","",(1+AI35)^(1/G35)-1) | AP35: =IF($G35="","",AO35-AN35)
H36: =IF(G36="","",SUMIFS(Add_Contributions[[#All],[Amount ($)]],Add_Contributions[[#All],[Year]],G36)) | I36: =IF($G36="","",IF($G36=1,(($C$2+$H36)*I$3)*(1+(I$4-I$5)),((I35+($H36*I$3))*(1+(I$4-I$5))))) | J36: =IF($G36="","",IF($G36=1,(($C$2+$H36)*J$3)*(1+(J$4-J$5)),((J35+($H36*J$3))*(1+(J$4-J$5))))) | K36: =IF($G36="","",IF($G36=1,(($C$2+$H36)*K$3)*(1+(K$4-K$5)),((K35+($H36*K$3))*(1+(K$4-K$5))))) | L36: =IF($G36="","",IF($G36=1,(($C$2+$H36)*L$3)*(1+(L$4-L$5)),((L35+($H36*L$3))*(1+(L$4-L$5))))) | M36: =IF($G36="","",IF($G36=1,(($C$2+$H36)*M$3)*(1+(M$4-M$5)),((M35+($H36*M$3))*(1+(M$4-M$5))))) | N36: =IF($G36="","",IF($G36=1,(($C$2+$H36)*N$3)*(1+(N$4-N$5)),((N35+($H36*N$3))*(1+(N$4-N$5))))) | O36: =IF($G36="","",IF($G36=1,(($C$2+$H36)*O$3)*(1+(O$4-O$5)),((O35+($H36*O$3))*(1+(O$4-O$5))))) | P36: =IF($G36="","",IF($G36=1,(($C$2+$H36)*P$3)*(1+(P$4-P$5)),((P35+($H36*P$3))*(1+(P$4-P$5))))) | ... T36: =IF($G36="","",IF($G36=1,(($C$2+$H36)*T$3)*(1+(T$4-T$5)),((T35+($H36*T$3))*(1+(T$4-T$5))))) | U36: =IF(G36="","",SUM(I36,K36,M36,O36,Q36,S36)) | V36: =IF(H36="","",SUM(J36,L36,N36,P36,R36,T36)) | W36: =IF($G36="","",IF($G36=1,(($C$2+$H36)*W$3)*(1+(W$4-W$5)),((W35+($H36*W$3))*(1+(W$4-W$5))))) | X36: =IF($G36="","",IF($G36=1,(($C$2+$H36)*X$3)*(1+(X$4-X$5)),((X35+($H36*X$3))*(1+(X$4-X$5))))) | Y36: =IF($G36="","",IF($G36=1,(U36-$C$2-H36)/($C$2+H36),(U36-U35-H36)/(U35+H36))) | Z36: =IF($G36="","",IF($G36=1,(V36-$C$2-H36)/($C$2+H36),(V36-V35-H36)/(V35+H36))) | AA36: =IF($G36="","",Z36-Y36) | AB36: =IF($G36="","",IF($G36=1,(W36-$C$2-H36)/($C$2+H36),(W36-W35-H36)/(W35+H36))) | AC36: =IF($G36="","",IF($G36=1,(X36-$C$2-H36)/($C$2+H36),(X36-X35-H36)/(X35+H36))) | AD36: =IF($G36="","",AC36-AB36) | AE36: =IF($G36="","",IF($G36=1,Y36,(1+Y36)*(1+AE35)-1)) | AF36: =IF($G36="","",IF($G36=1,Z36,(1+Z36)*(1+AF35)-1)) | AG36: =IF($G36="","",AF36-AE36) | AH36: =IF($G36="","",IF($G36=1,AB36,(1+AB36)*(1+AH35)-1)) | AI36: =IF($G36="","",IF($G36=1,AC36,(1+AC36)*(1+AI35)-1)) | AJ36: =IF($G36="","",AI36-AH36) | AK36: =IF($G36="","",(1+AE36)^(1/G36)-1) | AL36: =IF($G36="","",(1+AF36)^(1/G36)-1) | AM36: =IF($G36="","",AL36-AK36) | AN36: =IF($G36="","",(1+AH36)^(1/G36)-1) | AO36: =IF($G36="","",(1+AI36)^(1/G36)-1) | AP36: =IF($G36="","",AO36-AN36)
H37: =IF(G37="","",SUMIFS(Add_Contributions[[#All],[Amount ($)]],Add_Contributions[[#All],[Year]],G37)) | I37: =IF($G37="","",IF($G37=1,(($C$2+$H37)*I$3)*(1+(I$4-I$5)),((I36+($H37*I$3))*(1+(I$4-I$5))))) | J37: =IF($G37="","",IF($G37=1,(($C$2+$H37)*J$3)*(1+(J$4-J$5)),((J36+($H37*J$3))*(1+(J$4-J$5))))) | K37: =IF($G37="","",IF($G37=1,(($C$2+$H37)*K$3)*(1+(K$4-K$5)),((K36+($H37*K$3))*(1+(K$4-K$5))))) | L37: =IF($G37="","",IF($G37=1,(($C$2+$H37)*L$3)*(1+(L$4-L$5)),((L36+($H37*L$3))*(1+(L$4-L$5))))) | M37: =IF($G37="","",IF($G37=1,(($C$2+$H37)*M$3)*(1+(M$4-M$5)),((M36+($H37*M$3))*(1+(M$4-M$5))))) | N37: =IF($G37="","",IF($G37=1,(($C$2+$H37)*N$3)*(1+(N$4-N$5)),((N36+($H37*N$3))*(1+(N$4-N$5))))) | O37: =IF($G37="","",IF($G37=1,(($C$2+$H37)*O$3)*(1+(O$4-O$5)),((O36+($H37*O$3))*(1+(O$4-O$5))))) | P37: =IF($G37="","",IF($G37=1,(($C$2+$H37)*P$3)*(1+(P$4-P$5)),((P36+($H37*P$3))*(1+(P$4-P$5))))) | ... T37: =IF($G37="","",IF($G37=1,(($C$2+$H37)*T$3)*(1+(T$4-T$5)),((T36+($H37*T$3))*(1+(T$4-T$5))))) | U37: =IF(G37="","",SUM(I37,K37,M37,O37,Q37,S37)) | V37: =IF(H37="","",SUM(J37,L37,N37,P37,R37,T37)) | W37: =IF($G37="","",IF($G37=1,(($C$2+$H37)*W$3)*(1+(W$4-W$5)),((W36+($H37*W$3))*(1+(W$4-W$5))))) | X37: =IF($G37="","",IF($G37=1,(($C$2+$H37)*X$3)*(1+(X$4-X$5)),((X36+($H37*X$3))*(1+(X$4-X$5))))) | Y37: =IF($G37="","",IF($G37=1,(U37-$C$2-H37)/($C$2+H37),(U37-U36-H37)/(U36+H37))) | Z37: =IF($G37="","",IF($G37=1,(V37-$C$2-H37)/($C$2+H37),(V37-V36-H37)/(V36+H37))) | AA37: =IF($G37="","",Z37-Y37) | AB37: =IF($G37="","",IF($G37=1,(W37-$C$2-H37)/($C$2+H37),(W37-W36-H37)/(W36+H37))) | AC37: =IF($G37="","",IF($G37=1,(X37-$C$2-H37)/($C$2+H37),(X37-X36-H37)/(X36+H37))) | AD37: =IF($G37="","",AC37-AB37) | AE37: =IF($G37="","",IF($G37=1,Y37,(1+Y37)*(1+AE36)-1)) | AF37: =IF($G37="","",IF($G37=1,Z37,(1+Z37)*(1+AF36)-1)) | AG37: =IF($G37="","",AF37-AE37) | AH37: =IF($G37="","",IF($G37=1,AB37,(1+AB37)*(1+AH36)-1)) | AI37: =IF($G37="","",IF($G37=1,AC37,(1+AC37)*(1+AI36)-1)) | AJ37: =IF($G37="","",AI37-AH37) | AK37: =IF($G37="","",(1+AE37)^(1/G37)-1) | AL37: =IF($G37="","",(1+AF37)^(1/G37)-1) | AM37: =IF($G37="","",AL37-AK37) | AN37: =IF($G37="","",(1+AH37)^(1/G37)-1) | AO37: =IF($G37="","",(1+AI37)^(1/G37)-1) | AP37: =IF($G37="","",AO37-AN37)
